Workbook

Sheet DATA ENTRY
B1: Editable
C3: 1 Yr | D3: 2 Yrs | E3: 3 Yrs | F3: 4 Yrs | G3: 5 Yrs
B4: GROSS AMOUNT | C4: ='Computation Table'!C108 -> 112058.4 | D4: ='Computation Table'!C82 -> 118481.58 | E4: ='Computation Table'!C56 -> 53999.85 | F4: ='Computation Table'!C29 -> 133026.28 | G4: ='Computation Table'!C3 -> 900014.89
B5: NET PROCEEDS | C5: 93500 | D5: 93500 | E5: 37354.7 | F5: 93500 | G5: 600010.5
B6: Add:
B7: Service Fee | C7: ='Computation Table'!C110 -> 6545 | D7: ='Computation Table'!C84 -> 7012.5 | E7: ='Computation Table'!E58 -> 2988.376 | F7: ='Computation Table'!C31 -> 7480 | G7: ='Computation Table'!C5 -> 72601.27
B8: Insurance | C8: ='Computation Table'!C111 -> 1122 | D8: ='Computation Table'!C85 -> 2244 | E8: ='Computation Table'!C59 -> 1344.7692 | F8: ='Computation Table'!C32 -> 4488 | G8: ='Computation Table'!C6 -> 36000.63
B9: CapCon | C9: 5000 | D9: 5000 | E9: 5000 | F9: 5000 | G9: 5000
B10: membership fee | C10: 300 | E10: 300 | F10: 0 | G10: 0
B11: Advance Interest | C11: ='Computation Table'!C114 -> 1168.75 | D11: ='Computation Table'!C88 -> 1265.3667 | E11: ='Computation Table'!C62 -> 529.19158 | F11: ='Computation Table'!C35 -> 1368.2167 | G11: ='Computation Table'!C9 -> 9000.1575
B12: LOAN AMOUNT | C12: =SUM(C5:C11) -> 107635.75 | D12: =SUM(D5:D11) -> 109021.87 | E12: =SUM(E5:E11) -> 47517.037 | F12: =SUM(F5:F11) -> 111836.22 | G12: =SUM(G5:G11) -> 722612.56
B13: Annual Interest Rate | C13: ='Computation Table'!C116 -> 0.075 | D13: ='Computation Table'!C90 -> 0.0812 | E13: ='Computation Table'!C64 -> 0.085 | F13: ='Computation Table'!C37 -> 0.0878 | G13: ='Computation Table'!C11 -> 0.09
B14: Effective Interest Rate | C14: ='Computation Table'!C117 -> 0.077632599 | D14: ='Computation Table'!F91 -> 0.084439155 | E14: ='Computation Table'!F65 -> 0.088607994 | F14: ='Computation Table'!C38 -> 0.091682187 | G14: ='Computation Table'!C12 -> 0.094100503
B15: Monthly Amortization | C15: ='Computation Table'!C126 -> 9338.1996 | D15: ='Computation Table'!C100 -> 4936.7326 | E15: ='Computation Table'!C74 -> 1499.9958 | F15: ='Computation Table'!C47 -> 2771.3809 | G15: ='Computation Table'!C21 -> 15000.248

Sheet Sheet2
A1: HIGHEST LOAN OFFER FOR 18-65 YO | B1: HIGHEST LOAN OFFERED FOR 71-75 | C1: HIGHEST LOAN OFFERED FOR 66-70
A2: 1224665.6 | B2: 141889.63 | C2: 325836.12
A3: 31137.533 | B3: 3632.7121 | C3: 8303.3421

Sheet Amortization  Table
B2: PEOPLE'S MULTI-PURPOSE COOPERATIVE EFFECTIVE ON JANUARY 16, 2025 | G2: PEOPLE'S MULTI-PURPOSE COOPERATIVE EFFECTIVE ON JANUARY 16, 2025 | N2: PEOPLE'S MULTI-PURPOSE COOPERATIVE EFFECTIVE ON JANUARY 16, 2025
B5: CDEA LOAN TABLE | G5: AFP LOAN TABLE W/O CAPCON | N5: AFP LOAN TABLE W/ CAPCON
B6: Net Proceeds | C6: 1 Yr 12 Months | D6: 2 Yrs 24 Months | E6: 3 Yrs 36 Months | G6: Net Proceeds | H6: 12 Months | I6: 24 Months | J6: 36 Months | K6: 48 Months | L6: 60 Months | N6: Net Proceeds | O6: 12 Months | P6: 24 Months | Q6: 36 Months | R6: 48 Months | S6: 60 Months
B7: 25000 | C7: ='Computation Table'!E126 -> 2373.8998 | D7: ='Computation Table'!C100 -> 4936.7326 | E7: ='Computation Table'!E74 -> 923.11506 | G7: 25000 | H7: 2373.8998 | I7: 1259.4445 | J7: 891.91446 | K7: 721.48005 | L7: 620.67482 | N7: 25000 | O7: 2833.7141 | P7: 1499.4393 | Q7: 1059.2224 | R7: 852.81781 | S7: 730.6941 | T7: 5000
B8: 50000 | C8: ='Computation Table'!F126 -> 5207.6139 | D8: ='Computation Table'!F100 -> 2745.2992 | E8: ='Computation Table'!F74 -> 1943.245 | G8: 50000 | H8: 4747.7996 | I8: 2518.889 | J8: 1783.8289 | K8: 1442.9601 | L8: 1241.3496 | N8: 50000 | O8: 5207.6139 | P8: 2758.8838 | Q8: 1951.1369 | R8: 1574.2979 | S8: 1351.3689
B9: 75000 | C9: ='Computation Table'!G126 -> 7121.6995 | D9: ='Computation Table'!G100 -> 3778.3335 | E9: ='Computation Table'!G74 -> 2663.9056 | G9: 75000 | H9: 7121.6995 | I9: 3778.3335 | J9: 2675.7434 | K9: 2164.4401 | L9: 1862.0245 | N9: 75000 | O9: 7581.5138 | P9: 4018.3283 | Q9: 2843.0513 | R9: 2295.7779 | S9: 1972.0437
B10: 100000 | C10: ='Computation Table'!H126 -> 9955.4136 | D10: ='Computation Table'!H100 -> 5264.1882 | E10: ='Computation Table'!H74 -> 3719.182 | G10: 100000 | H10: 9495.5993 | I10: 5037.778 | J10: 3567.6579 | K10: 2885.9202 | L10: 2482.6993 | N10: 100000 | O10: 9955.4136 | P10: 5277.7728 | Q10: 3734.9658 | R10: 3017.258 | S10: 2592.7186
B11: 150000 | C11: ='Computation Table'!J126 -> 14703.213 | D11: ='Computation Table'!J100 -> 7783.0772 | E11: ='Computation Table'!J74 -> 5495.1191 | G11: 150000 | H11: 14243.399 | I11: 7556.667 | J11: 5351.4868 | K11: 4328.8803 | L11: 3724.0489 | N11: 150000 | O11: 14703.213 | P11: 7796.6618 | Q11: 5518.7947 | R11: 4460.2181 | S11: 3834.0682
B12: 200000 | C12: ='Computation Table'!L126 -> 19451.013 | D12: ='Computation Table'!L100 -> 10301.966 | E12: ='Computation Table'!L74 -> 7271.0561 | G12: 200000 | H12: 18991.199 | I12: 10075.556 | J12: 7135.3157 | K12: 5771.8404 | L12: 4965.3986 | N12: 200000 | O12: 19451.013 | P12: 10315.551 | Q12: 7302.6237 | R12: 5903.1782 | S12: 5075.4179
B13: 250000 | C13: ='Computation Table'!N126 -> 24198.813 | D13: ='Computation Table'!N100 -> 12820.855 | E13: ='Computation Table'!N74 -> 9046.9932 | G13: 250000 | H13: 23738.998 | I13: 12594.445 | J13: 8919.1446 | K13: 7214.8005 | L13: 6206.7482 | N13: 250000 | O13: 24198.813 | P13: 12834.44 | Q13: 9086.4526 | R13: 7346.1382 | S13: 6316.7675
B14: 300000 | C14: ='Computation Table'!P126 -> 28946.612 | D14: ='Computation Table'!P100 -> 15339.744 | E14: ='Computation Table'!P74 -> 10822.93 | G14: 300000 | H14: 28486.798 | I14: 15113.334 | J14: 10702.974 | K14: 8657.7606 | L14: 7448.0979 | N14: 300000 | O14: 29380.399 | P14: 15579.739 | Q14: 11028.119 | R14: 8913.0019 | S14: 7661.9089 | T14: 10000
B15: 350000 | C15: ='Computation Table'!R126 -> 33694.412 | D15: ='Computation Table'!R100 -> 17858.633 | E15: ='Computation Table'!R74 -> 12598.867 | G15: 350000 | H15: 33234.597 | I15: 17632.223 | J15: 12486.802 | K15: 10100.721 | L15: 8689.4475 | N15: 350000 | O15: 34128.199 | P15: 18098.628 | Q15: 12811.948 | R15: 10355.962 | S15: 8903.2586
B16: 400000 | C16: ='Computation Table'!T126 -> 38442.211 | D16: ='Computation Table'!T100 -> 20377.522 | E16: ='Computation Table'!T74 -> 14374.804 | G16: 400000 | H16: 37982.397 | I16: 20151.112 | J16: 14270.631 | K16: 11543.681 | L16: 9930.7971 | N16: 400000 | O16: 38875.999 | P16: 20617.517 | Q16: 14595.777 | R16: 11798.922 | S16: 10144.608
B17: 450000 | C17: ='Computation Table'!V126 -> 43190.011 | D17: ='Computation Table'!V100 -> 22896.411 | E17: ='Computation Table'!V74 -> 16150.741 | G17: 450000 | H17: 42730.197 | I17: 22670.001 | J17: 16054.46 | K17: 12986.641 | L17: 11172.147 | N17: 450000 | O17: 43623.798 | P17: 23136.406 | Q17: 16379.606 | R17: 13241.882 | S17: 11385.958
B18: 500000 | C18: ='Computation Table'!X126 -> 47937.811 | D18: ='Computation Table'!X100 -> 25415.3 | E18: ='Computation Table'!X74 -> 17926.678 | G18: 500000 | H18: 47477.996 | I18: 25188.89 | J18: 17838.289 | K18: 14429.601 | L18: 12413.496 | N18: 500000 | O18: 48371.598 | P18: 25655.295 | Q18: 18163.435 | R18: 14684.842 | S18: 12627.307
B19: 550000 | C19: ='Computation Table'!Z126 -> 52685.61 | D19: ='Computation Table'!Z100 -> 27934.189 | E19: ='Computation Table'!Z74 -> 19702.615 | G19: 550000 | H19: 52225.796 | I19: 27707.779 | J19: 19622.118 | K19: 15872.561 | L19: 13654.846 | N19: 550000 | O19: 53119.397 | P19: 28174.184 | Q19: 19947.264 | R19: 16127.802 | S19: 13868.657
B20: 600000 | C20: ='Computation Table'!AB126 -> 57433.41 | D20: ='Computation Table'!AB100 -> 30453.078 | E20: ='Computation Table'!AB74 -> 21478.552 | G20: 600000 | H20: 56973.596 | I20: 30226.668 | J20: 21405.947 | K20: 17315.521 | L20: 14896.196 | N20: 600000 | O20: 57867.197 | P20: 30693.073 | Q20: 21731.093 | R20: 17570.762 | S20: 15110.007
B21: 650000 | C21: ='Computation Table'!AD126 -> 62181.21 | D21: ='Computation Table'!AD100 -> 32971.967 | E21: ='Computation Table'!AD74 -> 23254.49 | G21: 650000 | H21: 61721.395 | I21: 32745.557 | J21: 23189.776 | K21: 18758.481 | L21: 16137.545 | N21: 650000 | O21: 62614.997 | P21: 33211.962 | Q21: 23514.922 | R21: 19013.723 | S21: 16351.356
B22: 700000 | C22: ='Computation Table'!AF126 -> 66929.009 | D22: ='Computation Table'!AF100 -> 35490.856 | E22: ='Computation Table'!AF74 -> 25030.427 | G22: 700000 | H22: 66469.195 | I22: 35264.446 | J22: 24973.605 | K22: 20201.441 | L22: 17378.895 | N22: 700000 | O22: 67362.796 | P22: 35730.851 | Q22: 25298.751 | R22: 20456.683 | S22: 17592.706
B23: 750000 | C23: ='Computation Table'!AH126 -> 71676.809 | D23: ='Computation Table'!AH100 -> 38009.745 | E23: ='Computation Table'!AH74 -> 26806.364 | G23: 750000 | H23: 71216.995 | I23: 37783.335 | J23: 26757.434 | K23: 21644.401 | L23: 18620.245 | N23: 750000 | O23: 72110.596 | P23: 38249.74 | Q23: 27082.58 | R23: 21899.643 | S23: 18834.056
B24: 800000 | C24: ='Computation Table'!AJ126 -> 76424.609 | D24: ='Computation Table'!AJ100 -> 40528.634 | E24: ='Computation Table'!AJ74 -> 28582.301 | G24: 800000 | H24: 75964.794 | I24: 40302.224 | J24: 28541.263 | K24: 23087.362 | L24: 19861.594 | N24: 800000 | O24: 76858.396 | P24: 40768.629 | Q24: 28866.408 | R24: 23342.603 | S24: 20075.405
B25: 850000 | C25: ='Computation Table'!AL126 -> 81172.408 | D25: ='Computation Table'!AL100 -> 43047.523 | E25: ='Computation Table'!AL74 -> 30358.238 | G25: 850000 | H25: 80712.594 | I25: 42821.113 | J25: 30325.092 | K25: 24530.322 | L25: 21102.944 | N25: 850000 | O25: 81606.195 | P25: 43287.518 | Q25: 30650.237 | R25: 24785.563 | S25: 21316.755
B26: 900000 | C26: ='Computation Table'!AN126 -> 85920.208 | D26: ='Computation Table'!AN100 -> 45566.412 | E26: ='Computation Table'!AN74 -> 32134.175 | G26: 900000 | H26: 85460.394 | I26: 45340.002 | J26: 32108.921 | K26: 25973.282 | L26: 22344.294 | N26: 900000 | O26: 86353.995 | P26: 45806.407 | Q26: 32434.066 | R26: 26228.523 | S26: 22558.105
B27: 950000 | C27: ='Computation Table'!AP126 -> 90668.007 | D27: ='Computation Table'!AP100 -> 48085.301 | E27: ='Computation Table'!AP74 -> 33910.112 | G27: 950000 | H27: 90208.193 | I27: 47858.891 | J27: 33892.75 | K27: 27416.242 | L27: 23585.643 | N27: 950000 | O27: 91101.795 | P27: 48325.296 | Q27: 34217.895 | R27: 27671.483 | S27: 23799.454
B28: 1000000 | C28: ='Computation Table'!AR126 -> 95415.807 | D28: ='Computation Table'!AR100 -> 50604.19 | E28: ='Computation Table'!AR74 -> 35686.049 | G28: 1000000 | H28: 94955.993 | I28: 50377.78 | J28: 35676.579 | K28: 28859.202 | L28: 24826.993 | N28: 1000000 | O28: 98018.53 | P28: 51976.236 | Q28: 36790.913 | R28: 29733.961 | S28: 25559.763 | T28: 35000
G29: 9% HIGHEST INTEREST RATE | N29: 9% HIGHEST INTEREST RATE
N33: Monthly Amortization | O33: 12 Months | P33: 24 Months | Q33: 36 Months | R33: 48 Months | S33: 60 Months
G34: AGE INSURANCE | H34: MAXIMUM NET PROCEEDS | J34: REQUIREMENTS | N34: 1000 | O34: 5688.8 | P34: 15086.1 | Q34: 23340 | R34: 30100 | S34: 35847.5
G35: 18 TO 65 | H35: 1200000 | J35: NON-MEDICAL LIMIT (HEALTH QUESTIONNAIRE) | N35: 1500 | O35: 10954.39 | P35: 25011.1 | Q35: 37354.8 | R35: 47425.5 | S35: 55986.8
G36: 66 TO 70 | H36: 325000 | J36: NON-MEDICAL LIMIT (HEALTH QUESTIONNAIRE) | N36: 2000 | O36: 16219.98 | P36: 34936.1 | Q36: 51369.6 | R36: 64751 | S36: 76126.1
G37: 71 TO 75 | H37: 120000 | J37: NON-MEDICAL LIMIT (HEALTH QUESTIONNAIRE) | N37: 2500 | O37: 21485.57 | P37: 44861.1 | Q37: 65384.4 | R37: 82076.5 | S37: 96265.4
N38: 3000 | O38: 26751.16 | P38: 54786.1 | Q38: 79399.2 | R38: 99402 | S38: 116404.7
N39: 3500 | O39: 32016.75 | P39: 64711.1 | Q39: 93414 | R39: 116727.5 | S39: 136544
N40: 4000 | O40: 37282.34 | P40: 74636.1 | Q40: 107428.8 | R40: 134053 | S40: 156683.3
N41: 4500 | O41: 42547.93 | P41: 84561.1 | Q41: 121443.6 | R41: 151378.5 | S41: 176822.6
N42: 5000 | O42: 47813.62 | P42: 94486.1 | Q42: 135458.4 | R42: 168704 | S42: 196961.9
N43: 5500 | O43: 53079.2 | P43: 104411.1 | Q43: 149473.2 | R43: 186029.5 | S43: 217101.2
N44: 6000 | O44: 58344.8 | P44: 114336.1 | Q44: 163488 | R44: 203355 | S44: 237240.5
N45: 6500 | O45: 63610.4 | P45: 124261.1 | Q45: 177502.8 | R45: 220680.5 | S45: 257379.8
N46: 7000 | O46: 68875.88 | P46: 134186.1 | Q46: 191517.6 | R46: 238006 | S46: 277519.1
N47: 7500 | O47: 74141.6 | P47: 144111.1 | Q47: 205532.4 | R47: 255331.5 | S47: 297658.4
N48: 8000 | O48: 79407.2 | P48: 154036.1 | Q48: 219547.2 | R48: 272657 | S48: 317797.7
N49: 8500 | O49: 84672.8 | P49: 163961.1 | Q49: 233562 | R49: 289982.5 | S49: 337937
... N62: 15000 | O62: 153125.32 | P62: 292986.1 | Q62: 415754.4 | R62: 515214 | S62: 599747.9

Sheet Computation Table
B2: 5 Yrs
B3: GROSS | C3: =C21*C15 -> 900014.89 | E3: =E21*E15 -> 36586.601 | F3: =F21*F15 -> 79400.709 | G3: =G21*G15 -> 109759.8 | H3: =H21*H15 -> 152573.91 | I3: =I21*I15 -> 182933.01 | J3: =J21*J15 -> 225747.11 | K3: =K21*K15 -> 256106.21 | L3: =L21*L15 -> 298920.32 | ... AR3: =AR21*AR15 -> 1469691.6
B4: NET | C4: ='DATA ENTRY'!G5 -> 600010.5 | E4: 25000 | F4: 50000 | G4: 75000 | H4: 100000 | I4: 125000 | J4: 150000 | K4: 175000 | L4: 200000 | M4: 225000 | N4: 250000 | O4: 275000 | P4: 300000 | Q4: 325000 | R4: 350000 | S4: 375000 | T4: 400000 | U4: 425000 | V4: 450000 | W4: 475000 | X4: 500000 | Y4: 525000 | Z4: 550000 | AA4: 575000 | AB4: 600000 | AC4: 625000 | AD4: 650000 | AE4: 675000 | AF4: 700000 | AG4: 725000 | AH4: 750000 | AI4: 775000 | AJ4: 800000 | AK4: 825000 | AL4: 850000 | AM4: 875000 | AN4: 900000 | AO4: 925000 | AP4: 950000 | AQ4: 975000 | AR4: 1000000
B5: SF | C5: =C4*0.121 -> 72601.27 | D5: =D4*0.1 -> 0 | E5: =E4*0.1 -> 2500 | F5: =F4*0.1 -> 5000 | G5: =G4*0.1 -> 7500 | H5: =H4*0.1 -> 10000 | I5: =I4*0.1 -> 12500 | J5: =J4*0.1 -> 15000 | K5: =K4*0.1 -> 17500 | ... AR5: =AR4*0.1 -> 100000
B6: Insurance | C6: =(C4/1000)*C15 -> 36000.63 | E6: =(E4/1000)*E15 -> 1500 | F6: =(F4/1000)*F15 -> 3000 | G6: =(G4/1000)*G15 -> 4500 | H6: =(H4/1000)*H15 -> 6000 | I6: =(I4/1000)*I15 -> 7500 | J6: =(J4/1000)*J15 -> 9000 | K6: =(K4/1000)*K15 -> 10500 | L6: =(L4/1000)*L15 -> 12000 | ... AR6: =(AR4/1000)*AR15 -> 60000
B7: CapCon | C7: ='DATA ENTRY'!G9 -> 5000 | F7: =C7 -> 5000 | G7: =E7 -> 0 | H7: =F7 -> 5000 | I7: =G7 -> 0 | J7: =H7 -> 5000 | K7: =I7 -> 0 | L7: =J7 -> 5000 | M7: =K7 -> 0 | N7: =L7 -> 5000 | ... AR7: =AP7 -> 5000
B8: membership fee | C8: ='DATA ENTRY'!G10 -> 0 | F8: =C8 -> 0 | G8: =E8 -> 0 | H8: =F8 -> 0 | I8: =G8 -> 0 | J8: =H8 -> 0 | K8: =I8 -> 0 | L8: =J8 -> 0 | M8: =K8 -> 0 | N8: =L8 -> 0 | ... AR8: =AP8 -> 0
B9: Advance Interest | C9: =C14*C4*2 -> 9000.1575 | E9: =E14*E4*2 -> 375 | F9: =F14*F4*2 -> 750 | G9: =G14*G4*2 -> 1125 | H9: =H14*H4*2 -> 1500 | I9: =I14*I4*2 -> 1875 | J9: =J14*J4*2 -> 2250 | K9: =K14*K4*2 -> 2625 | L9: =L14*L4*2 -> 3000 | ... AR9: =AR14*AR4*2 -> 15000
B10: LOAN AMOUNT | C10: =SUM(C4:C9) -> 722612.56 | E10: =SUM(E4:E9) -> 29375 | F10: =SUM(F4:F9) -> 63750 | G10: =SUM(G4:G9) -> 88125 | H10: =SUM(H4:H9) -> 122500 | I10: =SUM(I4:I9) -> 146875 | J10: =SUM(J4:J9) -> 181250 | K10: =SUM(K4:K9) -> 205625 | L10: =SUM(L4:L9) -> 240000 | ... AR10: =SUM(AR4:AR9) -> 1180000
B11: Annual Interest | C11: 0.09 | E11: =C11 -> 0.09 | F11: =C11 -> 0.09 | G11: =F11 -> 0.09 | H11: =G11 -> 0.09 | I11: =H11 -> 0.09 | J11: =I11 -> 0.09 | K11: =J11 -> 0.09 | L11: =K11 -> 0.09 | M11: =L11 -> 0.09 | N11: =M11 -> 0.09 | ... W11: =V11 -> 0.09 | X11: 0.087 | Y11: =W11 -> 0.09 | Z11: =Y11 -> 0.09 | AA11: =Z11 -> 0.09 | AB11: =AA11 -> 0.09 | AC11: =AB11 -> 0.09 | AD11: =AC11 -> 0.09 | AE11: =AD11 -> 0.09 | AF11: =AE11 -> 0.09 | AG11: =AF11 -> 0.09 | ... AQ11: =AP11 -> 0.09 | AR11: 0.09
B12: Effective Interest rate | C12: =(1+C11/C15)^C15-1 -> 0.094100503 | E12: =(1+E11/E15)^E15-1 -> 0.094100503 | F12: =(1+F11/F15)^F15-1 -> 0.094100503 | G12: =(1+G11/G15)^G15-1 -> 0.094100503 | H12: =(1+H11/H15)^H15-1 -> 0.094100503 | I12: =(1+I11/I15)^I15-1 -> 0.094100503 | J12: =(1+J11/J15)^J15-1 -> 0.094100503 | K12: =(1+K11/K15)^K15-1 -> 0.094100503 | L12: =(1+L11/L15)^L15-1 -> 0.094100503 | ... AR12: =(1+AR11/AR15)^AR15-1 -> 0.094100503
B13: Loan Term | C13: 5 | E13: 5 | F13: 5 | G13: 5 | H13: 5 | I13: 5 | J13: 5 | K13: 5 | L13: 5 | M13: 5 | N13: 5 | O13: 5 | P13: 5 | Q13: 5 | R13: 5 | S13: 5 | T13: =P13 -> 5 | U13: =Q13 -> 5 | V13: =R13 -> 5 | W13: =S13 -> 5 | X13: =T13 -> 5 | Y13: =U13 -> 5 | Z13: =V13 -> 5 | AA13: =W13 -> 5 | ... AR13: =AN13 -> 5
B14: Monthly Interest Rate | C14: =C11/12 -> 0.0075 | E14: =E11/12 -> 0.0075 | F14: =F11/12 -> 0.0075 | G14: =G11/12 -> 0.0075 | H14: =H11/12 -> 0.0075 | I14: =I11/12 -> 0.0075 | J14: =J11/12 -> 0.0075 | K14: =K11/12 -> 0.0075 | L14: =L11/12 -> 0.0075 | ... AR14: =AR11/12 -> 0.0075
B15: Nr of Payments | C15: =C13*12 -> 60 | E15: =E13*12 -> 60 | F15: =F13*12 -> 60 | G15: =G13*12 -> 60 | H15: =H13*12 -> 60 | I15: =I13*12 -> 60 | J15: =J13*12 -> 60 | K15: =K13*12 -> 60 | L15: =L13*12 -> 60 | ... AR15: =AR13*12 -> 60
B17: Monthly Amortization | C17: =(1+C14)^C15 -> 1.565681 | E17: =(1+E14)^E15 -> 1.565681 | F17: =(1+F14)^F15 -> 1.565681 | G17: =(1+G14)^G15 -> 1.565681 | H17: =(1+H14)^H15 -> 1.565681 | I17: =(1+I14)^I15 -> 1.565681 | J17: =(1+J14)^J15 -> 1.565681 | K17: =(1+K14)^K15 -> 1.565681 | L17: =(1+L14)^L15 -> 1.565681 | ... AR17: =(1+AR14)^AR15 -> 1.565681
C18: =C17*C14 -> 0.011742608 | E18: =E17*E14 -> 0.011742608 | F18: =F17*F14 -> 0.011742608 | G18: =G17*G14 -> 0.011742608 | H18: =H17*H14 -> 0.011742608 | I18: =I17*I14 -> 0.011742608 | J18: =J17*J14 -> 0.011742608 | K18: =K17*K14 -> 0.011742608 | L18: =L17*L14 -> 0.011742608 | ... AR18: =AR17*AR14 -> 0.011742608
C19: =C17-1 -> 0.56568103 | E19: =E17-1 -> 0.56568103 | F19: =F17-1 -> 0.56568103 | G19: =G17-1 -> 0.56568103 | H19: =H17-1 -> 0.56568103 | I19: =I17-1 -> 0.56568103 | J19: =J17-1 -> 0.56568103 | K19: =K17-1 -> 0.56568103 | L19: =L17-1 -> 0.56568103 | ... AR19: =AR17-1 -> 0.56568103
C20: =C18/C19 -> 0.020758355 | E20: =E18/E19 -> 0.020758355 | F20: =F18/F19 -> 0.020758355 | G20: =G18/G19 -> 0.020758355 | H20: =H18/H19 -> 0.020758355 | I20: =I18/I19 -> 0.020758355 | J20: =J18/J19 -> 0.020758355 | K20: =K18/K19 -> 0.020758355 | L20: =L18/L19 -> 0.020758355 | ... AR20: =AR18/AR19 -> 0.020758355
B21: Monthly Amortization | C21: =C20*C10 -> 15000.248 | E21: =E20*E10 -> 609.77668 | F21: =F20*F10 -> 1323.3451 | G21: =G20*G10 -> 1829.3301 | H21: =H20*H10 -> 2542.8985 | I21: =I20*I10 -> 3048.8834 | J21: =J20*J10 -> 3762.4519 | K21: =K20*K10 -> 4268.4368 | L21: =L20*L10 -> 4982.0053 | ... AR21: =AR20*AR10 -> 24494.859
B23: Income | C23: =C3-C4 -> 300004.39 | E23: =E3-E4 -> 11586.601 | F23: =F3-F4 -> 29400.709 | G23: =G3-G4 -> 34759.803 | H23: =H3-H4 -> 52573.911 | I23: =I3-I4 -> 57933.005 | J23: =J3-J4 -> 75747.113 | K23: =K3-K4 -> 81106.208 | L23: =L3-L4 -> 98920.315 | ... AR23: =AR3-AR4 -> 469691.55
B24: % Income | C24: =C23/C3 -> 0.3333327 | E24: =E23/E3 -> 0.31668974 | F24: =F23/F3 -> 0.3702827 | G24: =G23/G3 -> 0.31668974 | H24: =H23/H3 -> 0.34457995 | I24: =I23/I3 -> 0.31668974 | J24: =J23/J3 -> 0.33553968 | K24: =K23/K3 -> 0.31668974 | L24: =L23/L3 -> 0.33092537 | ... AR24: =AR23/AR3 -> 0.31958512
B28: 4 yrs
B29: GROSS | C29: =C47*C41 -> 133026.28 | E29: =E47*E41 -> 33543.169 | F29: =F47*F41 -> 73033.709 | G29: =G47*G41 -> 100629.51 | H29: =H47*H41 -> 140120.05 | I29: =I47*I41 -> 167715.85 | J29: =J47*J41 -> 207206.39 | K29: =K47*K41 -> 234802.18 | L29: =L47*L41 -> 274292.72 | ... AR29: =AR47*AR41 -> 1347674.1
B30: NET | C30: ='DATA ENTRY'!F5 -> 93500 | E30: 25000 | F30: 50000 | G30: 75000 | H30: 100000 | I30: 125000 | J30: 150000 | K30: 175000 | L30: 200000 | M30: 225000 | N30: 250000 | O30: 275000 | P30: 300000 | Q30: 325000 | R30: 350000 | S30: 375000 | T30: 400000 | U30: 425000 | V30: 450000 | W30: 475000 | X30: 500000 | Y30: 525000 | Z30: 550000 | AA30: 575000 | AB30: 600000 | AC30: 625000 | AD30: 650000 | AE30: 675000 | AF30: 700000 | AG30: 725000 | AH30: 750000 | AI30: 775000 | AJ30: 800000 | AK30: 825000 | AL30: 850000 | AM30: 875000 | AN30: 900000 | AO30: 925000 | AP30: 950000 | AQ30: 975000 | AR30: 1000000
B31: SF | C31: =C30*0.08 -> 7480 | E31: =E30*0.08 -> 2000 | F31: =F30*0.08 -> 4000 | G31: =G30*0.08 -> 6000 | H31: =H30*0.08 -> 8000 | I31: =I30*0.08 -> 10000 | J31: =J30*0.08 -> 12000 | K31: =K30*0.08 -> 14000 | L31: =L30*0.08 -> 16000 | ... AR31: =AR30*0.08 -> 80000
B32: Insurance | C32: =(C30/1000)*C41 -> 4488 | E32: =(E30/1000)*E41 -> 1200 | F32: =(F30/1000)*F41 -> 2400 | G32: =(G30/1000)*G41 -> 3600 | H32: =(H30/1000)*H41 -> 4800 | I32: =(I30/1000)*I41 -> 6000 | J32: =(J30/1000)*J41 -> 7200 | K32: =(K30/1000)*K41 -> 8400 | L32: =(L30/1000)*L41 -> 9600 | ... AR32: =(AR30/1000)*AR41 -> 48000
B33: CapCon | C33: ='DATA ENTRY'!F9 -> 5000 | F33: =C33 -> 5000 | G33: =E33 -> 0 | H33: =F33 -> 5000 | I33: =G33 -> 0 | J33: =H33 -> 5000 | K33: =I33 -> 0 | L33: =J33 -> 5000 | M33: =K33 -> 0 | N33: =L33 -> 5000 | ... AR33: =AP33 -> 5000
B34: membership fee | C34: ='DATA ENTRY'!F10 -> 0 | F34: =C34 -> 0 | G34: =E34 -> 0 | H34: =F34 -> 0 | I34: =G34 -> 0 | J34: =H34 -> 0 | K34: =I34 -> 0 | L34: =J34 -> 0 | M34: =K34 -> 0 | N34: =L34 -> 0 | ... AR34: =AP34 -> 0
B35: Advance Interest | C35: =C40*C30*2 -> 1368.2167 | E35: =E40*E30*2 -> 365.83333 | F35: =F40*F30*2 -> 731.66667 | G35: =G40*G30*2 -> 1097.5 | H35: =H40*H30*2 -> 1463.3333 | I35: =I40*I30*2 -> 1829.1667 | J35: =J40*J30*2 -> 2195 | K35: =K40*K30*2 -> 2560.8333 | L35: =L40*L30*2 -> 2926.6667 | ... AR35: =AR40*AR30*2 -> 14633.333
B36: LOAN AMOUNT | C36: =SUM(C30:C35) -> 111836.22 | E36: =SUM(E30:E34) -> 28200 | F36: =SUM(F30:F34) -> 61400 | G36: =SUM(G30:G34) -> 84600 | H36: =SUM(H30:H34) -> 117800 | I36: =SUM(I30:I34) -> 141000 | J36: =SUM(J30:J34) -> 174200 | K36: =SUM(K30:K34) -> 197400 | L36: =SUM(L30:L34) -> 230600 | ... AR36: =SUM(AR30:AR34) -> 1133000
B37: Annual Interest | C37: 0.0878 | E37: 0.0878 | F37: =C37 -> 0.0878 | G37: =F37 -> 0.0878 | H37: =F37 -> 0.0878 | I37: =G37 -> 0.0878 | J37: =H37 -> 0.0878 | K37: =I37 -> 0.0878 | L37: =J37 -> 0.0878 | M37: =K37 -> 0.0878 | N37: =L37 -> 0.0878 | O37: =M37 -> 0.0878 | ... AR37: =AP37 -> 0.0878
B38: Effective Interest rate | C38: =(1+C37/C41)^C41-1 -> 0.091682187 | E38: =(1+E37/E41)^E41-1 -> 0.091682187 | F38: =(1+F37/F41)^F41-1 -> 0.091682187 | G38: =(1+G37/G41)^G41-1 -> 0.091682187 | H38: =(1+H37/H41)^H41-1 -> 0.091682187 | I38: =(1+I37/I41)^I41-1 -> 0.091682187 | J38: =(1+J37/J41)^J41-1 -> 0.091682187 | K38: =(1+K37/K41)^K41-1 -> 0.091682187 | L38: =(1+L37/L41)^L41-1 -> 0.091682187 | ... AR38: =(1+AR37/AR41)^AR41-1 -> 0.091682187
B39: Loan Term | C39: 4 | E39: 4 | F39: 4 | G39: 4 | H39: 4 | I39: 4 | J39: 4 | K39: 4 | L39: =H39 -> 4 | M39: =I39 -> 4 | N39: =K39 -> 4 | O39: =K39 -> 4 | P39: =L39 -> 4 | Q39: =M39 -> 4 | R39: =N39 -> 4 | S39: =O39 -> 4 | T39: =P39 -> 4 | U39: =Q39 -> 4 | V39: =R39 -> 4 | ... AR39: =AN39 -> 4
B40: Monthly Interest Rate | C40: =C37/12 -> 0.0073166667 | E40: =E37/12 -> 0.0073166667 | F40: =F37/12 -> 0.0073166667 | G40: =G37/12 -> 0.0073166667 | H40: =H37/12 -> 0.0073166667 | I40: =I37/12 -> 0.0073166667 | J40: =J37/12 -> 0.0073166667 | K40: =K37/12 -> 0.0073166667 | L40: =L37/12 -> 0.0073166667 | ... AR40: =AR37/12 -> 0.0073166667
B41: Nr of Payments | C41: =C39*12 -> 48 | E41: =E39*12 -> 48 | F41: =F39*12 -> 48 | G41: =G39*12 -> 48 | H41: =H39*12 -> 48 | I41: =I39*12 -> 48 | J41: =J39*12 -> 48 | K41: =K39*12 -> 48 | L41: =L39*12 -> 48 | ... AR41: =AR39*12 -> 48
B43: Monthly Amortization | C43: =(1+C40)^C41 -> 1.4189561 | E43: =(1+E40)^E41 -> 1.4189561 | F43: =(1+F40)^F41 -> 1.4189561 | G43: =(1+G40)^G41 -> 1.4189561 | H43: =(1+H40)^H41 -> 1.4189561 | I43: =(1+I40)^I41 -> 1.4189561 | J43: =(1+J40)^J41 -> 1.4189561 | K43: =(1+K40)^K41 -> 1.4189561 | L43: =(1+L40)^L41 -> 1.4189561 | ... AR43: =(1+AR40)^AR41 -> 1.4189561
C44: =C43*C40 -> 0.010382028 | E44: =E43*E40 -> 0.010382028 | F44: =F43*F40 -> 0.010382028 | G44: =G43*G40 -> 0.010382028 | H44: =H43*H40 -> 0.010382028 | I44: =I43*I40 -> 0.010382028 | J44: =J43*J40 -> 0.010382028 | K44: =K43*K40 -> 0.010382028 | L44: =L43*L40 -> 0.010382028 | ... AR44: =AR43*AR40 -> 0.010382028
C45: =C43-1 -> 0.41895605 | E45: =E43-1 -> 0.41895605 | F45: =F43-1 -> 0.41895605 | G45: =G43-1 -> 0.41895605 | H45: =H43-1 -> 0.41895605 | I45: =I43-1 -> 0.41895605 | J45: =J43-1 -> 0.41895605 | K45: =K43-1 -> 0.41895605 | L45: =L43-1 -> 0.41895605 | ... AR45: =AR43-1 -> 0.41895605
C46: =C44/C45 -> 0.02478071 | E46: =E44/E45 -> 0.02478071 | F46: =F44/F45 -> 0.02478071 | G46: =G44/G45 -> 0.02478071 | H46: =H44/H45 -> 0.02478071 | I46: =I44/I45 -> 0.02478071 | J46: =J44/J45 -> 0.02478071 | K46: =K44/K45 -> 0.02478071 | L46: =L44/L45 -> 0.02478071 | ... AR46: =AR44/AR45 -> 0.02478071
B47: Monthly Amortization | C47: =C46*C36 -> 2771.3809 | E47: =E46*E36 -> 698.81602 | F47: =F46*F36 -> 1521.5356 | G47: =G46*G36 -> 2096.4481 | H47: =H46*H36 -> 2919.1676 | I47: =I46*I36 -> 3494.0801 | J47: =J46*J36 -> 4316.7997 | K47: =K46*K36 -> 4891.7122 | L47: =L46*L36 -> 5714.4317 | ... AR47: =AR46*AR36 -> 28076.545
B49: Income | C49: =C29-C30 -> 39526.281 | E49: =E29-E30 -> 8543.1692 | F49: =F29-F30 -> 23033.709 | G49: =G29-G30 -> 25629.507 | H49: =H29-H30 -> 40120.047 | I49: =I29-I30 -> 42715.846 | J49: =J29-J30 -> 57206.385 | K49: =K29-K30 -> 59802.184 | L49: =L29-L30 -> 74292.724 | ... AR49: =AR29-AR30 -> 347674.14
B50: % Income | C50: =C49/C29 -> 0.29713137 | E50: =E49/E29 -> 0.25469177 | F50: =F49/F29 -> 0.31538462 | G50: =G49/G29 -> 0.25469177 | H50: =H49/H29 -> 0.28632625 | I50: =I49/I29 -> 0.25469177 | J50: =J49/J29 -> 0.27608409 | K50: =K49/K29 -> 0.25469177 | L50: =L49/L29 -> 0.27085197 | ... AR50: =AR49/AR29 -> 0.25798086
B55: 3 Yrs
B56: GROSS | C56: =C74*C68 -> 53999.85 | E56: =E74*E68 -> 33232.142 | F56: =F74*F68 -> 69956.82 | G56: =G74*G68 -> 95900.6 | H56: =H74*H68 -> 133890.55 | I56: =I74*I68 -> 159834.33 | J56: =J74*J68 -> 197824.29 | K56: =K74*K68 -> 223768.07 | L56: =L74*L68 -> 261758.02 | ... AR56: =AR74*AR68 -> 1284697.8
B57: NET | C57: ='DATA ENTRY'!E5 -> 37354.7 | E57: 25000 | F57: 50000 | G57: 75000 | H57: 100000 | I57: 125000 | J57: 150000 | K57: 175000 | L57: 200000 | M57: 225000 | N57: 250000 | O57: 275000 | P57: 300000 | Q57: 325000 | R57: 350000 | S57: 375000 | T57: 400000 | U57: 425000 | V57: 450000 | W57: 475000 | X57: 500000 | Y57: 525000 | Z57: 550000 | AA57: 575000 | AB57: 600000 | AC57: 625000 | AD57: 650000 | AE57: 675000 | AF57: 700000 | AG57: 725000 | AH57: 750000 | AI57: 775000 | AJ57: 800000 | AK57: 825000 | AL57: 850000 | AM57: 875000 | AN57: 900000 | AO57: 925000 | AP57: 950000 | AQ57: 975000 | AR57: 1000000
B58: SF | C58: =C57*0.08 -> 2988.376 | E58: =C57*0.08 -> 2988.376 | F58: =F57*0.075 -> 3750 | G58: =G57*0.075 -> 5625 | H58: =H57*0.075 -> 7500 | I58: =I57*0.075 -> 9375 | J58: =J57*0.075 -> 11250 | K58: =K57*0.075 -> 13125 | L58: =L57*0.075 -> 15000 | M58: =M57*0.075 -> 16875 | ... AR58: =AR57*0.075 -> 75000
B59: Insurance | C59: =(C57/1000)*C68 -> 1344.7692 | E59: =(E57/1000)*E68 -> 900 | F59: =(F57/1000)*F68 -> 1800 | G59: =(G57/1000)*G68 -> 2700 | H59: =(H57/1000)*H68 -> 3600 | I59: =(I57/1000)*I68 -> 4500 | J59: =(J57/1000)*J68 -> 5400 | K59: =(K57/1000)*K68 -> 6300 | L59: =(L57/1000)*L68 -> 7200 | ... AR59: =(AR57/1000)*AR68 -> 36000
B60: CapCon | C60: ='DATA ENTRY'!E9 -> 5000 | F60: =C60 -> 5000 | G60: =E60 -> 0 | H60: =F60 -> 5000 | I60: =G60 -> 0 | J60: =H60 -> 5000 | K60: =I60 -> 0 | L60: =J60 -> 5000 | M60: =K60 -> 0 | N60: =L60 -> 5000 | ... AR60: =AP60 -> 5000
B61: membership fee | C61: ='DATA ENTRY'!E10 -> 300 | F61: =C61 -> 300 | G61: =E61 -> 0 | H61: =F61 -> 300 | I61: =G61 -> 0 | J61: =H61 -> 300 | K61: =I61 -> 0 | L61: =J61 -> 300 | M61: =K61 -> 0 | N61: =L61 -> 300 | ... AR61: =AP61 -> 300
B62: Advance Interest | C62: =C67*C57*2 -> 529.19158 | E62: =E67*E57*2 -> 354.16667 | F62: =F67*F57*2 -> 708.33333 | G62: =G67*G57*2 -> 1062.5 | H62: =H67*H57*2 -> 1416.6667 | I62: =I67*I57*2 -> 1770.8333 | J62: =J67*J57*2 -> 2125 | K62: =K67*K57*2 -> 2479.1667 | L62: =L67*L57*2 -> 2833.3333 | ... AR62: =AR67*AR57*2 -> 14166.667
B63: LOAN AMOUNT | C63: =SUM(C57:C62) -> 47517.037 | E63: =SUM(E57:E62) -> 29242.543 | F63: =SUM(F57:F62) -> 61558.333 | G63: =SUM(G57:G62) -> 84387.5 | H63: =SUM(H57:H62) -> 117816.67 | I63: =SUM(I57:I62) -> 140645.83 | J63: =SUM(J57:J62) -> 174075 | K63: =SUM(K57:K62) -> 196904.17 | L63: =SUM(L57:L62) -> 230333.33 | ... AR63: =SUM(AR57:AR62) -> 1130466.7
B64: Annual Interest | C64: 0.085 | E64: =C64 -> 0.085 | F64: =C64 -> 0.085 | G64: =F64 -> 0.085 | H64: =F64 -> 0.085 | I64: =G64 -> 0.085 | J64: =H64 -> 0.085 | K64: =I64 -> 0.085 | L64: =J64 -> 0.085 | M64: =K64 -> 0.085 | N64: =L64 -> 0.085 | O64: =M64 -> 0.085 | ... AR64: =AP64 -> 0.085
B65: Effective Interest rate | C65: =(1+C64/C68)^C68-1 -> 0.088607994 | E65: =(1+E64/E68)^E68-1 -> 0.088607994 | F65: =(1+F64/F68)^F68-1 -> 0.088607994 | G65: =(1+G64/G68)^G68-1 -> 0.088607994 | H65: =(1+H64/H68)^H68-1 -> 0.088607994 | I65: =(1+I64/I68)^I68-1 -> 0.088607994 | J65: =(1+J64/J68)^J68-1 -> 0.088607994 | K65: =(1+K64/K68)^K68-1 -> 0.088607994 | L65: =(1+L64/L68)^L68-1 -> 0.088607994 | ... AR65: =(1+AR64/AR68)^AR68-1 -> 0.088607994
B66: Loan Term | C66: 3 | E66: 3 | F66: 3 | G66: 3 | H66: 3 | I66: 3 | J66: 3 | K66: 3 | L66: =H66 -> 3 | M66: =I66 -> 3 | N66: =K66 -> 3 | O66: =K66 -> 3 | P66: =L66 -> 3 | Q66: =M66 -> 3 | R66: =N66 -> 3 | S66: =O66 -> 3 | T66: =P66 -> 3 | U66: =Q66 -> 3 | V66: =R66 -> 3 | ... AR66: =AN66 -> 3
B67: Monthly Interest Rate | C67: =C64/12 -> 0.0070833333 | E67: =E64/12 -> 0.0070833333 | F67: =F64/12 -> 0.0070833333 | G67: =G64/12 -> 0.0070833333 | H67: =H64/12 -> 0.0070833333 | I67: =I64/12 -> 0.0070833333 | J67: =J64/12 -> 0.0070833333 | K67: =K64/12 -> 0.0070833333 | L67: =L64/12 -> 0.0070833333 | ... AR67: =AR64/12 -> 0.0070833333
B68: Nr of Payments | C68: =C66*12 -> 36 | E68: =E66*12 -> 36 | F68: =F66*12 -> 36 | G68: =G66*12 -> 36 | H68: =H66*12 -> 36 | I68: =I66*12 -> 36 | J68: =J66*12 -> 36 | K68: =K66*12 -> 36 | L68: =L66*12 -> 36 | ... AR68: =AR66*12 -> 36
B70: Monthly Amortization | C70: =(1+C67)^C68 -> 1.2893022 | E70: =(1+E67)^E68 -> 1.2893022 | F70: =(1+F67)^F68 -> 1.2893022 | G70: =(1+G67)^G68 -> 1.2893022 | H70: =(1+H67)^H68 -> 1.2893022 | I70: =(1+I67)^I68 -> 1.2893022 | J70: =(1+J67)^J68 -> 1.2893022 | K70: =(1+K67)^K68 -> 1.2893022 | L70: =(1+L67)^L68 -> 1.2893022 | ... AR70: =(1+AR67)^AR68 -> 1.2893022
C71: =C70*C67 -> 0.009132557 | E71: =E70*E67 -> 0.009132557 | F71: =F70*F67 -> 0.009132557 | G71: =G70*G67 -> 0.009132557 | H71: =H70*H67 -> 0.009132557 | I71: =I70*I67 -> 0.009132557 | J71: =J70*J67 -> 0.009132557 | K71: =K70*K67 -> 0.009132557 | L71: =L70*L67 -> 0.009132557 | ... AR71: =AR70*AR67 -> 0.009132557
C72: =C70-1 -> 0.28930217 | E72: =E70-1 -> 0.28930217 | F72: =F70-1 -> 0.28930217 | G72: =G70-1 -> 0.28930217 | H72: =H70-1 -> 0.28930217 | I72: =I70-1 -> 0.28930217 | J72: =J70-1 -> 0.28930217 | K72: =K70-1 -> 0.28930217 | L72: =L70-1 -> 0.28930217 | ... AR72: =AR70-1 -> 0.28930217
C73: =C71/C72 -> 0.031567537 | E73: =E71/E72 -> 0.031567537 | F73: =F71/F72 -> 0.031567537 | G73: =G71/G72 -> 0.031567537 | H73: =H71/H72 -> 0.031567537 | I73: =I71/I72 -> 0.031567537 | J73: =J71/J72 -> 0.031567537 | K73: =K71/K72 -> 0.031567537 | L73: =L71/L72 -> 0.031567537 | ... AR73: =AR71/AR72 -> 0.031567537
B74: Monthly Amortization | C74: =C73*C63 -> 1499.9958 | E74: =E73*E63 -> 923.11506 | F74: =F73*F63 -> 1943.245 | G74: =G73*G63 -> 2663.9056 | H74: =H73*H63 -> 3719.182 | I74: =I73*I63 -> 4439.8426 | J74: =J73*J63 -> 5495.1191 | K74: =K73*K63 -> 6215.7797 | L74: =L73*L63 -> 7271.0561 | ... AR74: =AR73*AR63 -> 35686.049
B76: Income | C76: =C56-C57 -> 16645.15 | E76: =E56-E57 -> 8232.1422 | F76: =F56-F57 -> 19956.82 | G76: =G56-G57 -> 20900.6 | H76: =H56-H57 -> 33890.553 | I76: =I56-I57 -> 34834.334 | J76: =J56-J57 -> 47824.287 | K76: =K56-K57 -> 48768.067 | L76: =L56-L57 -> 61758.02 | ... AR76: =AR56-AR57 -> 284697.76
B77: % Income | C77: =C76/C56 -> 0.30824438 | E77: =E76/E56 -> 0.24771627 | F77: =F76/F56 -> 0.2852734 | G77: =G76/G56 -> 0.21794024 | H77: =H76/H56 -> 0.25312132 | I77: =I76/I56 -> 0.21794024 | J77: =J76/J56 -> 0.24175134 | K77: =K76/K56 -> 0.21794024 | L77: =L76/L56 -> 0.23593554 | ... AR77: =AR76/AR56 -> 0.2216068
B81: 2 Yrs
B82: GROSS | C82: =C100*C94 -> 118481.58 | E82: =E100*E94 -> 30226.668 | F82: =F100*F94 -> 65887.181 | G82: =G100*G94 -> 90680.004 | H82: =H100*H94 -> 126340.52 | I82: =I100*I94 -> 151133.34 | J82: =J100*J94 -> 186793.85 | K82: =K100*K94 -> 211586.68 | L82: =L100*L94 -> 247247.19 | ... AR82: =AR100*AR94 -> 1214500.6
B83: NET | C83: ='DATA ENTRY'!D5 -> 93500 | E83: 25000 | F83: 50000 | G83: 75000 | H83: 100000 | I83: 125000 | J83: 150000 | K83: 175000 | L83: 200000 | M83: 225000 | N83: 250000 | O83: 275000 | P83: 300000 | Q83: 325000 | R83: 350000 | S83: 375000 | T83: 400000 | U83: 425000 | V83: 450000 | W83: 475000 | X83: 500000 | Y83: 525000 | Z83: 550000 | AA83: 575000 | AB83: 600000 | AC83: 625000 | AD83: 650000 | AE83: 675000 | AF83: 700000 | AG83: 725000 | AH83: 750000 | AI83: 775000 | AJ83: 800000 | AK83: 825000 | AL83: 850000 | AM83: 875000 | AN83: 900000 | AO83: 925000 | AP83: 950000 | AQ83: 975000 | AR83: 1000000
B84: SF | C84: =C83*0.075 -> 7012.5 | E84: =E83*0.075 -> 1875 | F84: =F83*0.075 -> 3750 | G84: =G83*0.075 -> 5625 | H84: =H83*0.075 -> 7500 | I84: =I83*0.075 -> 9375 | J84: =J83*0.075 -> 11250 | K84: =K83*0.075 -> 13125 | L84: =L83*0.075 -> 15000 | ... AR84: =AR83*0.075 -> 75000
B85: Insurance | C85: =(C83/1000)*C94 -> 2244 | E85: =(E83/1000)*E94 -> 600 | F85: =(F83/1000)*F94 -> 1200 | G85: =(G83/1000)*G94 -> 1800 | H85: =(H83/1000)*H94 -> 2400 | I85: =(I83/1000)*I94 -> 3000 | J85: =(J83/1000)*J94 -> 3600 | K85: =(K83/1000)*K94 -> 4200 | L85: =(L83/1000)*L94 -> 4800 | ... AR85: =(AR83/1000)*AR94 -> 24000
B86: CapCon | C86: ='DATA ENTRY'!D9 -> 5000 | F86: =C86 -> 5000 | G86: =E86 -> 0 | H86: =F86 -> 5000 | I86: =G86 -> 0 | J86: =H86 -> 5000 | K86: =I86 -> 0 | L86: =J86 -> 5000 | M86: =K86 -> 0 | N86: =L86 -> 5000 | ... AR86: =AP86 -> 5000
B87: membership fee | C87: ='DATA ENTRY'!D10 -> 0 | F87: =C87 -> 0 | G87: =E87 -> 0 | H87: =F87 -> 0 | I87: =G87 -> 0 | J87: =H87 -> 0 | K87: =I87 -> 0 | L87: =J87 -> 0 | M87: =K87 -> 0 | N87: =L87 -> 0 | ... AR87: =AP87 -> 0
B88: Advance Interest | C88: =C93*C83*2 -> 1265.3667 | E88: =E93*E83*2 -> 338.33333 | F88: =F93*F83*2 -> 676.66667 | G88: =G93*G83*2 -> 1015 | H88: =H93*H83*2 -> 1353.3333 | I88: =I93*I83*2 -> 1691.6667 | J88: =J93*J83*2 -> 2030 | K88: =K93*K83*2 -> 2368.3333 | L88: =L93*L83*2 -> 2706.6667 | ... AR88: =AR93*AR83*2 -> 13533.333
B89: LOAN AMOUNT | C89: =SUM(C83:C88) -> 109021.87 | E89: =SUM(E83:E88) -> 27813.333 | F89: =SUM(F83:F88) -> 60626.667 | G89: =SUM(G83:G88) -> 83440 | H89: =SUM(H83:H88) -> 116253.33 | I89: =SUM(I83:I88) -> 139066.67 | J89: =SUM(J83:J88) -> 171880 | K89: =SUM(K83:K88) -> 194693.33 | L89: =SUM(L83:L88) -> 227506.67 | ... AR89: =SUM(AR83:AR88) -> 1117533.3
B90: Annual Interest | C90: 0.0812 | E90: =C90 -> 0.0812 | F90: =C90 -> 0.0812 | G90: =F90 -> 0.0812 | H90: =F90 -> 0.0812 | I90: =G90 -> 0.0812 | J90: =H90 -> 0.0812 | K90: =I90 -> 0.0812 | L90: =J90 -> 0.0812 | M90: =K90 -> 0.0812 | N90: =L90 -> 0.0812 | O90: =M90 -> 0.0812 | ... AR90: =AP90 -> 0.0812
B91: Effective Interest rate | C91: =(1+C90/C94)^C94-1 -> 0.084439155 | E91: =(1+E90/E94)^E94-1 -> 0.084439155 | F91: =(1+F90/F94)^F94-1 -> 0.084439155 | G91: =(1+G90/G94)^G94-1 -> 0.084439155 | H91: =(1+H90/H94)^H94-1 -> 0.084439155 | I91: =(1+I90/I94)^I94-1 -> 0.084439155 | J91: =(1+J90/J94)^J94-1 -> 0.084439155 | K91: =(1+K90/K94)^K94-1 -> 0.084439155 | L91: =(1+L90/L94)^L94-1 -> 0.084439155 | ... AR91: =(1+AR90/AR94)^AR94-1 -> 0.084439155
B92: Loan Term | C92: 2 | E92: 2 | F92: 2 | G92: 2 | H92: 2 | I92: 2 | J92: 2 | K92: 2 | L92: =H92 -> 2 | M92: =I92 -> 2 | N92: =K92 -> 2 | O92: =K92 -> 2 | P92: =L92 -> 2 | Q92: =M92 -> 2 | R92: =N92 -> 2 | S92: =O92 -> 2 | T92: =P92 -> 2 | U92: =Q92 -> 2 | V92: =R92 -> 2 | ... AR92: =AN92 -> 2
B93: Monthly Interest Rate | C93: =C90/12 -> 0.0067666667 | E93: =E90/12 -> 0.0067666667 | F93: =F90/12 -> 0.0067666667 | G93: =G90/12 -> 0.0067666667 | H93: =H90/12 -> 0.0067666667 | I93: =I90/12 -> 0.0067666667 | J93: =J90/12 -> 0.0067666667 | K93: =K90/12 -> 0.0067666667 | L93: =L90/12 -> 0.0067666667 | ... AR93: =AR90/12 -> 0.0067666667
B94: Nr of Payments | C94: =C92*12 -> 24 | E94: =E92*12 -> 24 | F94: =F92*12 -> 24 | G94: =G92*12 -> 24 | H94: =H92*12 -> 24 | I94: =I92*12 -> 24 | J94: =J92*12 -> 24 | K94: =K92*12 -> 24 | L94: =L92*12 -> 24 | ... AR94: =AR92*12 -> 24
B96: Monthly Amortization | C96: =(1+C93)^C94 -> 1.1756874 | E96: =(1+E93)^E94 -> 1.1756874 | F96: =(1+F93)^F94 -> 1.1756874 | G96: =(1+G93)^G94 -> 1.1756874 | H96: =(1+H93)^H94 -> 1.1756874 | I96: =(1+I93)^I94 -> 1.1756874 | J96: =(1+J93)^J94 -> 1.1756874 | K96: =(1+K93)^K94 -> 1.1756874 | L96: =(1+L93)^L94 -> 1.1756874 | ... AR96: =(1+AR93)^AR94 -> 1.1756874
C97: =C96*C93 -> 0.0079554849 | E97: =E96*E93 -> 0.0079554849 | F97: =F96*F93 -> 0.0079554849 | G97: =G96*G93 -> 0.0079554849 | H97: =H96*H93 -> 0.0079554849 | I97: =I96*I93 -> 0.0079554849 | J97: =J96*J93 -> 0.0079554849 | K97: =K96*K93 -> 0.0079554849 | L97: =L96*L93 -> 0.0079554849 | ... AR97: =AR96*AR93 -> 0.0079554849
C98: =C96-1 -> 0.17568742 | E98: =E96-1 -> 0.17568742 | F98: =F96-1 -> 0.17568742 | G98: =G96-1 -> 0.17568742 | H98: =H96-1 -> 0.17568742 | I98: =I96-1 -> 0.17568742 | J98: =J96-1 -> 0.17568742 | K98: =K96-1 -> 0.17568742 | L98: =L96-1 -> 0.17568742 | ... AR98: =AR96-1 -> 0.17568742
C99: =C97/C98 -> 0.045282041 | E99: =E97/E98 -> 0.045282041 | F99: =F97/F98 -> 0.045282041 | G99: =G97/G98 -> 0.045282041 | H99: =H97/H98 -> 0.045282041 | I99: =I97/I98 -> 0.045282041 | J99: =J97/J98 -> 0.045282041 | K99: =K97/K98 -> 0.045282041 | L99: =L97/L98 -> 0.045282041 | ... AR99: =AR97/AR98 -> 0.045282041
B100: Monthly Amortization | C100: =C99*C89 -> 4936.7326 | E100: =E99*E89 -> 1259.4445 | F100: =F99*F89 -> 2745.2992 | G100: =G99*G89 -> 3778.3335 | H100: =H99*H89 -> 5264.1882 | I100: =I99*I89 -> 6297.2225 | J100: =J99*J89 -> 7783.0772 | K100: =K99*K89 -> 8816.1115 | L100: =L99*L89 -> 10301.966 | ... AR100: =AR99*AR89 -> 50604.19
B102: Income | C102: =C82-C83 -> 24981.583 | E102: =E82-E83 -> 5226.6681 | F102: =F82-F83 -> 15887.181 | G102: =G82-G83 -> 15680.004 | H102: =H82-H83 -> 26340.517 | I102: =I82-I83 -> 26133.34 | J102: =J82-J83 -> 36793.853 | K102: =K82-K83 -> 36586.676 | L102: =L82-L83 -> 47247.189 | ... AR102: =AR82-AR83 -> 214500.57
B103: % Income | C103: =C102/C82 -> 0.21084782 | E103: =E102/E82 -> 0.17291579 | F103: =F102/F82 -> 0.24112704 | G103: =G102/G82 -> 0.17291579 | H103: =H102/H82 -> 0.20848828 | I103: =I102/I82 -> 0.17291579 | J103: =J102/J82 -> 0.19697572 | K103: =K102/K82 -> 0.17291579 | L103: =L102/L82 -> 0.19109293 | ... AR103: =AR102/AR82 -> 0.17661628
B107: 1 Yr
B108: GROSS | C108: =C126*C120 -> 112058.4 | E108: =E126*E120 -> 28486.798 | F108: =F126*F120 -> 62491.367 | G108: =G126*G120 -> 85460.394 | H108: =H126*H120 -> 119464.96 | I108: =I126*I120 -> 142433.99 | J108: =J126*J120 -> 176438.56 | K108: =K126*K120 -> 199407.58 | L108: =L126*L120 -> 233412.15 | ... AR108: =AR126*AR120 -> 1144989.7
B109: NET | C109: ='DATA ENTRY'!C5 -> 93500 | E109: 25000 | F109: 50000 | G109: 75000 | H109: 100000 | I109: 125000 | J109: 150000 | K109: 175000 | L109: 200000 | M109: 225000 | N109: 250000 | O109: 275000 | P109: 300000 | Q109: 325000 | R109: 350000 | S109: 375000 | T109: 400000 | U109: 425000 | V109: 450000 | W109: 475000 | X109: 500000 | Y109: 525000 | Z109: 550000 | AA109: 575000 | AB109: 600000 | AC109: 625000 | AD109: 650000 | AE109: 675000 | AF109: 700000 | AG109: 725000 | AH109: 750000 | AI109: 775000 | AJ109: 800000 | AK109: 825000 | AL109: 850000 | AM109: 875000 | AN109: 900000 | AO109: 925000 | AP109: 950000 | AQ109: 975000 | AR109: 1000000
B110: SF | C110: =C109*0.07 -> 6545 | E110: =E109*0.07 -> 1750 | F110: =F109*0.07 -> 3500 | G110: =G109*0.07 -> 5250 | H110: =H109*0.07 -> 7000 | I110: =I109*0.07 -> 8750 | J110: =J109*0.07 -> 10500 | K110: =K109*0.07 -> 12250 | L110: =L109*0.07 -> 14000 | ... AR110: =AR109*0.07 -> 70000
B111: Insurance | C111: =(C109/1000)*C120 -> 1122 | E111: =(E109/1000)*E120 -> 300 | F111: =(F109/1000)*F120 -> 600 | G111: =(G109/1000)*G120 -> 900 | H111: =(H109/1000)*H120 -> 1200 | I111: =(I109/1000)*I120 -> 1500 | J111: =(J109/1000)*J120 -> 1800 | K111: =(K109/1000)*K120 -> 2100 | L111: =(L109/1000)*L120 -> 2400 | ... AR111: =(AR109/1000)*AR120 -> 12000
B112: CapCon | C112: ='DATA ENTRY'!C9 -> 5000 | F112: =C112 -> 5000 | G112: =E112 -> 0 | H112: =F112 -> 5000 | I112: =G112 -> 0 | J112: =H112 -> 5000 | K112: =I112 -> 0 | L112: =J112 -> 5000 | M112: =K112 -> 0 | N112: =L112 -> 5000 | ... AR112: =AP112 -> 5000
B113: membership fee | C113: ='DATA ENTRY'!C10 -> 300 | F113: =C113 -> 300 | G113: =E113 -> 0 | H113: =F113 -> 300 | I113: =G113 -> 0 | J113: =H113 -> 300 | K113: =I113 -> 0 | L113: =J113 -> 300 | M113: =K113 -> 0 | N113: =L113 -> 300 | ... AR113: =AP113 -> 300
B114: Advance Interest | C114: =C119*C109*2 -> 1168.75 | E114: =E119*E109*2 -> 312.5 | F114: =F119*F109*2 -> 625 | G114: =G119*G109*2 -> 937.5 | H114: =H119*H109*2 -> 1250 | I114: =I119*I109*2 -> 1562.5 | J114: =J119*J109*2 -> 1875 | K114: =K119*K109*2 -> 2187.5 | L114: =L119*L109*2 -> 2500 | ... AR114: =AR119*AR109*2 -> 12500
B115: LOAN AMOUNT | C115: =SUM(C109:C114) -> 107635.75 | E115: =SUM(E109:E114) -> 27362.5 | F115: =SUM(F109:F114) -> 60025 | G115: =SUM(G109:G114) -> 82087.5 | H115: =SUM(H109:H114) -> 114750 | I115: =SUM(I109:I114) -> 136812.5 | J115: =SUM(J109:J114) -> 169475 | K115: =SUM(K109:K114) -> 191537.5 | L115: =SUM(L109:L114) -> 224200 | ... AR115: =SUM(AR109:AR114) -> 1099800
B116: Annual Interest | C116: 0.075 | E116: =C116 -> 0.075 | F116: =E116 -> 0.075 | G116: =E116 -> 0.075 | H116: =F116 -> 0.075 | I116: =G116 -> 0.075 | J116: =H116 -> 0.075 | K116: =I116 -> 0.075 | L116: =J116 -> 0.075 | M116: =K116 -> 0.075 | N116: =L116 -> 0.075 | ... AR116: =AP116 -> 0.075
B117: Effective Interest rate | C117: =(1+C116/C120)^C120-1 -> 0.077632599 | E117: =(1+E116/E120)^E120-1 -> 0.077632599 | F117: =(1+F116/F120)^F120-1 -> 0.077632599 | G117: =(1+G116/G120)^G120-1 -> 0.077632599 | H117: =(1+H116/H120)^H120-1 -> 0.077632599 | I117: =(1+I116/I120)^I120-1 -> 0.077632599 | J117: =(1+J116/J120)^J120-1 -> 0.077632599 | K117: =(1+K116/K120)^K120-1 -> 0.077632599 | L117: =(1+L116/L120)^L120-1 -> 0.077632599 | ... AR117: =(1+AR116/AR120)^AR120-1 -> 0.077632599
B118: Loan Term | C118: 1 | E118: 1 | F118: 1 | G118: 1 | H118: 1 | I118: 1 | J118: 1 | K118: 1 | L118: =H118 -> 1 | M118: =I118 -> 1 | N118: =K118 -> 1 | O118: =K118 -> 1 | P118: =L118 -> 1 | Q118: =M118 -> 1 | R118: =N118 -> 1 | S118: =O118 -> 1 | T118: =P118 -> 1 | U118: =Q118 -> 1 | V118: =R118 -> 1 | ... AR118: =AN118 -> 1
B119: Monthly Interest Rate | C119: =C116/12 -> 0.00625 | E119: =E116/12 -> 0.00625 | F119: =F116/12 -> 0.00625 | G119: =G116/12 -> 0.00625 | H119: =H116/12 -> 0.00625 | I119: =I116/12 -> 0.00625 | J119: =J116/12 -> 0.00625 | K119: =K116/12 -> 0.00625 | L119: =L116/12 -> 0.00625 | ... AR119: =AR116/12 -> 0.00625
B120: Nr of Payments | C120: =C118*12 -> 12 | E120: =E118*12 -> 12 | F120: =F118*12 -> 12 | G120: =G118*12 -> 12 | H120: =H118*12 -> 12 | I120: =I118*12 -> 12 | J120: =J118*12 -> 12 | K120: =K118*12 -> 12 | L120: =L118*12 -> 12 | ... AR120: =AR118*12 -> 12
B122: Monthly Amortization | C122: =(1+C119)^C120 -> 1.0776326 | E122: =(1+E119)^E120 -> 1.0776326 | F122: =(1+F119)^F120 -> 1.0776326 | G122: =(1+G119)^G120 -> 1.0776326 | H122: =(1+H119)^H120 -> 1.0776326 | I122: =(1+I119)^I120 -> 1.0776326 | J122: =(1+J119)^J120 -> 1.0776326 | K122: =(1+K119)^K120 -> 1.0776326 | L122: =(1+L119)^L120 -> 1.0776326 | ... AR122: =(1+AR119)^AR120 -> 1.0776326
C123: =C122*C119 -> 0.0067352037 | E123: =E122*E119 -> 0.0067352037 | F123: =F122*F119 -> 0.0067352037 | G123: =G122*G119 -> 0.0067352037 | H123: =H122*H119 -> 0.0067352037 | I123: =I122*I119 -> 0.0067352037 | J123: =J122*J119 -> 0.0067352037 | K123: =K122*K119 -> 0.0067352037 | L123: =L122*L119 -> 0.0067352037 | ... AR123: =AR122*AR119 -> 0.0067352037
...

Sheet 3 YEARS
B1: Amortization | C1: ='DATA ENTRY'!E15 -> 1499.9958
B2: Timeline | C2: 0 | D2: 1 | E2: 2 | F2: 3 | G2: 4 | H2: 5 | I2: 6 | J2: 7 | K2: 8 | L2: 9 | M2: 10 | N2: 11 | O2: 12 | P2: 13 | Q2: 14 | R2: 15 | S2: 16 | T2: 17 | U2: 18 | V2: 19 | W2: 20 | X2: 21 | Y2: 22 | Z2: 23 | AA2: 24 | AB2: 25 | AC2: 26 | AD2: 27 | AE2: 28 | AF2: 29 | AG2: 30 | AH2: 31 | AI2: 32 | AJ2: 33 | AK2: 34 | AL2: 35 | AM2: 36 | AN2: 37 | AO2: 38 | AP2: 39 | AQ2: 40 | AR2: 41 | AS2: 42 | AT2: 43 | AU2: 44 | AV2: 45 | AW2: 46 | AX2: 47 | AY2: 48 | AZ2: 49 | BA2: 50 | BB2: 51 | BC2: 52 | BD2: 53 | BE2: 54 | BF2: 55 | BG2: 56 | BH2: 57 | BI2: 58 | BJ2: 59 | BK2: 60
B3: GROSS AMOUNT | C3: ='DATA ENTRY'!E4 -> 53999.85
B4: LOAN AMOUNT | C4: ='DATA ENTRY'!D12 -> 109021.87 | D4: =D10 -> -1499.9958 | E4: =E10 -> -1499.9958 | F4: =F10 -> -1499.9958 | G4: =G10 -> -1499.9958 | H4: =H10 -> -1499.9958 | I4: =I10 -> -1499.9958 | J4: =J10 -> -1499.9958 | K4: =K10 -> -1499.9958 | ... AY4: =AY10 -> -1499.9958
B5: Service Fee | C5: ='DATA ENTRY'!E7 -> 2988.376
B6: Insurance | C6: ='DATA ENTRY'!E8 -> 1344.7692
B7: CapCon | C7: ='DATA ENTRY'!E9 -> 5000
B8: membership fee | C8: ='DATA ENTRY'!E10 -> 300
B9: Advance Interest | C9: ='DATA ENTRY'!E11 -> 529.19158
B10: NET PROCEEDS/CASH FLOW | C10: =C4-C5-C6-C7-C8-C9-C13 -> 57135.55 | D10: =-$C1 -> -1499.9958 | E10: =-$C1 -> -1499.9958 | F10: =-$C1 -> -1499.9958 | G10: =-$C1 -> -1499.9958 | H10: =-$C1 -> -1499.9958 | I10: =-$C1 -> -1499.9958 | J10: =-$C1 -> -1499.9958 | K10: =-$C1 -> -1499.9958 | ... BK10: =-$C1 -> -1499.9958
B12: Interest Rate of Return | C12: =IRR(C4:AY4) -> -0.015816905 | D12: =C12/5 -> -0.003163381
B13: Outstanding Balance | C13: ='[1]ACTIVE CIV.'!$D$41 -> 41723.98
B14: Annual Interest Rate | C14: ='[2]AMORTIZATION '!$D$26 -> 0.016
B15: Effective Interest Rate | C15: ='DATA ENTRY'!F14 -> 0.091682187
C20: LOAN LEDGER CARD
C22: Name: | D22: CARLITO VASQUEZ GARCIA | G22: Loan Voucher No. | H22: LV- 047
C23: Serial: | D23: 637617 | E23: Address: | F23: PEMBO, MAKATI CITY , METRO MANILA | G23: Amount: | H23: =C10 -> 57135.55
C24: Posting date | D24: Date of Loan: | E24: 45846 | F24: Maturity Date | G24: =B75 -> 47430
D25: Term: | E25: 48 | F25: MOS
D26: Loan | E26: Installment | F26: Principal | G26: EIR | H26: Balance
H27: =C4 -> 109021.87
B28: =DATE(YEAR($E$24),MONTH($E$24)+D28+4,DAY($E$24)) -> 45999 | C28: =TEXT(B28,"mmm-yyyy") -> Dec-2025 | D28: 1 | E28: =C$1 -> 1499.9958 | F28: =E28-G28 -> 3224.3843 | G28: =H27*C$12 -> -1724.3885 | H28: =H27-F28 -> 105797.48
B29: =DATE(YEAR($E$24),MONTH($E$24)+D29+4,DAY($E$24)) -> 46030 | C29: =TEXT(B29,"mmm-yyyy") -> Jan-2026 | D29: 2 | E29: =C$1 -> 1499.9958 | F29: =E29-G29 -> 3173.3846 | G29: =H28*C$12 -> -1673.3887 | H29: =H28-F29 -> 102624.1
B30: =DATE(YEAR($E$24),MONTH($E$24)+D30+4,DAY($E$24)) -> 46061 | C30: =TEXT(B30,"mmm-yyyy") -> Feb-2026 | D30: 3 | E30: =C$1 -> 1499.9958 | F30: =E30-G30 -> 3123.1914 | G30: =H29*C$12 -> -1623.1956 | H30: =H29-F30 -> 99500.906
B31: =DATE(YEAR($E$24),MONTH($E$24)+D31+4,DAY($E$24)) -> 46089 | C31: =TEXT(B31,"mmm-yyyy") -> Mar-2026 | D31: 4 | E31: =C$1 -> 1499.9958 | F31: =E31-G31 -> 3073.7922 | G31: =H30*C$12 -> -1573.7964 | H31: =H30-F31 -> 96427.114
B32: =DATE(YEAR($E$24),MONTH($E$24)+D32+4,DAY($E$24)) -> 46120 | C32: =TEXT(B32,"mmm-yyyy") -> Apr-2026 | D32: 5 | E32: =C$1 -> 1499.9958 | F32: =E32-G32 -> 3025.1743 | G32: =H31*C$12 -> -1525.1785 | H32: =H31-F32 -> 93401.94
B33: =DATE(YEAR($E$24),MONTH($E$24)+D33+4,DAY($E$24)) -> 46150 | C33: =TEXT(B33,"mmm-yyyy") -> May-2026 | D33: 6 | E33: =C$1 -> 1499.9958 | F33: =E33-G33 -> 2977.3254 | G33: =H32*C$12 -> -1477.3296 | H33: =H32-F33 -> 90424.614
B34: =DATE(YEAR($E$24),MONTH($E$24)+D34+4,DAY($E$24)) -> 46181 | C34: =TEXT(B34,"mmm-yyyy") -> Jun-2026 | D34: 7 | E34: =C$1 -> 1499.9958 | F34: =E34-G34 -> 2930.2334 | G34: =H33*C$12 -> -1430.2375 | H34: =H33-F34 -> 87494.381
B35: =DATE(YEAR($E$24),MONTH($E$24)+D35+4,DAY($E$24)) -> 46211 | C35: =TEXT(B35,"mmm-yyyy") -> Jul-2026 | D35: 8 | E35: =C$1 -> 1499.9958 | F35: =E35-G35 -> 2883.8861 | G35: =H34*C$12 -> -1383.8903 | H35: =H34-F35 -> 84610.495
B36: =DATE(YEAR($E$24),MONTH($E$24)+D36+4,DAY($E$24)) -> 46242 | C36: =TEXT(B36,"mmm-yyyy") -> Aug-2026 | D36: 9 | E36: =C$1 -> 1499.9958 | F36: =E36-G36 -> 2838.272 | G36: =H35*C$12 -> -1338.2762 | H36: =H35-F36 -> 81772.223
B37: =DATE(YEAR($E$24),MONTH($E$24)+D37+4,DAY($E$24)) -> 46273 | C37: =TEXT(B37,"mmm-yyyy") -> Sep-2026 | D37: 10 | E37: =C$1 -> 1499.9958 | F37: =E37-G37 -> 2793.3793 | G37: =H36*C$12 -> -1293.3835 | H37: =H36-F37 -> 78978.844
B38: =DATE(YEAR($E$24),MONTH($E$24)+D38+4,DAY($E$24)) -> 46303 | C38: =TEXT(B38,"mmm-yyyy") -> Oct-2026 | D38: 11 | E38: =C$1 -> 1499.9958 | F38: =E38-G38 -> 2749.1967 | G38: =H37*C$12 -> -1249.2009 | H38: =H37-F38 -> 76229.647
B39: =DATE(YEAR($E$24),MONTH($E$24)+D39+4,DAY($E$24)) -> 46334 | C39: =TEXT(B39,"mmm-yyyy") -> Nov-2026 | D39: 12 | E39: =C$1 -> 1499.9958 | F39: =E39-G39 -> 2705.7129 | G39: =H38*C$12 -> -1205.7171 | H39: =H38-F39 -> 73523.934
... B64: =DATE(YEAR($E$24),MONTH($E$24)+D64+4,DAY($E$24)) -> 47095 | C64: =TEXT(B64,"mmm-yyyy") -> Dec-2028 | D64: 37 | E64: =C$1 -> 1499.9958 | F64: =E64-G64 -> 1816.2651 | G64: =H63*C$12 -> -316.26928 | H64: =H63-F64 -> 18179.384
A65: i | B65: =DATE(YEAR($E$24),MONTH($E$24)+D65+4,DAY($E$24)) -> 47126 | C65: =TEXT(B65,"mmm-yyyy") -> Jan-2029 | D65: 38 | E65: =C$1 -> 1499.9958 | F65: =E65-G65 -> 1787.5374 | G65: =H64*C$12 -> -287.54158 | H65: =H64-F65 -> 16391.846
B66: =DATE(YEAR($E$24),MONTH($E$24)+D66+4,DAY($E$24)) -> 47157 | C66: =TEXT(B66,"mmm-yyyy") -> Feb-2029 | D66: 39 | E66: =C$1 -> 1499.9958 | F66: =E66-G66 -> 1759.2641 | G66: =H65*C$12 -> -259.26827 | H66: =H65-F66 -> 14632.582
B67: =DATE(YEAR($E$24),MONTH($E$24)+D67+4,DAY($E$24)) -> 47185 | C67: =TEXT(B67,"mmm-yyyy") -> Mar-2029 | D67: 40 | E67: =C$1 -> 1499.9958 | F67: =E67-G67 -> 1731.438 | G67: =H66*C$12 -> -231.44216 | H67: =H66-F67 -> 12901.144
B68: =DATE(YEAR($E$24),MONTH($E$24)+D68+4,DAY($E$24)) -> 47216 | C68: =TEXT(B68,"mmm-yyyy") -> Apr-2029 | D68: 41 | E68: =C$1 -> 1499.9958 | F68: =E68-G68 -> 1704.052 | G68: =H67*C$12 -> -204.05617 | H68: =H67-F68 -> 11197.092
B69: =DATE(YEAR($E$24),MONTH($E$24)+D69+4,DAY($E$24)) -> 47246 | C69: =TEXT(B69,"mmm-yyyy") -> May-2029 | D69: 42 | E69: =C$1 -> 1499.9958 | F69: =E69-G69 -> 1677.0992 | G69: =H68*C$12 -> -177.10334 | H69: =H68-F69 -> 9519.993
B70: =DATE(YEAR($E$24),MONTH($E$24)+D70+4,DAY($E$24)) -> 47277 | C70: =TEXT(B70,"mmm-yyyy") -> Jun-2029 | D70: 43 | E70: =C$1 -> 1499.9958 | F70: =E70-G70 -> 1650.5727 | G70: =H69*C$12 -> -150.57682 | H70: =H69-F70 -> 7869.4203
A71: i | B71: =DATE(YEAR($E$24),MONTH($E$24)+D71+4,DAY($E$24)) -> 47307 | C71: =TEXT(B71,"mmm-yyyy") -> Jul-2029 | D71: 44 | E71: =C$1 -> 1499.9958 | F71: =E71-G71 -> 1624.4657 | G71: =H70*C$12 -> -124.46987 | H71: =H70-F71 -> 6244.9546
B72: =DATE(YEAR($E$24),MONTH($E$24)+D72+4,DAY($E$24)) -> 47338 | C72: =TEXT(B72,"mmm-yyyy") -> Aug-2029 | D72: 45 | E72: =C$1 -> 1499.9958 | F72: =E72-G72 -> 1598.7717 | G72: =H71*C$12 -> -98.775853 | H72: =H71-F72 -> 4646.1829
A73: i | B73: =DATE(YEAR($E$24),MONTH($E$24)+D73+4,DAY($E$24)) -> 47369 | C73: =TEXT(B73,"mmm-yyyy") -> Sep-2029 | D73: 46 | E73: =C$1 -> 1499.9958 | F73: =E73-G73 -> 1573.4841 | G73: =H72*C$12 -> -73.488233 | H73: =H72-F73 -> 3072.6988
B74: =DATE(YEAR($E$24),MONTH($E$24)+D74+4,DAY($E$24)) -> 47399 | C74: =TEXT(B74,"mmm-yyyy") -> Oct-2029 | D74: 47 | E74: =C$1 -> 1499.9958 | F74: =E74-G74 -> 1548.5964 | G74: =H73*C$12 -> -48.600585 | H74: =H73-F74 -> 1524.1024
B75: =DATE(YEAR($E$24),MONTH($E$24)+D75+4,DAY($E$24)) -> 47430 | C75: =TEXT(B75,"mmm-yyyy") -> Nov-2029 | D75: 48 | E75: =C$1 -> 1499.9958 | F75: =E75-G75 -> 1524.1024 | G75: =H74*C$12 -> -24.106583 | H75: =H74-F75 -> -1.440435e-08
E76: =SUM(E28:E75) -> 71999.8 | F76: =SUM(F28:F75) -> 109021.87 | G76: =SUM(G28:G75) -> -37022.066
K83: PEOPLE'S MULTI-PURPOSE COOPERATIVE
K84: STALL # 2 PRINCIPE BLDG. MAHARLIKA HI-WAY UPI GAMU ISABELA
K86: LOAN RELEASE VOUCHER
R88: Date: | S88: =E24 -> 45846
R89: LV No: | S89: =H22 -> LV- 047
K91: Name of Borrower: | N91: =D22 -> CARLITO VASQUEZ GARCIA
K92: Serial No.: | N92: =D23 -> 637617
K93: Address: | N93: =F23 -> PEMBO, MAKATI CITY , METRO MANILA
L95: Principal Amount | R95: =H27 -> 109021.87
L97: (-) | M97: Balance Old Loan(s) | R97: 0
L98: (-) | M98: Membership Fee: | R98: =-C8 -> -300
L99: (-) | M99: Paid up Capital: | R99: =-C7 -> -5000
L100: (-) | M100: Service Fee | R100: =-C5 -> -2988.376
L101: (-) | M101: Advance interest | R101: =-C9 -> -529.19158
L102: (-) | M102: Insurance Premium - Paramount | R102: =-C6 -> -1344.7692
L103: NET PROCEEDS (Php): | R103: =SUM(R95:T102) -> 98859.53
K106: PAYMENT
L111: Term: | R111: 48 months
L112: Monthly Interest Payable | R112: =C1 -> 1499.9958
L113: First Payment Due On: | R113: =B28 -> 45999
L114: Maturity: | R114: =G24 -> 47430
L115: EIR (%): | R115: =C14 -> 0.016
L116: Interest Rate per Month (%): | R116: =C15 -> 0.091682187
K120: Certified & Corrected by: | Q120: Approved By:
P122: ALEXANDER A. FERIA JR
K123: PROCESSOR | Q123: LOAN VERIFIER
K126: Received By:
K127: =N91 -> CARLITO VASQUEZ GARCIA | P127: COL. ALEXANDER L. FERIA (RET) CPA MNSA
K128: Signature Over Printed Name/Date | Q128: President

Sheet 5 YEARS
B1: Amortization | C1: ='DATA ENTRY'!G15 -> 15000.248
B2: Timeline | C2: 0 | D2: 1 | E2: 2 | F2: 3 | G2: 4 | H2: 5 | I2: 6 | J2: 7 | K2: 8 | L2: 9 | M2: 10 | N2: 11 | O2: 12 | P2: 13 | Q2: 14 | R2: 15 | S2: 16 | T2: 17 | U2: 18 | V2: 19 | W2: 20 | X2: 21 | Y2: 22 | Z2: 23 | AA2: 24 | AB2: 25 | AC2: 26 | AD2: 27 | AE2: 28 | AF2: 29 | AG2: 30 | AH2: 31 | AI2: 32 | AJ2: 33 | AK2: 34 | AL2: 35 | AM2: 36 | AN2: 37 | AO2: 38 | AP2: 39 | AQ2: 40 | AR2: 41 | AS2: 42 | AT2: 43 | AU2: 44 | AV2: 45 | AW2: 46 | AX2: 47 | AY2: 48 | AZ2: 49 | BA2: 50 | BB2: 51 | BC2: 52 | BD2: 53 | BE2: 54 | BF2: 55 | BG2: 56 | BH2: 57 | BI2: 58 | BJ2: 59 | BK2: 60
B3: GROSS AMOUNT | C3: ='DATA ENTRY'!G4 -> 900014.89
B4: LOAN AMOUNT | C4: ='DATA ENTRY'!G12 -> 722612.56 | D4: =D10 -> -15000.248 | E4: =E10 -> -15000.248 | F4: =F10 -> -15000.248 | G4: =G10 -> -15000.248 | H4: =H10 -> -15000.248 | I4: =I10 -> -15000.248 | J4: =J10 -> -15000.248 | K4: =K10 -> -15000.248 | ... BK4: =BK10 -> -15000.248
B5: Service Fee | C5: ='DATA ENTRY'!G7 -> 72601.27
B6: Insurance | C6: ='DATA ENTRY'!G8 -> 36000.63
B7: CapCon | C7: ='DATA ENTRY'!G9 -> 5000
B8: membership fee | C8: ='DATA ENTRY'!G10 -> 0
B9: Advance Interest | C9: ='DATA ENTRY'!G11 -> 9000.1575
B10: NET PROCEEDS/CASH FLOW | C10: =C4-C5-C6-C7-C8-C9 -> 600010.5 | D10: =-$C1 -> -15000.248 | E10: =-$C1 -> -15000.248 | F10: =-$C1 -> -15000.248 | G10: =-$C1 -> -15000.248 | H10: =-$C1 -> -15000.248 | I10: =-$C1 -> -15000.248 | J10: =-$C1 -> -15000.248 | K10: =-$C1 -> -15000.248 | ... BK10: =-$C1 -> -15000.248
B12: Interest Rate of Return | C12: =IRR(C4:BK4) -> 0.0075 | D12: =C12/5 -> 0.0015
B14: ='DATA ENTRY'!B13 -> Annual Interest Rate | C14: ='DATA ENTRY'!G13 -> 0.09
B15: ='DATA ENTRY'!B14 -> Effective Interest Rate | C15: ='DATA ENTRY'!G14 -> 0.094100503
C20: LOAN LEDGER CARD
C22: Name: | D22: MARTIN BARROGA RICARDO | G22: Loan Voucher No. | H22: LV - 047
C23: Serial: | D23: O- 127212 | E23: Address: | F23: B4 L14 DEROSA ST. MS2, LNC, BRGY NAVARRO, CITY OF GENERAL TRIAS, CAVITE | G23: Amount: | H23: =C10 -> 600010.5
C24: Posting date | D24: Date of Loan: | E24: 45722 | F24: Maturity Date | G24: =B87 -> 47579
D25: Term: | E25: 60 | F25: MOS
D26: Loan | E26: Installment | F26: Principal | G26: EIR | H26: Balance
D27: Month 0 | H27: =C4 -> 722612.56
B28: =DATE(YEAR($E$24),MONTH($E$24)+D28+1,DAY($E$24)) -> 45783 | C28: =TEXT(B28,"mmm-yyyy") -> May-2025 | D28: 1 | E28: =C$1 -> 15000.248 | F28: =E28-G28 -> 9580.654 | G28: =H27*C$12 -> 5419.5942 | H28: =H27-F28 -> 713031.9
B29: =DATE(YEAR($E$24),MONTH($E$24)+D29+1,DAY($E$24)) -> 45814 | C29: =TEXT(B29,"mmm-yyyy") -> Jun-2025 | D29: 2 | E29: =C$1 -> 15000.248 | F29: =E29-G29 -> 9652.5089 | G29: =H28*C$12 -> 5347.7393 | H29: =H28-F29 -> 703379.4
B30: =DATE(YEAR($E$24),MONTH($E$24)+D30+1,DAY($E$24)) -> 45844 | C30: =TEXT(B30,"mmm-yyyy") -> Jul-2025 | D30: 3 | E30: =C$1 -> 15000.248 | F30: =E30-G30 -> 9724.9027 | G30: =H29*C$12 -> 5275.3455 | H30: =H29-F30 -> 693654.49
B31: =DATE(YEAR($E$24),MONTH($E$24)+D31+1,DAY($E$24)) -> 45875 | C31: =TEXT(B31,"mmm-yyyy") -> Aug-2025 | D31: 4 | E31: =C$1 -> 15000.248 | F31: =E31-G31 -> 9797.8395 | G31: =H30*C$12 -> 5202.4087 | H31: =H30-F31 -> 683856.65
B32: =DATE(YEAR($E$24),MONTH($E$24)+D32+1,DAY($E$24)) -> 45906 | C32: =TEXT(B32,"mmm-yyyy") -> Sep-2025 | D32: 5 | E32: =C$1 -> 15000.248 | F32: =E32-G32 -> 9871.3233 | G32: =H31*C$12 -> 5128.9249 | H32: =H31-F32 -> 673985.33
B33: =DATE(YEAR($E$24),MONTH($E$24)+D33+1,DAY($E$24)) -> 45936 | C33: =TEXT(B33,"mmm-yyyy") -> Oct-2025 | D33: 6 | E33: =C$1 -> 15000.248 | F33: =E33-G33 -> 9945.3582 | G33: =H32*C$12 -> 5054.89 | H33: =H32-F33 -> 664039.97
B34: =DATE(YEAR($E$24),MONTH($E$24)+D34+1,DAY($E$24)) -> 45967 | C34: =TEXT(B34,"mmm-yyyy") -> Nov-2025 | D34: 7 | E34: =C$1 -> 15000.248 | F34: =E34-G34 -> 10019.948 | G34: =H33*C$12 -> 4980.2998 | H34: =H33-F34 -> 654020.02
B35: =DATE(YEAR($E$24),MONTH($E$24)+D35+1,DAY($E$24)) -> 45997 | C35: =TEXT(B35,"mmm-yyyy") -> Dec-2025 | D35: 8 | E35: =C$1 -> 15000.248 | F35: =E35-G35 -> 10095.098 | G35: =H34*C$12 -> 4905.1502 | H35: =H34-F35 -> 643924.93
B36: =DATE(YEAR($E$24),MONTH($E$24)+D36+1,DAY($E$24)) -> 46028 | C36: =TEXT(B36,"mmm-yyyy") -> Jan-2026 | D36: 9 | E36: =C$1 -> 15000.248 | F36: =E36-G36 -> 10170.811 | G36: =H35*C$12 -> 4829.4369 | H36: =H35-F36 -> 633754.11
B37: =DATE(YEAR($E$24),MONTH($E$24)+D37+1,DAY($E$24)) -> 46059 | C37: =TEXT(B37,"mmm-yyyy") -> Feb-2026 | D37: 10 | E37: =C$1 -> 15000.248 | F37: =E37-G37 -> 10247.092 | G37: =H36*C$12 -> 4753.1559 | H37: =H36-F37 -> 623507.02
B38: =DATE(YEAR($E$24),MONTH($E$24)+D38+1,DAY($E$24)) -> 46087 | C38: =TEXT(B38,"mmm-yyyy") -> Mar-2026 | D38: 11 | E38: =C$1 -> 15000.248 | F38: =E38-G38 -> 10323.946 | G38: =H37*C$12 -> 4676.3027 | H38: =H37-F38 -> 613183.08
B39: =DATE(YEAR($E$24),MONTH($E$24)+D39+1,DAY($E$24)) -> 46118 | C39: =TEXT(B39,"mmm-yyyy") -> Apr-2026 | D39: 12 | E39: =C$1 -> 15000.248 | F39: =E39-G39 -> 10401.375 | G39: =H38*C$12 -> 4598.8731 | H39: =H38-F39 -> 602781.7
... B87: =DATE(YEAR($E$24),MONTH($E$24)+D87+1,DAY($E$24)) -> 47579 | C87: =TEXT(B87,"mmm-yyyy") -> Apr-2030 | D87: 60 | E87: =C$1 -> 15000.248 | F87: =E87-G87 -> 14888.584 | G87: =H86*C$12 -> 111.66438 | H87: =H86-F87 -> -1.8299033e-09
E88: =SUM(E28:E87) -> 900014.89 | F88: =SUM(F28:F87) -> 722612.56
K95: PEOPLE'S MULTI-PURPOSE COOPERATIVE
K96: 20-E 2nd Camarilla St. corner 15th Ave., Brgy. San Roque, Murphy Cubao, Quezon City
K98: LOAN RELEASE VOUCHER
R100: Date: | S100: =E24 -> 45722
R101: LV No: | S101: =H22 -> LV - 047
K104: Name of Borrower: | N104: =D22 -> MARTIN BARROGA RICARDO
K105: Serial No.: | N105: =D23 -> O- 127212
K106: Address: | N106: =F23 -> B4 L14 DEROSA ST. MS2, LNC, BRGY NAVARRO, CITY OF GENERAL TRIAS, CAVITE
L108: Principal Amount | R108: =C4 -> 722612.56
L111: (-) | M111: Membership Fee: | R111: =C8 -> 0
L112: (-) | M112: Paid up Capital: | R112: =-C7 -> -5000
L113: (-) | M113: Service Fee | R113: =-C5 -> -72601.27
L114: (-) | M114: Insurance Premium - Paramount | R114: =-C6 -> -36000.63
L115: (-) | M115: Insurance Premium - Paramount | R115: =-C9 -> -9000.1575
L116: NET PROCEEDS (Php): | R116: =SUM(R108:T115) -> 600010.5
K118: PAYMENT
L120: Term: | R120: 60 months
L121: Monthly Interest Payable | R121: =C1 -> 15000.248
L122: First Payment Due On: | R122: =E24 -> 45722
L123: Maturity: | R123: =G24 -> 47579
L124: EIR (%): | R124: =C14 -> 0.09
L125: Interest Rate per Month (%): | R125: =C15 -> 0.094100503
K134: Certified & Corrected by: | Q134: Approved By:
K136: PAMELA CHERRY A. REYES | P136: ALEXANDER A. FERIA JR
K137: Processor | Q137: Verifier
K139: Received By:
K140: RICARDO BARROGA MARTIN | P140: COL. ALEXANDER L. FERIA (RET) CPA MNSA
K141: Signature Over Printed Name/Date | Q141: President

Sheet LRV1YEAR
B1: Amortization | C1: ='DATA ENTRY'!C15 -> 9338.1996
B2: Timeline | C2: 0 | D2: 1 | E2: 2 | F2: 3 | G2: 4 | H2: 5 | I2: 6 | J2: 7 | K2: 8 | L2: 9 | M2: 10 | N2: 11 | O2: 12
B3: GROSS AMOUNT | C3: ='DATA ENTRY'!C4 -> 112058.4
A4: 41 | B4: LOAN AMOUNT | C4: ='DATA ENTRY'!C12 -> 107635.75 | D4: =-$C1 -> -9338.1996 | E4: =-$C1 -> -9338.1996 | F4: =-$C1 -> -9338.1996 | G4: =-$C1 -> -9338.1996 | H4: =-$C1 -> -9338.1996 | I4: =-$C1 -> -9338.1996 | J4: =-$C1 -> -9338.1996 | K4: =-$C1 -> -9338.1996 | ... O4: =-$C1 -> -9338.1996
B5: Service Fee | C5: ='DATA ENTRY'!C7 -> 6545
B6: Insurance | C6: ='DATA ENTRY'!C8 -> 1122
B7: CapCon | C7: 22000
B8: membership fee | C8: ='DATA ENTRY'!C10 -> 300
B9: Advance Interest | C9: ='DATA ENTRY'!C11 -> 1168.75
B10: NET PROCEEDS/CASH FLOW | C10: =C4-C5-C6-C7-C8-C9 -> 76500
B12: Interest Rate of Return | C12: =IRR(C4:O4) -> 0.00625 | D12: =C12/5 -> 0.00125
B14: Loan Balance
B15: Monthly Interest Rate | C15: ='[3]Data Entry'!D12/12 -> 0.0070833333
B16: Effective Interest Rate | C16: ='[3]Data Entry'!D13 -> 0.08855359
B17: Term | C17: 12 MON THS
C20: LOAN LEDGER CARD
C22: Name: | D22: SURAIDA S. ANOG | G22: Loan Voucher No. | H22: LV-054
C23: Serial Nr: | D23: 648091 | E23: Address: | F23: PUROK 4 GUIANG, GAMU, ISABELA
C24: Posting date | D24: Date of Loan: | E24: 45908 | F24: Maturity Date | G24: =B39 -> 46273 | K24: PEOPLE'S MULTI-PURPOSE COOPERATIVE
D25: Term: | E25: 12 | F25: MOS | K25: 20-E 2nd Camarilla St. corner 15th Ave., Brgy. San Roque, Murphy Cubao, Quezon City | X25: 20-E 2nd Camarilla St corner 15th Avenue,
D26: Loan | E26: Installment | F26: Principal | G26: EIR | H26: Balance | X26: Brgy San Roque, Murphy Cubao, Quezon City
D27: Month 0 | H27: =C4 -> 107635.75 | K27: LOAN RELEASE VOUCHER | X27: Mobile No. (+63)953-033-1580 (GLOBE)
B28: =DATE(YEAR(E$24),MONTH(E$24)+D28+0,DAY(E$24)) -> 45938 | C28: =TEXT(B28,"mmm-yyyy") -> Oct-2025 | D28: 1 | E28: =C$1 -> 9338.1996 | F28: =E28-G28 -> 8665.4762 | G28: =H27*C$12 -> 672.72344 | H28: =H27-F28 -> 98970.274
B29: =DATE(YEAR(E$24),MONTH(E$24)+D29+0,DAY(E$24)) -> 45969 | C29: =TEXT(B29,"mmm-yyyy") -> Nov-2025 | D29: 2 | E29: =C$1 -> 9338.1996 | F29: =E29-G29 -> 8719.6354 | G29: =H28*C$12 -> 618.56421 | H29: =H28-F29 -> 90250.638 | R29: Date: | S29: =E24 -> 45908 | X29: LOAN APPLICATION FORM
B30: =DATE(YEAR(E$24),MONTH(E$24)+D30+0,DAY(E$24)) -> 45999 | C30: =TEXT(B30,"mmm-yyyy") -> Dec-2025 | D30: 3 | E30: =C$1 -> 9338.1996 | F30: =E30-G30 -> 8774.1331 | G30: =H29*C$12 -> 564.06649 | H30: =H29-F30 -> 81476.505 | R30: LV No: | S30: =H22 -> LV-054 | AU30: Date: | AW30: 0 | AX30: 9 | AY30: 0 | AZ30: 8 | BA30: 2 | BB30: 0 | BC30: 2 | BD30: 5
B31: =DATE(YEAR(E$24),MONTH(E$24)+D31+0,DAY(E$24)) -> 46030 | C31: =TEXT(B31,"mmm-yyyy") -> Jan-2026 | D31: 4 | E31: =C$1 -> 9338.1996 | F31: =E31-G31 -> 8828.9715 | G31: =H30*C$12 -> 509.22816 | H31: =H30-F31 -> 72647.534 | AW31: m | AX31: m | AY31: d | AZ31: d | BA31: y | BB31: y | BC31: y | BD31: y
B32: =DATE(YEAR(E$24),MONTH(E$24)+D32+0,DAY(E$24)) -> 46061 | C32: =TEXT(B32,"mmm-yyyy") -> Feb-2026 | D32: 5 | E32: =C$1 -> 9338.1996 | F32: =E32-G32 -> 8884.1525 | G32: =H31*C$12 -> 454.04709 | H32: =H31-F32 -> 63763.381 | K32: Name of Borrower: | N32: =D22 -> SURAIDA S. ANOG | X32: APPLICATION TYPE | AE32: LOAN CLASSIFICATION | AM32: TERM | AT32: RELEASE OF LOAN PROCEEDS
B33: =DATE(YEAR(E$24),MONTH(E$24)+D33+0,DAY(E$24)) -> 46089 | C33: =TEXT(B33,"mmm-yyyy") -> Mar-2026 | D33: 6 | E33: =C$1 -> 9338.1996 | F33: =E33-G33 -> 8939.6785 | G33: =H32*C$12 -> 398.52113 | H33: =H32-F33 -> 54823.703 | K33: Serial No.: | N33: =D23 -> 648091 | Y33: New | AF33: Salary Loan | AN33: 12 Months | AU33: CHEQUE
B34: =DATE(YEAR(E$24),MONTH(E$24)+D34+0,DAY(E$24)) -> 46120 | C34: =TEXT(B34,"mmm-yyyy") -> Apr-2026 | D34: 7 | E34: =C$1 -> 9338.1996 | F34: =E34-G34 -> 8995.5515 | G34: =H33*C$12 -> 342.64814 | H34: =H33-F34 -> 45828.151 | K34: Address: | N34: =F23 -> PUROK 4 GUIANG, GAMU, ISABELA | Y34: Renewal | AF34: Pension Loan | AN34: 24 Months | AU34: Bank Electronic Transfer to Borrowers Account
B35: =DATE(YEAR(E$24),MONTH(E$24)+D35+0,DAY(E$24)) -> 46150 | C35: =TEXT(B35,"mmm-yyyy") -> May-2026 | D35: 8 | E35: =C$1 -> 9338.1996 | F35: =E35-G35 -> 9051.7737 | G35: =H34*C$12 -> 286.42595 | H35: =H34-F35 -> 36776.378 | Y35: Additional | AF35: Emergency | AN35: 36 Months | AU35: Others:
B36: =DATE(YEAR(E$24),MONTH(E$24)+D36+0,DAY(E$24)) -> 46181 | C36: =TEXT(B36,"mmm-yyyy") -> Jun-2026 | D36: 9 | E36: =C$1 -> 9338.1996 | F36: =E36-G36 -> 9108.3473 | G36: =H35*C$12 -> 229.85236 | H36: =H35-F36 -> 27668.03 | L36: Principal Amount | R36: =C4 -> 107635.75 | Y36: Reloan | AF36: Health Assistance Loan | AN36: 48 Months
B37: =DATE(YEAR(E$24),MONTH(E$24)+D37+0,DAY(E$24)) -> 46211 | C37: =TEXT(B37,"mmm-yyyy") -> Jul-2026 | D37: 10 | E37: =C$1 -> 9338.1996 | F37: =E37-G37 -> 9165.2744 | G37: =H36*C$12 -> 172.92519 | H37: =H36-F37 -> 18502.756 | Y37: Restructure | AF37: Educational Loan | AN37: 60 Months
B38: =DATE(YEAR(E$24),MONTH(E$24)+D38+0,DAY(E$24)) -> 46242 | C38: =TEXT(B38,"mmm-yyyy") -> Aug-2026 | D38: 11 | E38: =C$1 -> 9338.1996 | F38: =E38-G38 -> 9222.5574 | G38: =H37*C$12 -> 115.64222 | H38: =H37-F38 -> 9280.1984 | L38: (-) | M38: Balance Old Loan(s) | R38: =-C14 -> 0 | AF38: Others: | AH38: SMALL BUSINESS LOAN | AN38: Others:
B39: =DATE(YEAR(E$24),MONTH(E$24)+D39+0,DAY(E$24)) -> 46273 | C39: =TEXT(B39,"mmm-yyyy") -> Sep-2026 | D39: 12 | E39: =C$1 -> 9338.1996 | F39: =E39-G39 -> 9280.1984 | G39: =H38*C$12 -> 58.00124 | H39: =H38-F39 -> -5.0931703e-11 | L39: (-) | M39: Membership Fee: | R39: =-C8 -> -300 | X39: AMOUNT APPLIED: | AB39: =R44 -> 76500 | AN39: MONTHLY AMORTIZATION: | AT39: =C1 -> 9338.1996
E40: =SUM(E28:E39) -> 112058.4 | F40: =SUM(F28:F39) -> 107635.75 | G40: =SUM(G28:G39) -> 4422.6456 | L40: (-) | M40: Paid up Capital: | R40: =-C7 -> -22000
L41: (-) | M41: Service Fee | R41: =-C5 -> -6545 | X41: LOAN ID: | AF41: DEDUCTION CODE: | AR41: LOAN PURPOSE:
L42: (-) | M42: Insurance Premium - Paramount | R42: =-C6 -> -1122 | X42: MEM ID: | AG42: Regular Member | AS42: Old Member
L43: (-) | M43: Advance Interest | R43: =-C9 -> -1168.75 | AG43: Associate Member | AS43: New Member
L44: NET PROCEEDS (Php): | R44: =SUM(R36:T43) -> 76500 | X44: BORROWER'S INFORMATION
X45: ANOG | AD45: SURAIDA | AN45: SASAPAN
K46: PAYMENT | X46: (LAST NAME) | AD46: (FIRST NAME) | AN46: (MIDDLE NAME) | AZ46: (SUFFIX)
X47: Rank/Position: | AD47: Serial No.: | AI47: Branch of Service: | AO47: Date of Appointment: | AW47: Date of Retirement:
L48: Term of loan in months: | R48: 12 | T48: month(s) | X48: BENEFICIARY | AD48: =N33 -> 648091 | AI48: PMPC
L49: Monthly Amortization | R49: =C1 -> 9338.1996 | AO49: m | AP49: m | AQ49: d | AR49: d | AS49: y | AT49: y | AU49: y | AV49: y | AW49: m | AX49: m | AY49: d | AZ49: d | BA49: y | BB49: y | BC49: y | BD49: y
L50: First Payment Due On: | R50: =B28 -> 45938
L51: Maturity: | R51: =B39 -> 46273 | X51: Length of Service: | AE51: Date of Birth: | AJ51: Age: | AK51: 60 | AM51: Civil Status: | AR51: Single | AU51: Widower | AX51: Home Phone No.
L52: EIR (%): | R52: =C16 -> 0.08855359 | X52: 1 YEAR | AE52: MARCH 14 1965 | AR52: Married | AU52: Separated
L53: Interest Rate per Month (%): | R53: =C15 -> 0.0070833333 | X53: Unit Assignment: | AE53: Unit/Office/Business Address: | AX53: Unit/Office Telephone No/s:
X55: AFP/Company ID No: | AG55: Email Address: | AT55: Tax Identification No/s:
K56: Certified & Corrected by: | R56: Verified by: | AW56: - | BA56: -
X57: Present Address: | AB57: =F23 -> PUROK 4 GUIANG, GAMU, ISABELA
X58: NOTIFICATION CLAUSE
K60: ALEXANDER A. FERIA JR | R60: ALEXANDER A. FERIA JR | Y60: I hereby acknowledge and authorized the People's Multi-Purpose Cooperative (PMPC) for the following: 1) the regular submission and disclosure
K61: Processor | R61: Verifier/PELVAMS Liason | X61: of my basic credit data (as defined under Republic Act Nr 9510 and its Implementing Rules and Regulations) to the Credit Information Corporation (CIC)
X62: as well as any updates or corrections thereof; and 2) the sharing of my basic data and with other lenders authorized by the CIC, and credit reporting
X63: agencies duly accredited by the CIC.
AU64: =K69 -> SURAIDA S. ANOG
AU65: Printed Name & Signature of Borrower
K66: Received By: | R66: Approved By: | X66: CERTIFICATION
Y68: I hereby certify that the applicant is assigned to this Office; is not on leave without pay; has no pending case; and, that all information he/she
K69: =N32 -> SURAIDA S. ANOG | P69: COL.ALEXANDER L. FERIA (RET) CPA MNSA | X69: provided is true and correct.
K70: Signature Over Printed Name/Date | R70: President
X72: CERTIFYING OFFICER | AG72: DESIGNATION | AP72: OFFICE | AX72: CONTACT NUMBER
X73: (Signature Over Printed Name)
X74: CREDIT HISTORY
X75: Loan ID | AA75: Date Granted | AE75: Loan Granted | AJ75: Term | AM75: Maturity Date | AR75: MA | AU75: Status/Remarks | AZ75: Principal Balance
N79: 20-E 15th Avenue Corner, 2nd Camarilla St.
M80: Brgy. San Roque, Murphy, Cubao, Quezon City
N81: Mobile Number: 09194983770 / 09530331580 | X81: LOAN APPROVAL
X82: Loan Amount: | AC82: MA: | AG82: Term: | AK82: Required NTHP: | AR82: NTHP after MA | AW82: Total Loan Exposure:
M83: AUTHORIZATION FOR ACTIVE DEDUCTION | X83: =C4 -> 107635.75 | AC83: =AT39 -> 9338.1996 | AG83: =E25 -> 12 | AK83: 650 | AW83: =C3 -> 112058.4
X84: PROCESSED & VERIFIED BY:
R85: =S29 -> 45908
R86: DATE | AJ86: =K60 -> ALEXANDER A. FERIA JR
W87: SIGNATURE OVER PRINTED NAME
K90: To whom it may concern: | X90: RECOMMEND APPROVAL/DISAPPROVAL: | AO90: APPROVED/DISAPPROVED:
K92: I hereby authorize that the amount of | O92: Five Thousand Six Hundred Ten and 02/100 (Php 5,610.02) | AB92: JEFFRAE A. SAPLA | AS92: COL.ALEXANDER L. FERIA (RET)CPA MNSA
K93: for a period | M93: months with the total amount of | P93: Two Hundred One Thousand Nine Hundred | X93: SIGNATURE OVER PRINTED NAME | AO93: SIGNATURE OVER PRINTED NAME
K94: Sixty and 56/100
X100: PROMISORY NOTE NO: | AL100: =H22 -> LV-054
Y101: FOR VALUE RECEIVED, the undersigned promise to pay the People's Multi-Purpose Cooperative (PMPC) the sum of Php | AY101: =AW83 -> 112058.4
AA102: in | AB102: 12 | AC102: equal monthly installments amounting to Php | AN102: =AC83 -> 9338.1996 | AR102: each, to be paid on the 28th day of every month starting on
X103: =B28 -> 45938 | AB103: / Single Payment of due on unpaid installments from maturity will bear charges on unpaid principal
X104: at the rate of 2% per month as penatly thereof.
X105: I hereby waive presentment for payment and notice of dishonor. PMPC may accept partial payment reserving its right of recourse against me. PMPC is hereby authorized and empowered to set off or apply without notice what is due under this Note from whatever funds I have in the Cooperative.
X108: It is further agreed that in case of separation from the service of whatever cause, the unpaid balance with its accumulated surcharges and interest as stipulated above be deducted from my last paymnet, commutation of leave/furlough and/or from my pension.
X111: It is further agreed that when installments are not paid when due and payable, the whole of the principal sum remaining unpaid shall forthwith become due and payable at the election of the Cooperative. I promise and agree to pay for a reasonable attorney's fee if this note is not paid according to its legal tenor and effect when palced in a lawyer's hand for collection. In case litigation, venue shall be vested in the competent court as may be allowed by the Rules of Court at the sole option of PMPC.
X116: Further, I hereby agree and authorized PMPC to encumber, assign or sell to any person or entity any right which it may have under thi Note, and/or any assignment, mortgage lien, pledge or other encumbrances constituted in favor of PMPC pursuant to the provisions of this Note if any. The consent herein granted is recognized and acknowledged by me/us as a waiver, to all intent and purposes of whatever right I may have to notice of actual encumbrance/ assignment.
AM120: Military/Pensioners ID
AM121: Employee's ID/Office ID
AM122: Driver's License
Z123: =AU64 -> SURAIDA S. ANOG | AM123: Others: | AO123: UMID I.D.
X124: Signature over Printed Name
X126: ID No:
X127: Expiration Date: | AT127: LEFT THUMBMARK | AZ127: RIGHT THUMBMARK
X130: ACKNOWLEDGEMENT
X132: REPUBLIC OF THE PHILIPPINES
X133: (20-E, 2nd Camarilla St., Cor. 15th Ave.,BRGY San Roque, Murphy Cubao, Quezon City) S.S
X135: BEFORE ME, a Notary Public for and in Cubao, Quezon City this _______ day of _______________, 20_____, personally appeared __________________
X136: __________, who presented to me the Identification Cards mentioned above, known to me to be the same person who executed the forgoing application for loan and promissory note and acknowledged that the same as his/her true act and deed and took oath that the statement herein are true and correct and that the application is made for the purpose under consideration.
...

Sheet LRV2YEAR
B1: Amortization | C1: ='DATA ENTRY'!D15 -> 4936.7326 | T1: pvap
B2: Timeline | C2: 0 | D2: 1 | E2: 2 | F2: 3 | G2: 4 | H2: 5 | I2: 6 | J2: 7 | K2: 8 | L2: 9 | M2: 10 | N2: 11 | O2: 12 | P2: 13 | Q2: 14 | R2: 15 | S2: 16 | T2: 17 | U2: 18 | V2: 19 | W2: 20 | X2: 21 | Y2: 22 | Z2: 23 | AA2: 24 | AB2: 25 | AC2: 26 | AD2: 27 | AE2: 28 | AF2: 29 | AG2: 30 | AH2: 31 | AI2: 32 | AJ2: 33 | AK2: 34 | AL2: 35 | AM2: 36
B3: GROSS AMOUNT | C3: ='DATA ENTRY'!D4 -> 118481.58
A4: 41 | B4: LOAN AMOUNT | C4: ='DATA ENTRY'!D12 -> 109021.87
B5: Service Fee | C5: ='DATA ENTRY'!D7 -> 7012.5
B6: Insurance | C6: ='DATA ENTRY'!D8 -> 2244
B7: CapCon | C7: ='DATA ENTRY'!D9 -> 5000
B8: membership fee | C8: ='DATA ENTRY'!D10 -> 0
B9: Advance Interest | C9: ='DATA ENTRY'!D11 -> 1265.3667
B10: NET PROCEEDS/CASH FLOW | C10: =C4-C5-C6-C7-C8-C9 -> 93500 | D10: =-$C1 -> -4936.7326 | E10: =-$C1 -> -4936.7326 | F10: =-$C1 -> -4936.7326 | G10: =-$C1 -> -4936.7326 | H10: =-$C1 -> -4936.7326 | I10: =-$C1 -> -4936.7326 | J10: =-$C1 -> -4936.7326 | K10: =-$C1 -> -4936.7326 | ... AM10: =-$C1 -> -4936.7326
B12: Interest Rate of Return | C12: =IRR(C10:AM10) -> 0.039880345 | D12: =C12/5 -> 0.0079760691
B14: Loan Balance
B15: Monthly Interest Rate | C15: ='[3]Data Entry'!D12/12 -> 0.0070833333
B16: Effective Interest Rate | C16: ='[3]Data Entry'!D13 -> 0.08855359
B17: Term | C17: 24
C20: LOAN LEDGER CARD
C22: Name: | D22: MADONNA LYN ORTEGA MARQUEZ | G22: Loan Voucher No. | H22: CDEA-001
C23: Serial Nr: | D23: 2004-023 | E23: Address: | F23: BLK 1 LOT 8 JOSHUA ST., BEYOND HOMES BRGY SAN FRANCISCO, GENERAL TRIAS, CAVITE
C24: Posting date | D24: Date of Loan: | E24: 45701 | F24: Maturity Date | G24: =B51 -> 46431 | K24: PEOPLE'S MULTI-PURPOSE COOPERATIVE
D25: Term: | E25: 36 | F25: MOS | K25: 20-E 2nd Camarilla St. corner 15th Ave., Brgy. San Roque, Murphy Cubao, Quezon City | X25: 20-E 2nd Camarilla St corner 15th Avenue,
D26: Loan | E26: Installment | F26: Principal | G26: EIR | H26: Balance | X26: Brgy San Roque, Murphy Cubao, Quezon City
D27: Month 0 | H27: =C10 -> 93500 | K27: LOAN RELEASE VOUCHER | X27: Mobile No. (+63)953-033-1580 (GLOBE)
B28: =DATE(YEAR(E$24),MONTH(E$24)+D28+0,DAY(E$24)) -> 45729 | C28: =TEXT(B28,"mmm-yyyy") -> Mar-2025 | D28: 1 | E28: =C$1 -> 4936.7326 | F28: =E28-G28 -> 1207.9203 | G28: =H27*C$12 -> 3728.8123 | H28: =H27-F28 -> 92292.08
B29: =DATE(YEAR(E$24),MONTH(E$24)+D29+0,DAY(E$24)) -> 45760 | C29: =TEXT(B29,"mmm-yyyy") -> Apr-2025 | D29: 2 | E29: =C$1 -> 4936.7326 | F29: =E29-G29 -> 1256.0926 | G29: =H28*C$12 -> 3680.64 | H29: =H28-F29 -> 91035.987 | R29: Date: | S29: =E24 -> 45701 | X29: LOAN APPLICATION FORM
B30: =DATE(YEAR(E$24),MONTH(E$24)+D30+0,DAY(E$24)) -> 45790 | C30: =TEXT(B30,"mmm-yyyy") -> May-2025 | D30: 3 | E30: =C$1 -> 4936.7326 | F30: =E30-G30 -> 1306.186 | G30: =H29*C$12 -> 3630.5466 | H30: =H29-F30 -> 89729.801 | R30: LV No: | S30: =D23 -> 2004-023 | AU30: Date: | AW30: 0 | AX30: 2 | AY30: 1 | AZ30: 3 | BA30: 2 | BB30: 0 | BC30: 2 | BD30: 5
B31: =DATE(YEAR(E$24),MONTH(E$24)+D31+0,DAY(E$24)) -> 45821 | C31: =TEXT(B31,"mmm-yyyy") -> Jun-2025 | D31: 4 | E31: =C$1 -> 4936.7326 | F31: =E31-G31 -> 1358.2772 | G31: =H30*C$12 -> 3578.4555 | H31: =H30-F31 -> 88371.524 | AW31: m | AX31: m | AY31: d | AZ31: d | BA31: y | BB31: y | BC31: y | BD31: y
B32: =DATE(YEAR(E$24),MONTH(E$24)+D32+0,DAY(E$24)) -> 45851 | C32: =TEXT(B32,"mmm-yyyy") -> Jul-2025 | D32: 5 | E32: =C$1 -> 4936.7326 | F32: =E32-G32 -> 1412.4457 | G32: =H31*C$12 -> 3524.2869 | H32: =H31-F32 -> 86959.078 | K32: Name of Borrower: | N32: =D22 -> MADONNA LYN ORTEGA MARQUEZ | X32: APPLICATION TYPE | AE32: LOAN CLASSIFICATION | AM32: TERM | AT32: RELEASE OF LOAN PROCEEDS
B33: =DATE(YEAR(E$24),MONTH(E$24)+D33+0,DAY(E$24)) -> 45882 | C33: =TEXT(B33,"mmm-yyyy") -> Aug-2025 | D33: 6 | E33: =C$1 -> 4936.7326 | F33: =E33-G33 -> 1468.7746 | G33: =H32*C$12 -> 3467.9581 | H33: =H32-F33 -> 85490.303 | K33: Serial No.: | N33: =D23 -> 2004-023 | Y33: New | AF33: Salary Loan | AN33: 12 Months | AU33: Check
B34: =DATE(YEAR(E$24),MONTH(E$24)+D34+0,DAY(E$24)) -> 45913 | C34: =TEXT(B34,"mmm-yyyy") -> Sep-2025 | D34: 7 | E34: =C$1 -> 4936.7326 | F34: =E34-G34 -> 1527.3498 | G34: =H33*C$12 -> 3409.3828 | H34: =H33-F34 -> 83962.954 | K34: Address: | N34: =F23 -> BLK 1 LOT 8 JOSHUA ST., BEYOND HOMES BRGY SAN FRANCISCO, GENERAL TRIAS, CAVITE | Y34: Renewal | AF34: Pension Loan | AN34: 24 Months | AU34: Bank Electronic Transfer to Borrowers Account
B35: =DATE(YEAR(E$24),MONTH(E$24)+D35+0,DAY(E$24)) -> 45943 | C35: =TEXT(B35,"mmm-yyyy") -> Oct-2025 | D35: 8 | E35: =C$1 -> 4936.7326 | F35: =E35-G35 -> 1588.261 | G35: =H34*C$12 -> 3348.4716 | H35: =H34-F35 -> 82374.693 | Y35: Additional | AF35: Emergency | AN35: 36 Months | AU35: Others:
B36: =DATE(YEAR(E$24),MONTH(E$24)+D36+0,DAY(E$24)) -> 45974 | C36: =TEXT(B36,"mmm-yyyy") -> Nov-2025 | D36: 9 | E36: =C$1 -> 4936.7326 | F36: =E36-G36 -> 1651.6014 | G36: =H35*C$12 -> 3285.1312 | H36: =H35-F36 -> 80723.091 | L36: Principal Amount | R36: =C4 -> 109021.87 | Y36: Reloan | AF36: Health Assistance Loan | AN36: 48 Months
B37: =DATE(YEAR(E$24),MONTH(E$24)+D37+0,DAY(E$24)) -> 46004 | C37: =TEXT(B37,"mmm-yyyy") -> Dec-2025 | D37: 10 | E37: =C$1 -> 4936.7326 | F37: =E37-G37 -> 1717.4679 | G37: =H36*C$12 -> 3219.2648 | H37: =H36-F37 -> 79005.623 | Y37: Restructure | AF37: Educational Loan | AN37: 60 Months
B38: =DATE(YEAR(E$24),MONTH(E$24)+D38+0,DAY(E$24)) -> 46035 | C38: =TEXT(B38,"mmm-yyyy") -> Jan-2026 | D38: 11 | E38: =C$1 -> 4936.7326 | F38: =E38-G38 -> 1785.9611 | G38: =H37*C$12 -> 3150.7715 | H38: =H37-F38 -> 77219.662 | L38: (-) | M38: Balance Old Loan(s) | R38: =-C14 -> 0 | AF38: Others: | AN38: Others:
B39: =DATE(YEAR(E$24),MONTH(E$24)+D39+0,DAY(E$24)) -> 46066 | C39: =TEXT(B39,"mmm-yyyy") -> Feb-2026 | D39: 12 | E39: =C$1 -> 4936.7326 | F39: =E39-G39 -> 1857.1858 | G39: =H38*C$12 -> 3079.5468 | H39: =H38-F39 -> 75362.476 | L39: (-) | M39: Membership Fee: | R39: =-C8 -> 0 | X39: AMOUNT APPLIED: | AB39: ='[3]Data Entry'!E4 -> 150000 | AN39: MONTHLY AMORTIZATION: | AT39: =R49 -> 4936.7326
B40: =DATE(YEAR(E$24),MONTH(E$24)+D40+0,DAY(E$24)) -> 46094 | C40: =TEXT(B40,"mmm-yyyy") -> Mar-2026 | D40: 13 | E40: =C$1 -> 4936.7326 | F40: =E40-G40 -> 1931.2511 | G40: =H39*C$12 -> 3005.4816 | H40: =H39-F40 -> 73431.225 | L40: (-) | M40: Paid up Capital: | R40: =-C7 -> -5000
B41: =DATE(YEAR(E$24),MONTH(E$24)+D41+0,DAY(E$24)) -> 46125 | C41: =TEXT(B41,"mmm-yyyy") -> Apr-2026 | D41: 14 | E41: =C$1 -> 4936.7326 | F41: =E41-G41 -> 2008.27 | G41: =H40*C$12 -> 2928.4626 | H41: =H40-F41 -> 71422.955 | L41: (-) | M41: Service Fee | R41: =-C5 -> -7012.5 | X41: LOAN ID: | AF41: DEDUCTION CODE: | AR41: LOAN PURPOSE:
B42: =DATE(YEAR(E$24),MONTH(E$24)+D42+0,DAY(E$24)) -> 46155 | C42: =TEXT(B42,"mmm-yyyy") -> May-2026 | D42: 15 | E42: =C$1 -> 4936.7326 | F42: =E42-G42 -> 2088.3605 | G42: =H41*C$12 -> 2848.3721 | H42: =H41-F42 -> 69334.595 | L42: (-) | M42: Insurance Premium - Paramount | R42: =-C6 -> -2244 | X42: MEM ID: | AG42: Regular Member | AS42: Old Member
B43: =DATE(YEAR(E$24),MONTH(E$24)+D43+0,DAY(E$24)) -> 46186 | C43: =TEXT(B43,"mmm-yyyy") -> Jun-2026 | D43: 16 | E43: =C$1 -> 4936.7326 | F43: =E43-G43 -> 2171.6451 | G43: =H42*C$12 -> 2765.0876 | H43: =H42-F43 -> 67162.95 | L43: (-) | M43: Advance Interest | R43: =-C9 -> -1265.3667 | AG43: Associate Member | AS43: New Member
B44: =DATE(YEAR(E$24),MONTH(E$24)+D44+0,DAY(E$24)) -> 46216 | C44: =TEXT(B44,"mmm-yyyy") -> Jul-2026 | D44: 17 | E44: =C$1 -> 4936.7326 | F44: =E44-G44 -> 2258.251 | G44: =H43*C$12 -> 2678.4816 | H44: =H43-F44 -> 64904.699 | L44: NET PROCEEDS (Php): | R44: =SUM(R36:T43) -> 93500 | X44: BORROWER'S INFORMATION
B45: =DATE(YEAR(E$24),MONTH(E$24)+D45+0,DAY(E$24)) -> 46247 | C45: =TEXT(B45,"mmm-yyyy") -> Aug-2026 | D45: 18 | E45: =C$1 -> 4936.7326 | F45: =E45-G45 -> 2348.3108 | G45: =H44*C$12 -> 2588.4218 | H45: =H44-F45 -> 62556.388 | X45: MARQUEZ | AD45: MADONNA LYN | AN45: ORTEGA
B46: =DATE(YEAR(E$24),MONTH(E$24)+D46+0,DAY(E$24)) -> 46278 | C46: =TEXT(B46,"mmm-yyyy") -> Sep-2026 | D46: 19 | E46: =C$1 -> 4936.7326 | F46: =E46-G46 -> 2441.9623 | G46: =H45*C$12 -> 2494.7704 | H46: =H45-F46 -> 60114.426 | K46: PAYMENT | X46: (LAST NAME) | AD46: (FIRST NAME) | AN46: (MIDDLE NAME) | AZ46: (SUFFIX)
B47: =DATE(YEAR(E$24),MONTH(E$24)+D47+0,DAY(E$24)) -> 46308 | C47: =TEXT(B47,"mmm-yyyy") -> Oct-2026 | D47: 20 | E47: =C$1 -> 4936.7326 | F47: =E47-G47 -> 2539.3486 | G47: =H46*C$12 -> 2397.3841 | H47: =H46-F47 -> 57575.077 | X47: Rank/Position: | AD47: Serial No.: | AI47: Branch of Service: | AO47: Date of Appointment: | AW47: Date of Retirement:
B48: =DATE(YEAR(E$24),MONTH(E$24)+D48+0,DAY(E$24)) -> 46339 | C48: =TEXT(B48,"mmm-yyyy") -> Nov-2026 | D48: 21 | E48: =C$1 -> 4936.7326 | F48: =E48-G48 -> 2640.6187 | G48: =H47*C$12 -> 2296.114 | H48: =H47-F48 -> 54934.458 | L48: Term of loan in months: | R48: =E25 -> 36 | T48: month(s) | X48: HRMD IV | AD48: 2004-023 OCD | AI48: OCD | AO48: 0 | AP48: 7 | AQ48: 1 | AR48: 9 | AS48: 2 | AT48: 0 | AU48: 0 | AV48: 4 | AW48: 1 | AX48: 0 | AY48: 0 | AZ48: 1 | BA48: 2 | BB48: 0 | BC48: 4 | BD48: 6
B49: =DATE(YEAR(E$24),MONTH(E$24)+D49+0,DAY(E$24)) -> 46369 | C49: =TEXT(B49,"mmm-yyyy") -> Dec-2026 | D49: 22 | E49: =C$1 -> 4936.7326 | F49: =E49-G49 -> 2745.9275 | G49: =H48*C$12 -> 2190.8052 | H49: =H48-F49 -> 52188.531 | L49: Monthly Amortization | R49: =C1 -> 4936.7326 | AO49: m | AP49: m | AQ49: d | AR49: d | AS49: y | AT49: y | AU49: y | AV49: y | AW49: m | AX49: m | AY49: d | AZ49: d | BA49: y | BB49: y | BC49: y | BD49: y
B50: =DATE(YEAR(E$24),MONTH(E$24)+D50+0,DAY(E$24)) -> 46400 | C50: =TEXT(B50,"mmm-yyyy") -> Jan-2027 | D50: 23 | E50: =C$1 -> 4936.7326 | F50: =E50-G50 -> 2855.436 | G50: =H49*C$12 -> 2081.2966 | H50: =H49-F50 -> 49333.095 | L50: First Payment Due On: | R50: =B28 -> 45729
B51: =DATE(YEAR(E$24),MONTH(E$24)+D51+0,DAY(E$24)) -> 46431 | C51: =TEXT(B51,"mmm-yyyy") -> Feb-2027 | D51: 24 | E51: =C$1 -> 4936.7326 | F51: =E51-G51 -> 2969.3118 | G51: =H50*C$12 -> 1967.4209 | H51: =H50-F51 -> 46363.783 | L51: Maturity: | R51: =B63 -> 46796 | X51: Length of Service: | AE51: Date of Birth: | AJ51: Age: | AK51: 43 | AM51: Civil Status: | AR51: Single | AU51: Widower | AX51: Home Phone No.
B52: =DATE(YEAR(E$24),MONTH(E$24)+D52+0,DAY(E$24)) -> 46459 | C52: =TEXT(B52,"mmm-yyyy") -> Mar-2027 | D52: 25 | E52: =C$1 -> 4936.7326 | F52: =E52-G52 -> 3087.729 | G52: =H51*C$12 -> 1849.0037 | H52: =H51-F52 -> 43276.054 | L52: EIR (%): | R52: =C16 -> 0.08855359 | X52: 20 YEARS AND 6 MOS | AE52: OCT 1 1981 | AR52: Married | AU52: Separated
B53: =DATE(YEAR(E$24),MONTH(E$24)+D53+0,DAY(E$24)) -> 46490 | C53: =TEXT(B53,"mmm-yyyy") -> Apr-2027 | D53: 26 | E53: =C$1 -> 4936.7326 | F53: =E53-G53 -> 3210.8687 | G53: =H52*C$12 -> 1725.864 | H53: =H52-F53 -> 40065.186 | L53: Interest Rate per Month (%): | R53: ='[3]Data Entry'!E12/12 -> 0.0069166667 | X53: Unit Assignment: | AE53: Unit/Office/Business Address: | AX53: Unit/Office Telephone No/s:
B54: =DATE(YEAR(E$24),MONTH(E$24)+D54+0,DAY(E$24)) -> 46520 | C54: =TEXT(B54,"mmm-yyyy") -> May-2027 | D54: 27 | E54: =C$1 -> 4936.7326 | F54: =E54-G54 -> 3338.9192 | G54: =H53*C$12 -> 1597.8134 | H54: =H53-F54 -> 36726.266 | X54: HRMDD - OCD | AE54: CAMP AGUINALDO QUEZON CITY | AX54: 2912596
B55: =DATE(YEAR(E$24),MONTH(E$24)+D55+0,DAY(E$24)) -> 46551 | C55: =TEXT(B55,"mmm-yyyy") -> Jun-2027 | D55: 28 | E55: =C$1 -> 4936.7326 | F55: =E55-G55 -> 3472.0765 | G55: =H54*C$12 -> 1464.6562 | H55: =H54-F55 -> 33254.19 | X55: AFP/Company ID No: | AG55: Email Address: | AT55: Tax Identification No/s:
B56: =DATE(YEAR(E$24),MONTH(E$24)+D56+0,DAY(E$24)) -> 46581 | C56: =TEXT(B56,"mmm-yyyy") -> Jul-2027 | D56: 29 | E56: =C$1 -> 4936.7326 | F56: =E56-G56 -> 3610.5441 | G56: =H55*C$12 -> 1326.1886 | H56: =H55-F56 -> 29643.646 | K56: Certified & Corrected by: | R56: Verified by: | X56: 2004-023 OCD | AG56: madomarquez819@gmail.com | AT56: 3 | AU56: 0 | AV56: 0 | AW56: - | AX56: 1 | AY56: 6 | AZ56: 6 | BA56: - | BB56: 0 | BC56: 1 | BD56: 1
B57: =DATE(YEAR(E$24),MONTH(E$24)+D57+0,DAY(E$24)) -> 46612 | C57: =TEXT(B57,"mmm-yyyy") -> Aug-2027 | D57: 30 | E57: =C$1 -> 4936.7326 | F57: =E57-G57 -> 3754.5338 | G57: =H56*C$12 -> 1182.1988 | H57: =H56-F57 -> 25889.112 | X57: Present Address: | AB57: BLK 1 LOT 8 JOSHUA ST., BEYOND HOMES BRGY SAN FRANCISCO, GENERAL TRIAS, CAVITE
B58: =DATE(YEAR(E$24),MONTH(E$24)+D58+0,DAY(E$24)) -> 46643 | C58: =TEXT(B58,"mmm-yyyy") -> Sep-2027 | D58: 31 | E58: =C$1 -> 4936.7326 | F58: =E58-G58 -> 3904.2659 | G58: =H57*C$12 -> 1032.4667 | H58: =H57-F58 -> 21984.846 | X58: NOTIFICATION CLAUSE
B59: =DATE(YEAR(E$24),MONTH(E$24)+D59+0,DAY(E$24)) -> 46673 | C59: =TEXT(B59,"mmm-yyyy") -> Oct-2027 | D59: 32 | E59: =C$1 -> 4936.7326 | F59: =E59-G59 -> 4059.9694 | G59: =H58*C$12 -> 876.76325 | H59: =H58-F59 -> 17924.877
B60: =DATE(YEAR(E$24),MONTH(E$24)+D60+0,DAY(E$24)) -> 46704 | C60: =TEXT(B60,"mmm-yyyy") -> Nov-2027 | D60: 33 | E60: =C$1 -> 4936.7326 | F60: =E60-G60 -> 4221.8824 | G60: =H59*C$12 -> 714.85027 | H60: =H59-F60 -> 13702.994 | K60: PAMELA CHERRY A. REYES | R60: ALEXANDER A. FERIA JR. | Y60: I hereby acknowledge and authorized the People's Multi-Purpose Cooperative (PMPC) for the following: 1) the regular submission and disclosure
B61: =DATE(YEAR(E$24),MONTH(E$24)+D61+0,DAY(E$24)) -> 46734 | C61: =TEXT(B61,"mmm-yyyy") -> Dec-2027 | D61: 34 | E61: =C$1 -> 4936.7326 | F61: =E61-G61 -> 4390.2525 | G61: =H60*C$12 -> 546.48015 | H61: =H60-F61 -> 9312.7418 | K61: Processor | R61: Verifier/PELVAMS Liason | X61: of my basic credit data (as defined under Republic Act Nr 9510 and its Implementing Rules and Regulations) to the Credit Information Corporation (CIC)
B62: =DATE(YEAR(E$24),MONTH(E$24)+D62+0,DAY(E$24)) -> 46765 | C62: =TEXT(B62,"mmm-yyyy") -> Jan-2028 | D62: 35 | E62: =C$1 -> 4936.7326 | F62: =E62-G62 -> 4565.3373 | G62: =H61*C$12 -> 371.39536 | H62: =H61-F62 -> 4747.4045 | X62: as well as any updates or corrections thereof; and 2) the sharing of my basic data and with other lenders authorized by the CIC, and credit reporting
B63: =DATE(YEAR(E$24),MONTH(E$24)+D63+0,DAY(E$24)) -> 46796 | C63: =TEXT(B63,"mmm-yyyy") -> Feb-2028 | D63: 36 | E63: =C$1 -> 4936.7326 | F63: =E63-G63 -> 4747.4045 | G63: =H62*C$12 -> 189.32813 | H63: =H62-F63 -> 1.2357305e-07 | X63: agencies duly accredited by the CIC.
AU64: MADONNA LYN O MARQUEZ
AU65: Printed Name & Signature of Borrower
K66: Received By: | R66: Approved By: | X66: CERTIFICATION
E68: =SUM(E28:E51) -> 118481.58 | F68: =SUM(F28:F51) -> 47136.217 | G68: =SUM(G28:G51) -> 71345.367 | Y68: I hereby certify that the applicant is assigned to this Office; is not on leave without pay; has no pending case; and, that all information he/she
P69: COL.ALEXANDER L. FERIA (RET) CPA MNSA | X69: provided is true and correct.
K70: Signature Over Printed Name/Date | R70: President
X71: MS RUBY D ABELLADO | AG71: HRMD III | AP71: HRMDD | AX71: 02125296
X72: CERTIFYING OFFICER | AG72: DESIGNATION | AP72: OFFICE | AX72: CONTACT NUMBER
X73: (Signature Over Printed Name)
X74: CREDIT HISTORY
X75: Loan ID | AA75: Date Granted | AE75: Loan Granted | AJ75: Term | AM75: Maturity Date | AR75: MA | AU75: Status/Remarks | AZ75: Principal Balance
N79: 20-E 15th Avenue Corner, 2nd Camarilla St.
M80: Brgy. San Roque, Murphy, Cubao, Quezon City
N81: Mobile Number: 09194983770 / 09530331580 | X81: LOAN APPROVAL
X82: Loan Amount: | AC82: MA: | AG82: Term: | AK82: Required NTHP: | AR82: NTHP after MA | AW82: Total Loan Exposure:
M83: AUTHORIZATION FOR ACTIVE DEDUCTION | X83: ='[3]Data Entry'!E11 -> 178237.5 | AC83: =AT39 -> 4936.7326 | AG83: =AN35 -> 36 Months | AK83: 5000 | AR83: =11617.19-(AC83+AK83) -> 1680.4574 | AW83: ='[3]Data Entry'!E3 -> 201960.56
X84: PROCESSED & VERIFIED BY:
R85: =S29 -> 45701
R86: DATE | AJ86: PAMELA CHERRY A. REYES
W87: SIGNATURE OVER PRINTED NAME
K90: To whom it may concern: | X90: RECOMMEND APPROVAL/DISAPPROVAL: | AO90: APPROVED/DISAPPROVED:
K92: I hereby authorize that the amount of | O92: Five Thousand Six Hundred Ten and 02/100 (Php 5,610.02) | AB92: JEFFRAE A. SAPLA | AS92: COL.ALEXANDER L. FERIA (RET)CPA MNSA
K93: for a period | M93: months with the total amount of | P93: Two Hundred One Thousand Nine Hundred | X93: SIGNATURE OVER PRINTED NAME | AO93: SIGNATURE OVER PRINTED NAME
K94: Sixty and 56/100
X100: PROMISORY NOTE NO:
Y101: FOR VALUE RECEIVED, the undersigned promise to pay the People's Multi-Purpose Cooperative (PMPC) the sum of Php | AY101: =AW83 -> 201960.56
AA102: in | AB102: 36 | AC102: equal monthly installments amounting to Php | AN102: =AC83 -> 4936.7326 | AR102: each, to be paid on the 28th day of every month starting on
X103: =B28 -> 45729 | AB103: / Single Payment of due on unpaid installments from maturity will bear charges on unpaid principal
X104: at the rate of 2% per month as penatly thereof.
X105: I hereby waive presentment for payment and notice of dishonor. PMPC may accept partial payment reserving its right of recourse against me. PMPC is hereby authorized and empowered to set off or apply without notice what is due under this Note from whatever funds I have in the Cooperative.
X108: It is further agreed that in case of separation from the service of whatever cause, the unpaid balance with its accumulated surcharges and interest as stipulated above be deducted from my last paymnet, commutation of leave/furlough and/or from my pension.
X111: It is further agreed that when installments are not paid when due and payable, the whole of the principal sum remaining unpaid shall forthwith become due and payable at the election of the Cooperative. I promise and agree to pay for a reasonable attorney's fee if this note is not paid according to its legal tenor and effect when palced in a lawyer's hand for collection. In case litigation, venue shall be vested in the competent court as may be allowed by the Rules of Court at the sole option of PMPC.
X116: Further, I hereby agree and authorized PMPC to encumber, assign or sell to any person or entity any right which it may have under thi Note, and/or any assignment, mortgage lien, pledge or other encumbrances constituted in favor of PMPC pursuant to the provisions of this Note if any. The consent herein granted is recognized and acknowledged by me/us as a waiver, to all intent and purposes of whatever right I may have to notice of actual encumbrance/ assignment.
AM120: Military/Pensioners ID
AM121: Employee's ID/Office ID
AM122: Driver's License
Z123: =AU64 -> MADONNA LYN O MARQUEZ | AM123: Others: | AO123: UMID I.D.
X124: Signature over Printed Name
X126: ID No: | Z126: 006-0082-1396-1
X127: Expiration Date: | AT127: LEFT THUMBMARK | AZ127: RIGHT THUMBMARK
X130: ACKNOWLEDGEMENT
X132: REPUBLIC OF THE PHILIPPINES
...

Sheet LRV3YEAR
B1: Amortization | C1: ='DATA ENTRY'!E15 -> 1499.9958 | T1: pvap
B2: Timeline | C2: 0 | D2: 1 | E2: 2 | F2: 3 | G2: 4 | H2: 5 | I2: 6 | J2: 7 | K2: 8 | L2: 9 | M2: 10 | N2: 11 | O2: 12 | P2: 13 | Q2: 14 | R2: 15 | S2: 16 | T2: 17 | U2: 18 | V2: 19 | W2: 20 | X2: 21 | Y2: 22 | Z2: 23 | AA2: 24 | AB2: 25 | AC2: 26 | AD2: 27 | AE2: 28 | AF2: 29 | AG2: 30 | AH2: 31 | AI2: 32 | AJ2: 33 | AK2: 34 | AL2: 35 | AM2: 36
B3: GROSS AMOUNT | C3: ='DATA ENTRY'!E4 -> 53999.85
A4: 41 | B4: LOAN AMOUNT | C4: ='DATA ENTRY'!E12 -> 47517.037 | D4: =-$C1 -> -1499.9958 | E4: =-$C1 -> -1499.9958 | F4: =-$C1 -> -1499.9958 | G4: =-$C1 -> -1499.9958 | H4: =-$C1 -> -1499.9958 | I4: =-$C1 -> -1499.9958 | J4: =-$C1 -> -1499.9958 | K4: =-$C1 -> -1499.9958 | ... AM4: =-$C1 -> -1499.9958
B5: Service Fee | C5: ='DATA ENTRY'!E7 -> 2988.376
B6: Insurance | C6: ='DATA ENTRY'!E8 -> 1344.7692
B7: CapCon | C7: ='DATA ENTRY'!E9 -> 5000
B8: membership fee | C8: ='DATA ENTRY'!E10 -> 300
B9: Advance Interest | C9: ='DATA ENTRY'!E11 -> 529.19158
B10: NET PROCEEDS/CASH FLOW | C10: =C4-C5-C6-C7-C8-C9 -> 37354.7
B12: Interest Rate of Return | C12: =IRR(C4:AM4) -> 0.0070833333 | D12: =C12/5 -> 0.0014166667
B14: Loan Balance
B15: Monthly Interest Rate | C15: ='[3]Data Entry'!D12/12 -> 0.0070833333
B16: Effective Interest Rate | C16: ='[3]Data Entry'!D13 -> 0.08855359
B17: Term | C17: 36
C20: LOAN LEDGER CARD
C22: Name: | D22: TABAQUERO, ARTHUR I. | G22: Loan Voucher No. | H22: LV-059
C23: Serial Nr: | D23: O-7704 | E23: Address: | F23: #49 RICARTE ST. AFPOVAI WESTERN BICUTAN TAGUIG CITY METRO MANILA
C24: Posting date | D24: Date of Loan: | E24: 46031 | F24: Maturity Date | G24: =B63 -> 47186 | K24: PEOPLE'S MULTI-PURPOSE COOPERATIVE
D25: Term: | E25: 36 | F25: MOS | K25: 20-E 2nd Camarilla St. corner 15th Ave., Brgy. San Roque, Murphy Cubao, Quezon City | X25: 20-E 2nd Camarilla St corner 15th Avenue,
D26: Loan | E26: Installment | F26: Principal | G26: EIR | H26: Balance | X26: Brgy San Roque, Murphy Cubao, Quezon City
D27: Month 0 | H27: =C4 -> 47517.037 | K27: LOAN RELEASE VOUCHER | X27: Mobile No. (+63)953-033-1580 (GLOBE)
B28: =DATE(YEAR(E$24),MONTH(E$24)+D28+2,DAY(E$24)) -> 46121 | C28: =TEXT(B28,"mmm-yyyy") -> Apr-2026 | D28: 1 | E28: =C$1 -> 1499.9958 | F28: =E28-G28 -> 1163.4168 | G28: =H27*C$12 -> 336.57901 | H28: =H27-F28 -> 46353.62
B29: =DATE(YEAR(E$24),MONTH(E$24)+D29+2,DAY(E$24)) -> 46151 | C29: =TEXT(B29,"mmm-yyyy") -> May-2026 | D29: 2 | E29: =C$1 -> 1499.9958 | F29: =E29-G29 -> 1171.6577 | G29: =H28*C$12 -> 328.33814 | H29: =H28-F29 -> 45181.962 | R29: Date: | S29: 01/09/2026 | X29: LOAN APPLICATION FORM
B30: =DATE(YEAR(E$24),MONTH(E$24)+D30+2,DAY(E$24)) -> 46182 | C30: =TEXT(B30,"mmm-yyyy") -> Jun-2026 | D30: 3 | E30: =C$1 -> 1499.9958 | F30: =E30-G30 -> 1179.9569 | G30: =H29*C$12 -> 320.0389 | H30: =H29-F30 -> 44002.005 | R30: LV No: | S30: =H22 -> LV-059 | AU30: Date: | AW30: 0 | AX30: 1 | AY30: 0 | AZ30: 9 | BA30: 2 | BB30: 0 | BC30: 2 | BD30: 6
B31: =DATE(YEAR(E$24),MONTH(E$24)+D31+2,DAY(E$24)) -> 46212 | C31: =TEXT(B31,"mmm-yyyy") -> Jul-2026 | D31: 4 | E31: =C$1 -> 1499.9958 | F31: =E31-G31 -> 1188.315 | G31: =H30*C$12 -> 311.68087 | H31: =H30-F31 -> 42813.69 | AW31: m | AX31: m | AY31: d | AZ31: d | BA31: y | BB31: y | BC31: y | BD31: y
B32: =DATE(YEAR(E$24),MONTH(E$24)+D32+2,DAY(E$24)) -> 46243 | C32: =TEXT(B32,"mmm-yyyy") -> Aug-2026 | D32: 5 | E32: =C$1 -> 1499.9958 | F32: =E32-G32 -> 1196.7322 | G32: =H31*C$12 -> 303.26364 | H32: =H31-F32 -> 41616.958 | K32: Name of Borrower: | N32: =D22 -> TABAQUERO, ARTHUR I. | X32: APPLICATION TYPE | AE32: LOAN CLASSIFICATION | AM32: TERM | AT32: RELEASE OF LOAN PROCEEDS
B33: =DATE(YEAR(E$24),MONTH(E$24)+D33+2,DAY(E$24)) -> 46274 | C33: =TEXT(B33,"mmm-yyyy") -> Sep-2026 | D33: 6 | E33: =C$1 -> 1499.9958 | F33: =E33-G33 -> 1205.209 | G33: =H32*C$12 -> 294.78679 | H33: =H32-F33 -> 40411.749 | K33: Serial No.: | N33: =D23 -> O-7704 | Y33: New | AF33: Salary Loan | AN33: 12 Months | AU33: Check
B34: =DATE(YEAR(E$24),MONTH(E$24)+D34+2,DAY(E$24)) -> 46304 | C34: =TEXT(B34,"mmm-yyyy") -> Oct-2026 | D34: 7 | E34: =C$1 -> 1499.9958 | F34: =E34-G34 -> 1213.7459 | G34: =H33*C$12 -> 286.24989 | H34: =H33-F34 -> 39198.003 | K34: Address: | N34: =F23 -> #49 RICARTE ST. AFPOVAI WESTERN BICUTAN TAGUIG CITY METRO MANILA | Y34: Renewal | AF34: Pension Loan | AN34: 24 Months | AU34: Bank Electronic Transfer to Borrowers Account
B35: =DATE(YEAR(E$24),MONTH(E$24)+D35+2,DAY(E$24)) -> 46335 | C35: =TEXT(B35,"mmm-yyyy") -> Nov-2026 | D35: 8 | E35: =C$1 -> 1499.9958 | F35: =E35-G35 -> 1222.3433 | G35: =H34*C$12 -> 277.65252 | H35: =H34-F35 -> 37975.66 | Y35: Additional | AF35: Emergency | AN35: 36 Months | AU35: Others:
B36: =DATE(YEAR(E$24),MONTH(E$24)+D36+2,DAY(E$24)) -> 46365 | C36: =TEXT(B36,"mmm-yyyy") -> Dec-2026 | D36: 9 | E36: =C$1 -> 1499.9958 | F36: =E36-G36 -> 1231.0016 | G36: =H35*C$12 -> 268.99426 | H36: =H35-F36 -> 36744.658 | L36: Principal Amount | R36: =C4 -> 47517.037 | Y36: Reloan | AF36: Health Assistance Loan | AN36: 48 Months
B37: =DATE(YEAR(E$24),MONTH(E$24)+D37+2,DAY(E$24)) -> 46396 | C37: =TEXT(B37,"mmm-yyyy") -> Jan-2027 | D37: 10 | E37: =C$1 -> 1499.9958 | F37: =E37-G37 -> 1239.7212 | G37: =H36*C$12 -> 260.27466 | H37: =H36-F37 -> 35504.937 | Y37: Restructure | AF37: Educational Loan | AN37: 60 Months
B38: =DATE(YEAR(E$24),MONTH(E$24)+D38+2,DAY(E$24)) -> 46427 | C38: =TEXT(B38,"mmm-yyyy") -> Feb-2027 | D38: 11 | E38: =C$1 -> 1499.9958 | F38: =E38-G38 -> 1248.5025 | G38: =H37*C$12 -> 251.4933 | H38: =H37-F38 -> 34256.435 | L38: (-) | M38: Balance Old Loan(s) | R38: =-C14 -> 0 | AF38: Others: | AN38: Others:
B39: =DATE(YEAR(E$24),MONTH(E$24)+D39+2,DAY(E$24)) -> 46455 | C39: =TEXT(B39,"mmm-yyyy") -> Mar-2027 | D39: 12 | E39: =C$1 -> 1499.9958 | F39: =E39-G39 -> 1257.3461 | G39: =H38*C$12 -> 242.64974 | H39: =H38-F39 -> 32999.088 | L39: (-) | M39: Membership Fee: | R39: =-C8 -> -300 | X39: AMOUNT APPLIED: | AB39: =R44 -> 37354.7 | AN39: MONTHLY AMORTIZATION: | AT39: =R49 -> 1499.9958
B40: =DATE(YEAR(E$24),MONTH(E$24)+D40+2,DAY(E$24)) -> 46486 | C40: =TEXT(B40,"mmm-yyyy") -> Apr-2027 | D40: 13 | E40: =C$1 -> 1499.9958 | F40: =E40-G40 -> 1266.2523 | G40: =H39*C$12 -> 233.74354 | H40: =H39-F40 -> 31732.836 | L40: (-) | M40: Paid up Capital: | R40: =-C7 -> -5000
B41: =DATE(YEAR(E$24),MONTH(E$24)+D41+2,DAY(E$24)) -> 46516 | C41: =TEXT(B41,"mmm-yyyy") -> May-2027 | D41: 14 | E41: =C$1 -> 1499.9958 | F41: =E41-G41 -> 1275.2216 | G41: =H40*C$12 -> 224.77426 | H41: =H40-F41 -> 30457.615 | L41: (-) | M41: Service Fee | R41: =-C5 -> -2988.376 | X41: LOAN ID: | AF41: DEDUCTION CODE: | AJ41: 691 PL | AR41: LOAN PURPOSE:
B42: =DATE(YEAR(E$24),MONTH(E$24)+D42+2,DAY(E$24)) -> 46547 | C42: =TEXT(B42,"mmm-yyyy") -> Jun-2027 | D42: 15 | E42: =C$1 -> 1499.9958 | F42: =E42-G42 -> 1284.2544 | G42: =H41*C$12 -> 215.74144 | H42: =H41-F42 -> 29173.36 | L42: (-) | M42: Insurance Premium - Paramount | R42: =-C6 -> -1344.7692 | X42: MEM ID: | AG42: Regular Member | AS42: Old Member
B43: =DATE(YEAR(E$24),MONTH(E$24)+D43+2,DAY(E$24)) -> 46577 | C43: =TEXT(B43,"mmm-yyyy") -> Jul-2027 | D43: 16 | E43: =C$1 -> 1499.9958 | F43: =E43-G43 -> 1293.3512 | G43: =H42*C$12 -> 206.64463 | H43: =H42-F43 -> 27880.009 | L43: (-) | M43: Advance Interest | R43: =-C9 -> -529.19158 | AG43: Associate Member | AS43: New Member
B44: =DATE(YEAR(E$24),MONTH(E$24)+D44+2,DAY(E$24)) -> 46608 | C44: =TEXT(B44,"mmm-yyyy") -> Aug-2027 | D44: 17 | E44: =C$1 -> 1499.9958 | F44: =E44-G44 -> 1302.5124 | G44: =H43*C$12 -> 197.4834 | H44: =H43-F44 -> 26577.497 | L44: NET PROCEEDS (Php): | R44: =SUM(R36:T43) -> 37354.7 | X44: BORROWER'S INFORMATION
B45: =DATE(YEAR(E$24),MONTH(E$24)+D45+2,DAY(E$24)) -> 46639 | C45: =TEXT(B45,"mmm-yyyy") -> Sep-2027 | D45: 18 | E45: =C$1 -> 1499.9958 | F45: =E45-G45 -> 1311.7386 | G45: =H44*C$12 -> 188.25727 | H45: =H44-F45 -> 25265.758 | X45: TABAQUERO | AD45: ARTHUR | AN45: IBANEZ
B46: =DATE(YEAR(E$24),MONTH(E$24)+D46+2,DAY(E$24)) -> 46669 | C46: =TEXT(B46,"mmm-yyyy") -> Oct-2027 | D46: 19 | E46: =C$1 -> 1499.9958 | F46: =E46-G46 -> 1321.0301 | G46: =H45*C$12 -> 178.96579 | H46: =H45-F46 -> 23944.728 | K46: PAYMENT | X46: (LAST NAME) | AD46: (FIRST NAME) | AN46: (MIDDLE NAME) | AZ46: (SUFFIX)
B47: =DATE(YEAR(E$24),MONTH(E$24)+D47+2,DAY(E$24)) -> 46700 | C47: =TEXT(B47,"mmm-yyyy") -> Nov-2027 | D47: 20 | E47: =C$1 -> 1499.9958 | F47: =E47-G47 -> 1330.3873 | G47: =H46*C$12 -> 169.60849 | H47: =H46-F47 -> 22614.341 | X47: Rank/Position: | AD47: Serial No.: | AI47: Branch of Service: | AO47: Date of Appointment: | AW47: Date of Retirement:
B48: =DATE(YEAR(E$24),MONTH(E$24)+D48+2,DAY(E$24)) -> 46730 | C48: =TEXT(B48,"mmm-yyyy") -> Dec-2027 | D48: 21 | E48: =C$1 -> 1499.9958 | F48: =E48-G48 -> 1339.8109 | G48: =H47*C$12 -> 160.18491 | H48: =H47-F48 -> 21274.53 | L48: Term of loan in months: | R48: =E25 -> 36 | T48: month(s) | X48: LTGEN | AD48: =N33 -> O-7704 | AI48: PA
B49: =DATE(YEAR(E$24),MONTH(E$24)+D49+2,DAY(E$24)) -> 46761 | C49: =TEXT(B49,"mmm-yyyy") -> Jan-2028 | D49: 22 | E49: =C$1 -> 1499.9958 | F49: =E49-G49 -> 1349.3013 | G49: =H48*C$12 -> 150.69459 | H49: =H48-F49 -> 19925.228 | L49: Monthly Amortization | R49: =C1 -> 1499.9958 | AO49: m | AP49: m | AQ49: d | AR49: d | AS49: y | AT49: y | AU49: y | AV49: y | AW49: m | AX49: m | AY49: d | AZ49: d | BA49: y | BB49: y | BC49: y | BD49: y
B50: =DATE(YEAR(E$24),MONTH(E$24)+D50+2,DAY(E$24)) -> 46792 | C50: =TEXT(B50,"mmm-yyyy") -> Feb-2028 | D50: 23 | E50: =C$1 -> 1499.9958 | F50: =E50-G50 -> 1358.8588 | G50: =H49*C$12 -> 141.13703 | H50: =H49-F50 -> 18566.37 | L50: First Payment Due On: | R50: =B28 -> 46121
B51: =DATE(YEAR(E$24),MONTH(E$24)+D51+2,DAY(E$24)) -> 46821 | C51: =TEXT(B51,"mmm-yyyy") -> Mar-2028 | D51: 24 | E51: =C$1 -> 1499.9958 | F51: =E51-G51 -> 1368.4841 | G51: =H50*C$12 -> 131.51178 | H51: =H50-F51 -> 17197.886 | L51: Maturity: | R51: =B63 -> 47186 | X51: Length of Service: | AE51: Date of Birth: | AJ51: Age: | AK51: 69 | AM51: Civil Status: | AR51: Single | AU51: Widower | AX51: Home Phone No.
B52: =DATE(YEAR(E$24),MONTH(E$24)+D52+2,DAY(E$24)) -> 46852 | C52: =TEXT(B52,"mmm-yyyy") -> Apr-2028 | D52: 25 | E52: =C$1 -> 1499.9958 | F52: =E52-G52 -> 1378.1775 | G52: =H51*C$12 -> 121.81836 | H52: =H51-F52 -> 15819.708 | L52: EIR (%): | R52: =C16 -> 0.08855359 | AE52: 20562 | AR52: Married | AU52: Separated
B53: =DATE(YEAR(E$24),MONTH(E$24)+D53+2,DAY(E$24)) -> 46882 | C53: =TEXT(B53,"mmm-yyyy") -> May-2028 | D53: 26 | E53: =C$1 -> 1499.9958 | F53: =E53-G53 -> 1387.9396 | G53: =H52*C$12 -> 112.05627 | H53: =H52-F53 -> 14431.769 | L53: Interest Rate per Month (%): | R53: ='[3]Data Entry'!E12/12 -> 0.0069166667 | X53: Unit Assignment: | AE53: Unit/Office/Business Address: | AX53: Unit/Office Telephone No/s:
B54: =DATE(YEAR(E$24),MONTH(E$24)+D54+2,DAY(E$24)) -> 46913 | C54: =TEXT(B54,"mmm-yyyy") -> Jun-2028 | D54: 27 | E54: =C$1 -> 1499.9958 | F54: =E54-G54 -> 1397.7708 | G54: =H53*C$12 -> 102.22503 | H54: =H53-F54 -> 13033.998
B55: =DATE(YEAR(E$24),MONTH(E$24)+D55+2,DAY(E$24)) -> 46943 | C55: =TEXT(B55,"mmm-yyyy") -> Jul-2028 | D55: 28 | E55: =C$1 -> 1499.9958 | F55: =E55-G55 -> 1407.6717 | G55: =H54*C$12 -> 92.32415 | H55: =H54-F55 -> 11626.326 | X55: AFP/Company ID No: | AG55: Email Address: | AT55: Tax Identification No/s:
B56: =DATE(YEAR(E$24),MONTH(E$24)+D56+2,DAY(E$24)) -> 46974 | C56: =TEXT(B56,"mmm-yyyy") -> Aug-2028 | D56: 29 | E56: =C$1 -> 1499.9958 | F56: =E56-G56 -> 1417.6427 | G56: =H55*C$12 -> 82.353143 | H56: =H55-F56 -> 10208.683 | K56: Certified & Corrected by: | R56: Verified by: | AG56: ait38467704@gmail.com | AT56: 1 | AU56: 3 | AV56: 8 | AW56: - | AX56: 0 | AY56: 0 | AZ56: 6 | BA56: - | BB56: 2 | BC56: 9 | BD56: 3
B57: =DATE(YEAR(E$24),MONTH(E$24)+D57+2,DAY(E$24)) -> 47005 | C57: =TEXT(B57,"mmm-yyyy") -> Sep-2028 | D57: 30 | E57: =C$1 -> 1499.9958 | F57: =E57-G57 -> 1427.6843 | G57: =H56*C$12 -> 72.311507 | H57: =H56-F57 -> 8780.999 | X57: Present Address: | AB57: =N34 -> #49 RICARTE ST. AFPOVAI WESTERN BICUTAN TAGUIG CITY METRO MANILA
B58: =DATE(YEAR(E$24),MONTH(E$24)+D58+2,DAY(E$24)) -> 47035 | C58: =TEXT(B58,"mmm-yyyy") -> Oct-2028 | D58: 31 | E58: =C$1 -> 1499.9958 | F58: =E58-G58 -> 1437.7971 | G58: =H57*C$12 -> 62.198743 | H58: =H57-F58 -> 7343.2019 | X58: NOTIFICATION CLAUSE
B59: =DATE(YEAR(E$24),MONTH(E$24)+D59+2,DAY(E$24)) -> 47066 | C59: =TEXT(B59,"mmm-yyyy") -> Nov-2028 | D59: 32 | E59: =C$1 -> 1499.9958 | F59: =E59-G59 -> 1447.9815 | G59: =H58*C$12 -> 52.014347 | H59: =H58-F59 -> 5895.2204
B60: =DATE(YEAR(E$24),MONTH(E$24)+D60+2,DAY(E$24)) -> 47096 | C60: =TEXT(B60,"mmm-yyyy") -> Dec-2028 | D60: 33 | E60: =C$1 -> 1499.9958 | F60: =E60-G60 -> 1458.238 | G60: =H59*C$12 -> 41.757811 | H60: =H59-F60 -> 4436.9824 | K60: JEFFRAE A. SAPLA | R60: ALEXANDER A. FERIA JR. | Y60: I hereby acknowledge and authorized the People's Multi-Purpose Cooperative (PMPC) for the following: 1) the regular submission and disclosure
B61: =DATE(YEAR(E$24),MONTH(E$24)+D61+2,DAY(E$24)) -> 47127 | C61: =TEXT(B61,"mmm-yyyy") -> Jan-2029 | D61: 34 | E61: =C$1 -> 1499.9958 | F61: =E61-G61 -> 1468.5672 | G61: =H60*C$12 -> 31.428625 | H61: =H60-F61 -> 2968.4152 | K61: Processor | R61: Verifier/PELVAMS Liason | X61: of my basic credit data (as defined under Republic Act Nr 9510 and its Implementing Rules and Regulations) to the Credit Information Corporation (CIC)
B62: =DATE(YEAR(E$24),MONTH(E$24)+D62+2,DAY(E$24)) -> 47158 | C62: =TEXT(B62,"mmm-yyyy") -> Feb-2029 | D62: 35 | E62: =C$1 -> 1499.9958 | F62: =E62-G62 -> 1478.9696 | G62: =H61*C$12 -> 21.026274 | H62: =H61-F62 -> 1489.4456 | X62: as well as any updates or corrections thereof; and 2) the sharing of my basic data and with other lenders authorized by the CIC, and credit reporting
B63: =DATE(YEAR(E$24),MONTH(E$24)+D63+2,DAY(E$24)) -> 47186 | C63: =TEXT(B63,"mmm-yyyy") -> Mar-2029 | D63: 36 | E63: =C$1 -> 1499.9958 | F63: =E63-G63 -> 1489.4456 | G63: =H62*C$12 -> 10.55024 | H63: =H62-F63 -> 1.5393198e-10 | X63: agencies duly accredited by the CIC.
E64: =SUM(E28:E63) -> 53999.85 | F64: =SUM(F28:F63) -> 47517.037 | G64: =SUM(G28:G63) -> 6482.8133 | AU64: =D22 -> TABAQUERO, ARTHUR I.
AU65: Printed Name & Signature of Borrower
K66: Received By: | R66: Approved By: | X66: CERTIFICATION
Y68: I hereby certify that the applicant is assigned to this Office; is not on leave without pay; has no pending case; and, that all information he/she
K69: =D22 -> TABAQUERO, ARTHUR I. | P69: COL.ALEXANDER L. FERIA (RET) CPA MNSA | X69: provided is true and correct.
K70: Signature Over Printed Name/Date | R70: President
X72: CERTIFYING OFFICER | AG72: DESIGNATION | AP72: OFFICE | AX72: CONTACT NUMBER
X73: (Signature Over Printed Name)
X74: CREDIT HISTORY
X75: Loan ID | AA75: Date Granted | AE75: Loan Granted | AJ75: Term | AM75: Maturity Date | AR75: MA | AU75: Status/Remarks | AZ75: Principal Balance
N79: 20-E 15th Avenue Corner, 2nd Camarilla St.
M80: Brgy. San Roque, Murphy, Cubao, Quezon City
N81: Mobile Number: 09194983770 / 09530331580 | X81: LOAN APPROVAL
X82: Loan Amount: | AC82: MA: | AG82: Term: | AK82: Required NTHP: | AR82: NTHP after MA | AW82: Total Loan Exposure:
M83: AUTHORIZATION FOR ACTIVE DEDUCTION | X83: =C4 -> 47517.037 | AC83: =R49 -> 1499.9958 | AG83: =AN35 -> 36 Months | AK83: 650 | AW83: =C3 -> 53999.85
X84: PROCESSED & VERIFIED BY:
R85: =S29 -> 01/09/2026
R86: DATE | AJ86: JEFFRAE A. SAPLA
W87: SIGNATURE OVER PRINTED NAME
K90: To whom it may concern: | X90: RECOMMEND APPROVAL/DISAPPROVAL: | AO90: APPROVED/DISAPPROVED:
K92: I hereby authorize that the amount of | O92: Five Thousand Six Hundred Ten and 02/100 (Php 5,610.02) | AB92: ALEXANDER A. FERIA JR | AR92: COL. ALEXANDER L. FERIA (RET),CPA, MNSA
K93: for a period | M93: months with the total amount of | P93: Two Hundred One Thousand Nine Hundred | X93: SIGNATURE OVER PRINTED NAME | AO93: SIGNATURE OVER PRINTED NAME
K94: Sixty and 56/100
X100: PROMISORY NOTE NO: | AL100: =S30 -> LV-059
Y101: FOR VALUE RECEIVED, the undersigned promise to pay the People's Multi-Purpose Cooperative (PMPC) the sum of Php | AY101: =AW83 -> 53999.85
AA102: in | AB102: 36 | AC102: equal monthly installments amounting to Php | AN102: =AC83 -> 1499.9958 | AR102: each, to be paid on the 28th day of every month starting on
X103: =B28 -> 46121 | AB103: / Single Payment of due on unpaid installments from maturity will bear charges on unpaid principal
X104: at the rate of 2% per month as penatly thereof.
X105: I hereby waive presentment for payment and notice of dishonor. PMPC may accept partial payment reserving its right of recourse against me. PMPC is hereby authorized and empowered to set off or apply without notice what is due under this Note from whatever funds I have in the Cooperative.
X108: It is further agreed that in case of separation from the service of whatever cause, the unpaid balance with its accumulated surcharges and interest as stipulated above be deducted from my last paymnet, commutation of leave/furlough, capital contribution, and/or from my pension.
X111: It is further agreed that when installments are not paid when due and payable, the whole of the principal sum remaining unpaid shall forthwith become due and payable at the election of the Cooperative. I promise and agree to pay for a reasonable attorney's fee if this note is not paid according to its legal tenor and effect when palced in a lawyer's hand for collection. In case litigation, venue shall be vested in the competent court as may be allowed by the Rules of Court at the sole option of PMPC.
X116: Further, I hereby agree and authorized PMPC to encumber, assign or sell to any person or entity any right which it may have under thi Note, and/or any assignment, mortgage lien, pledge or other encumbrances constituted in favor of PMPC pursuant to the provisions of this Note if any. The consent herein granted is recognized and acknowledged by me/us as a waiver, to all intent and purposes of whatever right I may have to notice of actual encumbrance/ assignment.
AM120: Military/Pensioners ID
AM121: Employee's ID/Office ID
AM122: Driver's License
Z123: =AU64 -> TABAQUERO, ARTHUR I. | AM123: Others:
X124: Signature over Printed Name
X126: ID No: | Z126: =AD48 -> O-7704
X127: Expiration Date: | AT127: LEFT THUMBMARK | AZ127: RIGHT THUMBMARK
X130: ACKNOWLEDGEMENT
X132: REPUBLIC OF THE PHILIPPINES
X133: (20-E, 2nd Camarilla St., Cor. 15th Ave.,BRGY San Roque, Murphy Cubao, Quezon City) S.S
...

Sheet LRV4YEAR
B1: Amortization | C1: ='DATA ENTRY'!F15 -> 2771.3809 | T1: pvap
B2: Timeline | C2: 0 | D2: 1 | E2: 2 | F2: 3 | G2: 4 | H2: 5 | I2: 6 | J2: 7 | K2: 8 | L2: 9 | M2: 10 | N2: 11 | O2: 12 | P2: 13 | Q2: 14 | R2: 15 | S2: 16 | T2: 17 | U2: 18 | V2: 19 | W2: 20 | X2: 21 | Y2: 22 | Z2: 23 | AA2: 24 | AB2: 25 | AC2: 26 | AD2: 27 | AE2: 28 | AF2: 29 | AG2: 30 | AH2: 31 | AI2: 32 | AJ2: 33 | AK2: 34 | AL2: 35 | AM2: 36 | AN2: 37 | AO2: 38 | AP2: 39 | AQ2: 40 | AR2: 41 | AS2: 42 | AT2: 43 | AU2: 44 | AV2: 45 | AW2: 46 | AX2: 47 | AY2: 48
B3: GROSS AMOUNT | C3: ='DATA ENTRY'!F4 -> 133026.28
A4: 41 | B4: LOAN AMOUNT | C4: ='DATA ENTRY'!F12 -> 111836.22 | D4: -9912.2841 | E4: -9912.2841 | F4: -9912.2841 | G4: -9912.2841 | H4: -9912.2841 | I4: -9912.2841 | J4: -9912.2841 | K4: -9912.2841 | L4: -9912.2841 | M4: -9912.2841 | N4: -9912.2841 | O4: -9912.2841 | P4: -9912.2841 | Q4: -9912.2841 | R4: -9912.2841 | S4: -9912.2841 | T4: -9912.2841 | U4: -9912.2841 | V4: -9912.2841 | W4: -9912.2841 | X4: -9912.2841 | Y4: -9912.2841 | Z4: -9912.2841 | AA4: -9912.2841 | AB4: -9912.2841 | AC4: -9912.2841 | AD4: -9912.2841 | AE4: -9912.2841 | AF4: -9912.2841 | AG4: -9912.2841 | AH4: -9912.2841 | AI4: -9912.2841 | AJ4: -9912.2841 | AK4: -9912.2841 | AL4: -9912.2841 | AM4: -9912.2841 | AN4: -9912.2841 | AO4: -9912.2841 | AP4: -9912.2841 | AQ4: -9912.2841 | AR4: -9912.2841 | AS4: -9912.2841 | AT4: -9912.2841 | AU4: -9912.2841 | AV4: -9912.2841 | AW4: -9912.2841 | AX4: -9912.2841 | AY4: -9912.2841
B5: Service Fee | C5: ='DATA ENTRY'!F7 -> 7480
B6: Insurance | C6: ='DATA ENTRY'!F8 -> 4488
B7: CapCon | C7: ='DATA ENTRY'!F9 -> 5000
B8: membership fee | C8: ='DATA ENTRY'!D10 -> 0
B9: Advance Interest | C9: ='DATA ENTRY'!F11 -> 1368.2167
B10: NET PROCEEDS/CASH FLOW | C10: =C4-C5-C6-C7-C8-C9 -> 93500 | D10: =-$C1 -> -2771.3809 | E10: =-$C1 -> -2771.3809 | F10: =-$C1 -> -2771.3809 | G10: =-$C1 -> -2771.3809 | H10: =-$C1 -> -2771.3809 | I10: =-$C1 -> -2771.3809 | J10: =-$C1 -> -2771.3809 | K10: =-$C1 -> -2771.3809 | ... AY10: =-$C1 -> -2771.3809
B12: Interest Rate of Return | C12: =IRR(C4:AY4) -> 0.08701686 | D12: =C12/5 -> 0.017403372
B14: Loan Balance | C14: 122655.42
B15: Monthly Interest Rate | C15: ='[3]Data Entry'!D12/12 -> 0.0070833333
B16: Effective Interest Rate | C16: ='[3]Data Entry'!D13 -> 0.08855359
B17: Term | C17: 48
C20: LOAN LEDGER CARD
C22: Name: | D22: MADONNA LYN ORTEGA MARQUEZ | G22: Loan Voucher No. | H22: CDEA-001
C23: Serial Nr: | D23: 2004-023 | E23: Address: | F23: BLK 1 LOT 8 JOSHUA ST., BEYOND HOMES BRGY SAN FRANCISCO, GENERAL TRIAS, CAVITE
C24: Posting date | D24: Date of Loan: | E24: 45701 | F24: Maturity Date | G24: =B51 -> 46431 | K24: PEOPLE'S MULTI-PURPOSE COOPERATIVE
D25: Term: | E25: 36 | F25: MOS | K25: 20-E 2nd Camarilla St. corner 15th Ave., Brgy. San Roque, Murphy Cubao, Quezon City | X25: 20-E 2nd Camarilla St corner 15th Avenue,
D26: Loan | E26: Installment | F26: Principal | G26: EIR | H26: Balance | X26: Brgy San Roque, Murphy Cubao, Quezon City
D27: Month 0 | H27: =C10 -> 93500 | K27: LOAN RELEASE VOUCHER | X27: Mobile No. (+63)953-033-1580 (GLOBE)
B28: =DATE(YEAR(E$24),MONTH(E$24)+D28+0,DAY(E$24)) -> 45729 | C28: =TEXT(B28,"mmm-yyyy") -> Mar-2025 | D28: 1 | E28: =C$1 -> 2771.3809 | F28: =E28-G28 -> -5364.6956 | G28: =H27*C$12 -> 8136.0764 | H28: =H27-F28 -> 98864.696
B29: =DATE(YEAR(E$24),MONTH(E$24)+D29+0,DAY(E$24)) -> 45760 | C29: =TEXT(B29,"mmm-yyyy") -> Apr-2025 | D29: 2 | E29: =C$1 -> 2771.3809 | F29: =E29-G29 -> -5831.5145 | G29: =H28*C$12 -> 8602.8954 | H29: =H28-F29 -> 104696.21 | R29: Date: | S29: =E24 -> 45701 | X29: LOAN APPLICATION FORM
B30: =DATE(YEAR(E$24),MONTH(E$24)+D30+0,DAY(E$24)) -> 45790 | C30: =TEXT(B30,"mmm-yyyy") -> May-2025 | D30: 3 | E30: =C$1 -> 2771.3809 | F30: =E30-G30 -> -6338.9546 | G30: =H29*C$12 -> 9110.3355 | H30: =H29-F30 -> 111035.16 | R30: LV No: | S30: =D23 -> 2004-023 | AU30: Date: | AW30: 0 | AX30: 2 | AY30: 1 | AZ30: 3 | BA30: 2 | BB30: 0 | BC30: 2 | BD30: 5
B31: =DATE(YEAR(E$24),MONTH(E$24)+D31+0,DAY(E$24)) -> 45821 | C31: =TEXT(B31,"mmm-yyyy") -> Jun-2025 | D31: 4 | E31: =C$1 -> 2771.3809 | F31: =E31-G31 -> -6890.5506 | G31: =H30*C$12 -> 9661.9314 | H31: =H30-F31 -> 117925.72 | AW31: m | AX31: m | AY31: d | AZ31: d | BA31: y | BB31: y | BC31: y | BD31: y
B32: =DATE(YEAR(E$24),MONTH(E$24)+D32+0,DAY(E$24)) -> 45851 | C32: =TEXT(B32,"mmm-yyyy") -> Jul-2025 | D32: 5 | E32: =C$1 -> 2771.3809 | F32: =E32-G32 -> -7490.1446 | G32: =H31*C$12 -> 10261.526 | H32: =H31-F32 -> 125415.86 | K32: Name of Borrower: | N32: =D22 -> MADONNA LYN ORTEGA MARQUEZ | X32: APPLICATION TYPE | AE32: LOAN CLASSIFICATION | AM32: TERM | AT32: RELEASE OF LOAN PROCEEDS
B33: =DATE(YEAR(E$24),MONTH(E$24)+D33+0,DAY(E$24)) -> 45882 | C33: =TEXT(B33,"mmm-yyyy") -> Aug-2025 | D33: 6 | E33: =C$1 -> 2771.3809 | F33: =E33-G33 -> -8141.9135 | G33: =H32*C$12 -> 10913.294 | H33: =H32-F33 -> 133557.77 | K33: Serial No.: | N33: =D23 -> 2004-023 | Y33: New | AF33: Salary Loan | AN33: 12 Months | AU33: Check
B34: =DATE(YEAR(E$24),MONTH(E$24)+D34+0,DAY(E$24)) -> 45913 | C34: =TEXT(B34,"mmm-yyyy") -> Sep-2025 | D34: 7 | E34: =C$1 -> 2771.3809 | F34: =E34-G34 -> -8850.3973 | G34: =H33*C$12 -> 11621.778 | H34: =H33-F34 -> 142408.17 | K34: Address: | N34: =F23 -> BLK 1 LOT 8 JOSHUA ST., BEYOND HOMES BRGY SAN FRANCISCO, GENERAL TRIAS, CAVITE | Y34: Renewal | AF34: Pension Loan | AN34: 24 Months | AU34: Bank Electronic Transfer to Borrowers Account
B35: =DATE(YEAR(E$24),MONTH(E$24)+D35+0,DAY(E$24)) -> 45943 | C35: =TEXT(B35,"mmm-yyyy") -> Oct-2025 | D35: 8 | E35: =C$1 -> 2771.3809 | F35: =E35-G35 -> -9620.531 | G35: =H34*C$12 -> 12391.912 | H35: =H34-F35 -> 152028.7 | Y35: Additional | AF35: Emergency | AN35: 36 Months | AU35: Others:
B36: =DATE(YEAR(E$24),MONTH(E$24)+D36+0,DAY(E$24)) -> 45974 | C36: =TEXT(B36,"mmm-yyyy") -> Nov-2025 | D36: 9 | E36: =C$1 -> 2771.3809 | F36: =E36-G36 -> -10457.679 | G36: =H35*C$12 -> 13229.06 | H36: =H35-F36 -> 162486.38 | L36: Principal Amount | R36: =C4 -> 111836.22 | Y36: Reloan | AF36: Health Assistance Loan | AN36: 48 Months
B37: =DATE(YEAR(E$24),MONTH(E$24)+D37+0,DAY(E$24)) -> 46004 | C37: =TEXT(B37,"mmm-yyyy") -> Dec-2025 | D37: 10 | E37: =C$1 -> 2771.3809 | F37: =E37-G37 -> -11367.674 | G37: =H36*C$12 -> 14139.055 | H37: =H36-F37 -> 173854.06 | Y37: Restructure | AF37: Educational Loan | AN37: 60 Months
B38: =DATE(YEAR(E$24),MONTH(E$24)+D38+0,DAY(E$24)) -> 46035 | C38: =TEXT(B38,"mmm-yyyy") -> Jan-2026 | D38: 11 | E38: =C$1 -> 2771.3809 | F38: =E38-G38 -> -12356.853 | G38: =H37*C$12 -> 15128.234 | H38: =H37-F38 -> 186210.91 | L38: (-) | M38: Balance Old Loan(s) | R38: =-C14 -> -122655.42 | AF38: Others: | AN38: Others:
B39: =DATE(YEAR(E$24),MONTH(E$24)+D39+0,DAY(E$24)) -> 46066 | C39: =TEXT(B39,"mmm-yyyy") -> Feb-2026 | D39: 12 | E39: =C$1 -> 2771.3809 | F39: =E39-G39 -> -13432.108 | G39: =H38*C$12 -> 16203.489 | H39: =H38-F39 -> 199643.02 | L39: (-) | M39: Membership Fee: | R39: =-C8 -> 0 | X39: AMOUNT APPLIED: | AB39: ='[3]Data Entry'!E4 -> 150000 | AN39: MONTHLY AMORTIZATION: | AT39: =R49 -> 2771.3809
B40: =DATE(YEAR(E$24),MONTH(E$24)+D40+0,DAY(E$24)) -> 46094 | C40: =TEXT(B40,"mmm-yyyy") -> Mar-2026 | D40: 13 | E40: =C$1 -> 2771.3809 | F40: =E40-G40 -> -14600.928 | G40: =H39*C$12 -> 17372.308 | H40: =H39-F40 -> 214243.94 | L40: (-) | M40: Paid up Capital: | R40: =-C7 -> -5000
B41: =DATE(YEAR(E$24),MONTH(E$24)+D41+0,DAY(E$24)) -> 46125 | C41: =TEXT(B41,"mmm-yyyy") -> Apr-2026 | D41: 14 | E41: =C$1 -> 2771.3809 | F41: =E41-G41 -> -15871.454 | G41: =H40*C$12 -> 18642.835 | H41: =H40-F41 -> 230115.4 | L41: (-) | M41: Service Fee | R41: =-C5 -> -7480 | X41: LOAN ID: | AF41: DEDUCTION CODE: | AR41: LOAN PURPOSE:
B42: =DATE(YEAR(E$24),MONTH(E$24)+D42+0,DAY(E$24)) -> 46155 | C42: =TEXT(B42,"mmm-yyyy") -> May-2026 | D42: 15 | E42: =C$1 -> 2771.3809 | F42: =E42-G42 -> -17252.539 | G42: =H41*C$12 -> 20023.919 | H42: =H41-F42 -> 247367.94 | L42: (-) | M42: Insurance Premium - Paramount | R42: =-C6 -> -4488 | X42: MEM ID: | AG42: Regular Member | AS42: Old Member
B43: =DATE(YEAR(E$24),MONTH(E$24)+D43+0,DAY(E$24)) -> 46186 | C43: =TEXT(B43,"mmm-yyyy") -> Jun-2026 | D43: 16 | E43: =C$1 -> 2771.3809 | F43: =E43-G43 -> -18753.8 | G43: =H42*C$12 -> 21525.181 | H43: =H42-F43 -> 266121.74 | L43: (-) | M43: Advance Interest | R43: =-C9 -> -1368.2167 | AG43: Associate Member | AS43: New Member
B44: =DATE(YEAR(E$24),MONTH(E$24)+D44+0,DAY(E$24)) -> 46216 | C44: =TEXT(B44,"mmm-yyyy") -> Jul-2026 | D44: 17 | E44: =C$1 -> 2771.3809 | F44: =E44-G44 -> -20385.697 | G44: =H43*C$12 -> 23157.078 | H44: =H43-F44 -> 286507.43 | L44: NET PROCEEDS (Php): | R44: =SUM(R36:T43) -> -29155.42 | X44: BORROWER'S INFORMATION
B45: =DATE(YEAR(E$24),MONTH(E$24)+D45+0,DAY(E$24)) -> 46247 | C45: =TEXT(B45,"mmm-yyyy") -> Aug-2026 | D45: 18 | E45: =C$1 -> 2771.3809 | F45: =E45-G45 -> -22159.597 | G45: =H44*C$12 -> 24930.977 | H45: =H44-F45 -> 308667.03 | X45: MARQUEZ | AD45: MADONNA LYN | AN45: ORTEGA
B46: =DATE(YEAR(E$24),MONTH(E$24)+D46+0,DAY(E$24)) -> 46278 | C46: =TEXT(B46,"mmm-yyyy") -> Sep-2026 | D46: 19 | E46: =C$1 -> 2771.3809 | F46: =E46-G46 -> -24087.855 | G46: =H45*C$12 -> 26859.236 | H46: =H45-F46 -> 332754.89 | K46: PAYMENT | X46: (LAST NAME) | AD46: (FIRST NAME) | AN46: (MIDDLE NAME) | AZ46: (SUFFIX)
B47: =DATE(YEAR(E$24),MONTH(E$24)+D47+0,DAY(E$24)) -> 46308 | C47: =TEXT(B47,"mmm-yyyy") -> Oct-2026 | D47: 20 | E47: =C$1 -> 2771.3809 | F47: =E47-G47 -> -26183.905 | G47: =H46*C$12 -> 28955.285 | H47: =H46-F47 -> 358938.79 | X47: Rank/Position: | AD47: Serial No.: | AI47: Branch of Service: | AO47: Date of Appointment: | AW47: Date of Retirement:
B48: =DATE(YEAR(E$24),MONTH(E$24)+D48+0,DAY(E$24)) -> 46339 | C48: =TEXT(B48,"mmm-yyyy") -> Nov-2026 | D48: 21 | E48: =C$1 -> 2771.3809 | F48: =E48-G48 -> -28462.346 | G48: =H47*C$12 -> 31233.727 | H48: =H47-F48 -> 387401.14 | L48: Term of loan in months: | R48: =E25 -> 36 | T48: month(s) | X48: HRMD IV | AD48: 2004-023 OCD | AI48: OCD | AO48: 0 | AP48: 7 | AQ48: 1 | AR48: 9 | AS48: 2 | AT48: 0 | AU48: 0 | AV48: 4 | AW48: 1 | AX48: 0 | AY48: 0 | AZ48: 1 | BA48: 2 | BB48: 0 | BC48: 4 | BD48: 6
B49: =DATE(YEAR(E$24),MONTH(E$24)+D49+0,DAY(E$24)) -> 46369 | C49: =TEXT(B49,"mmm-yyyy") -> Dec-2026 | D49: 22 | E49: =C$1 -> 2771.3809 | F49: =E49-G49 -> -30939.05 | G49: =H48*C$12 -> 33710.431 | H49: =H48-F49 -> 418340.19 | L49: Monthly Amortization | R49: =C1 -> 2771.3809 | AO49: m | AP49: m | AQ49: d | AR49: d | AS49: y | AT49: y | AU49: y | AV49: y | AW49: m | AX49: m | AY49: d | AZ49: d | BA49: y | BB49: y | BC49: y | BD49: y
B50: =DATE(YEAR(E$24),MONTH(E$24)+D50+0,DAY(E$24)) -> 46400 | C50: =TEXT(B50,"mmm-yyyy") -> Jan-2027 | D50: 23 | E50: =C$1 -> 2771.3809 | F50: =E50-G50 -> -33631.269 | G50: =H49*C$12 -> 36402.65 | H50: =H49-F50 -> 451971.45 | L50: First Payment Due On: | R50: =B28 -> 45729
B51: =DATE(YEAR(E$24),MONTH(E$24)+D51+0,DAY(E$24)) -> 46431 | C51: =TEXT(B51,"mmm-yyyy") -> Feb-2027 | D51: 24 | E51: =C$1 -> 2771.3809 | F51: =E51-G51 -> -36557.756 | G51: =H50*C$12 -> 39329.137 | H51: =H50-F51 -> 488529.21 | L51: Maturity: | R51: =B63 -> 46796 | X51: Length of Service: | AE51: Date of Birth: | AJ51: Age: | AK51: 43 | AM51: Civil Status: | AR51: Single | AU51: Widower | AX51: Home Phone No.
B52: =DATE(YEAR(E$24),MONTH(E$24)+D52+0,DAY(E$24)) -> 46459 | C52: =TEXT(B52,"mmm-yyyy") -> Mar-2027 | D52: 25 | E52: =C$1 -> 2771.3809 | F52: =E52-G52 -> -39738.897 | G52: =H51*C$12 -> 42510.278 | H52: =H51-F52 -> 528268.11 | L52: EIR (%): | R52: =C16 -> 0.08855359 | X52: 20 YEARS AND 6 MOS | AE52: OCT 1 1981 | AR52: Married | AU52: Separated
B53: =DATE(YEAR(E$24),MONTH(E$24)+D53+0,DAY(E$24)) -> 46490 | C53: =TEXT(B53,"mmm-yyyy") -> Apr-2027 | D53: 26 | E53: =C$1 -> 2771.3809 | F53: =E53-G53 -> -43196.851 | G53: =H52*C$12 -> 45968.232 | H53: =H52-F53 -> 571464.96 | L53: Interest Rate per Month (%): | R53: ='[3]Data Entry'!E12/12 -> 0.0069166667 | X53: Unit Assignment: | AE53: Unit/Office/Business Address: | AX53: Unit/Office Telephone No/s:
B54: =DATE(YEAR(E$24),MONTH(E$24)+D54+0,DAY(E$24)) -> 46520 | C54: =TEXT(B54,"mmm-yyyy") -> May-2027 | D54: 27 | E54: =C$1 -> 2771.3809 | F54: =E54-G54 -> -46955.706 | G54: =H53*C$12 -> 49727.087 | H54: =H53-F54 -> 618420.66 | X54: HRMDD - OCD | AE54: CAMP AGUINALDO QUEZON CITY | AX54: 2912596
B55: =DATE(YEAR(E$24),MONTH(E$24)+D55+0,DAY(E$24)) -> 46551 | C55: =TEXT(B55,"mmm-yyyy") -> Jun-2027 | D55: 28 | E55: =C$1 -> 2771.3809 | F55: =E55-G55 -> -51041.644 | G55: =H54*C$12 -> 53813.025 | H55: =H54-F55 -> 669462.31 | X55: AFP/Company ID No: | AG55: Email Address: | AT55: Tax Identification No/s:
B56: =DATE(YEAR(E$24),MONTH(E$24)+D56+0,DAY(E$24)) -> 46581 | C56: =TEXT(B56,"mmm-yyyy") -> Jul-2027 | D56: 29 | E56: =C$1 -> 2771.3809 | F56: =E56-G56 -> -55483.127 | G56: =H55*C$12 -> 58254.508 | H56: =H55-F56 -> 724945.44 | K56: Certified & Corrected by: | R56: Verified by: | X56: 2004-023 OCD | AG56: madomarquez819@gmail.com | AT56: 3 | AU56: 0 | AV56: 0 | AW56: - | AX56: 1 | AY56: 6 | AZ56: 6 | BA56: - | BB56: 0 | BC56: 1 | BD56: 1
B57: =DATE(YEAR(E$24),MONTH(E$24)+D57+0,DAY(E$24)) -> 46612 | C57: =TEXT(B57,"mmm-yyyy") -> Aug-2027 | D57: 30 | E57: =C$1 -> 2771.3809 | F57: =E57-G57 -> -60311.095 | G57: =H56*C$12 -> 63082.476 | H57: =H56-F57 -> 785256.53 | X57: Present Address: | AB57: BLK 1 LOT 8 JOSHUA ST., BEYOND HOMES BRGY SAN FRANCISCO, GENERAL TRIAS, CAVITE
B58: =DATE(YEAR(E$24),MONTH(E$24)+D58+0,DAY(E$24)) -> 46643 | C58: =TEXT(B58,"mmm-yyyy") -> Sep-2027 | D58: 31 | E58: =C$1 -> 2771.3809 | F58: =E58-G58 -> -65559.177 | G58: =H57*C$12 -> 68330.558 | H58: =H57-F58 -> 850815.71 | X58: NOTIFICATION CLAUSE
B59: =DATE(YEAR(E$24),MONTH(E$24)+D59+0,DAY(E$24)) -> 46673 | C59: =TEXT(B59,"mmm-yyyy") -> Oct-2027 | D59: 32 | E59: =C$1 -> 2771.3809 | F59: =E59-G59 -> -71263.931 | G59: =H58*C$12 -> 74035.312 | H59: =H58-F59 -> 922079.64
B60: =DATE(YEAR(E$24),MONTH(E$24)+D60+0,DAY(E$24)) -> 46704 | C60: =TEXT(B60,"mmm-yyyy") -> Nov-2027 | D60: 33 | E60: =C$1 -> 2771.3809 | F60: =E60-G60 -> -77465.094 | G60: =H59*C$12 -> 80236.475 | H60: =H59-F60 -> 999544.73 | K60: PAMELA CHERRY A. REYES | R60: ALEXANDER A. FERIA JR. | Y60: I hereby acknowledge and authorized the People's Multi-Purpose Cooperative (PMPC) for the following: 1) the regular submission and disclosure
B61: =DATE(YEAR(E$24),MONTH(E$24)+D61+0,DAY(E$24)) -> 46734 | C61: =TEXT(B61,"mmm-yyyy") -> Dec-2027 | D61: 34 | E61: =C$1 -> 2771.3809 | F61: =E61-G61 -> -84205.864 | G61: =H60*C$12 -> 86977.244 | H61: =H60-F61 -> 1083750.6 | K61: Processor | R61: Verifier/PELVAMS Liason | X61: of my basic credit data (as defined under Republic Act Nr 9510 and its Implementing Rules and Regulations) to the Credit Information Corporation (CIC)
B62: =DATE(YEAR(E$24),MONTH(E$24)+D62+0,DAY(E$24)) -> 46765 | C62: =TEXT(B62,"mmm-yyyy") -> Jan-2028 | D62: 35 | E62: =C$1 -> 2771.3809 | F62: =E62-G62 -> -91533.193 | G62: =H61*C$12 -> 94304.574 | H62: =H61-F62 -> 1175283.8 | X62: as well as any updates or corrections thereof; and 2) the sharing of my basic data and with other lenders authorized by the CIC, and credit reporting
B63: =DATE(YEAR(E$24),MONTH(E$24)+D63+0,DAY(E$24)) -> 46796 | C63: =TEXT(B63,"mmm-yyyy") -> Feb-2028 | D63: 36 | E63: =C$1 -> 2771.3809 | F63: =E63-G63 -> -99498.125 | G63: =H62*C$12 -> 102269.51 | H63: =H62-F63 -> 1274781.9 | X63: agencies duly accredited by the CIC.
AU64: MADONNA LYN O MARQUEZ
AU65: Printed Name & Signature of Borrower
K66: Received By: | R66: Approved By: | X66: CERTIFICATION
E68: =SUM(E28:E51) -> 66513.141 | F68: =SUM(F28:F51) -> -395029.21 | G68: =SUM(G28:G51) -> 461542.35 | Y68: I hereby certify that the applicant is assigned to this Office; is not on leave without pay; has no pending case; and, that all information he/she
P69: COL.ALEXANDER L. FERIA (RET) CPA MNSA | X69: provided is true and correct.
K70: Signature Over Printed Name/Date | R70: President
X71: MS RUBY D ABELLADO | AG71: HRMD III | AP71: HRMDD | AX71: 02125296
X72: CERTIFYING OFFICER | AG72: DESIGNATION | AP72: OFFICE | AX72: CONTACT NUMBER
X73: (Signature Over Printed Name)
X74: CREDIT HISTORY
X75: Loan ID | AA75: Date Granted | AE75: Loan Granted | AJ75: Term | AM75: Maturity Date | AR75: MA | AU75: Status/Remarks | AZ75: Principal Balance
N79: 20-E 15th Avenue Corner, 2nd Camarilla St.
M80: Brgy. San Roque, Murphy, Cubao, Quezon City
N81: Mobile Number: 09194983770 / 09530331580 | X81: LOAN APPROVAL
X82: Loan Amount: | AC82: MA: | AG82: Term: | AK82: Required NTHP: | AR82: NTHP after MA | AW82: Total Loan Exposure:
M83: AUTHORIZATION FOR ACTIVE DEDUCTION | X83: ='[3]Data Entry'!E11 -> 178237.5 | AC83: =AT39 -> 2771.3809 | AG83: =AN35 -> 36 Months | AK83: 5000 | AR83: =11617.19-(AC83+AK83) -> 3845.8091 | AW83: ='[3]Data Entry'!E3 -> 201960.56
X84: PROCESSED & VERIFIED BY:
R85: =S29 -> 45701
R86: DATE | AJ86: PAMELA CHERRY A. REYES
W87: SIGNATURE OVER PRINTED NAME
K90: To whom it may concern: | X90: RECOMMEND APPROVAL/DISAPPROVAL: | AO90: APPROVED/DISAPPROVED:
K92: I hereby authorize that the amount of | O92: Five Thousand Six Hundred Ten and 02/100 (Php 5,610.02) | AB92: JEFFRAE A. SAPLA | AS92: COL.ALEXANDER L. FERIA (RET)CPA MNSA
K93: for a period | M93: months with the total amount of | P93: Two Hundred One Thousand Nine Hundred | X93: SIGNATURE OVER PRINTED NAME | AO93: SIGNATURE OVER PRINTED NAME
K94: Sixty and 56/100
X100: PROMISORY NOTE NO:
Y101: FOR VALUE RECEIVED, the undersigned promise to pay the People's Multi-Purpose Cooperative (PMPC) the sum of Php | AY101: =AW83 -> 201960.56
AA102: in | AB102: 36 | AC102: equal monthly installments amounting to Php | AN102: =AC83 -> 2771.3809 | AR102: each, to be paid on the 28th day of every month starting on
X103: =B28 -> 45729 | AB103: / Single Payment of due on unpaid installments from maturity will bear charges on unpaid principal
X104: at the rate of 2% per month as penatly thereof.
X105: I hereby waive presentment for payment and notice of dishonor. PMPC may accept partial payment reserving its right of recourse against me. PMPC is hereby authorized and empowered to set off or apply without notice what is due under this Note from whatever funds I have in the Cooperative.
X108: It is further agreed that in case of separation from the service of whatever cause, the unpaid balance with its accumulated surcharges and interest as stipulated above be deducted from my last paymnet, commutation of leave/furlough and/or from my pension.
X111: It is further agreed that when installments are not paid when due and payable, the whole of the principal sum remaining unpaid shall forthwith become due and payable at the election of the Cooperative. I promise and agree to pay for a reasonable attorney's fee if this note is not paid according to its legal tenor and effect when palced in a lawyer's hand for collection. In case litigation, venue shall be vested in the competent court as may be allowed by the Rules of Court at the sole option of PMPC.
X116: Further, I hereby agree and authorized PMPC to encumber, assign or sell to any person or entity any right which it may have under thi Note, and/or any assignment, mortgage lien, pledge or other encumbrances constituted in favor of PMPC pursuant to the provisions of this Note if any. The consent herein granted is recognized and acknowledged by me/us as a waiver, to all intent and purposes of whatever right I may have to notice of actual encumbrance/ assignment.
AM120: Military/Pensioners ID
AM121: Employee's ID/Office ID
AM122: Driver's License
Z123: =AU64 -> MADONNA LYN O MARQUEZ | AM123: Others: | AO123: UMID I.D.
X124: Signature over Printed Name
X126: ID No: | Z126: 006-0082-1396-1
X127: Expiration Date: | AT127: LEFT THUMBMARK | AZ127: RIGHT THUMBMARK
X130: ACKNOWLEDGEMENT
X132: REPUBLIC OF THE PHILIPPINES
...

Sheet LRV 5YEAR
B1: Amortization | C1: ='DATA ENTRY'!G15 -> 15000.248 | T1: pvap
B2: Timeline | C2: 0 | D2: 1 | E2: 2 | F2: 3 | G2: 4 | H2: 5 | I2: 6 | J2: 7 | K2: 8 | L2: 9 | M2: 10 | N2: 11 | O2: 12 | P2: 13 | Q2: 14 | R2: 15 | S2: 16 | T2: 17 | U2: 18 | V2: 19 | W2: 20 | X2: 21 | Y2: 22 | Z2: 23 | AA2: 24 | AB2: 25 | AC2: 26 | AD2: 27 | AE2: 28 | AF2: 29 | AG2: 30 | AH2: 31 | AI2: 32 | AJ2: 33 | AK2: 34 | AL2: 35 | AM2: 36 | AN2: 37 | AO2: 38 | AP2: 39 | AQ2: 40 | AR2: 41 | AS2: 42 | AT2: 43 | AU2: 44 | AV2: 45 | AW2: 46 | AX2: 47 | AY2: 48 | AZ2: 49 | BA2: 50 | BB2: 51 | BC2: 52 | BD2: 53 | BE2: 54 | BF2: 55 | BG2: 56 | BH2: 57 | BI2: 58 | BJ2: 59 | BK2: 60
B3: GROSS AMOUNT | C3: ='DATA ENTRY'!G4 -> 900014.89
A4: 41 | B4: LOAN AMOUNT | C4: ='DATA ENTRY'!G12 -> 722612.56 | D4: =-$C1 -> -15000.248 | E4: =-$C1 -> -15000.248 | F4: =-$C1 -> -15000.248 | G4: =-$C1 -> -15000.248 | H4: =-$C1 -> -15000.248 | I4: =-$C1 -> -15000.248 | J4: =-$C1 -> -15000.248 | K4: =-$C1 -> -15000.248 | ... BK4: =-$C1 -> -15000.248
B5: Service Fee | C5: ='DATA ENTRY'!G7 -> 72601.27
B6: Insurance | C6: ='DATA ENTRY'!G8 -> 36000.63
B7: CapCon | C7: ='DATA ENTRY'!G9 -> 5000
B8: membership fee | C8: ='DATA ENTRY'!G10 -> 0
B9: Advance Interest | C9: ='DATA ENTRY'!G11 -> 9000.1575
B10: NET PROCEEDS/CASH FLOW | C10: =C4-C5-C6-C7-C8-C9 -> 600010.5
B12: Interest Rate of Return | C12: =IRR(C4:BK4) -> 0.0075 | D12: =C12/5 -> 0.0015
B14: Loan Balance | C14: 315350.25
B15: Monthly Interest Rate | C15: ='DATA ENTRY'!G13/12 -> 0.0075
B16: Effective Interest Rate | C16: ='DATA ENTRY'!G14 -> 0.094100503
B17: Term | C17: 60
C20: LOAN LEDGER CARD
C22: Name: | D22: TABAQUERO, ARTHUR I. | G22: Loan Voucher No. | H22: LRV-059
C23: Serial Nr: | D23: O-7704 | E23: Address: | F23: #49 RICARTE ST. AFPOVAI WESTERN BICUTAN TAGUIG CITY METRO MANILA
C24: Posting date | D24: Date of Loan: | E24: 46031 | F24: Maturity Date | G24: =B87 -> 47916 | K24: PEOPLE'S MULTI-PURPOSE COOPERATIVE
D25: Term: | E25: =C17 -> 60 | F25: MOS | K25: 20-E 2nd Camarilla St. corner 15th Ave., Brgy. San Roque, Murphy Cubao, Quezon City | X25: 20-E 2nd Camarilla St corner 15th Avenue,
D26: Loan | E26: Installment | F26: Principal | G26: EIR | H26: Balance | X26: Brgy San Roque, Murphy Cubao, Quezon City
D27: Month 0 | H27: =C4 -> 722612.56 | K27: LOAN RELEASE VOUCHER | X27: Mobile No. (+63)953-033-1580 (GLOBE)
B28: =DATE(YEAR(E$24),MONTH(E$24)+D28+2,DAY(E$24)) -> 46121 | C28: =TEXT(B28,"mmm-yyyy") -> Apr-2026 | D28: 1 | E28: =C$1 -> 15000.248 | F28: =E28-G28 -> 9580.654 | G28: =H27*C$12 -> 5419.5942 | H28: =H27-F28 -> 713031.9
B29: =DATE(YEAR(E$24),MONTH(E$24)+D29+2,DAY(E$24)) -> 46151 | C29: =TEXT(B29,"mmm-yyyy") -> May-2026 | D29: 2 | E29: =C$1 -> 15000.248 | F29: =E29-G29 -> 9652.5089 | G29: =H28*C$12 -> 5347.7393 | H29: =H28-F29 -> 703379.4 | R29: Date: | S29: =E24 -> 46031 | X29: LOAN APPLICATION FORM
B30: =DATE(YEAR(E$24),MONTH(E$24)+D30+2,DAY(E$24)) -> 46182 | C30: =TEXT(B30,"mmm-yyyy") -> Jun-2026 | D30: 3 | E30: =C$1 -> 15000.248 | F30: =E30-G30 -> 9724.9027 | G30: =H29*C$12 -> 5275.3455 | H30: =H29-F30 -> 693654.49 | R30: LV No: | S30: =H22 -> LRV-059 | AU30: Date: | AW30: 0 | AX30: 1 | AY30: 0 | AZ30: 9 | BA30: 2 | BB30: 0 | BC30: 2 | BD30: 6
B31: =DATE(YEAR(E$24),MONTH(E$24)+D31+2,DAY(E$24)) -> 46212 | C31: =TEXT(B31,"mmm-yyyy") -> Jul-2026 | D31: 4 | E31: =C$1 -> 15000.248 | F31: =E31-G31 -> 9797.8395 | G31: =H30*C$12 -> 5202.4087 | H31: =H30-F31 -> 683856.65 | AW31: m | AX31: m | AY31: d | AZ31: d | BA31: y | BB31: y | BC31: y | BD31: y
B32: =DATE(YEAR(E$24),MONTH(E$24)+D32+2,DAY(E$24)) -> 46243 | C32: =TEXT(B32,"mmm-yyyy") -> Aug-2026 | D32: 5 | E32: =C$1 -> 15000.248 | F32: =E32-G32 -> 9871.3233 | G32: =H31*C$12 -> 5128.9249 | H32: =H31-F32 -> 673985.33 | K32: Name of Borrower: | N32: =D22 -> TABAQUERO, ARTHUR I. | X32: APPLICATION TYPE | AE32: LOAN CLASSIFICATION | AM32: TERM | AT32: RELEASE OF LOAN PROCEEDS
B33: =DATE(YEAR(E$24),MONTH(E$24)+D33+2,DAY(E$24)) -> 46274 | C33: =TEXT(B33,"mmm-yyyy") -> Sep-2026 | D33: 6 | E33: =C$1 -> 15000.248 | F33: =E33-G33 -> 9945.3582 | G33: =H32*C$12 -> 5054.89 | H33: =H32-F33 -> 664039.97 | K33: Serial No.: | N33: =D23 -> O-7704 | Y33: New | AF33: Salary Loan | AN33: 12 Months | AU33: CHEQUE
B34: =DATE(YEAR(E$24),MONTH(E$24)+D34+2,DAY(E$24)) -> 46304 | C34: =TEXT(B34,"mmm-yyyy") -> Oct-2026 | D34: 7 | E34: =C$1 -> 15000.248 | F34: =E34-G34 -> 10019.948 | G34: =H33*C$12 -> 4980.2998 | H34: =H33-F34 -> 654020.02 | K34: Address: | N34: =F23 -> #49 RICARTE ST. AFPOVAI WESTERN BICUTAN TAGUIG CITY METRO MANILA | Y34: Renewal | AF34: Pension Loan | AN34: 24 Months | AU34: Bank Electronic Transfer to Borrowers Account
B35: =DATE(YEAR(E$24),MONTH(E$24)+D35+2,DAY(E$24)) -> 46335 | C35: =TEXT(B35,"mmm-yyyy") -> Nov-2026 | D35: 8 | E35: =C$1 -> 15000.248 | F35: =E35-G35 -> 10095.098 | G35: =H34*C$12 -> 4905.1502 | H35: =H34-F35 -> 643924.93 | Y35: Additional | AF35: Emergency | AN35: 36 Months | AU35: Others:
B36: =DATE(YEAR(E$24),MONTH(E$24)+D36+2,DAY(E$24)) -> 46365 | C36: =TEXT(B36,"mmm-yyyy") -> Dec-2026 | D36: 9 | E36: =C$1 -> 15000.248 | F36: =E36-G36 -> 10170.811 | G36: =H35*C$12 -> 4829.4369 | H36: =H35-F36 -> 633754.11 | L36: Principal Amount | R36: =C4 -> 722612.56 | Y36: Reloan | AF36: Health Assistance Loan | AN36: 48 Months
B37: =DATE(YEAR(E$24),MONTH(E$24)+D37+2,DAY(E$24)) -> 46396 | C37: =TEXT(B37,"mmm-yyyy") -> Jan-2027 | D37: 10 | E37: =C$1 -> 15000.248 | F37: =E37-G37 -> 10247.092 | G37: =H36*C$12 -> 4753.1559 | H37: =H36-F37 -> 623507.02 | Y37: Restructure | AF37: Educational Loan | AN37: 60 Months
B38: =DATE(YEAR(E$24),MONTH(E$24)+D38+2,DAY(E$24)) -> 46427 | C38: =TEXT(B38,"mmm-yyyy") -> Feb-2027 | D38: 11 | E38: =C$1 -> 15000.248 | F38: =E38-G38 -> 10323.946 | G38: =H37*C$12 -> 4676.3027 | H38: =H37-F38 -> 613183.08 | L38: (-) | M38: Balance Old Loan(s) | R38: =-C14 -> -315350.25 | AF38: Others: | AN38: Others:
B39: =DATE(YEAR(E$24),MONTH(E$24)+D39+2,DAY(E$24)) -> 46455 | C39: =TEXT(B39,"mmm-yyyy") -> Mar-2027 | D39: 12 | E39: =C$1 -> 15000.248 | F39: =E39-G39 -> 10401.375 | G39: =H38*C$12 -> 4598.8731 | H39: =H38-F39 -> 602781.7 | L39: (-) | M39: Membership Fee: | R39: =-C8 -> 0 | X39: AMOUNT APPLIED: | AB39: =R44 -> 284660.25 | AN39: MONTHLY AMORTIZATION: | AT39: =C1 -> 15000.248
B40: =DATE(YEAR(E$24),MONTH(E$24)+D40+2,DAY(E$24)) -> 46486 | C40: =TEXT(B40,"mmm-yyyy") -> Apr-2027 | D40: 13 | E40: =C$1 -> 15000.248 | F40: =E40-G40 -> 10479.385 | G40: =H39*C$12 -> 4520.8628 | H40: =H39-F40 -> 592302.32 | L40: (-) | M40: Paid up Capital: | R40: =-C7 -> -5000
B41: =DATE(YEAR(E$24),MONTH(E$24)+D41+2,DAY(E$24)) -> 46516 | C41: =TEXT(B41,"mmm-yyyy") -> May-2027 | D41: 14 | E41: =C$1 -> 15000.248 | F41: =E41-G41 -> 10557.981 | G41: =H40*C$12 -> 4442.2674 | H41: =H40-F41 -> 581744.33 | L41: (-) | M41: Service Fee | R41: =-C5 -> -72601.27 | X41: LOAN ID: | AF41: DEDUCTION CODE: | AR41: LOAN PURPOSE:
B42: =DATE(YEAR(E$24),MONTH(E$24)+D42+2,DAY(E$24)) -> 46547 | C42: =TEXT(B42,"mmm-yyyy") -> Jun-2027 | D42: 15 | E42: =C$1 -> 15000.248 | F42: =E42-G42 -> 10637.166 | G42: =H41*C$12 -> 4363.0825 | H42: =H41-F42 -> 571107.17 | L42: (-) | M42: Insurance Premium - Paramount | R42: =-C6 -> -36000.63 | X42: MEM ID: | AG42: Regular Member | AS42: Old Member
B43: =DATE(YEAR(E$24),MONTH(E$24)+D43+2,DAY(E$24)) -> 46577 | C43: =TEXT(B43,"mmm-yyyy") -> Jul-2027 | D43: 16 | E43: =C$1 -> 15000.248 | F43: =E43-G43 -> 10716.944 | G43: =H42*C$12 -> 4283.3038 | H43: =H42-F43 -> 560390.22 | L43: (-) | M43: Advance Interest | R43: =-C9 -> -9000.1575 | AG43: Associate Member | AS43: New Member
B44: =DATE(YEAR(E$24),MONTH(E$24)+D44+2,DAY(E$24)) -> 46608 | C44: =TEXT(B44,"mmm-yyyy") -> Aug-2027 | D44: 17 | E44: =C$1 -> 15000.248 | F44: =E44-G44 -> 10797.321 | G44: =H43*C$12 -> 4202.9267 | H44: =H43-F44 -> 549592.9 | L44: NET PROCEEDS (Php): | R44: =SUM(R36:T43) -> 284660.25 | X44: BORROWER'S INFORMATION
B45: =DATE(YEAR(E$24),MONTH(E$24)+D45+2,DAY(E$24)) -> 46639 | C45: =TEXT(B45,"mmm-yyyy") -> Sep-2027 | D45: 18 | E45: =C$1 -> 15000.248 | F45: =E45-G45 -> 10878.301 | G45: =H44*C$12 -> 4121.9468 | H45: =H44-F45 -> 538714.6 | X45: TABAQUERO | AD45: ARTHUR | AN45: IBANEZ
B46: =DATE(YEAR(E$24),MONTH(E$24)+D46+2,DAY(E$24)) -> 46669 | C46: =TEXT(B46,"mmm-yyyy") -> Oct-2027 | D46: 19 | E46: =C$1 -> 15000.248 | F46: =E46-G46 -> 10959.889 | G46: =H45*C$12 -> 4040.3595 | H46: =H45-F46 -> 527754.71 | K46: PAYMENT | X46: (LAST NAME) | AD46: (FIRST NAME) | AN46: (MIDDLE NAME) | AZ46: (SUFFIX)
B47: =DATE(YEAR(E$24),MONTH(E$24)+D47+2,DAY(E$24)) -> 46700 | C47: =TEXT(B47,"mmm-yyyy") -> Nov-2027 | D47: 20 | E47: =C$1 -> 15000.248 | F47: =E47-G47 -> 11042.088 | G47: =H46*C$12 -> 3958.1603 | H47: =H46-F47 -> 516712.63 | X47: Rank/Position: | AD47: Serial No.: | AI47: Branch of Service: | AO47: Date of Appointment: | AW47: Date of Retirement:
B48: =DATE(YEAR(E$24),MONTH(E$24)+D48+2,DAY(E$24)) -> 46730 | C48: =TEXT(B48,"mmm-yyyy") -> Dec-2027 | D48: 21 | E48: =C$1 -> 15000.248 | F48: =E48-G48 -> 11124.903 | G48: =H47*C$12 -> 3875.3447 | H48: =H47-F48 -> 505587.72 | L48: Term of loan in months: | R48: 60 | T48: month(s) | X48: LTGEN | AD48: =D23 -> O-7704 | AI48: PA
B49: =DATE(YEAR(E$24),MONTH(E$24)+D49+2,DAY(E$24)) -> 46761 | C49: =TEXT(B49,"mmm-yyyy") -> Jan-2028 | D49: 22 | E49: =C$1 -> 15000.248 | F49: =E49-G49 -> 11208.34 | G49: =H48*C$12 -> 3791.9079 | H49: =H48-F49 -> 494379.38 | L49: Monthly Amortization | R49: =C1 -> 15000.248 | AO49: m | AP49: m | AQ49: d | AR49: d | AS49: y | AT49: y | AU49: y | AV49: y | AW49: m | AX49: m | AY49: d | AZ49: d | BA49: y | BB49: y | BC49: y | BD49: y
B50: =DATE(YEAR(E$24),MONTH(E$24)+D50+2,DAY(E$24)) -> 46792 | C50: =TEXT(B50,"mmm-yyyy") -> Feb-2028 | D50: 23 | E50: =C$1 -> 15000.248 | F50: =E50-G50 -> 11292.403 | G50: =H49*C$12 -> 3707.8454 | H50: =H49-F50 -> 483086.98 | L50: First Payment Due On: | R50: =B28 -> 46121
B51: =DATE(YEAR(E$24),MONTH(E$24)+D51+2,DAY(E$24)) -> 46821 | C51: =TEXT(B51,"mmm-yyyy") -> Mar-2028 | D51: 24 | E51: =C$1 -> 15000.248 | F51: =E51-G51 -> 11377.096 | G51: =H50*C$12 -> 3623.1523 | H51: =H50-F51 -> 471709.88 | L51: Maturity: | R51: =B87 -> 47916 | X51: Length of Service: | AE51: Date of Birth: | AJ51: Age: | AK51: 69 | AM51: Civil Status: | AR51: Single | AU51: Widower | AX51: Home Phone No.
B52: =DATE(YEAR(E$24),MONTH(E$24)+D52+2,DAY(E$24)) -> 46852 | C52: =TEXT(B52,"mmm-yyyy") -> Apr-2028 | D52: 25 | E52: =C$1 -> 15000.248 | F52: =E52-G52 -> 11462.424 | G52: =H51*C$12 -> 3537.8241 | H52: =H51-F52 -> 460247.46 | L52: EIR (%): | R52: =C16 -> 0.094100503 | AE52: 20562 | AR52: Married | AU52: Separated
B53: =DATE(YEAR(E$24),MONTH(E$24)+D53+2,DAY(E$24)) -> 46882 | C53: =TEXT(B53,"mmm-yyyy") -> May-2028 | D53: 26 | E53: =C$1 -> 15000.248 | F53: =E53-G53 -> 11548.392 | G53: =H52*C$12 -> 3451.8559 | H53: =H52-F53 -> 448699.07 | L53: Interest Rate per Month (%): | R53: =C15 -> 0.0075 | X53: Unit Assignment: | AE53: Unit/Office/Business Address: | AX53: Unit/Office Telephone No/s:
B54: =DATE(YEAR(E$24),MONTH(E$24)+D54+2,DAY(E$24)) -> 46913 | C54: =TEXT(B54,"mmm-yyyy") -> Jun-2028 | D54: 27 | E54: =C$1 -> 15000.248 | F54: =E54-G54 -> 11635.005 | G54: =H53*C$12 -> 3365.243 | H54: =H53-F54 -> 437064.06
B55: =DATE(YEAR(E$24),MONTH(E$24)+D55+2,DAY(E$24)) -> 46943 | C55: =TEXT(B55,"mmm-yyyy") -> Jul-2028 | D55: 28 | E55: =C$1 -> 15000.248 | F55: =E55-G55 -> 11722.268 | G55: =H54*C$12 -> 3277.9805 | H55: =H54-F55 -> 425341.79 | X55: AFP/Company ID No: | AG55: Email Address: | AT55: Tax Identification No/s:
B56: =DATE(YEAR(E$24),MONTH(E$24)+D56+2,DAY(E$24)) -> 46974 | C56: =TEXT(B56,"mmm-yyyy") -> Aug-2028 | D56: 29 | E56: =C$1 -> 15000.248 | F56: =E56-G56 -> 11810.185 | G56: =H55*C$12 -> 3190.0635 | H56: =H55-F56 -> 413531.61 | K56: Certified & Corrected by: | R56: Verified by: | AG56: ait38467704@gmail.com | AT56: 1 | AU56: 3 | AV56: 8 | AW56: - | AX56: 0 | AY56: 0 | AZ56: 6 | BA56: - | BB56: 2 | BC56: 9 | BD56: 3
B57: =DATE(YEAR(E$24),MONTH(E$24)+D57+2,DAY(E$24)) -> 47005 | C57: =TEXT(B57,"mmm-yyyy") -> Sep-2028 | D57: 30 | E57: =C$1 -> 15000.248 | F57: =E57-G57 -> 11898.761 | G57: =H56*C$12 -> 3101.4871 | H57: =H56-F57 -> 401632.85 | X57: Present Address: | AB57: =N34 -> #49 RICARTE ST. AFPOVAI WESTERN BICUTAN TAGUIG CITY METRO MANILA
B58: =DATE(YEAR(E$24),MONTH(E$24)+D58+2,DAY(E$24)) -> 47035 | C58: =TEXT(B58,"mmm-yyyy") -> Oct-2028 | D58: 31 | E58: =C$1 -> 15000.248 | F58: =E58-G58 -> 11988.002 | G58: =H57*C$12 -> 3012.2464 | H58: =H57-F58 -> 389644.85 | X58: NOTIFICATION CLAUSE
B59: =DATE(YEAR(E$24),MONTH(E$24)+D59+2,DAY(E$24)) -> 47066 | C59: =TEXT(B59,"mmm-yyyy") -> Nov-2028 | D59: 32 | E59: =C$1 -> 15000.248 | F59: =E59-G59 -> 12077.912 | G59: =H58*C$12 -> 2922.3363 | H59: =H58-F59 -> 377566.93
B60: =DATE(YEAR(E$24),MONTH(E$24)+D60+2,DAY(E$24)) -> 47096 | C60: =TEXT(B60,"mmm-yyyy") -> Dec-2028 | D60: 33 | E60: =C$1 -> 15000.248 | F60: =E60-G60 -> 12168.496 | G60: =H59*C$12 -> 2831.752 | H60: =H59-F60 -> 365398.44 | K60: JEFFRAE A. SAPLA | R60: ALEXANDER A. FERIA JR | Y60: I hereby acknowledge and authorized the People's Multi-Purpose Cooperative (PMPC) for the following: 1) the regular submission and disclosure
B61: =DATE(YEAR(E$24),MONTH(E$24)+D61+2,DAY(E$24)) -> 47127 | C61: =TEXT(B61,"mmm-yyyy") -> Jan-2029 | D61: 34 | E61: =C$1 -> 15000.248 | F61: =E61-G61 -> 12259.76 | G61: =H60*C$12 -> 2740.4883 | H61: =H60-F61 -> 353138.68 | K61: Processor | R61: Verifier/PELVAMS Liason | X61: of my basic credit data (as defined under Republic Act Nr 9510 and its Implementing Rules and Regulations) to the Credit Information Corporation (CIC)
B62: =DATE(YEAR(E$24),MONTH(E$24)+D62+2,DAY(E$24)) -> 47158 | C62: =TEXT(B62,"mmm-yyyy") -> Feb-2029 | D62: 35 | E62: =C$1 -> 15000.248 | F62: =E62-G62 -> 12351.708 | G62: =H61*C$12 -> 2648.5401 | H62: =H61-F62 -> 340786.97 | X62: as well as any updates or corrections thereof; and 2) the sharing of my basic data and with other lenders authorized by the CIC, and credit reporting
B63: =DATE(YEAR(E$24),MONTH(E$24)+D63+2,DAY(E$24)) -> 47186 | C63: =TEXT(B63,"mmm-yyyy") -> Mar-2029 | D63: 36 | E63: =C$1 -> 15000.248 | F63: =E63-G63 -> 12444.346 | G63: =H62*C$12 -> 2555.9023 | H63: =H62-F63 -> 328342.62 | X63: agencies duly accredited by the CIC.
B64: =DATE(YEAR(E$24),MONTH(E$24)+D64+2,DAY(E$24)) -> 47217 | C64: =TEXT(B64,"mmm-yyyy") -> Apr-2029 | D64: 37 | E64: =C$1 -> 15000.248 | F64: =E64-G64 -> 12537.678 | G64: =H63*C$12 -> 2462.5697 | H64: =H63-F64 -> 315804.95 | AU64: =K69 -> TABAQUERO, ARTHUR I.
B65: =DATE(YEAR(E$24),MONTH(E$24)+D65+2,DAY(E$24)) -> 47247 | C65: =TEXT(B65,"mmm-yyyy") -> May-2029 | D65: 38 | E65: =C$1 -> 15000.248 | F65: =E65-G65 -> 12631.711 | G65: =H64*C$12 -> 2368.5371 | H65: =H64-F65 -> 303173.23 | AU65: Printed Name & Signature of Borrower
B66: =DATE(YEAR(E$24),MONTH(E$24)+D66+2,DAY(E$24)) -> 47278 | C66: =TEXT(B66,"mmm-yyyy") -> Jun-2029 | D66: 39 | E66: =C$1 -> 15000.248 | F66: =E66-G66 -> 12726.449 | G66: =H65*C$12 -> 2273.7993 | H66: =H65-F66 -> 290446.79 | K66: Received By: | R66: Approved By: | X66: CERTIFICATION
B67: =DATE(YEAR(E$24),MONTH(E$24)+D67+2,DAY(E$24)) -> 47308 | C67: =TEXT(B67,"mmm-yyyy") -> Jul-2029 | D67: 40 | E67: =C$1 -> 15000.248 | F67: =E67-G67 -> 12821.897 | G67: =H66*C$12 -> 2178.3509 | H67: =H66-F67 -> 277624.89
B68: =DATE(YEAR(E$24),MONTH(E$24)+D68+2,DAY(E$24)) -> 47339 | C68: =TEXT(B68,"mmm-yyyy") -> Aug-2029 | D68: 41 | E68: =C$1 -> 15000.248 | F68: =E68-G68 -> 12918.062 | G68: =H67*C$12 -> 2082.1867 | H68: =H67-F68 -> 264706.83 | Y68: I hereby certify that the applicant is assigned to this Office; is not on leave without pay; has no pending case; and, that all information he/she
B69: =DATE(YEAR(E$24),MONTH(E$24)+D69+2,DAY(E$24)) -> 47370 | C69: =TEXT(B69,"mmm-yyyy") -> Sep-2029 | D69: 42 | E69: =C$1 -> 15000.248 | F69: =E69-G69 -> 13014.947 | G69: =H68*C$12 -> 1985.3012 | H69: =H68-F69 -> 251691.88 | K69: =N32 -> TABAQUERO, ARTHUR I. | P69: COL.ALEXANDER L. FERIA (RET) CPA MNSA | X69: provided is true and correct.
B70: =DATE(YEAR(E$24),MONTH(E$24)+D70+2,DAY(E$24)) -> 47400 | C70: =TEXT(B70,"mmm-yyyy") -> Oct-2029 | D70: 43 | E70: =C$1 -> 15000.248 | F70: =E70-G70 -> 13112.559 | G70: =H69*C$12 -> 1887.6891 | H70: =H69-F70 -> 238579.32 | K70: Signature Over Printed Name/Date | R70: President
B71: =DATE(YEAR(E$24),MONTH(E$24)+D71+2,DAY(E$24)) -> 47431 | C71: =TEXT(B71,"mmm-yyyy") -> Nov-2029 | D71: 44 | E71: =C$1 -> 15000.248 | F71: =E71-G71 -> 13210.903 | G71: =H70*C$12 -> 1789.3449 | H71: =H70-F71 -> 225368.42
B72: =DATE(YEAR(E$24),MONTH(E$24)+D72+2,DAY(E$24)) -> 47461 | C72: =TEXT(B72,"mmm-yyyy") -> Dec-2029 | D72: 45 | E72: =C$1 -> 15000.248 | F72: =E72-G72 -> 13309.985 | G72: =H71*C$12 -> 1690.2631 | H72: =H71-F72 -> 212058.43 | X72: CERTIFYING OFFICER | AG72: DESIGNATION | AP72: OFFICE | AX72: CONTACT NUMBER
B73: =DATE(YEAR(E$24),MONTH(E$24)+D73+2,DAY(E$24)) -> 47492 | C73: =TEXT(B73,"mmm-yyyy") -> Jan-2030 | D73: 46 | E73: =C$1 -> 15000.248 | F73: =E73-G73 -> 13409.81 | G73: =H72*C$12 -> 1590.4382 | H73: =H72-F73 -> 198648.62 | X73: (Signature Over Printed Name)
B74: =DATE(YEAR(E$24),MONTH(E$24)+D74+2,DAY(E$24)) -> 47523 | C74: =TEXT(B74,"mmm-yyyy") -> Feb-2030 | D74: 47 | E74: =C$1 -> 15000.248 | F74: =E74-G74 -> 13510.383 | G74: =H73*C$12 -> 1489.8647 | H74: =H73-F74 -> 185138.24 | X74: CREDIT HISTORY
B75: =DATE(YEAR(E$24),MONTH(E$24)+D75+2,DAY(E$24)) -> 47551 | C75: =TEXT(B75,"mmm-yyyy") -> Mar-2030 | D75: 48 | E75: =C$1 -> 15000.248 | F75: =E75-G75 -> 13611.711 | G75: =H74*C$12 -> 1388.5368 | H75: =H74-F75 -> 171526.53 | X75: Loan ID | AA75: Date Granted | AE75: Loan Granted | AJ75: Term | AM75: Maturity Date | AR75: MA | AU75: Status/Remarks | AZ75: Principal Balance
B76: =DATE(YEAR(E$24),MONTH(E$24)+D76+2,DAY(E$24)) -> 47582 | C76: =TEXT(B76,"mmm-yyyy") -> Apr-2030 | D76: 49 | E76: =C$1 -> 15000.248 | F76: =E76-G76 -> 13713.799 | G76: =H75*C$12 -> 1286.449 | H76: =H75-F76 -> 157812.73
B77: =DATE(YEAR(E$24),MONTH(E$24)+D77+2,DAY(E$24)) -> 47612 | C77: =TEXT(B77,"mmm-yyyy") -> May-2030 | D77: 50 | E77: =C$1 -> 15000.248 | F77: =E77-G77 -> 13816.653 | G77: =H76*C$12 -> 1183.5955 | H77: =H76-F77 -> 143996.08
B78: =DATE(YEAR(E$24),MONTH(E$24)+D78+2,DAY(E$24)) -> 47643 | C78: =TEXT(B78,"mmm-yyyy") -> Jun-2030 | D78: 51 | E78: =C$1 -> 15000.248 | F78: =E78-G78 -> 13920.278 | G78: =H77*C$12 -> 1079.9706 | H78: =H77-F78 -> 130075.8
B79: =DATE(YEAR(E$24),MONTH(E$24)+D79+2,DAY(E$24)) -> 47673 | C79: =TEXT(B79,"mmm-yyyy") -> Jul-2030 | D79: 52 | E79: =C$1 -> 15000.248 | F79: =E79-G79 -> 14024.68 | G79: =H78*C$12 -> 975.56849 | H79: =H78-F79 -> 116051.12
B80: =DATE(YEAR(E$24),MONTH(E$24)+D80+2,DAY(E$24)) -> 47704 | C80: =TEXT(B80,"mmm-yyyy") -> Aug-2030 | D80: 53 | E80: =C$1 -> 15000.248 | F80: =E80-G80 -> 14129.865 | G80: =H79*C$12 -> 870.38339 | H80: =H79-F80 -> 101921.25
B81: =DATE(YEAR(E$24),MONTH(E$24)+D81+2,DAY(E$24)) -> 47735 | C81: =TEXT(B81,"mmm-yyyy") -> Sep-2030 | D81: 54 | E81: =C$1 -> 15000.248 | F81: =E81-G81 -> 14235.839 | G81: =H80*C$12 -> 764.4094 | H81: =H80-F81 -> 87685.415 | X81: LOAN APPROVAL
B82: =DATE(YEAR(E$24),MONTH(E$24)+D82+2,DAY(E$24)) -> 47765 | C82: =TEXT(B82,"mmm-yyyy") -> Oct-2030 | D82: 55 | E82: =C$1 -> 15000.248 | F82: =E82-G82 -> 14342.608 | G82: =H81*C$12 -> 657.64061 | H82: =H81-F82 -> 73342.808 | X82: Loan Amount: | AC82: MA: | AG82: Term: | AK82: Required NTHP: | AR82: NTHP after MA | AW82: Total Loan Exposure:
B83: =DATE(YEAR(E$24),MONTH(E$24)+D83+2,DAY(E$24)) -> 47796 | C83: =TEXT(B83,"mmm-yyyy") -> Nov-2030 | D83: 56 | E83: =C$1 -> 15000.248 | F83: =E83-G83 -> 14450.177 | G83: =H82*C$12 -> 550.07106 | H83: =H82-F83 -> 58892.63 | X83: =C4 -> 722612.56 | AC83: =AT39 -> 15000.248 | AG83: =E25 -> 60 | AW83: =C3 -> 900014.89
B84: =DATE(YEAR(E$24),MONTH(E$24)+D84+2,DAY(E$24)) -> 47826 | C84: =TEXT(B84,"mmm-yyyy") -> Dec-2030 | D84: 57 | E84: =C$1 -> 15000.248 | F84: =E84-G84 -> 14558.553 | G84: =H83*C$12 -> 441.69473 | H84: =H83-F84 -> 44334.077 | X84: PROCESSED & VERIFIED BY:
B85: =DATE(YEAR(E$24),MONTH(E$24)+D85+2,DAY(E$24)) -> 47857 | C85: =TEXT(B85,"mmm-yyyy") -> Jan-2031 | D85: 58 | E85: =C$1 -> 15000.248 | F85: =E85-G85 -> 14667.743 | G85: =H84*C$12 -> 332.50558 | H85: =H84-F85 -> 29666.334
B86: =DATE(YEAR(E$24),MONTH(E$24)+D86+2,DAY(E$24)) -> 47888 | C86: =TEXT(B86,"mmm-yyyy") -> Feb-2031 | D86: 59 | E86: =C$1 -> 15000.248 | F86: =E86-G86 -> 14777.751 | G86: =H85*C$12 -> 222.49751 | H86: =H85-F86 -> 14888.584 | AJ86: =K60 -> JEFFRAE A. SAPLA
B87: =DATE(YEAR(E$24),MONTH(E$24)+D87+2,DAY(E$24)) -> 47916 | C87: =TEXT(B87,"mmm-yyyy") -> Mar-2031 | D87: 60 | E87: =C$1 -> 15000.248 | F87: =E87-G87 -> 14888.584 | G87: =H86*C$12 -> 111.66438 | H87: =H86-F87 -> -1.8299033e-09 | W87: SIGNATURE OVER PRINTED NAME
E88: =SUM(E28:E87) -> 900014.89 | F88: =SUM(F28:F87) -> 722612.56 | G88: =SUM(G28:G87) -> 177402.33
X90: RECOMMEND APPROVAL/DISAPPROVAL: | AO90: APPROVED/DISAPPROVED:
AB92: =R60 -> ALEXANDER A. FERIA JR | AR92: COL.ALEXANDER L. FERIA (RET)CPA MNSA
X93: SIGNATURE OVER PRINTED NAME | AO93: SIGNATURE OVER PRINTED NAME
X100: PROMISORY NOTE NO: | AL100: =H22 -> LRV-059
Y101: FOR VALUE RECEIVED, the undersigned promise to pay the People's Multi-Purpose Cooperative (PMPC) the sum of Php | AY101: =AW83 -> 900014.89
AA102: in | AB102: =E25 -> 60 | AC102: equal monthly installments amounting to Php | AN102: =AC83 -> 15000.248 | AR102: each, to be paid on the 28th day of every month starting on
X103: =R50 -> 46121 | AB103: / Single Payment of due on unpaid installments from maturity will bear charges on unpaid principal
X104: at the rate of 2% per month as penatly thereof.
X105: I hereby waive presentment for payment and notice of dishonor. PMPC may accept partial payment reserving its right of recourse against me. PMPC is hereby authorized and empowered to set off or apply without notice what is due under this Note from whatever funds I have in the Cooperative.
X108: It is further agreed that in case of separation from the service of whatever cause, the unpaid balance with its accumulated surcharges and interest as stipulated above be deducted from my last paymnet, commutation of leave/furlough, capital contribution, and/or from my pension.
X111: It is further agreed that when installments are not paid when due and payable, the whole of the principal sum remaining unpaid shall forthwith become due and payable at the election of the Cooperative. I promise and agree to pay for a reasonable attorney's fee if this note is not paid according to its legal tenor and effect when palced in a lawyer's hand for collection. In case litigation, venue shall be vested in the competent court as may be allowed by the Rules of Court at the sole option of PMPC.
X116: Further, I hereby agree and authorized PMPC to encumber, assign or sell to any person or entity any right which it may have under thi Note, and/or any assignment, mortgage lien, pledge or other encumbrances constituted in favor of PMPC pursuant to the provisions of this Note if any. The consent herein granted is recognized and acknowledged by me/us as a waiver, to all intent and purposes of whatever right I may have to notice of actual encumbrance/ assignment.
AM120: Military/Pensioners ID
AM121: Employee's ID/Office ID
AM122: Driver's License
Z123: =AU64 -> TABAQUERO, ARTHUR I. | AM123: Others:
X124: Signature over Printed Name
...

Sheet Sheet3

Sheet Sheet1
L6: 140000 | M6: 60 | N6: TO WITHDRAW
L7: 200000
L8: =L7-L6 -> 60000
E10: total number of income | F10: 1800000 | K10: xander
E11: cooperative income | F11: =F10*0.2 -> 360000 | K11: cc | L11: 100000
E12: income | F12: =F10-F11 -> 1440000 | L12: =L11/500 -> 200
E13: Dividends | F13: 2000000 | G13: 40000 | H13: =F13/G13 -> 50 | L13: =L12*H13 -> 10000
E14: Patronage Refund | F14: =F12*0.3 -> 432000
E19: misson
E20: vision | F20: 2022 | G20: jan | H20: december
G21: 800000 | H21: 8000000 | K21: cc | L21: savings | M21: time
F22: 2023 | G22: jan | H22: december | J22: 2023 - 2024 | K22: 0.06 | L22: 0.063 | M22: 0.063
G23: =H21 -> 8000000 | H23: 14000000 | J23: 2024-2025 | K23: 0.0908 | L23: 0.063 | M23: 0.063
F24: 2024 | G24: jan | H24: december | J24: 2025-2026
G25: =H23 -> 14000000 | H25: 23000000
F26: 2025 | G26: jan | H26: currrent
G27: =H25 -> 23000000 | H27: 27000000
