Workbook

Sheet DATA ENTRY
B1: Editable
C3: 1 Yr | D3: 2 Yrs | E3: 3 Yrs | F3: 4 Yrs | G3: 5 Yrs
B4: GROSS AMOUNT | C4: ='Computation Table'!C108 -> 174984.11 | D4: ='Computation Table'!C82 -> 127991.37 | E4: ='Computation Table'!C56 -> 601062.61 | F4: ='Computation Table'!C29 -> 649762.37 | G4: ='Computation Table'!C3 -> 629999.88
B5: NET PROCEEDS | C5: 152000 | D5: 100000 | E5: 443817.41 | F5: 444037 | G5: 388616
B6: Add:
B7: Previous Loan Balance
B8: Service Fee | C8: ='Computation Table'!C110 -> 10640 | D8: ='Computation Table'!C84 -> 7500 | E8: ='Computation Table'!C58 -> 39943.567 | F8: ='Computation Table'!C31 -> 39963.33 | G8: ='Computation Table'!C5 -> 47022.536
B9: Insurance | C9: ='Computation Table'!C111 -> 1824 | D9: ='Computation Table'!C85 -> 2400 | E9: ='Computation Table'!C59 -> 15977.427 | F9: ='Computation Table'!C32 -> 21313.776 | G9: ='Computation Table'!C6 -> 23316.96
B10: CapCon | D10: 5000 | E10: 10000 | F10: 10000 | G10: 5000
B11: membership fee | E11: 300 | F11: 300 | G11: 300
B12: Advance Interest | C12: ='Computation Table'!C114 -> 2280 | D12: ='Computation Table'!C88 -> 1541.6667 | E12: ='Computation Table'!C62 -> 7396.9568 | F12: ='Computation Table'!C35 -> 8140.6783 | G12: ='Computation Table'!C9 -> 7772.32
B13: LOAN AMOUNT | C13: =SUM(C5:C11) -> 164464 | D13: =SUM(D5:D12) -> 116441.67 | E13: =SUM(E5:E12) -> 517435.36 | F13: =SUM(F5:F12) -> 523754.78 | G13: =SUM(G5:G12) -> 472027.82 | J13: 352669.13 | K13: 91376.87
B14: Annual Interest Rate | C14: ='Computation Table'!C116 -> 0.09 | D14: ='Computation Table'!C90 -> 0.0925 | E14: ='Computation Table'!C64 -> 0.1 | F14: ='Computation Table'!C37 -> 0.11 | G14: ='Computation Table'!C11 -> 0.12 | K14: =J13+K13 -> 444046
B15: Effective Interest Rate | C15: ='Computation Table'!C117 -> 0.093806898 | D15: ='Computation Table'!F91 -> 0.096718129 | E15: ='Computation Table'!F65 -> 0.10501772 | F15: ='Computation Table'!C38 -> 0.1161376 | G15: ='Computation Table'!C12 -> 0.12736174
B16: Monthly Amortization | C16: ='Computation Table'!C126 -> 14582.009 | D16: ='Computation Table'!C100 -> 5332.9739 | E16: ='Computation Table'!C74 -> 16696.184 | F16: ='Computation Table'!C47 -> 13536.716 | G16: ='Computation Table'!C21 -> 10499.998

Sheet Amortization  Table
B1: PEOPLE'S MULTI-PURPOSE COOPERATIVE EFFECTIVE ON JANUARY 16, 2025
B4: AFP LOAN TABLE - BUY OUT
B5: Net Proceeds | C5: 1 Yr 12 Months | D5: 2 Yrs 24 Months | E5: 3 Yrs 36 Months | F5: 4 Yrs 48 Months | G5: 5 Yrs 60 Months
B7: 25000 | C7: ='Computation Table'!E126 -> 2398.3568 | D7: ='Computation Table'!C100 -> 5332.9739 | E7: ='Computation Table'!E74 -> 913.69918 | F7: ='Computation Table'!E47 -> 735.30512 | G7: ='Computation Table'!E21 -> 667.88954
B8: 50000 | C8: ='Computation Table'!F126 -> 4796.7135 | D8: ='Computation Table'!F100 -> 2780.9858 | E8: ='Computation Table'!F74 -> 2159.7504 | F8: ='Computation Table'!F47 -> 1736.8191 | G8: ='Computation Table'!F21 -> 1453.6747
B9: 75000 | C9: ='Computation Table'!G126 -> 7195.0703 | D9: ='Computation Table'!G100 -> 3827.9822 | E9: ='Computation Table'!G74 -> 2741.0976 | F9: ='Computation Table'!G47 -> 2205.9154 | G9: ='Computation Table'!G21 -> 2003.6686
B10: 100000 | C10: ='Computation Table'!H126 -> 9593.427 | D10: ='Computation Table'!H100 -> 5332.9739 | E10: ='Computation Table'!H74 -> 3987.1488 | F10: ='Computation Table'!H47 -> 3207.4294 | G10: ='Computation Table'!H21 -> 2789.4537
B11: 150000 | C11: ='Computation Table'!J126 -> 14390.141 | D11: ='Computation Table'!J100 -> 7884.962 | E11: ='Computation Table'!J74 -> 5814.5471 | F11: ='Computation Table'!J47 -> 4678.0396 | G11: ='Computation Table'!J21 -> 4125.2328
B12: 200000 | C12: ='Computation Table'!L126 -> 19186.854 | D12: ='Computation Table'!L100 -> 10436.95 | E12: ='Computation Table'!L74 -> 7641.9455 | F12: ='Computation Table'!L47 -> 6148.6498 | G12: ='Computation Table'!L21 -> 5461.0119
B13: 250000 | C13: ='Computation Table'!N126 -> 23983.568 | D13: ='Computation Table'!N100 -> 12988.938 | E13: ='Computation Table'!N74 -> 9469.3439 | F13: ='Computation Table'!N47 -> 7619.2601 | G13: ='Computation Table'!N21 -> 6796.791
B14: 300000 | C14: ='Computation Table'!P126 -> 28780.281 | D14: ='Computation Table'!P100 -> 15540.926 | E14: ='Computation Table'!P74 -> 11296.742 | F14: ='Computation Table'!P47 -> 9089.8703 | G14: ='Computation Table'!P21 -> 8132.5701
B15: 350000 | C15: ='Computation Table'!R126 -> 33576.995 | D15: ='Computation Table'!R100 -> 18092.914 | E15: ='Computation Table'!R74 -> 13124.141 | F15: ='Computation Table'!R47 -> 10560.481 | G15: ='Computation Table'!R21 -> 9468.3492
B16: 400000 | C16: ='Computation Table'!T126 -> 38373.708 | D16: ='Computation Table'!T100 -> 20644.902 | E16: ='Computation Table'!T74 -> 14951.539 | F16: ='Computation Table'!T47 -> 12031.091 | G16: ='Computation Table'!T21 -> 10804.128
B17: 450000 | C17: ='Computation Table'!V126 -> 43170.422 | D17: ='Computation Table'!V100 -> 23196.891 | E17: ='Computation Table'!V74 -> 16778.937 | F17: ='Computation Table'!V47 -> 13501.701 | G17: ='Computation Table'!V21 -> 12139.907
B18: 500000 | C18: ='Computation Table'!X126 -> 47967.135 | D18: ='Computation Table'!X100 -> 25748.879 | E18: ='Computation Table'!X74 -> 18606.336 | F18: ='Computation Table'!X47 -> 14972.311 | G18: ='Computation Table'!X21 -> 13353.342
B19: 550000 | C19: ='Computation Table'!Z126 -> 52763.849 | D19: ='Computation Table'!Z100 -> 28300.867 | E19: ='Computation Table'!Z74 -> 20433.734 | F19: ='Computation Table'!Z47 -> 16442.921 | G19: ='Computation Table'!Z21 -> 14811.465
B20: 600000 | C20: ='Computation Table'!AB126 -> 57560.562 | D20: ='Computation Table'!AB100 -> 30852.855 | E20: ='Computation Table'!AB74 -> 22261.132 | F20: ='Computation Table'!AB47 -> 17913.532 | G20: ='Computation Table'!AB21 -> 16147.245
B21: 650000 | C21: ='Computation Table'!AD126 -> 62357.276 | D21: ='Computation Table'!AD100 -> 33404.843 | E21: ='Computation Table'!AD74 -> 24088.531 | F21: ='Computation Table'!AD47 -> 19384.142 | G21: ='Computation Table'!AD21 -> 17483.024
B22: 700000 | C22: ='Computation Table'!AF126 -> 67153.989 | D22: ='Computation Table'!AF100 -> 35956.831 | E22: ='Computation Table'!AF74 -> 25915.929 | F22: ='Computation Table'!AF47 -> 20854.752 | G22: ='Computation Table'!AF21 -> 18818.803
B23: 750000 | C23: ='Computation Table'!AH126 -> 71950.703 | D23: ='Computation Table'!AH100 -> 38508.819 | E23: ='Computation Table'!AH74 -> 27743.328 | F23: ='Computation Table'!AH47 -> 22325.362 | G23: ='Computation Table'!AH21 -> 20154.582
B24: 800000 | C24: ='Computation Table'!AJ126 -> 76747.416 | D24: ='Computation Table'!AJ100 -> 41060.807 | E24: ='Computation Table'!AJ74 -> 29570.726 | F24: ='Computation Table'!AJ47 -> 23795.973 | G24: ='Computation Table'!AJ21 -> 21490.361
B25: 850000 | C25: ='Computation Table'!AL126 -> 81544.13 | D25: ='Computation Table'!AL100 -> 43612.795 | E25: ='Computation Table'!AL74 -> 31398.124 | F25: ='Computation Table'!AL47 -> 25266.583 | G25: ='Computation Table'!AL21 -> 22826.14
B26: 900000 | C26: ='Computation Table'!AN126 -> 86340.843 | D26: ='Computation Table'!AN100 -> 46164.784 | E26: ='Computation Table'!AN74 -> 33225.523 | F26: ='Computation Table'!AN47 -> 26737.193 | G26: ='Computation Table'!AN21 -> 24161.919
B27: 950000 | C27: ='Computation Table'!AP126 -> 91137.557 | D27: ='Computation Table'!AP100 -> 48716.772 | E27: ='Computation Table'!AP74 -> 35052.921 | F27: ='Computation Table'!AP47 -> 28207.803 | G27: ='Computation Table'!AP21 -> 25497.698
B28: 1000000 | C28: ='Computation Table'!AR126 -> 95934.27 | D28: ='Computation Table'!AR100 -> 51268.76 | E28: ='Computation Table'!AR74 -> 36880.319 | F28: ='Computation Table'!AR47 -> 29678.414 | G28: ='Computation Table'!AR21 -> 26588.788

Sheet Computation Table
B2: 5 Yrs
B3: GROSS | C3: =C21*C15 -> 629999.88 | E3: =E21*E15 -> 40073.373 | F3: =F21*F15 -> 87220.479 | G3: =G21*G15 -> 120220.12 | H3: =H21*H15 -> 167367.22 | I3: =I21*I15 -> 200366.86 | J3: =J21*J15 -> 247513.97 | K3: =K21*K15 -> 280513.61 | L3: =L21*L15 -> 327660.71 | ... AR3: =AR21*AR15 -> 1595327.3
B4: NET | C4: ='DATA ENTRY'!G5 -> 388616 | E4: 25000 | F4: 50000 | G4: 75000 | H4: 100000 | I4: 125000 | J4: 150000 | K4: 175000 | L4: 200000 | M4: 225000 | N4: 250000 | O4: 275000 | P4: 300000 | Q4: 325000 | R4: 350000 | S4: 375000 | T4: 400000 | U4: 425000 | V4: 450000 | W4: 475000 | X4: 500000 | Y4: 525000 | Z4: 550000 | AA4: 575000 | AB4: 600000 | AC4: 625000 | AD4: 650000 | AE4: 675000 | AF4: 700000 | AG4: 725000 | AH4: 750000 | AI4: 775000 | AJ4: 800000 | AK4: 825000 | AL4: 850000 | AM4: 875000 | AN4: 900000 | AO4: 925000 | AP4: 950000 | AQ4: 975000 | AR4: 1000000
B5: SF | C5: =C4*0.121 -> 47022.536 | E5: =E4*0.121 -> 3025 | F5: =F4*0.121 -> 6050 | G5: =G4*0.121 -> 9075 | H5: =H4*0.121 -> 12100 | I5: =I4*0.121 -> 15125 | J5: =J4*0.121 -> 18150 | K5: =K4*0.121 -> 21175 | L5: =L4*0.121 -> 24200 | ... W5: =W4*0.121 -> 57475 | X5: =X4*0.11 -> 55000 | Y5: =Y4*0.121 -> 63525 | Z5: =Z4*0.121 -> 66550 | AA5: =AA4*0.121 -> 69575 | AB5: =AB4*0.121 -> 72600 | AC5: =AC4*0.121 -> 75625 | AD5: =AD4*0.121 -> 78650 | AE5: =AE4*0.121 -> 81675 | AF5: =AF4*0.121 -> 84700 | ... AQ5: =AQ4*0.121 -> 117975 | AR5: =AR4*0.11 -> 110000
B6: Insurance | C6: =(C4/1000)*C15 -> 23316.96 | E6: =(E4/1000)*E15 -> 1500 | F6: =(F4/1000)*F15 -> 3000 | G6: =(G4/1000)*G15 -> 4500 | H6: =(H4/1000)*H15 -> 6000 | I6: =(I4/1000)*I15 -> 7500 | J6: =(J4/1000)*J15 -> 9000 | K6: =(K4/1000)*K15 -> 10500 | L6: =(L4/1000)*L15 -> 12000 | ... AR6: =(AR4/1000)*AR15 -> 60000
B7: CapCon | C7: ='DATA ENTRY'!G10 -> 5000 | F7: =C7 -> 5000 | G7: =E7 -> 0 | H7: =F7 -> 5000 | I7: =G7 -> 0 | J7: =H7 -> 5000 | K7: =I7 -> 0 | L7: =J7 -> 5000 | M7: =K7 -> 0 | N7: =L7 -> 5000 | ... AR7: =AP7 -> 5000
B8: membership fee | C8: ='DATA ENTRY'!G11 -> 300 | F8: =C8 -> 300 | G8: =E8 -> 0 | H8: =F8 -> 300 | I8: =G8 -> 0 | J8: =H8 -> 300 | K8: =I8 -> 0 | L8: =J8 -> 300 | M8: =K8 -> 0 | N8: =L8 -> 300 | ... AR8: =AP8 -> 300
B9: Advance Interest | C9: =C14*C4*2 -> 7772.32 | E9: =E14*E4*2 -> 500 | F9: =F14*F4*2 -> 1000 | G9: =G14*G4*2 -> 1500 | H9: =H14*H4*2 -> 2000 | I9: =I14*I4*2 -> 2500 | J9: =J14*J4*2 -> 3000 | K9: =K14*K4*2 -> 3500 | L9: =L14*L4*2 -> 4000 | ... AR9: =AR14*AR4*2 -> 20000
B10: LOAN AMOUNT | C10: =SUM(C4:C9) -> 472027.82 | E10: =SUM(E4:E9) -> 30025 | F10: =SUM(F4:F9) -> 65350 | G10: =SUM(G4:G9) -> 90075 | H10: =SUM(H4:H9) -> 125400 | I10: =SUM(I4:I9) -> 150125 | J10: =SUM(J4:J9) -> 185450 | K10: =SUM(K4:K9) -> 210175 | L10: =SUM(L4:L9) -> 245500 | ... AR10: =SUM(AR4:AR9) -> 1195300
B11: Annual Interest | C11: 0.12 | E11: =C11 -> 0.12 | F11: =C11 -> 0.12 | G11: =F11 -> 0.12 | H11: =G11 -> 0.12 | I11: =H11 -> 0.12 | J11: =I11 -> 0.12 | K11: =J11 -> 0.12 | L11: =K11 -> 0.12 | M11: =L11 -> 0.12 | N11: =M11 -> 0.12 | ... X11: =W11 -> 0.12 | Y11: =W11 -> 0.12 | Z11: =Y11 -> 0.12 | AA11: =Z11 -> 0.12 | AB11: =AA11 -> 0.12 | AC11: =AB11 -> 0.12 | AD11: =AC11 -> 0.12 | AE11: =AD11 -> 0.12 | AF11: =AE11 -> 0.12 | AG11: =AF11 -> 0.12 | ... AR11: =AQ11 -> 0.12
B12: Effective Interest rate | C12: =(1+C11/C15)^C15-1 -> 0.12736174 | E12: =(1+E11/E15)^E15-1 -> 0.12736174 | F12: =(1+F11/F15)^F15-1 -> 0.12736174 | G12: =(1+G11/G15)^G15-1 -> 0.12736174 | H12: =(1+H11/H15)^H15-1 -> 0.12736174 | I12: =(1+I11/I15)^I15-1 -> 0.12736174 | J12: =(1+J11/J15)^J15-1 -> 0.12736174 | K12: =(1+K11/K15)^K15-1 -> 0.12736174 | L12: =(1+L11/L15)^L15-1 -> 0.12736174 | ... AR12: =(1+AR11/AR15)^AR15-1 -> 0.12736174
B13: Loan Term | C13: 5 | E13: 5 | F13: 5 | G13: 5 | H13: 5 | I13: 5 | J13: 5 | K13: 5 | L13: 5 | M13: 5 | N13: 5 | O13: 5 | P13: 5 | Q13: 5 | R13: 5 | S13: 5 | T13: =P13 -> 5 | U13: =Q13 -> 5 | V13: =R13 -> 5 | W13: =S13 -> 5 | X13: =T13 -> 5 | Y13: =U13 -> 5 | Z13: =V13 -> 5 | AA13: =W13 -> 5 | ... AR13: =AN13 -> 5
B14: Monthly Interest Rate | C14: =C11/12 -> 0.01 | E14: =E11/12 -> 0.01 | F14: =F11/12 -> 0.01 | G14: =G11/12 -> 0.01 | H14: =H11/12 -> 0.01 | I14: =I11/12 -> 0.01 | J14: =J11/12 -> 0.01 | K14: =K11/12 -> 0.01 | L14: =L11/12 -> 0.01 | ... AR14: =AR11/12 -> 0.01
B15: Nr of Payments | C15: =C13*12 -> 60 | E15: =E13*12 -> 60 | F15: =F13*12 -> 60 | G15: =G13*12 -> 60 | H15: =H13*12 -> 60 | I15: =I13*12 -> 60 | J15: =J13*12 -> 60 | K15: =K13*12 -> 60 | L15: =L13*12 -> 60 | ... AR15: =AR13*12 -> 60
B17: Monthly Amortization | C17: =(1+C14)^C15 -> 1.8166967 | E17: =(1+E14)^E15 -> 1.8166967 | F17: =(1+F14)^F15 -> 1.8166967 | G17: =(1+G14)^G15 -> 1.8166967 | H17: =(1+H14)^H15 -> 1.8166967 | I17: =(1+I14)^I15 -> 1.8166967 | J17: =(1+J14)^J15 -> 1.8166967 | K17: =(1+K14)^K15 -> 1.8166967 | L17: =(1+L14)^L15 -> 1.8166967 | ... AR17: =(1+AR14)^AR15 -> 1.8166967
C18: =C17*C14 -> 0.018166967 | E18: =E17*E14 -> 0.018166967 | F18: =F17*F14 -> 0.018166967 | G18: =G17*G14 -> 0.018166967 | H18: =H17*H14 -> 0.018166967 | I18: =I17*I14 -> 0.018166967 | J18: =J17*J14 -> 0.018166967 | K18: =K17*K14 -> 0.018166967 | L18: =L17*L14 -> 0.018166967 | ... AR18: =AR17*AR14 -> 0.018166967
C19: =C17-1 -> 0.8166967 | E19: =E17-1 -> 0.8166967 | F19: =F17-1 -> 0.8166967 | G19: =G17-1 -> 0.8166967 | H19: =H17-1 -> 0.8166967 | I19: =I17-1 -> 0.8166967 | J19: =J17-1 -> 0.8166967 | K19: =K17-1 -> 0.8166967 | L19: =L17-1 -> 0.8166967 | ... AR19: =AR17-1 -> 0.8166967
C20: =C18/C19 -> 0.022244448 | E20: =E18/E19 -> 0.022244448 | F20: =F18/F19 -> 0.022244448 | G20: =G18/G19 -> 0.022244448 | H20: =H18/H19 -> 0.022244448 | I20: =I18/I19 -> 0.022244448 | J20: =J18/J19 -> 0.022244448 | K20: =K18/K19 -> 0.022244448 | L20: =L18/L19 -> 0.022244448 | ... AR20: =AR18/AR19 -> 0.022244448
B21: Monthly Amortization | C21: =C20*C10 -> 10499.998 | E21: =E20*E10 -> 667.88954 | F21: =F20*F10 -> 1453.6747 | G21: =G20*G10 -> 2003.6686 | H21: =H20*H10 -> 2789.4537 | I21: =I20*I10 -> 3339.4477 | J21: =J20*J10 -> 4125.2328 | K21: =K20*K10 -> 4675.2268 | L21: =L20*L10 -> 5461.0119 | ... AR21: =AR20*AR10 -> 26588.788
B23: Income | C23: =C3-C4 -> 241383.88 | E23: =E3-E4 -> 15073.373 | F23: =F3-F4 -> 37220.479 | G23: =G3-G4 -> 45220.118 | H23: =H3-H4 -> 67367.224 | I23: =I3-I4 -> 75366.863 | J23: =J3-J4 -> 97513.969 | K23: =K3-K4 -> 105513.61 | L23: =L3-L4 -> 127660.71 | ... AR23: =AR3-AR4 -> 595327.3
B24: % Income | C24: =C23/C3 -> 0.38314909 | E24: =E23/E3 -> 0.37614435 | F24: =F23/F3 -> 0.42674014 | G24: =G23/G3 -> 0.37614435 | H24: =H23/H3 -> 0.40251145 | I24: =I23/I3 -> 0.37614435 | J24: =J23/J3 -> 0.3939736 | K24: =K23/K3 -> 0.37614435 | L24: =L23/L3 -> 0.38961251 | ... AR24: =AR23/AR3 -> 0.37316938
B28: 4 yrs
B29: GROSS | C29: =C47*C41 -> 649762.37 | E29: =E47*E41 -> 35294.646 | F29: =F47*F41 -> 83367.318 | G29: =G47*G41 -> 105883.94 | H29: =H47*H41 -> 153956.61 | I29: =I47*I41 -> 176473.23 | J29: =J47*J41 -> 224545.9 | K29: =K47*K41 -> 247062.52 | L29: =L47*L41 -> 295135.19 | ... AR29: =AR47*AR41 -> 1424563.9
B30: NET | C30: ='DATA ENTRY'!F5 -> 444037 | E30: 25000 | F30: 50000 | G30: 75000 | H30: 100000 | I30: 125000 | J30: 150000 | K30: 175000 | L30: 200000 | M30: 225000 | N30: 250000 | O30: 275000 | P30: 300000 | Q30: 325000 | R30: 350000 | S30: 375000 | T30: 400000 | U30: 425000 | V30: 450000 | W30: 475000 | X30: 500000 | Y30: 525000 | Z30: 550000 | AA30: 575000 | AB30: 600000 | AC30: 625000 | AD30: 650000 | AE30: 675000 | AF30: 700000 | AG30: 725000 | AH30: 750000 | AI30: 775000 | AJ30: 800000 | AK30: 825000 | AL30: 850000 | AM30: 875000 | AN30: 900000 | AO30: 925000 | AP30: 950000 | AQ30: 975000 | AR30: 1000000
B31: SF | C31: =C30*0.09 -> 39963.33 | D31: =D30*0.09 -> 0 | E31: =E30*0.09 -> 2250 | F31: =F30*0.09 -> 4500 | G31: =G30*0.09 -> 6750 | H31: =H30*0.09 -> 9000 | I31: =I30*0.09 -> 11250 | J31: =J30*0.09 -> 13500 | ... AR31: =AR30*0.09 -> 90000
B32: Insurance | C32: =(C30/1000)*C41 -> 21313.776 | E32: =(E30/1000)*E41 -> 1200 | F32: =(F30/1000)*F41 -> 2400 | G32: =(G30/1000)*G41 -> 3600 | H32: =(H30/1000)*H41 -> 4800 | I32: =(I30/1000)*I41 -> 6000 | J32: =(J30/1000)*J41 -> 7200 | K32: =(K30/1000)*K41 -> 8400 | L32: =(L30/1000)*L41 -> 9600 | ... AR32: =(AR30/1000)*AR41 -> 48000
B33: CapCon | C33: ='DATA ENTRY'!F10 -> 10000 | F33: =C33 -> 10000 | G33: =E33 -> 0 | H33: =F33 -> 10000 | I33: =G33 -> 0 | J33: =H33 -> 10000 | K33: =I33 -> 0 | L33: =J33 -> 10000 | M33: =K33 -> 0 | N33: =L33 -> 10000 | ... AR33: =AP33 -> 10000
B34: membership fee | C34: ='DATA ENTRY'!F11 -> 300 | F34: =C34 -> 300 | G34: =E34 -> 0 | H34: =F34 -> 300 | I34: =G34 -> 0 | J34: =H34 -> 300 | K34: =I34 -> 0 | L34: =J34 -> 300 | M34: =K34 -> 0 | N34: =L34 -> 300 | ... AR34: =AP34 -> 300
B35: Advance Interest | C35: =C40*C30*2 -> 8140.6783 | E35: =E40*E30*2 -> 458.33333 | F35: =F40*F30*2 -> 916.66667 | G35: =G40*G30*2 -> 1375 | H35: =H40*H30*2 -> 1833.3333 | I35: =I40*I30*2 -> 2291.6667 | J35: =J40*J30*2 -> 2750 | K35: =K40*K30*2 -> 3208.3333 | L35: =L40*L30*2 -> 3666.6667 | ... AR35: =AR40*AR30*2 -> 18333.333
B36: LOAN AMOUNT | C36: =SUM(C30:C35) -> 523754.78 | E36: =SUM(E30:E34) -> 28450 | F36: =SUM(F30:F34) -> 67200 | G36: =SUM(G30:G34) -> 85350 | H36: =SUM(H30:H34) -> 124100 | I36: =SUM(I30:I34) -> 142250 | J36: =SUM(J30:J34) -> 181000 | K36: =SUM(K30:K34) -> 199150 | L36: =SUM(L30:L34) -> 237900 | ... AR36: =SUM(AR30:AR34) -> 1148300
B37: Annual Interest | C37: 0.11 | E37: =C37 -> 0.11 | F37: =C37 -> 0.11 | G37: =F37 -> 0.11 | H37: =F37 -> 0.11 | I37: =G37 -> 0.11 | J37: =H37 -> 0.11 | K37: =I37 -> 0.11 | L37: =J37 -> 0.11 | M37: =K37 -> 0.11 | N37: =L37 -> 0.11 | O37: =M37 -> 0.11 | ... AR37: =AP37 -> 0.11
B38: Effective Interest rate | C38: =(1+C37/C41)^C41-1 -> 0.1161376 | E38: =(1+E37/E41)^E41-1 -> 0.1161376 | F38: =(1+F37/F41)^F41-1 -> 0.1161376 | G38: =(1+G37/G41)^G41-1 -> 0.1161376 | H38: =(1+H37/H41)^H41-1 -> 0.1161376 | I38: =(1+I37/I41)^I41-1 -> 0.1161376 | J38: =(1+J37/J41)^J41-1 -> 0.1161376 | K38: =(1+K37/K41)^K41-1 -> 0.1161376 | L38: =(1+L37/L41)^L41-1 -> 0.1161376 | ... AR38: =(1+AR37/AR41)^AR41-1 -> 0.1161376
B39: Loan Term | C39: 4 | E39: 4 | F39: 4 | G39: 4 | H39: 4 | I39: 4 | J39: 4 | K39: 4 | L39: =H39 -> 4 | M39: =I39 -> 4 | N39: =K39 -> 4 | O39: =K39 -> 4 | P39: =L39 -> 4 | Q39: =M39 -> 4 | R39: =N39 -> 4 | S39: =O39 -> 4 | T39: =P39 -> 4 | U39: =Q39 -> 4 | V39: =R39 -> 4 | ... AR39: =AN39 -> 4
B40: Monthly Interest Rate | C40: =C37/12 -> 0.0091666667 | E40: =E37/12 -> 0.0091666667 | F40: =F37/12 -> 0.0091666667 | G40: =G37/12 -> 0.0091666667 | H40: =H37/12 -> 0.0091666667 | I40: =I37/12 -> 0.0091666667 | J40: =J37/12 -> 0.0091666667 | K40: =K37/12 -> 0.0091666667 | L40: =L37/12 -> 0.0091666667 | ... AR40: =AR37/12 -> 0.0091666667
B41: Nr of Payments | C41: =C39*12 -> 48 | E41: =E39*12 -> 48 | F41: =F39*12 -> 48 | G41: =G39*12 -> 48 | H41: =H39*12 -> 48 | I41: =I39*12 -> 48 | J41: =J39*12 -> 48 | K41: =K39*12 -> 48 | L41: =L39*12 -> 48 | ... AR41: =AR39*12 -> 48
B43: Monthly Amortization | C43: =(1+C40)^C41 -> 1.549598 | E43: =(1+E40)^E41 -> 1.549598 | F43: =(1+F40)^F41 -> 1.549598 | G43: =(1+G40)^G41 -> 1.549598 | H43: =(1+H40)^H41 -> 1.549598 | I43: =(1+I40)^I41 -> 1.549598 | J43: =(1+J40)^J41 -> 1.549598 | K43: =(1+K40)^K41 -> 1.549598 | L43: =(1+L40)^L41 -> 1.549598 | ... AR43: =(1+AR40)^AR41 -> 1.549598
C44: =C43*C40 -> 0.014204649 | E44: =E43*E40 -> 0.014204649 | F44: =F43*F40 -> 0.014204649 | G44: =G43*G40 -> 0.014204649 | H44: =H43*H40 -> 0.014204649 | I44: =I43*I40 -> 0.014204649 | J44: =J43*J40 -> 0.014204649 | K44: =K43*K40 -> 0.014204649 | L44: =L43*L40 -> 0.014204649 | ... AR44: =AR43*AR40 -> 0.014204649
C45: =C43-1 -> 0.54959805 | E45: =E43-1 -> 0.54959805 | F45: =F43-1 -> 0.54959805 | G45: =G43-1 -> 0.54959805 | H45: =H43-1 -> 0.54959805 | I45: =I43-1 -> 0.54959805 | J45: =J43-1 -> 0.54959805 | K45: =K43-1 -> 0.54959805 | L45: =L43-1 -> 0.54959805 | ... AR45: =AR43-1 -> 0.54959805
C46: =C44/C45 -> 0.025845523 | E46: =E44/E45 -> 0.025845523 | F46: =F44/F45 -> 0.025845523 | G46: =G44/G45 -> 0.025845523 | H46: =H44/H45 -> 0.025845523 | I46: =I44/I45 -> 0.025845523 | J46: =J44/J45 -> 0.025845523 | K46: =K44/K45 -> 0.025845523 | L46: =L44/L45 -> 0.025845523 | ... AR46: =AR44/AR45 -> 0.025845523
B47: Monthly Amortization | C47: =C46*C36 -> 13536.716 | E47: =E46*E36 -> 735.30512 | F47: =F46*F36 -> 1736.8191 | G47: =G46*G36 -> 2205.9154 | H47: =H46*H36 -> 3207.4294 | I47: =I46*I36 -> 3676.5256 | J47: =J46*J36 -> 4678.0396 | K47: =K46*K36 -> 5147.1358 | L47: =L46*L36 -> 6148.6498 | ... AR47: =AR46*AR36 -> 29678.414
B49: Income | C49: =C29-C30 -> 205725.37 | E49: =E29-E30 -> 10294.646 | F49: =F29-F30 -> 33367.318 | G49: =G29-G30 -> 30883.937 | H49: =H29-H30 -> 53956.609 | I49: =I29-I30 -> 51473.228 | J49: =J29-J30 -> 74545.9 | K49: =K29-K30 -> 72062.52 | L49: =L29-L30 -> 95135.192 | ... AR49: =AR29-AR30 -> 424563.85
B50: % Income | C50: =C49/C29 -> 0.31661632 | E50: =E49/E29 -> 0.29167726 | F50: =F49/F29 -> 0.40024459 | G50: =G49/G29 -> 0.29167726 | H50: =H49/H29 -> 0.35046634 | I50: =I49/I29 -> 0.29167726 | J50: =J49/J29 -> 0.33198513 | K50: =K49/K29 -> 0.29167726 | L50: =L49/L29 -> 0.32234445 | ... AR50: =AR49/AR29 -> 0.29803076
B55: 3 Yrs
B56: GROSS | C56: =C74*C68 -> 601062.61 | E56: =E74*E68 -> 32893.171 | F56: =F74*F68 -> 77751.014 | G56: =G74*G68 -> 98679.512 | H56: =H74*H68 -> 143537.36 | I56: =I74*I68 -> 164465.85 | J56: =J74*J68 -> 209323.7 | K56: =K74*K68 -> 230252.19 | L56: =L74*L68 -> 275110.04 | ... AR56: =AR74*AR68 -> 1327691.5
B57: NET | C57: ='DATA ENTRY'!E5 -> 443817.41 | E57: 25000 | F57: 50000 | G57: 75000 | H57: 100000 | I57: 125000 | J57: 150000 | K57: 175000 | L57: 200000 | M57: 225000 | N57: 250000 | O57: 275000 | P57: 300000 | Q57: 325000 | R57: 350000 | S57: 375000 | T57: 400000 | U57: 425000 | V57: 450000 | W57: 475000 | X57: 500000 | Y57: 525000 | Z57: 550000 | AA57: 575000 | AB57: 600000 | AC57: 625000 | AD57: 650000 | AE57: 675000 | AF57: 700000 | AG57: 725000 | AH57: 750000 | AI57: 775000 | AJ57: 800000 | AK57: 825000 | AL57: 850000 | AM57: 875000 | AN57: 900000 | AO57: 925000 | AP57: 950000 | AQ57: 975000 | AR57: 1000000
B58: SF | C58: =C57*0.09 -> 39943.567 | E58: =E57*0.08 -> 2000 | F58: =F57*0.08 -> 4000 | G58: =G57*0.08 -> 6000 | H58: =H57*0.08 -> 8000 | I58: =I57*0.08 -> 10000 | J58: =J57*0.08 -> 12000 | K58: =K57*0.08 -> 14000 | L58: =L57*0.08 -> 16000 | ... AR58: =AR57*0.08 -> 80000
B59: Insurance | C59: =(C57/1000)*C68 -> 15977.427 | E59: =(E57/1000)*E68 -> 900 | F59: =(F57/1000)*F68 -> 1800 | G59: =(G57/1000)*G68 -> 2700 | H59: =(H57/1000)*H68 -> 3600 | I59: =(I57/1000)*I68 -> 4500 | J59: =(J57/1000)*J68 -> 5400 | K59: =(K57/1000)*K68 -> 6300 | L59: =(L57/1000)*L68 -> 7200 | ... AR59: =(AR57/1000)*AR68 -> 36000
B60: CapCon | C60: ='DATA ENTRY'!E10 -> 10000 | F60: =C60 -> 10000 | G60: =E60 -> 0 | H60: =F60 -> 10000 | I60: =G60 -> 0 | J60: =H60 -> 10000 | K60: =I60 -> 0 | L60: =J60 -> 10000 | M60: =K60 -> 0 | N60: =L60 -> 10000 | ... AR60: =AP60 -> 10000
B61: membership fee | C61: ='DATA ENTRY'!E11 -> 300 | F61: =C61 -> 300 | G61: =E61 -> 0 | H61: =F61 -> 300 | I61: =G61 -> 0 | J61: =H61 -> 300 | K61: =I61 -> 0 | L61: =J61 -> 300 | M61: =K61 -> 0 | N61: =L61 -> 300 | ... AR61: =AP61 -> 300
B62: Advance Interest | C62: =C67*C57*2 -> 7396.9568 | E62: =E67*E57*2 -> 416.66667 | F62: =F67*F57*2 -> 833.33333 | G62: =G67*G57*2 -> 1250 | H62: =H67*H57*2 -> 1666.6667 | I62: =I67*I57*2 -> 2083.3333 | J62: =J67*J57*2 -> 2500 | K62: =K67*K57*2 -> 2916.6667 | L62: =L67*L57*2 -> 3333.3333 | ... AR62: =AR67*AR57*2 -> 16666.667
B63: LOAN AMOUNT | C63: =SUM(C57:C62) -> 517435.36 | E63: =SUM(E57:E62) -> 28316.667 | F63: =SUM(F57:F62) -> 66933.333 | G63: =SUM(G57:G62) -> 84950 | H63: =SUM(H57:H62) -> 123566.67 | I63: =SUM(I57:I62) -> 141583.33 | J63: =SUM(J57:J62) -> 180200 | K63: =SUM(K57:K62) -> 198216.67 | L63: =SUM(L57:L62) -> 236833.33 | ... AR63: =SUM(AR57:AR62) -> 1142966.7
B64: Annual Interest | C64: 0.1 | E64: =C64 -> 0.1 | F64: =C64 -> 0.1 | G64: =F64 -> 0.1 | H64: =F64 -> 0.1 | I64: =G64 -> 0.1 | J64: =H64 -> 0.1 | K64: =I64 -> 0.1 | L64: =J64 -> 0.1 | M64: =K64 -> 0.1 | N64: =L64 -> 0.1 | O64: =M64 -> 0.1 | ... AR64: =AP64 -> 0.1
B65: Effective Interest rate | C65: =(1+C64/C68)^C68-1 -> 0.10501772 | E65: =(1+E64/E68)^E68-1 -> 0.10501772 | F65: =(1+F64/F68)^F68-1 -> 0.10501772 | G65: =(1+G64/G68)^G68-1 -> 0.10501772 | H65: =(1+H64/H68)^H68-1 -> 0.10501772 | I65: =(1+I64/I68)^I68-1 -> 0.10501772 | J65: =(1+J64/J68)^J68-1 -> 0.10501772 | K65: =(1+K64/K68)^K68-1 -> 0.10501772 | L65: =(1+L64/L68)^L68-1 -> 0.10501772 | ... AR65: =(1+AR64/AR68)^AR68-1 -> 0.10501772
B66: Loan Term | C66: 3 | E66: 3 | F66: 3 | G66: 3 | H66: 3 | I66: 3 | J66: 3 | K66: 3 | L66: =H66 -> 3 | M66: =I66 -> 3 | N66: =K66 -> 3 | O66: =K66 -> 3 | P66: =L66 -> 3 | Q66: =M66 -> 3 | R66: =N66 -> 3 | S66: =O66 -> 3 | T66: =P66 -> 3 | U66: =Q66 -> 3 | V66: =R66 -> 3 | ... AR66: =AN66 -> 3
B67: Monthly Interest Rate | C67: =C64/12 -> 0.0083333333 | E67: =E64/12 -> 0.0083333333 | F67: =F64/12 -> 0.0083333333 | G67: =G64/12 -> 0.0083333333 | H67: =H64/12 -> 0.0083333333 | I67: =I64/12 -> 0.0083333333 | J67: =J64/12 -> 0.0083333333 | K67: =K64/12 -> 0.0083333333 | L67: =L64/12 -> 0.0083333333 | ... AR67: =AR64/12 -> 0.0083333333
B68: Nr of Payments | C68: =C66*12 -> 36 | E68: =E66*12 -> 36 | F68: =F66*12 -> 36 | G68: =G66*12 -> 36 | H68: =H66*12 -> 36 | I68: =I66*12 -> 36 | J68: =J66*12 -> 36 | K68: =K66*12 -> 36 | L68: =L66*12 -> 36 | ... AR68: =AR66*12 -> 36
B70: Monthly Amortization | C70: =(1+C67)^C68 -> 1.3481818 | E70: =(1+E67)^E68 -> 1.3481818 | F70: =(1+F67)^F68 -> 1.3481818 | G70: =(1+G67)^G68 -> 1.3481818 | H70: =(1+H67)^H68 -> 1.3481818 | I70: =(1+I67)^I68 -> 1.3481818 | J70: =(1+J67)^J68 -> 1.3481818 | K70: =(1+K67)^K68 -> 1.3481818 | L70: =(1+L67)^L68 -> 1.3481818 | ... AR70: =(1+AR67)^AR68 -> 1.3481818
C71: =C70*C67 -> 0.011234849 | E71: =E70*E67 -> 0.011234849 | F71: =F70*F67 -> 0.011234849 | G71: =G70*G67 -> 0.011234849 | H71: =H70*H67 -> 0.011234849 | I71: =I70*I67 -> 0.011234849 | J71: =J70*J67 -> 0.011234849 | K71: =K70*K67 -> 0.011234849 | L71: =L70*L67 -> 0.011234849 | ... AR71: =AR70*AR67 -> 0.011234849
C72: =C70-1 -> 0.34818184 | E72: =E70-1 -> 0.34818184 | F72: =F70-1 -> 0.34818184 | G72: =G70-1 -> 0.34818184 | H72: =H70-1 -> 0.34818184 | I72: =I70-1 -> 0.34818184 | J72: =J70-1 -> 0.34818184 | K72: =K70-1 -> 0.34818184 | L72: =L70-1 -> 0.34818184 | ... AR72: =AR70-1 -> 0.34818184
C73: =C71/C72 -> 0.032267187 | E73: =E71/E72 -> 0.032267187 | F73: =F71/F72 -> 0.032267187 | G73: =G71/G72 -> 0.032267187 | H73: =H71/H72 -> 0.032267187 | I73: =I71/I72 -> 0.032267187 | J73: =J71/J72 -> 0.032267187 | K73: =K71/K72 -> 0.032267187 | L73: =L71/L72 -> 0.032267187 | ... AR73: =AR71/AR72 -> 0.032267187
B74: Monthly Amortization | C74: =C73*C63 -> 16696.184 | E74: =E73*E63 -> 913.69918 | F74: =F73*F63 -> 2159.7504 | G74: =G73*G63 -> 2741.0976 | H74: =H73*H63 -> 3987.1488 | I74: =I73*I63 -> 4568.4959 | J74: =J73*J63 -> 5814.5471 | K74: =K73*K63 -> 6395.8943 | L74: =L73*L63 -> 7641.9455 | ... AR74: =AR73*AR63 -> 36880.319
B76: Income | C76: =C56-C57 -> 157245.2 | E76: =E56-E57 -> 7893.1706 | F76: =F56-F57 -> 27751.014 | G76: =G56-G57 -> 23679.512 | H76: =H56-H57 -> 43537.356 | I76: =I56-I57 -> 39465.853 | J76: =J56-J57 -> 59323.697 | K76: =K56-K57 -> 55252.194 | L76: =L56-L57 -> 75110.038 | ... AR76: =AR56-AR57 -> 327691.5
B77: % Income | C77: =C76/C56 -> 0.26161202 | E77: =E76/E56 -> 0.23996381 | F77: =F76/F56 -> 0.35692157 | G77: =G76/G56 -> 0.23996381 | H77: =H76/H56 -> 0.30331725 | I77: =I76/I56 -> 0.23996381 | J77: =J76/J56 -> 0.2834065 | K77: =K76/K56 -> 0.23996381 | L77: =L76/L56 -> 0.27301817 | ... AR77: =AR76/AR56 -> 0.24681298
B81: 2 Yrs
B82: GROSS | C82: =C100*C94 -> 127991.37 | E82: =E100*E94 -> 30623.857 | F82: =F100*F94 -> 66743.658 | G82: =G100*G94 -> 91871.572 | H82: =H100*H94 -> 127991.37 | I82: =I100*I94 -> 153119.29 | J82: =J100*J94 -> 189239.09 | K82: =K100*K94 -> 214367 | L82: =L100*L94 -> 250486.8 | ... AR82: =AR100*AR94 -> 1230450.2
B83: NET | C83: ='DATA ENTRY'!D5 -> 100000 | E83: 25000 | F83: 50000 | G83: 75000 | H83: 100000 | I83: 125000 | J83: 150000 | K83: 175000 | L83: 200000 | M83: 225000 | N83: 250000 | O83: 275000 | P83: 300000 | Q83: 325000 | R83: 350000 | S83: 375000 | T83: 400000 | U83: 425000 | V83: 450000 | W83: 475000 | X83: 500000 | Y83: 525000 | Z83: 550000 | AA83: 575000 | AB83: 600000 | AC83: 625000 | AD83: 650000 | AE83: 675000 | AF83: 700000 | AG83: 725000 | AH83: 750000 | AI83: 775000 | AJ83: 800000 | AK83: 825000 | AL83: 850000 | AM83: 875000 | AN83: 900000 | AO83: 925000 | AP83: 950000 | AQ83: 975000 | AR83: 1000000
B84: SF | C84: =C83*0.075 -> 7500 | E84: =E83*0.075 -> 1875 | F84: =F83*0.075 -> 3750 | G84: =G83*0.075 -> 5625 | H84: =H83*0.075 -> 7500 | I84: =I83*0.075 -> 9375 | J84: =J83*0.075 -> 11250 | K84: =K83*0.075 -> 13125 | L84: =L83*0.075 -> 15000 | ... AR84: =AR83*0.075 -> 75000
B85: Insurance | C85: =(C83/1000)*C94 -> 2400 | E85: =(E83/1000)*E94 -> 600 | F85: =(F83/1000)*F94 -> 1200 | G85: =(G83/1000)*G94 -> 1800 | H85: =(H83/1000)*H94 -> 2400 | I85: =(I83/1000)*I94 -> 3000 | J85: =(J83/1000)*J94 -> 3600 | K85: =(K83/1000)*K94 -> 4200 | L85: =(L83/1000)*L94 -> 4800 | ... AR85: =(AR83/1000)*AR94 -> 24000
B86: CapCon | C86: ='DATA ENTRY'!D10 -> 5000 | F86: =C86 -> 5000 | G86: =E86 -> 0 | H86: =F86 -> 5000 | I86: =G86 -> 0 | J86: =H86 -> 5000 | K86: =I86 -> 0 | L86: =J86 -> 5000 | M86: =K86 -> 0 | N86: =L86 -> 5000 | ... AR86: =AP86 -> 5000
B87: membership fee | C87: ='DATA ENTRY'!D11 -> 0 | F87: =C87 -> 0 | G87: =E87 -> 0 | H87: =F87 -> 0 | I87: =G87 -> 0 | J87: =H87 -> 0 | K87: =I87 -> 0 | L87: =J87 -> 0 | M87: =K87 -> 0 | N87: =L87 -> 0 | ... AR87: =AP87 -> 0
B88: Advance Interest | C88: =C93*C83*2 -> 1541.6667 | E88: =E93*E83*2 -> 385.41667 | F88: =F93*F83*2 -> 770.83333 | G88: =G93*G83*2 -> 1156.25 | H88: =H93*H83*2 -> 1541.6667 | I88: =I93*I83*2 -> 1927.0833 | J88: =J93*J83*2 -> 2312.5 | K88: =K93*K83*2 -> 2697.9167 | L88: =L93*L83*2 -> 3083.3333 | ... AR88: =AR93*AR83*2 -> 15416.667
B89: LOAN AMOUNT | C89: =SUM(C83:C88) -> 116441.67 | E89: =SUM(E83:E88) -> 27860.417 | F89: =SUM(F83:F88) -> 60720.833 | G89: =SUM(G83:G88) -> 83581.25 | H89: =SUM(H83:H88) -> 116441.67 | I89: =SUM(I83:I88) -> 139302.08 | J89: =SUM(J83:J88) -> 172162.5 | K89: =SUM(K83:K88) -> 195022.92 | L89: =SUM(L83:L88) -> 227883.33 | ... AR89: =SUM(AR83:AR88) -> 1119416.7
B90: Annual Interest | C90: 0.0925 | E90: =C90 -> 0.0925 | F90: =C90 -> 0.0925 | G90: =F90 -> 0.0925 | H90: =F90 -> 0.0925 | I90: =G90 -> 0.0925 | J90: =H90 -> 0.0925 | K90: =I90 -> 0.0925 | L90: =J90 -> 0.0925 | M90: =K90 -> 0.0925 | N90: =L90 -> 0.0925 | O90: =M90 -> 0.0925 | ... AR90: =AP90 -> 0.0925
B91: Effective Interest rate | C91: =(1+C90/C94)^C94-1 -> 0.096718129 | E91: =(1+E90/E94)^E94-1 -> 0.096718129 | F91: =(1+F90/F94)^F94-1 -> 0.096718129 | G91: =(1+G90/G94)^G94-1 -> 0.096718129 | H91: =(1+H90/H94)^H94-1 -> 0.096718129 | I91: =(1+I90/I94)^I94-1 -> 0.096718129 | J91: =(1+J90/J94)^J94-1 -> 0.096718129 | K91: =(1+K90/K94)^K94-1 -> 0.096718129 | L91: =(1+L90/L94)^L94-1 -> 0.096718129 | ... AR91: =(1+AR90/AR94)^AR94-1 -> 0.096718129
B92: Loan Term | C92: 2 | E92: 2 | F92: 2 | G92: 2 | H92: 2 | I92: 2 | J92: 2 | K92: 2 | L92: =H92 -> 2 | M92: =I92 -> 2 | N92: =K92 -> 2 | O92: =K92 -> 2 | P92: =L92 -> 2 | Q92: =M92 -> 2 | R92: =N92 -> 2 | S92: =O92 -> 2 | T92: =P92 -> 2 | U92: =Q92 -> 2 | V92: =R92 -> 2 | ... AR92: =AN92 -> 2
B93: Monthly Interest Rate | C93: =C90/12 -> 0.0077083333 | E93: =E90/12 -> 0.0077083333 | F93: =F90/12 -> 0.0077083333 | G93: =G90/12 -> 0.0077083333 | H93: =H90/12 -> 0.0077083333 | I93: =I90/12 -> 0.0077083333 | J93: =J90/12 -> 0.0077083333 | K93: =K90/12 -> 0.0077083333 | L93: =L90/12 -> 0.0077083333 | ... AR93: =AR90/12 -> 0.0077083333
B94: Nr of Payments | C94: =C92*12 -> 24 | E94: =E92*12 -> 24 | F94: =F92*12 -> 24 | G94: =G92*12 -> 24 | H94: =H92*12 -> 24 | I94: =I92*12 -> 24 | J94: =J92*12 -> 24 | K94: =K92*12 -> 24 | L94: =L92*12 -> 24 | ... AR94: =AR92*12 -> 24
B96: Monthly Amortization | C96: =(1+C93)^C94 -> 1.2023652 | E96: =(1+E93)^E94 -> 1.2023652 | F96: =(1+F93)^F94 -> 1.2023652 | G96: =(1+G93)^G94 -> 1.2023652 | H96: =(1+H93)^H94 -> 1.2023652 | I96: =(1+I93)^I94 -> 1.2023652 | J96: =(1+J93)^J94 -> 1.2023652 | K96: =(1+K93)^K94 -> 1.2023652 | L96: =(1+L93)^L94 -> 1.2023652 | ... AR96: =(1+AR93)^AR94 -> 1.2023652
C97: =C96*C93 -> 0.0092682318 | E97: =E96*E93 -> 0.0092682318 | F97: =F96*F93 -> 0.0092682318 | G97: =G96*G93 -> 0.0092682318 | H97: =H96*H93 -> 0.0092682318 | I97: =I96*I93 -> 0.0092682318 | J97: =J96*J93 -> 0.0092682318 | K97: =K96*K93 -> 0.0092682318 | L97: =L96*L93 -> 0.0092682318 | ... AR97: =AR96*AR93 -> 0.0092682318
C98: =C96-1 -> 0.20236521 | E98: =E96-1 -> 0.20236521 | F98: =F96-1 -> 0.20236521 | G98: =G96-1 -> 0.20236521 | H98: =H96-1 -> 0.20236521 | I98: =I96-1 -> 0.20236521 | J98: =J96-1 -> 0.20236521 | K98: =K96-1 -> 0.20236521 | L98: =L96-1 -> 0.20236521 | ... AR98: =AR96-1 -> 0.20236521
C99: =C97/C98 -> 0.045799532 | E99: =E97/E98 -> 0.045799532 | F99: =F97/F98 -> 0.045799532 | G99: =G97/G98 -> 0.045799532 | H99: =H97/H98 -> 0.045799532 | I99: =I97/I98 -> 0.045799532 | J99: =J97/J98 -> 0.045799532 | K99: =K97/K98 -> 0.045799532 | L99: =L97/L98 -> 0.045799532 | ... AR99: =AR97/AR98 -> 0.045799532
B100: Monthly Amortization | C100: =C99*C89 -> 5332.9739 | E100: =E99*E89 -> 1275.9941 | F100: =F99*F89 -> 2780.9858 | G100: =G99*G89 -> 3827.9822 | H100: =H99*H89 -> 5332.9739 | I100: =I99*I89 -> 6379.9703 | J100: =J99*J89 -> 7884.962 | K100: =K99*K89 -> 8931.9584 | L100: =L99*L89 -> 10436.95 | ... AR100: =AR99*AR89 -> 51268.76
B102: Income | C102: =C82-C83 -> 27991.373 | E102: =E82-E83 -> 5623.8572 | F102: =F82-F83 -> 16743.658 | G102: =G82-G83 -> 16871.572 | H102: =H82-H83 -> 27991.373 | I102: =I82-I83 -> 28119.286 | J102: =J82-J83 -> 39239.087 | K102: =K82-K83 -> 39367.001 | L102: =L82-L83 -> 50486.802 | ... AR102: =AR82-AR83 -> 230450.23
B103: % Income | C103: =C102/C82 -> 0.21869734 | E103: =E102/E82 -> 0.18364301 | F103: =F102/F82 -> 0.25086516 | G103: =G102/G82 -> 0.18364301 | H103: =H102/H82 -> 0.21869734 | I103: =I102/I82 -> 0.18364301 | J103: =J102/J82 -> 0.20735192 | K103: =K102/K82 -> 0.18364301 | L103: =L102/L82 -> 0.20155474 | ... AR103: =AR102/AR82 -> 0.18728936
B107: 1 Yr
B108: GROSS | C108: =C126*C120 -> 174984.11 | E108: =E126*E120 -> 28780.281 | F108: =F126*F120 -> 57560.562 | G108: =G126*G120 -> 86340.843 | H108: =H126*H120 -> 115121.12 | I108: =I126*I120 -> 143901.41 | J108: =J126*J120 -> 172681.69 | K108: =K126*K120 -> 201461.97 | L108: =L126*L120 -> 230242.25 | ... AR108: =AR126*AR120 -> 1151211.2
B109: NET | C109: ='DATA ENTRY'!C5 -> 152000 | E109: 25000 | F109: 50000 | G109: 75000 | H109: 100000 | I109: 125000 | J109: 150000 | K109: 175000 | L109: 200000 | M109: 225000 | N109: 250000 | O109: 275000 | P109: 300000 | Q109: 325000 | R109: 350000 | S109: 375000 | T109: 400000 | U109: 425000 | V109: 450000 | W109: 475000 | X109: 500000 | Y109: 525000 | Z109: 550000 | AA109: 575000 | AB109: 600000 | AC109: 625000 | AD109: 650000 | AE109: 675000 | AF109: 700000 | AG109: 725000 | AH109: 750000 | AI109: 775000 | AJ109: 800000 | AK109: 825000 | AL109: 850000 | AM109: 875000 | AN109: 900000 | AO109: 925000 | AP109: 950000 | AQ109: 975000 | AR109: 1000000
B110: SF | C110: =C109*0.07 -> 10640 | E110: =E109*0.07 -> 1750 | F110: =F109*0.07 -> 3500 | G110: =G109*0.07 -> 5250 | H110: =H109*0.07 -> 7000 | I110: =I109*0.07 -> 8750 | J110: =J109*0.07 -> 10500 | K110: =K109*0.07 -> 12250 | L110: =L109*0.07 -> 14000 | ... AR110: =AR109*0.07 -> 70000
B111: Insurance | C111: =(C109/1000)*C120 -> 1824 | E111: =(E109/1000)*E120 -> 300 | F111: =(F109/1000)*F120 -> 600 | G111: =(G109/1000)*G120 -> 900 | H111: =(H109/1000)*H120 -> 1200 | I111: =(I109/1000)*I120 -> 1500 | J111: =(J109/1000)*J120 -> 1800 | K111: =(K109/1000)*K120 -> 2100 | L111: =(L109/1000)*L120 -> 2400 | ... AR111: =(AR109/1000)*AR120 -> 12000
B112: CapCon | C112: ='DATA ENTRY'!C10 -> 0 | F112: =C112 -> 0 | G112: =E112 -> 0 | H112: =F112 -> 0 | I112: =G112 -> 0 | J112: =H112 -> 0 | K112: =I112 -> 0 | L112: =J112 -> 0 | M112: =K112 -> 0 | N112: =L112 -> 0 | ... AR112: =AP112 -> 0
B113: membership fee | C113: ='DATA ENTRY'!C11 -> 0 | F113: =C113 -> 0 | G113: =E113 -> 0 | H113: =F113 -> 0 | I113: =G113 -> 0 | J113: =H113 -> 0 | K113: =I113 -> 0 | L113: =J113 -> 0 | M113: =K113 -> 0 | N113: =L113 -> 0 | ... AR113: =AP113 -> 0
B114: Advance Interest | C114: =C119*C109*2 -> 2280 | E114: =E119*E109*2 -> 375 | F114: =F119*F109*2 -> 750 | G114: =G119*G109*2 -> 1125 | H114: =H119*H109*2 -> 1500 | I114: =I119*I109*2 -> 1875 | J114: =J119*J109*2 -> 2250 | K114: =K119*K109*2 -> 2625 | L114: =L119*L109*2 -> 3000 | ... AR114: =AR119*AR109*2 -> 15000
B115: LOAN AMOUNT | C115: =SUM(C109:C114) -> 166744 | E115: =SUM(E109:E114) -> 27425 | F115: =SUM(F109:F114) -> 54850 | G115: =SUM(G109:G114) -> 82275 | H115: =SUM(H109:H114) -> 109700 | I115: =SUM(I109:I114) -> 137125 | J115: =SUM(J109:J114) -> 164550 | K115: =SUM(K109:K114) -> 191975 | L115: =SUM(L109:L114) -> 219400 | ... AR115: =SUM(AR109:AR114) -> 1097000
B116: Annual Interest | C116: 0.09 | E116: =C116 -> 0.09 | F116: =E116 -> 0.09 | G116: =E116 -> 0.09 | H116: =F116 -> 0.09 | I116: =G116 -> 0.09 | J116: =H116 -> 0.09 | K116: =I116 -> 0.09 | L116: =J116 -> 0.09 | M116: =K116 -> 0.09 | N116: =L116 -> 0.09 | ... AR116: =AP116 -> 0.09
B117: Effective Interest rate | C117: =(1+C116/C120)^C120-1 -> 0.093806898 | E117: =(1+E116/E120)^E120-1 -> 0.093806898 | F117: =(1+F116/F120)^F120-1 -> 0.093806898 | G117: =(1+G116/G120)^G120-1 -> 0.093806898 | H117: =(1+H116/H120)^H120-1 -> 0.093806898 | I117: =(1+I116/I120)^I120-1 -> 0.093806898 | J117: =(1+J116/J120)^J120-1 -> 0.093806898 | K117: =(1+K116/K120)^K120-1 -> 0.093806898 | L117: =(1+L116/L120)^L120-1 -> 0.093806898 | ... AR117: =(1+AR116/AR120)^AR120-1 -> 0.093806898
B118: Loan Term | C118: 1 | E118: 1 | F118: 1 | G118: 1 | H118: 1 | I118: 1 | J118: 1 | K118: 1 | L118: =H118 -> 1 | M118: =I118 -> 1 | N118: =K118 -> 1 | O118: =K118 -> 1 | P118: =L118 -> 1 | Q118: =M118 -> 1 | R118: =N118 -> 1 | S118: =O118 -> 1 | T118: =P118 -> 1 | U118: =Q118 -> 1 | V118: =R118 -> 1 | ... AR118: =AN118 -> 1
B119: Monthly Interest Rate | C119: =C116/12 -> 0.0075 | E119: =E116/12 -> 0.0075 | F119: =F116/12 -> 0.0075 | G119: =G116/12 -> 0.0075 | H119: =H116/12 -> 0.0075 | I119: =I116/12 -> 0.0075 | J119: =J116/12 -> 0.0075 | K119: =K116/12 -> 0.0075 | L119: =L116/12 -> 0.0075 | ... AR119: =AR116/12 -> 0.0075
B120: Nr of Payments | C120: =C118*12 -> 12 | E120: =E118*12 -> 12 | F120: =F118*12 -> 12 | G120: =G118*12 -> 12 | H120: =H118*12 -> 12 | I120: =I118*12 -> 12 | J120: =J118*12 -> 12 | K120: =K118*12 -> 12 | L120: =L118*12 -> 12 | ... AR120: =AR118*12 -> 12
B122: Monthly Amortization | C122: =(1+C119)^C120 -> 1.0938069 | E122: =(1+E119)^E120 -> 1.0938069 | F122: =(1+F119)^F120 -> 1.0938069 | G122: =(1+G119)^G120 -> 1.0938069 | H122: =(1+H119)^H120 -> 1.0938069 | I122: =(1+I119)^I120 -> 1.0938069 | J122: =(1+J119)^J120 -> 1.0938069 | K122: =(1+K119)^K120 -> 1.0938069 | L122: =(1+L119)^L120 -> 1.0938069 | ... AR122: =(1+AR119)^AR120 -> 1.0938069
C123: =C122*C119 -> 0.0082035517 | E123: =E122*E119 -> 0.0082035517 | F123: =F122*F119 -> 0.0082035517 | G123: =G122*G119 -> 0.0082035517 | H123: =H122*H119 -> 0.0082035517 | I123: =I122*I119 -> 0.0082035517 | J123: =J122*J119 -> 0.0082035517 | K123: =K122*K119 -> 0.0082035517 | L123: =L122*L119 -> 0.0082035517 | ... AR123: =AR122*AR119 -> 0.0082035517
...

Sheet 2 years
A1: \ | B1: Amortization | C1: ='DATA ENTRY'!D16 -> 5332.9739
B2: Timeline | C2: 0 | D2: 1 | E2: 2 | F2: 3 | G2: 4 | H2: 5 | I2: 6 | J2: 7 | K2: 8 | L2: 9 | M2: 10 | N2: 11 | O2: 12 | P2: 13 | Q2: 14 | R2: 15 | S2: 16 | T2: 17 | U2: 18 | V2: 19 | W2: 20 | X2: 21 | Y2: 22 | Z2: 23 | AA2: 24
B3: GROSS AMOUNT | C3: ='DATA ENTRY'!D4 -> 127991.37
B4: LOAN AMOUNT | C4: ='DATA ENTRY'!D13 -> 116441.67 | D4: =-$C1 -> -5332.9739 | E4: =-$C1 -> -5332.9739 | F4: =-$C1 -> -5332.9739 | G4: =-$C1 -> -5332.9739 | H4: =-$C1 -> -5332.9739 | I4: =-$C1 -> -5332.9739 | J4: =-$C1 -> -5332.9739 | K4: =-$C1 -> -5332.9739 | ... AA4: =-$C1 -> -5332.9739
B5: Service Fee | C5: ='DATA ENTRY'!D8 -> 7500
B6: Insurance | C6: ='DATA ENTRY'!D9 -> 2400
B7: CapCon | C7: ='DATA ENTRY'!D10 -> 5000
B8: membership fee | C8: ='DATA ENTRY'!D11 -> 0
B9: Advance Interest | C9: ='DATA ENTRY'!D12 -> 1541.6667
B10: NET PROCEEDS/CASH FLOW | C10: =C4-C5-C6-C7-C8-C9 -> 100000
B12: Interest Rate of Return | C12: =IRR(C4:AA4) -> 0.0077083333 | D12: =C12/5 -> 0.0015416667
B14: Loan Balance
B15: Monthly Interest Rate | C15: ='DATA ENTRY'!D14/12 -> 0.0077083333
B16: Effective Interest Rate | C16: ='DATA ENTRY'!D15 -> 0.096718129 | K16: APPROVED
C20: LOAN LEDGER CARD
C22: Name: | D22: MARIA CRISELDA G. MACAPILI | G22: Loan Voucher No. | H22: LV-052
C23: Serial Nr: | D23: 734219 | E23: Address: | F23: PUROK 3 ,DAET, CAMARINEZ NORTE | G23: Amount: | H23: =C10-C14 -> 100000
C24: Posting date | D24: Date of Loan: | E24: 45915 | F24: Maturity Date | G24: =B51 -> 46675 | K24: PEOPLE'S MULTI-PURPOSE COOPERATIVE
D25: Term: | E25: 24 | F25: MOS | K25: 20-E 2nd Camarilla St. corner 15th Ave., Brgy. San Roque, Murphy Cubao, Quezon City | X25: 20-E 2nd Camarilla St corner 15th Avenue,
D26: Loan | E26: Installment | F26: Principal | G26: EIR | H26: Balance | X26: Brgy San Roque, Murphy Cubao, Quezon City
D27: Month 0 | H27: =C4 -> 116441.67 | K27: LOAN RELEASE VOUCHER | X27: Mobile No. (+63)953-033-1580 (GLOBE)
B28: =DATE(YEAR(E$24),MONTH(E$24)+D28+1,DAY(E$24)) -> 45976 | C28: =TEXT(B28,"mmm-yyyy") -> Nov-2025 | D28: 1 | E28: =C$1 -> 5332.9739 | F28: =E28-G28 -> 4435.4027 | G28: =H27*C$12 -> 897.57118 | H28: =H27-F28 -> 112006.26
B29: =DATE(YEAR(E$24),MONTH(E$24)+D29+1,DAY(E$24)) -> 46006 | C29: =TEXT(B29,"mmm-yyyy") -> Dec-2025 | D29: 2 | E29: =C$1 -> 5332.9739 | F29: =E29-G29 -> 4469.5923 | G29: =H28*C$12 -> 863.38162 | H29: =H28-F29 -> 107536.67 | R29: Date: | S29: =E24 -> 45915 | X29: LOAN APPLICATION FORM
B30: =DATE(YEAR(E$24),MONTH(E$24)+D30+1,DAY(E$24)) -> 46037 | C30: =TEXT(B30,"mmm-yyyy") -> Jan-2026 | D30: 3 | E30: =C$1 -> 5332.9739 | F30: =E30-G30 -> 4504.0454 | G30: =H29*C$12 -> 828.92851 | H30: =H29-F30 -> 103032.63 | R30: LV No: | S30: =H22 -> LV-052 | AU30: Date: | AW30: 0 | AX30: 9 | AY30: 1 | AZ30: 5 | BA30: 2 | BB30: 0 | BC30: 2 | BD30: 5
B31: =DATE(YEAR(E$24),MONTH(E$24)+D31+1,DAY(E$24)) -> 46068 | C31: =TEXT(B31,"mmm-yyyy") -> Feb-2026 | D31: 4 | E31: =C$1 -> 5332.9739 | F31: =E31-G31 -> 4538.764 | G31: =H30*C$12 -> 794.20983 | H31: =H30-F31 -> 98493.862 | AW31: m | AX31: m | AY31: d | AZ31: d | BA31: y | BB31: y | BC31: y | BD31: y
B32: =DATE(YEAR(E$24),MONTH(E$24)+D32+1,DAY(E$24)) -> 46096 | C32: =TEXT(B32,"mmm-yyyy") -> Mar-2026 | D32: 5 | E32: =C$1 -> 5332.9739 | F32: =E32-G32 -> 4573.7503 | G32: =H31*C$12 -> 759.22352 | H32: =H31-F32 -> 93920.112 | K32: Name of Borrower: | N32: =D22 -> MARIA CRISELDA G. MACAPILI | X32: APPLICATION TYPE | AE32: LOAN CLASSIFICATION | AM32: TERM | AT32: RELEASE OF LOAN PROCEEDS
B33: =DATE(YEAR(E$24),MONTH(E$24)+D33+1,DAY(E$24)) -> 46127 | C33: =TEXT(B33,"mmm-yyyy") -> Apr-2026 | D33: 6 | E33: =C$1 -> 5332.9739 | F33: =E33-G33 -> 4609.0063 | G33: =H32*C$12 -> 723.96753 | H33: =H32-F33 -> 89311.106 | K33: Serial No.: | N33: =D23 -> 734219 | Y33: New | AF33: Salary Loan | AN33: 12 Months | AU33: Check
B34: =DATE(YEAR(E$24),MONTH(E$24)+D34+1,DAY(E$24)) -> 46157 | C34: =TEXT(B34,"mmm-yyyy") -> May-2026 | D34: 7 | E34: =C$1 -> 5332.9739 | F34: =E34-G34 -> 4644.5341 | G34: =H33*C$12 -> 688.43977 | H34: =H33-F34 -> 84666.572 | K34: Address: | N34: =F23 -> PUROK 3 ,DAET, CAMARINEZ NORTE | Y34: Renewal | AF34: Pension Loan | AN34: 24 Months | AU34: Bank Electronic Transfer to Borrowers Account
B35: =DATE(YEAR(E$24),MONTH(E$24)+D35+1,DAY(E$24)) -> 46188 | C35: =TEXT(B35,"mmm-yyyy") -> Jun-2026 | D35: 8 | E35: =C$1 -> 5332.9739 | F35: =E35-G35 -> 4680.3357 | G35: =H34*C$12 -> 652.63816 | H35: =H34-F35 -> 79986.236 | Y35: Additional | AF35: Emergency | AN35: 36 Months | AU35: Others:
B36: =DATE(YEAR(E$24),MONTH(E$24)+D36+1,DAY(E$24)) -> 46218 | C36: =TEXT(B36,"mmm-yyyy") -> Jul-2026 | D36: 9 | E36: =C$1 -> 5332.9739 | F36: =E36-G36 -> 4716.4133 | G36: =H35*C$12 -> 616.56057 | H36: =H35-F36 -> 75269.823 | L36: Principal Amount | R36: =C4 -> 116441.67 | Y36: Reloan | AF36: Health Assistance Loan | AN36: 48 Months
B37: =DATE(YEAR(E$24),MONTH(E$24)+D37+1,DAY(E$24)) -> 46249 | C37: =TEXT(B37,"mmm-yyyy") -> Aug-2026 | D37: 10 | E37: =C$1 -> 5332.9739 | F37: =E37-G37 -> 4752.769 | G37: =H36*C$12 -> 580.20488 | H37: =H36-F37 -> 70517.054 | Y37: Restructure | AF37: Educational Loan | AN37: 60 Months
B38: =DATE(YEAR(E$24),MONTH(E$24)+D38+1,DAY(E$24)) -> 46280 | C38: =TEXT(B38,"mmm-yyyy") -> Sep-2026 | D38: 11 | E38: =C$1 -> 5332.9739 | F38: =E38-G38 -> 4789.4049 | G38: =H37*C$12 -> 543.56895 | H38: =H37-F38 -> 65727.649 | L38: (-) | M38: Balance Old Loan(s) | R38: =-C14 -> 0 | AF38: Others: | AN38: Others:
B39: =DATE(YEAR(E$24),MONTH(E$24)+D39+1,DAY(E$24)) -> 46310 | C39: =TEXT(B39,"mmm-yyyy") -> Oct-2026 | D39: 12 | E39: =C$1 -> 5332.9739 | F39: =E39-G39 -> 4826.3232 | G39: =H38*C$12 -> 506.65062 | H39: =H38-F39 -> 60901.325 | L39: (-) | M39: Membership Fee: | R39: =-C8 -> 0 | X39: AMOUNT APPLIED: | AB39: =R44 -> 100000 | AN39: MONTHLY AMORTIZATION: | AT39: =R49 -> 5332.9739
B40: =DATE(YEAR(E$24),MONTH(E$24)+D40+1,DAY(E$24)) -> 46341 | C40: =TEXT(B40,"mmm-yyyy") -> Nov-2026 | D40: 13 | E40: =C$1 -> 5332.9739 | F40: =E40-G40 -> 4863.5262 | G40: =H39*C$12 -> 469.44772 | H40: =H39-F40 -> 56037.799 | L40: (-) | M40: Paid up Capital: | R40: =-C7 -> -5000
B41: =DATE(YEAR(E$24),MONTH(E$24)+D41+1,DAY(E$24)) -> 46371 | C41: =TEXT(B41,"mmm-yyyy") -> Dec-2026 | D41: 14 | E41: =C$1 -> 5332.9739 | F41: =E41-G41 -> 4901.0158 | G41: =H40*C$12 -> 431.95804 | H41: =H40-F41 -> 51136.783 | L41: (-) | M41: Service Fee | R41: =-C5 -> -7500 | X41: LOAN ID: | AF41: DEDUCTION CODE: | AR41: LOAN PURPOSE:
B42: =DATE(YEAR(E$24),MONTH(E$24)+D42+1,DAY(E$24)) -> 46402 | C42: =TEXT(B42,"mmm-yyyy") -> Jan-2027 | D42: 15 | E42: =C$1 -> 5332.9739 | F42: =E42-G42 -> 4938.7945 | G42: =H41*C$12 -> 394.17937 | H42: =H41-F42 -> 46197.989 | L42: (-) | M42: Insurance Premium - Paramount | R42: =-C6 -> -2400 | X42: MEM ID: | AG42: Regular Member | AS42: Old Member
B43: =DATE(YEAR(E$24),MONTH(E$24)+D43+1,DAY(E$24)) -> 46433 | C43: =TEXT(B43,"mmm-yyyy") -> Feb-2027 | D43: 16 | E43: =C$1 -> 5332.9739 | F43: =E43-G43 -> 4976.8644 | G43: =H42*C$12 -> 356.1095 | H43: =H42-F43 -> 41221.125 | L43: (-) | M43: Advance Interest | R43: =-C9 -> -1541.6667 | AG43: Associate Member | AS43: New Member
B44: =DATE(YEAR(E$24),MONTH(E$24)+D44+1,DAY(E$24)) -> 46461 | C44: =TEXT(B44,"mmm-yyyy") -> Mar-2027 | D44: 17 | E44: =C$1 -> 5332.9739 | F44: =E44-G44 -> 5015.2277 | G44: =H43*C$12 -> 317.74617 | H44: =H43-F44 -> 36205.897 | L44: NET PROCEEDS (Php): | R44: =SUM(R36:T43) -> 100000 | X44: BORROWER'S INFORMATION
B45: =DATE(YEAR(E$24),MONTH(E$24)+D45+1,DAY(E$24)) -> 46492 | C45: =TEXT(B45,"mmm-yyyy") -> Apr-2027 | D45: 18 | E45: =C$1 -> 5332.9739 | F45: =E45-G45 -> 5053.8867 | G45: =H44*C$12 -> 279.08712 | H45: =H44-F45 -> 31152.01 | X45: MACAPILI | AD45: MARIA CRISELDA | AN45: GINAGA
B46: =DATE(YEAR(E$24),MONTH(E$24)+D46+1,DAY(E$24)) -> 46522 | C46: =TEXT(B46,"mmm-yyyy") -> May-2027 | D46: 19 | E46: =C$1 -> 5332.9739 | F46: =E46-G46 -> 5092.8438 | G46: =H45*C$12 -> 240.13008 | H46: =H45-F46 -> 26059.166 | K46: PAYMENT | X46: (LAST NAME) | AD46: (FIRST NAME) | AN46: (MIDDLE NAME) | AZ46: (SUFFIX)
B47: =DATE(YEAR(E$24),MONTH(E$24)+D47+1,DAY(E$24)) -> 46553 | C47: =TEXT(B47,"mmm-yyyy") -> Jun-2027 | D47: 20 | E47: =C$1 -> 5332.9739 | F47: =E47-G47 -> 5132.1011 | G47: =H46*C$12 -> 200.87274 | H47: =H46-F47 -> 20927.065 | X47: Rank/Position: | AD47: Serial No.: | AI47: Branch of Service: | AO47: Date of Appointment: | AW47: Date of Retirement:
B48: =DATE(YEAR(E$24),MONTH(E$24)+D48+1,DAY(E$24)) -> 46583 | C48: =TEXT(B48,"mmm-yyyy") -> Jul-2027 | D48: 21 | E48: =C$1 -> 5332.9739 | F48: =E48-G48 -> 5171.6611 | G48: =H47*C$12 -> 161.31279 | H48: =H47-F48 -> 15755.404 | L48: Term of loan in months: | R48: =E25 -> 24 | T48: month(s) | X48: BENEFICIARY - W | AD48: =D23 -> 734219 | AI48: PA | AP48: , | AR48: , | AX48: , | AZ48: ,
B49: =DATE(YEAR(E$24),MONTH(E$24)+D49+1,DAY(E$24)) -> 46614 | C49: =TEXT(B49,"mmm-yyyy") -> Aug-2027 | D49: 22 | E49: =C$1 -> 5332.9739 | F49: =E49-G49 -> 5211.526 | G49: =H48*C$12 -> 121.44791 | H49: =H48-F49 -> 10543.878 | L49: Monthly Amortization | R49: =C1 -> 5332.9739 | AO49: m | AP49: m | AQ49: d | AR49: d | AS49: y | AT49: y | AU49: y | AV49: y | AW49: m | AX49: m | AY49: d | AZ49: d | BA49: y | BB49: y | BC49: y | BD49: y
B50: =DATE(YEAR(E$24),MONTH(E$24)+D50+1,DAY(E$24)) -> 46645 | C50: =TEXT(B50,"mmm-yyyy") -> Sep-2027 | D50: 23 | E50: =C$1 -> 5332.9739 | F50: =E50-G50 -> 5251.6981 | G50: =H49*C$12 -> 81.275727 | H50: =H49-F50 -> 5292.18 | L50: First Payment Due On: | R50: =B28 -> 45976
B51: =DATE(YEAR(E$24),MONTH(E$24)+D51+1,DAY(E$24)) -> 46675 | C51: =TEXT(B51,"mmm-yyyy") -> Oct-2027 | D51: 24 | E51: =C$1 -> 5332.9739 | F51: =E51-G51 -> 5292.18 | G51: =H50*C$12 -> 40.793887 | H51: =H50-F51 -> 2.3719622e-09 | L51: Maturity: | R51: =B51 -> 46675 | X51: Length of Service: | AE51: Date of Birth: | AJ51: Age: | AK51: 58 | AM51: Civil Status: | AR51: Single | AU51: Widower | AX51: Home Phone No.
E52: =SUM(E28:E51) -> 127991.37 | F52: =SUM(F28:F51) -> 116441.67 | G52: =SUM(G28:G51) -> 11549.706 | L52: EIR (%): | R52: =C16 -> 0.096718129 | AE52: FEBRUARY 14 1959 | AR52: Married | AU52: Separated
L53: Interest Rate per Month (%): | R53: =C15 -> 0.0077083333 | X53: Unit Assignment: | AE53: Unit/Office/Business Address: | AX53: Unit/Office Telephone No/s:
AX54: 0956-936-5968
X55: AFP/Company ID No: | AG55: Email Address: | AT55: Tax Identification No/s:
K56: Certified & Corrected by: | R56: Verified by: | AT56: 9 | AU56: 4 | AV56: 6 | AW56: - | AX56: 5 | AY56: 0 | AZ56: 6 | BA56: - | BB56: 7 | BC56: 1 | BD56: 2
X57: Present Address: | AB57: =N34 -> PUROK 3 ,DAET, CAMARINEZ NORTE
X58: NOTIFICATION CLAUSE
K60: ALEXANDER A. FERIA JR | R60: ALEXANDER A. FERIA JR. | Y60: I hereby acknowledge and authorized the People's Multi-Purpose Cooperative (PMPC) for the following: 1) the regular submission and disclosure
K61: Processor | R61: Verifier/PELVAMS Liason | X61: of my basic credit data (as defined under Republic Act Nr 9510 and its Implementing Rules and Regulations) to the Credit Information Corporation (CIC)
X62: as well as any updates or corrections thereof; and 2) the sharing of my basic data and with other lenders authorized by the CIC, and credit reporting
X63: agencies duly accredited by the CIC.
AU64: =D22 -> MARIA CRISELDA G. MACAPILI
AU65: Printed Name & Signature of Borrower
K66: Received By: | R66: Approved By: | X66: CERTIFICATION
Y68: I hereby certify that the applicant is assigned to this Office; is not on leave without pay; has no pending case; and, that all information he/she
K69: =D22 -> MARIA CRISELDA G. MACAPILI | P69: COL.ALEXANDER L. FERIA (RET) CPA MNSA | X69: provided is true and correct.
K70: Signature Over Printed Name/Date | R70: President
X72: CERTIFYING OFFICER | AG72: DESIGNATION | AP72: OFFICE | AX72: CONTACT NUMBER
X73: (Signature Over Printed Name)
X74: CREDIT HISTORY
X75: Loan ID | AA75: Date Granted | AE75: Loan Granted | AJ75: Term | AM75: Maturity Date | AR75: MA | AU75: Status/Remarks | AZ75: Principal Balance
X81: LOAN APPROVAL
X82: Loan Amount: | AC82: MA: | AG82: Term: | AK82: Required NTHP: | AR82: NTHP after MA | AW82: Total Loan Exposure:
X83: =C4 -> 116441.67 | AC83: =R49 -> 5332.9739 | AG83: =R48 -> 24 | AK83: 650 | AW83: =C3 -> 127991.37
X84: PROCESSED & VERIFIED BY:
AJ86: =K60 -> ALEXANDER A. FERIA JR
W87: SIGNATURE OVER PRINTED NAME
E88: =SUM(E28:E87) -> 255982.75 | F88: =SUM(F28:F87) -> 232883.33 | G88: =SUM(G28:G87) -> 23099.412
X90: RECOMMEND APPROVAL/DISAPPROVAL: | AO90: APPROVED/DISAPPROVED:
AB92: ALEXANDER A FERIA JR | AS92: ALEXANDER L FERIA
X93: SIGNATURE OVER PRINTED NAME | AO93: SIGNATURE OVER PRINTED NAME
X100: PROMISORY NOTE NO: | AL100: =S30 -> LV-052
Y101: FOR VALUE RECEIVED, the undersigned promise to pay the People's Multi-Purpose Cooperative (PMPC) the sum of Php | AY101: =AW83 -> 127991.37
AA102: in | AB102: =AG83 -> 24 | AC102: equal monthly installments amounting to Php | AN102: =AC83 -> 5332.9739 | AR102: each, to be paid on the 28th day of every month starting on
X103: =R50 -> 45976 | AB103: / Single Payment of due on unpaid installments from maturity will bear charges on unpaid principal
X104: at the rate of 2% per month as penatly thereof.
X105: I hereby waive presentment for payment and notice of dishonor. PMPC may accept partial payment reserving its right of recourse against me. PMPC is hereby authorized and empowered to set off or apply without notice what is due under this Note from whatever funds I have in the Cooperative.
X108: It is further agreed that in case of separation from the service of whatever cause, the unpaid balance with its accumulated surcharges and interest as stipulated above be deducted from my last paymnet, commutation of leave/furlough and/or from my pension.
X111: It is further agreed that when installments are not paid when due and payable, the whole of the principal sum remaining unpaid shall forthwith become due and payable at the election of the Cooperative. I promise and agree to pay for a reasonable attorney's fee if this note is not paid according to its legal tenor and effect when palced in a lawyer's hand for collection. In case litigation, venue shall be vested in the competent court as may be allowed by the Rules of Court at the sole option of PMPC.
X116: Further, I hereby agree and authorized PMPC to encumber, assign or sell to any person or entity any right which it may have under thi Note, and/or any assignment, mortgage lien, pledge or other encumbrances constituted in favor of PMPC pursuant to the provisions of this Note if any. The consent herein granted is recognized and acknowledged by me/us as a waiver, to all intent and purposes of whatever right I may have to notice of actual encumbrance/ assignment.
AM120: Military/Pensioners ID
AM121: Employee's ID/Office ID
AM122: Driver's License
Z123: =N32 -> MARIA CRISELDA G. MACAPILI | AM123: Others:
X124: Signature over Printed Name
X126: ID No:
X127: Expiration Date: | AT127: LEFT THUMBMARK | AZ127: RIGHT THUMBMARK
X130: ACKNOWLEDGEMENT
X132: REPUBLIC OF THE PHILIPPINES
X133: (20-E, 2nd Camarilla St., Cor. 15th Ave.,BRGY San Roque, Murphy Cubao, Quezon City) S.S
X135: BEFORE ME, a Notary Public for and in Cubao, Quezon City this _______ day of _______________, 20_____, personally appeared __________________
X136: __________, who presented to me the Identification Cards mentioned above, known to me to be the same person who executed the forgoing application for loan and promissory note and acknowledged that the same as his/her true act and deed and took oath that the statement herein are true and correct and that the application is made for the purpose under consideration.
Y140: WITNESS MY HAND AND NOTARIAL SEAL, on the date, year and palce first above written.
X142: Doc No.
X143: Page No.
...

Sheet 3 years
A1: \ | B1: Amortization | C1: ='DATA ENTRY'!E16 -> 16696.184
B2: Timeline | C2: 0 | D2: 1 | E2: 2 | F2: 3 | G2: 4 | H2: 5 | I2: 6 | J2: 7 | K2: 8 | L2: 9 | M2: 10 | N2: 11 | O2: 12 | P2: 13 | Q2: 14 | R2: 15 | S2: 16 | T2: 17 | U2: 18 | V2: 19 | W2: 20 | X2: 21 | Y2: 22 | Z2: 23 | AA2: 24 | AB2: 25 | AC2: 26 | AD2: 27 | AE2: 28 | AF2: 29 | AG2: 30 | AH2: 31 | AI2: 32 | AJ2: 33 | AK2: 34 | AL2: 35 | AM2: 36
B3: GROSS AMOUNT | C3: ='DATA ENTRY'!E4 -> 601062.61
B4: LOAN AMOUNT | C4: ='DATA ENTRY'!E13 -> 517435.36 | D4: -13536.72 | E4: -13536.72 | F4: -13536.72 | G4: -13536.72 | H4: -13536.72 | I4: -13536.72 | J4: -13536.72 | K4: -13536.72 | L4: -13536.72 | M4: -13536.72 | N4: -13536.72 | O4: -13536.72 | P4: -13536.72 | Q4: -13536.72 | R4: -13536.72 | S4: -13536.72 | T4: -13536.72 | U4: -13536.72 | V4: -13536.72 | W4: -13536.72 | X4: -13536.72 | Y4: -13536.72 | Z4: -13536.72 | AA4: -13536.72 | AB4: -13536.72 | AC4: -13536.72 | AD4: -13536.72 | AE4: -13536.72 | AF4: -13536.72 | AG4: -13536.72 | AH4: -13536.72 | AI4: -13536.72 | AJ4: -13536.72 | AK4: -13536.72 | AL4: -13536.72 | AM4: -13536.72
B5: Service Fee | C5: ='DATA ENTRY'!E8 -> 39943.567
B6: Insurance | C6: ='DATA ENTRY'!E9 -> 15977.427
B7: CapCon | C7: ='DATA ENTRY'!E10 -> 10000
B8: membership fee | C8: ='DATA ENTRY'!E11 -> 300
B9: Advance Interest | C9: ='DATA ENTRY'!E12 -> 7396.9568
B10: NET PROCEEDS/CASH FLOW | C10: =C4-C5-C6-C7-C8-C9 -> 443817.41 | D10: =-$C1 -> -16696.184 | E10: =-$C1 -> -16696.184 | F10: =-$C1 -> -16696.184 | G10: =-$C1 -> -16696.184 | H10: =-$C1 -> -16696.184 | I10: =-$C1 -> -16696.184 | J10: =-$C1 -> -16696.184 | K10: =-$C1 -> -16696.184 | ... AM10: =-$C1 -> -16696.184
B12: Interest Rate of Return | C12: =IRR(C4:AM4) -> -0.0032058465 | D12: =C12/5 -> -0.00064116929 | G12: sinense LB
E13: =C10+C14 -> 534965.69 | G13: 72462.47
B14: Loan Balance | C14: =G15 -> 91148.28 | G14: 18685.81
B15: Monthly Interest Rate | C15: ='DATA ENTRY'!E14/12 -> 0.0083333333 | G15: =G13+G14 -> 91148.28
B16: Effective Interest Rate | C16: ='DATA ENTRY'!E15 -> 0.10501772 | K16: APPROVED
C20: LOAN LEDGER CARD
C22: Name: | D22: SEVERO B. SINENSE | G22: Loan Voucher No. | H22: LV- 004-BO
C23: Serial Nr: | D23: O-121408 | E23: Address: | F23: P7 CABUGAO, ECHAGUE ISABELA | G23: Amount: | H23: =C10-C14 -> 352669.13
C24: Posting date | D24: Date of Loan: | E24: 45868 | F24: Maturity Date | G24: =B63 -> 47026 | K24: PEOPLE'S MULTI-PURPOSE COOPERATIVE
D25: Term: | E25: 36 | F25: MOS | K25: 20-E 2nd Camarilla St. corner 15th Ave., Brgy. San Roque, Murphy Cubao, Quezon City | X25: 20-E 2nd Camarilla St corner 15th Avenue,
D26: Loan | E26: Installment | F26: Principal | G26: EIR | H26: Balance | X26: Brgy San Roque, Murphy Cubao, Quezon City
D27: Month 0 | H27: =C4 -> 517435.36 | K27: LOAN RELEASE VOUCHER | X27: Mobile No. (+63)953-033-1580 (GLOBE)
B28: =DATE(YEAR(E$24),MONTH(E$24)+D28+2,DAY(E$24)) -> 45960 | C28: =TEXT(B28,"mmm-yyyy") -> Oct-2025 | D28: 1 | E28: =C$1 -> 16696.184 | F28: =E28-G28 -> 18355.002 | G28: =H27*C$12 -> -1658.8183 | H28: =H27-F28 -> 499080.36
B29: =DATE(YEAR(E$24),MONTH(E$24)+D29+2,DAY(E$24)) -> 45991 | C29: =TEXT(B29,"mmm-yyyy") -> Nov-2025 | D29: 2 | E29: =C$1 -> 16696.184 | F29: =E29-G29 -> 18296.159 | G29: =H28*C$12 -> -1599.975 | H29: =H28-F29 -> 480784.2 | R29: Date: | S29: =E24 -> 45868 | X29: LOAN APPLICATION FORM
B30: =DATE(YEAR(E$24),MONTH(E$24)+D30+2,DAY(E$24)) -> 46021 | C30: =TEXT(B30,"mmm-yyyy") -> Dec-2025 | D30: 3 | E30: =C$1 -> 16696.184 | F30: =E30-G30 -> 18237.504 | G30: =H29*C$12 -> -1541.3203 | H30: =H29-F30 -> 462546.7 | R30: LV No: | S30: =H22 -> LV- 004-BO | AU30: Date: | AX30: , | AZ30: ,
B31: =DATE(YEAR(E$24),MONTH(E$24)+D31+2,DAY(E$24)) -> 46052 | C31: =TEXT(B31,"mmm-yyyy") -> Jan-2026 | D31: 4 | E31: =C$1 -> 16696.184 | F31: =E31-G31 -> 18179.037 | G31: =H30*C$12 -> -1482.8537 | H31: =H30-F31 -> 444367.66 | AW31: m | AX31: m | AY31: d | AZ31: d | BA31: y | BB31: y | BC31: y | BD31: y
B32: =DATE(YEAR(E$24),MONTH(E$24)+D32+2,DAY(E$24)) -> 46083 | C32: =TEXT(B32,"mmm-yyyy") -> Mar-2026 | D32: 5 | E32: =C$1 -> 16696.184 | F32: =E32-G32 -> 18120.758 | G32: =H31*C$12 -> -1424.5745 | H32: =H31-F32 -> 426246.9 | K32: Name of Borrower: | N32: =D22 -> SEVERO B. SINENSE | X32: APPLICATION TYPE | AE32: LOAN CLASSIFICATION | AM32: TERM | AT32: RELEASE OF LOAN PROCEEDS
B33: =DATE(YEAR(E$24),MONTH(E$24)+D33+2,DAY(E$24)) -> 46111 | C33: =TEXT(B33,"mmm-yyyy") -> Mar-2026 | D33: 6 | E33: =C$1 -> 16696.184 | F33: =E33-G33 -> 18062.666 | G33: =H32*C$12 -> -1366.4821 | H33: =H32-F33 -> 408184.23 | K33: Serial No.: | N33: =D23 -> O-121408 | Y33: New | AF33: Salary Loan | AN33: 12 Months | AU33: Check
B34: =DATE(YEAR(E$24),MONTH(E$24)+D34+2,DAY(E$24)) -> 46142 | C34: =TEXT(B34,"mmm-yyyy") -> Apr-2026 | D34: 7 | E34: =C$1 -> 16696.184 | F34: =E34-G34 -> 18004.76 | G34: =H33*C$12 -> -1308.576 | H34: =H33-F34 -> 390179.48 | K34: Address: | N34: =F23 -> P7 CABUGAO, ECHAGUE ISABELA | Y34: Renewal | AF34: Pension Loan | AN34: 24 Months | AU34: Bank Electronic Transfer to Borrowers Account
B35: =DATE(YEAR(E$24),MONTH(E$24)+D35+2,DAY(E$24)) -> 46172 | C35: =TEXT(B35,"mmm-yyyy") -> May-2026 | D35: 8 | E35: =C$1 -> 16696.184 | F35: =E35-G35 -> 17947.039 | G35: =H34*C$12 -> -1250.8555 | H35: =H34-F35 -> 372232.44 | Y35: Additional | AF35: Emergency | AN35: 36 Months | AU35: Others:
B36: =DATE(YEAR(E$24),MONTH(E$24)+D36+2,DAY(E$24)) -> 46203 | C36: =TEXT(B36,"mmm-yyyy") -> Jun-2026 | D36: 9 | E36: =C$1 -> 16696.184 | F36: =E36-G36 -> 17889.504 | G36: =H35*C$12 -> -1193.32 | H36: =H35-F36 -> 354342.93 | L36: Principal Amount | R36: =C4 -> 517435.36 | Y36: Reloan | AF36: Health Assistance Loan | AN36: 48 Months
B37: =DATE(YEAR(E$24),MONTH(E$24)+D37+2,DAY(E$24)) -> 46233 | C37: =TEXT(B37,"mmm-yyyy") -> Jul-2026 | D37: 10 | E37: =C$1 -> 16696.184 | F37: =E37-G37 -> 17832.153 | G37: =H36*C$12 -> -1135.969 | H37: =H36-F37 -> 336510.78 | Y37: Restructure | AF37: Educational Loan | AN37: 60 Months
B38: =DATE(YEAR(E$24),MONTH(E$24)+D38+2,DAY(E$24)) -> 46264 | C38: =TEXT(B38,"mmm-yyyy") -> Aug-2026 | D38: 11 | E38: =C$1 -> 16696.184 | F38: =E38-G38 -> 17774.986 | G38: =H37*C$12 -> -1078.8019 | H38: =H37-F38 -> 318735.79 | L38: (-) | M38: Balance Old Loan(s) | R38: =-C14 -> -91148.28 | AF38: Others: | AN38: Others:
B39: =DATE(YEAR(E$24),MONTH(E$24)+D39+2,DAY(E$24)) -> 46295 | C39: =TEXT(B39,"mmm-yyyy") -> Sep-2026 | D39: 12 | E39: =C$1 -> 16696.184 | F39: =E39-G39 -> 17718.002 | G39: =H38*C$12 -> -1021.818 | H39: =H38-F39 -> 301017.79 | L39: (-) | M39: Membership Fee: | R39: =-C8 -> -300 | X39: AMOUNT APPLIED: | AB39: =R44 -> 352669.13 | AN39: MONTHLY AMORTIZATION: | AT39: =R49 -> 16696.184
B40: =DATE(YEAR(E$24),MONTH(E$24)+D40+2,DAY(E$24)) -> 46325 | C40: =TEXT(B40,"mmm-yyyy") -> Oct-2026 | D40: 13 | E40: =C$1 -> 16696.184 | F40: =E40-G40 -> 17661.2 | G40: =H39*C$12 -> -965.01683 | H40: =H39-F40 -> 283356.59 | L40: (-) | M40: Paid up Capital: | R40: =-C7 -> -10000
B41: =DATE(YEAR(E$24),MONTH(E$24)+D41+2,DAY(E$24)) -> 46356 | C41: =TEXT(B41,"mmm-yyyy") -> Nov-2026 | D41: 14 | E41: =C$1 -> 16696.184 | F41: =E41-G41 -> 17604.581 | G41: =H40*C$12 -> -908.39773 | H41: =H40-F41 -> 265752.01 | L41: (-) | M41: Service Fee | R41: =-C5 -> -39943.567 | X41: LOAN ID: | AF41: DEDUCTION CODE: | AR41: LOAN PURPOSE:
B42: =DATE(YEAR(E$24),MONTH(E$24)+D42+2,DAY(E$24)) -> 46386 | C42: =TEXT(B42,"mmm-yyyy") -> Dec-2026 | D42: 15 | E42: =C$1 -> 16696.184 | F42: =E42-G42 -> 17548.144 | G42: =H41*C$12 -> -851.96014 | H42: =H41-F42 -> 248203.87 | L42: (-) | M42: Insurance Premium - Paramount | R42: =-C6 -> -15977.427 | X42: MEM ID: | AG42: Regular Member | AS42: Old Member
B43: =DATE(YEAR(E$24),MONTH(E$24)+D43+2,DAY(E$24)) -> 46417 | C43: =TEXT(B43,"mmm-yyyy") -> Jan-2027 | D43: 16 | E43: =C$1 -> 16696.184 | F43: =E43-G43 -> 17491.887 | G43: =H42*C$12 -> -795.70349 | H43: =H42-F43 -> 230711.98 | L43: (-) | M43: Advance Interest | R43: =-C9 -> -7396.9568 | AG43: Associate Member | AS43: New Member
B44: =DATE(YEAR(E$24),MONTH(E$24)+D44+2,DAY(E$24)) -> 46448 | C44: =TEXT(B44,"mmm-yyyy") -> Mar-2027 | D44: 17 | E44: =C$1 -> 16696.184 | F44: =E44-G44 -> 17435.811 | G44: =H43*C$12 -> -739.62719 | H44: =H43-F44 -> 213276.17 | L44: NET PROCEEDS (Php): | R44: =SUM(R36:T43) -> 352669.13 | X44: BORROWER'S INFORMATION
B45: =DATE(YEAR(E$24),MONTH(E$24)+D45+2,DAY(E$24)) -> 46476 | C45: =TEXT(B45,"mmm-yyyy") -> Mar-2027 | D45: 18 | E45: =C$1 -> 16696.184 | F45: =E45-G45 -> 17379.914 | G45: =H44*C$12 -> -683.73065 | H45: =H44-F45 -> 195896.25 | X45: SINENSE | AD45: SEVERO | AN45: BATOBATO
B46: =DATE(YEAR(E$24),MONTH(E$24)+D46+2,DAY(E$24)) -> 46507 | C46: =TEXT(B46,"mmm-yyyy") -> Apr-2027 | D46: 19 | E46: =C$1 -> 16696.184 | F46: =E46-G46 -> 17324.197 | G46: =H45*C$12 -> -628.01332 | H46: =H45-F46 -> 178572.06 | K46: PAYMENT | X46: (LAST NAME) | AD46: (FIRST NAME) | AN46: (MIDDLE NAME) | AZ46: (SUFFIX)
B47: =DATE(YEAR(E$24),MONTH(E$24)+D47+2,DAY(E$24)) -> 46537 | C47: =TEXT(B47,"mmm-yyyy") -> May-2027 | D47: 20 | E47: =C$1 -> 16696.184 | F47: =E47-G47 -> 17268.658 | G47: =H46*C$12 -> -572.4746 | H47: =H46-F47 -> 161303.4 | X47: Rank/Position: | AD47: Serial No.: | AI47: Branch of Service: | AO47: Date of Appointment: | AW47: Date of Retirement:
B48: =DATE(YEAR(E$24),MONTH(E$24)+D48+2,DAY(E$24)) -> 46568 | C48: =TEXT(B48,"mmm-yyyy") -> Jun-2027 | D48: 21 | E48: =C$1 -> 16696.184 | F48: =E48-G48 -> 17213.298 | G48: =H47*C$12 -> -517.11393 | H48: =H47-F48 -> 144090.1 | L48: Term of loan in months: | R48: =E25 -> 36 | T48: month(s) | X48: COL | AD48: =D23 -> O-121408 | AI48: PA | AP48: , | AR48: , | AX48: , | AZ48: ,
B49: =DATE(YEAR(E$24),MONTH(E$24)+D49+2,DAY(E$24)) -> 46598 | C49: =TEXT(B49,"mmm-yyyy") -> Jul-2027 | D49: 22 | E49: =C$1 -> 16696.184 | F49: =E49-G49 -> 17158.114 | G49: =H48*C$12 -> -461.93074 | H49: =H48-F49 -> 126931.99 | L49: Monthly Amortization | R49: =C1 -> 16696.184 | AO49: m | AP49: m | AQ49: d | AR49: d | AS49: y | AT49: y | AU49: y | AV49: y | AW49: m | AX49: m | AY49: d | AZ49: d | BA49: y | BB49: y | BC49: y | BD49: y
B50: =DATE(YEAR(E$24),MONTH(E$24)+D50+2,DAY(E$24)) -> 46629 | C50: =TEXT(B50,"mmm-yyyy") -> Aug-2027 | D50: 23 | E50: =C$1 -> 16696.184 | F50: =E50-G50 -> 17103.108 | G50: =H49*C$12 -> -406.92446 | H50: =H49-F50 -> 109828.88 | L50: First Payment Due On: | R50: =B28 -> 45960
B51: =DATE(YEAR(E$24),MONTH(E$24)+D51+2,DAY(E$24)) -> 46660 | C51: =TEXT(B51,"mmm-yyyy") -> Sep-2027 | D51: 24 | E51: =C$1 -> 16696.184 | F51: =E51-G51 -> 17048.278 | G51: =H50*C$12 -> -352.09452 | H51: =H50-F51 -> 92780.601 | L51: Maturity: | R51: =B63 -> 47026 | X51: Length of Service: | AE51: Date of Birth: | AJ51: Age: | AM51: Civil Status: | AR51: Single | AU51: Widower | AX51: Home Phone No.
B52: =DATE(YEAR(E$24),MONTH(E$24)+D52+2,DAY(E$24)) -> 46690 | C52: =TEXT(B52,"mmm-yyyy") -> Oct-2027 | D52: 25 | E52: =C$1 -> 16696.184 | F52: =E52-G52 -> 16993.624 | G52: =H51*C$12 -> -297.44036 | H52: =H51-F52 -> 75786.977 | L52: EIR (%): | R52: =C16 -> 0.10501772 | AR52: Married | AU52: Separated
B53: =DATE(YEAR(E$24),MONTH(E$24)+D53+2,DAY(E$24)) -> 46721 | C53: =TEXT(B53,"mmm-yyyy") -> Nov-2027 | D53: 26 | E53: =C$1 -> 16696.184 | F53: =E53-G53 -> 16939.145 | G53: =H52*C$12 -> -242.96141 | H53: =H52-F53 -> 58847.832 | L53: Interest Rate per Month (%): | R53: =C15 -> 0.0083333333 | X53: Unit Assignment: | AE53: Unit/Office/Business Address: | AX53: Unit/Office Telephone No/s:
B54: =DATE(YEAR(E$24),MONTH(E$24)+D54+2,DAY(E$24)) -> 46751 | C54: =TEXT(B54,"mmm-yyyy") -> Dec-2027 | D54: 27 | E54: =C$1 -> 16696.184 | F54: =E54-G54 -> 16884.841 | G54: =H53*C$12 -> -188.65711 | H54: =H53-F54 -> 41962.991 | AX54: 0956-936-5968
B55: =DATE(YEAR(E$24),MONTH(E$24)+D55+2,DAY(E$24)) -> 46782 | C55: =TEXT(B55,"mmm-yyyy") -> Jan-2028 | D55: 28 | E55: =C$1 -> 16696.184 | F55: =E55-G55 -> 16830.711 | G55: =H54*C$12 -> -134.52691 | H55: =H54-F55 -> 25132.281 | X55: AFP/Company ID No: | AG55: Email Address: | AT55: Tax Identification No/s:
B56: =DATE(YEAR(E$24),MONTH(E$24)+D56+2,DAY(E$24)) -> 46813 | C56: =TEXT(B56,"mmm-yyyy") -> Mar-2028 | D56: 29 | E56: =C$1 -> 16696.184 | F56: =E56-G56 -> 16776.754 | G56: =H55*C$12 -> -80.570234 | H56: =H55-F56 -> 8355.5269 | K56: Certified & Corrected by: | R56: Verified by: | AT56: 1 | AU56: 3 | AV56: 7 | AW56: - | AX56: 6 | AY56: 2 | AZ56: 4 | BA56: - | BB56: 8 | BC56: 2 | BD56: 9
B57: =DATE(YEAR(E$24),MONTH(E$24)+D57+2,DAY(E$24)) -> 46842 | C57: =TEXT(B57,"mmm-yyyy") -> Mar-2028 | D57: 30 | E57: =C$1 -> 16696.184 | F57: =E57-G57 -> 16722.97 | G57: =H56*C$12 -> -26.786536 | H57: =H56-F57 -> -8367.4433 | X57: Present Address: | AB57: =N34 -> P7 CABUGAO, ECHAGUE ISABELA
B58: =DATE(YEAR(E$24),MONTH(E$24)+D58+2,DAY(E$24)) -> 46873 | C58: =TEXT(B58,"mmm-yyyy") -> Apr-2028 | D58: 31 | E58: =C$1 -> 16696.184 | F58: =E58-G58 -> 16669.359 | G58: =H57*C$12 -> 26.824738 | H58: =H57-F58 -> -25036.802 | X58: NOTIFICATION CLAUSE
B59: =DATE(YEAR(E$24),MONTH(E$24)+D59+2,DAY(E$24)) -> 46903 | C59: =TEXT(B59,"mmm-yyyy") -> May-2028 | D59: 32 | E59: =C$1 -> 16696.184 | F59: =E59-G59 -> 16615.919 | G59: =H58*C$12 -> 80.264144 | H59: =H58-F59 -> -41652.722
B60: =DATE(YEAR(E$24),MONTH(E$24)+D60+2,DAY(E$24)) -> 46934 | C60: =TEXT(B60,"mmm-yyyy") -> Jun-2028 | D60: 33 | E60: =C$1 -> 16696.184 | F60: =E60-G60 -> 16562.651 | G60: =H59*C$12 -> 133.53223 | H60: =H59-F60 -> -58215.373 | K60: PAMELA CHERRY A. REYES | R60: ALEXANDER A. FERIA JR. | Y60: I hereby acknowledge and authorized the People's Multi-Purpose Cooperative (PMPC) for the following: 1) the regular submission and disclosure
B61: =DATE(YEAR(E$24),MONTH(E$24)+D61+2,DAY(E$24)) -> 46964 | C61: =TEXT(B61,"mmm-yyyy") -> Jul-2028 | D61: 34 | E61: =C$1 -> 16696.184 | F61: =E61-G61 -> 16509.554 | G61: =H60*C$12 -> 186.62955 | H61: =H60-F61 -> -74724.927 | K61: Processor | R61: Verifier/PELVAMS Liason | X61: of my basic credit data (as defined under Republic Act Nr 9510 and its Implementing Rules and Regulations) to the Credit Information Corporation (CIC)
B62: =DATE(YEAR(E$24),MONTH(E$24)+D62+2,DAY(E$24)) -> 46995 | C62: =TEXT(B62,"mmm-yyyy") -> Aug-2028 | D62: 35 | E62: =C$1 -> 16696.184 | F62: =E62-G62 -> 16456.627 | G62: =H61*C$12 -> 239.55664 | H62: =H61-F62 -> -91181.554 | X62: as well as any updates or corrections thereof; and 2) the sharing of my basic data and with other lenders authorized by the CIC, and credit reporting
B63: =DATE(YEAR(E$24),MONTH(E$24)+D63+2,DAY(E$24)) -> 47026 | C63: =TEXT(B63,"mmm-yyyy") -> Sep-2028 | D63: 36 | E63: =C$1 -> 16696.184 | F63: =E63-G63 -> 16403.87 | G63: =H62*C$12 -> 292.31406 | H63: =H62-F63 -> -107585.42 | X63: agencies duly accredited by the CIC.
E64: =SUM(E28:E63) -> 601062.61 | F64: =SUM(F28:F63) -> 625020.78 | G64: =SUM(G28:G63) -> -23958.173 | AU64: =D22 -> SEVERO B. SINENSE
AU65: Printed Name & Signature of Borrower
K66: Received By: | R66: Approved By: | X66: CERTIFICATION
Y68: I hereby certify that the applicant is assigned to this Office; is not on leave without pay; has no pending case; and, that all information he/she
K69: =D22 -> SEVERO B. SINENSE | P69: COL.ALEXANDER L. FERIA (RET) CPA MNSA | X69: provided is true and correct.
K70: Signature Over Printed Name/Date | R70: President
X72: CERTIFYING OFFICER | AG72: DESIGNATION | AP72: OFFICE | AX72: CONTACT NUMBER
X73: (Signature Over Printed Name)
X74: CREDIT HISTORY
X75: Loan ID | AA75: Date Granted | AE75: Loan Granted | AJ75: Term | AM75: Maturity Date | AR75: MA | AU75: Status/Remarks | AZ75: Principal Balance
AZ76: =H23 -> 352669.13
X81: LOAN APPROVAL
X82: Loan Amount: | AC82: MA: | AG82: Term: | AK82: Required NTHP: | AR82: NTHP after MA | AW82: Total Loan Exposure:
X83: =AZ76 -> 352669.13 | AC83: =R49 -> 16696.184 | AG83: =R48 -> 36 | AK83: 650 | AW83: =C3 -> 601062.61
X84: PROCESSED & VERIFIED BY:
AJ86: PAMELA CHERRY A REYES
W87: SIGNATURE OVER PRINTED NAME
E88: =SUM(E28:E87) -> 1202125.2 | F88: =SUM(F28:F87) -> 1250041.6 | G88: =SUM(G28:G87) -> -47916.346
X90: RECOMMEND APPROVAL/DISAPPROVAL: | AO90: APPROVED/DISAPPROVED:
AB92: ALEXANDER A FERIA JR | AS92: ALEXANDER L FERIA
X93: SIGNATURE OVER PRINTED NAME | AO93: SIGNATURE OVER PRINTED NAME
X100: PROMISORY NOTE NO: | AL100: =S30 -> LV- 004-BO
Y101: FOR VALUE RECEIVED, the undersigned promise to pay the People's Multi-Purpose Cooperative (PMPC) the sum of Php | AY101: =AW83 -> 601062.61
AA102: in | AB102: =AG83 -> 36 | AC102: equal monthly installments amounting to Php | AN102: =AC83 -> 16696.184 | AR102: each, to be paid on the 28th day of every month starting on
X103: =R50 -> 45960 | AB103: / Single Payment of due on unpaid installments from maturity will bear charges on unpaid principal
X104: at the rate of 2% per month as penatly thereof.
X105: I hereby waive presentment for payment and notice of dishonor. PMPC may accept partial payment reserving its right of recourse against me. PMPC is hereby authorized and empowered to set off or apply without notice what is due under this Note from whatever funds I have in the Cooperative.
X108: It is further agreed that in case of separation from the service of whatever cause, the unpaid balance with its accumulated surcharges and interest as stipulated above be deducted from my last paymnet, commutation of leave/furlough and/or from my pension.
X111: It is further agreed that when installments are not paid when due and payable, the whole of the principal sum remaining unpaid shall forthwith become due and payable at the election of the Cooperative. I promise and agree to pay for a reasonable attorney's fee if this note is not paid according to its legal tenor and effect when palced in a lawyer's hand for collection. In case litigation, venue shall be vested in the competent court as may be allowed by the Rules of Court at the sole option of PMPC.
X116: Further, I hereby agree and authorized PMPC to encumber, assign or sell to any person or entity any right which it may have under thi Note, and/or any assignment, mortgage lien, pledge or other encumbrances constituted in favor of PMPC pursuant to the provisions of this Note if any. The consent herein granted is recognized and acknowledged by me/us as a waiver, to all intent and purposes of whatever right I may have to notice of actual encumbrance/ assignment.
AM120: Military/Pensioners ID
AM121: Employee's ID/Office ID
AM122: Driver's License
Z123: =N32 -> SEVERO B. SINENSE | AM123: Others:
X124: Signature over Printed Name
X126: ID No:
X127: Expiration Date: | AT127: LEFT THUMBMARK | AZ127: RIGHT THUMBMARK
X130: ACKNOWLEDGEMENT
X132: REPUBLIC OF THE PHILIPPINES
X133: (20-E, 2nd Camarilla St., Cor. 15th Ave.,BRGY San Roque, Murphy Cubao, Quezon City) S.S
X135: BEFORE ME, a Notary Public for and in Cubao, Quezon City this _______ day of _______________, 20_____, personally appeared __________________
X136: __________, who presented to me the Identification Cards mentioned above, known to me to be the same person who executed the forgoing application for loan and promissory note and acknowledged that the same as his/her true act and deed and took oath that the statement herein are true and correct and that the application is made for the purpose under consideration.
...

Sheet 4 years
A1: \ | B1: Amortization | C1: ='DATA ENTRY'!F16 -> 13536.716
B2: Timeline | C2: 0 | D2: 1 | E2: 2 | F2: 3 | G2: 4 | H2: 5 | I2: 6 | J2: 7 | K2: 8 | L2: 9 | M2: 10 | N2: 11 | O2: 12 | P2: 13 | Q2: 14 | R2: 15 | S2: 16 | T2: 17 | U2: 18 | V2: 19 | W2: 20 | X2: 21 | Y2: 22 | Z2: 23 | AA2: 24 | AB2: 25 | AC2: 26 | AD2: 27 | AE2: 28 | AF2: 29 | AG2: 30 | AH2: 31 | AI2: 32 | AJ2: 33 | AK2: 34 | AL2: 35 | AM2: 36 | AN2: 37 | AO2: 38 | AP2: 39 | AQ2: 40 | AR2: 41 | AS2: 42 | AT2: 43 | AU2: 44 | AV2: 45 | AW2: 46 | AX2: 47 | AY2: 48 | AZ2: 49 | BA2: 50 | BB2: 51 | BC2: 52 | BD2: 53 | BE2: 54 | BF2: 55 | BG2: 56 | BH2: 57 | BI2: 58 | BJ2: 59 | BK2: 60
B3: GROSS AMOUNT | C3: ='DATA ENTRY'!F4 -> 649762.37
B4: LOAN AMOUNT | C4: ='DATA ENTRY'!F13 -> 523754.78 | D4: =D10 -> -13536.716 | E4: =E10 -> -13536.716 | F4: =F10 -> -13536.716 | G4: =G10 -> -13536.716 | H4: =H10 -> -13536.716 | I4: =I10 -> -13536.716 | J4: =J10 -> -13536.716 | K4: =K10 -> -13536.716 | ... BK4: =BK10 -> -13536.716
B5: Service Fee | C5: ='DATA ENTRY'!F8 -> 39963.33
B6: Insurance | C6: ='DATA ENTRY'!F9 -> 21313.776
B7: CapCon | C7: ='DATA ENTRY'!F10 -> 10000
B8: membership fee | C8: ='DATA ENTRY'!G11 -> 300
B9: Advance Interest | C9: ='DATA ENTRY'!F12 -> 8140.6783
B10: NET PROCEEDS/CASH FLOW | C10: =C4-C5-C6-C7-C8-C9 -> 444037 | D10: =-$C1 -> -13536.716 | E10: =-$C1 -> -13536.716 | F10: =-$C1 -> -13536.716 | G10: =-$C1 -> -13536.716 | H10: =-$C1 -> -13536.716 | I10: =-$C1 -> -13536.716 | J10: =-$C1 -> -13536.716 | K10: =-$C1 -> -13536.716 | ... BK10: =-$C1 -> -13536.716
B12: Interest Rate of Return | C12: =IRR(C4:AY4) -> 0.0091666667 | D12: =C12/5 -> 0.0018333333
B14: Loan Balance | C14: 91367.87
B15: Monthly Interest Rate | C15: ='DATA ENTRY'!G14/12 -> 0.01
B16: Effective Interest Rate | C16: ='DATA ENTRY'!G15 -> 0.12736174 | K16: APPROVED
C20: LOAN LEDGER CARD
C22: Name: | D22: SEVERO B. SINENSE | G22: Loan Voucher No. | H22: LV- 004-BO
C23: Serial Nr: | D23: O-121408 | E23: Address: | F23: P7 CABUGAO, ECHAGUE, ISABELA | G23: Amount: | H23: =C10 -> 444037
C24: Posting date | D24: Date of Loan: | E24: 45874 | F24: Maturity Date | G24: =B75 -> 47366 | K24: PEOPLE'S MULTI-PURPOSE COOPERATIVE
D25: Term: | E25: 48 | F25: MOS | K25: 20-E 2nd Camarilla St. corner 15th Ave., Brgy. San Roque, Murphy Cubao, Quezon City | X25: 20-E 2nd Camarilla St corner 15th Avenue,
D26: Loan | E26: Installment | F26: Principal | G26: EIR | H26: Balance | X26: Brgy San Roque, Murphy Cubao, Quezon City
D27: Month 0 | H27: =C4 -> 523754.78 | K27: LOAN RELEASE VOUCHER | X27: Mobile No. (+63)953-033-1580 (GLOBE)
B28: =DATE(YEAR(E$24),MONTH(E$24)+D28+1,DAY(E$24)) -> 45935 | C28: =TEXT(B28,"mmm-yyyy") -> Oct-2025 | D28: 1 | E28: =C$1 -> 13536.716 | F28: =E28-G28 -> 8735.6306 | G28: =H27*C$12 -> 4801.0855 | H28: =H27-F28 -> 515019.15
B29: =DATE(YEAR(E$24),MONTH(E$24)+D29+1,DAY(E$24)) -> 45966 | C29: =TEXT(B29,"mmm-yyyy") -> Nov-2025 | D29: 2 | E29: =C$1 -> 13536.716 | F29: =E29-G29 -> 8815.7072 | G29: =H28*C$12 -> 4721.0089 | H29: =H28-F29 -> 506203.45 | R29: Date: | S29: =E24 -> 45874 | X29: LOAN APPLICATION FORM
B30: =DATE(YEAR(E$24),MONTH(E$24)+D30+1,DAY(E$24)) -> 45996 | C30: =TEXT(B30,"mmm-yyyy") -> Dec-2025 | D30: 3 | E30: =C$1 -> 13536.716 | F30: =E30-G30 -> 8896.5179 | G30: =H29*C$12 -> 4640.1983 | H30: =H29-F30 -> 497306.93 | R30: LV No: | S30: =H22 -> LV- 004-BO | AU30: Date: | AX30: , | AZ30: ,
B31: =DATE(YEAR(E$24),MONTH(E$24)+D31+1,DAY(E$24)) -> 46027 | C31: =TEXT(B31,"mmm-yyyy") -> Jan-2026 | D31: 4 | E31: =C$1 -> 13536.716 | F31: =E31-G31 -> 8978.0693 | G31: =H30*C$12 -> 4558.6468 | H31: =H30-F31 -> 488328.86 | AW31: m | AX31: m | AY31: d | AZ31: d | BA31: y | BB31: y | BC31: y | BD31: y
B32: =DATE(YEAR(E$24),MONTH(E$24)+D32+1,DAY(E$24)) -> 46058 | C32: =TEXT(B32,"mmm-yyyy") -> Feb-2026 | D32: 5 | E32: =C$1 -> 13536.716 | F32: =E32-G32 -> 9060.3682 | G32: =H31*C$12 -> 4476.3479 | H32: =H31-F32 -> 479268.49 | K32: Name of Borrower: | N32: =D22 -> SEVERO B. SINENSE | X32: APPLICATION TYPE | AE32: LOAN CLASSIFICATION | AM32: TERM | AT32: RELEASE OF LOAN PROCEEDS
B33: =DATE(YEAR(E$24),MONTH(E$24)+D33+1,DAY(E$24)) -> 46086 | C33: =TEXT(B33,"mmm-yyyy") -> Mar-2026 | D33: 6 | E33: =C$1 -> 13536.716 | F33: =E33-G33 -> 9143.4216 | G33: =H32*C$12 -> 4393.2945 | H33: =H32-F33 -> 470125.07 | K33: Serial No.: | N33: =D23 -> O-121408 | Y33: New | AF33: Salary Loan | AN33: 12 Months | AU33: Check
B34: =DATE(YEAR(E$24),MONTH(E$24)+D34+1,DAY(E$24)) -> 46117 | C34: =TEXT(B34,"mmm-yyyy") -> Apr-2026 | D34: 7 | E34: =C$1 -> 13536.716 | F34: =E34-G34 -> 9227.2363 | G34: =H33*C$12 -> 4309.4798 | H34: =H33-F34 -> 460897.83 | K34: Address: | N34: =F23 -> P7 CABUGAO, ECHAGUE, ISABELA | Y34: Renewal | AF34: Pension Loan | AN34: 24 Months | AU34: Bank Electronic Transfer to Borrowers Account
B35: =DATE(YEAR(E$24),MONTH(E$24)+D35+1,DAY(E$24)) -> 46147 | C35: =TEXT(B35,"mmm-yyyy") -> May-2026 | D35: 8 | E35: =C$1 -> 13536.716 | F35: =E35-G35 -> 9311.8193 | G35: =H34*C$12 -> 4224.8968 | H35: =H34-F35 -> 451586.01 | Y35: Additional | AF35: Emergency | AN35: 36 Months | AU35: Others:
B36: =DATE(YEAR(E$24),MONTH(E$24)+D36+1,DAY(E$24)) -> 46178 | C36: =TEXT(B36,"mmm-yyyy") -> Jun-2026 | D36: 9 | E36: =C$1 -> 13536.716 | F36: =E36-G36 -> 9397.1777 | G36: =H35*C$12 -> 4139.5385 | H36: =H35-F36 -> 442188.84 | L36: Principal Amount | R36: =C4 -> 523754.78 | Y36: Reloan | AF36: Health Assistance Loan | AN36: 48 Months
B37: =DATE(YEAR(E$24),MONTH(E$24)+D37+1,DAY(E$24)) -> 46208 | C37: =TEXT(B37,"mmm-yyyy") -> Jul-2026 | D37: 10 | E37: =C$1 -> 13536.716 | F37: =E37-G37 -> 9483.3185 | G37: =H36*C$12 -> 4053.3977 | H37: =H36-F37 -> 432705.52 | Y37: Restructure | AF37: Educational Loan | AN37: 60 Months
B38: =DATE(YEAR(E$24),MONTH(E$24)+D38+1,DAY(E$24)) -> 46239 | C38: =TEXT(B38,"mmm-yyyy") -> Aug-2026 | D38: 11 | E38: =C$1 -> 13536.716 | F38: =E38-G38 -> 9570.2489 | G38: =H37*C$12 -> 3966.4672 | H38: =H37-F38 -> 423135.27 | L38: (-) | M38: Balance Old Loan(s) | R38: =-C14 -> -91367.87 | AF38: Others: | AN38: Others:
B39: =DATE(YEAR(E$24),MONTH(E$24)+D39+1,DAY(E$24)) -> 46270 | C39: =TEXT(B39,"mmm-yyyy") -> Sep-2026 | D39: 12 | E39: =C$1 -> 13536.716 | F39: =E39-G39 -> 9657.9762 | G39: =H38*C$12 -> 3878.74 | H39: =H38-F39 -> 413477.29 | L39: (-) | M39: Membership Fee: | R39: =-C8 -> -300 | X39: AMOUNT APPLIED: | AB39: =R44 -> 352669.13 | AN39: MONTHLY AMORTIZATION: | AT39: =R49 -> 13536.716
B40: =DATE(YEAR(E$24),MONTH(E$24)+D40+1,DAY(E$24)) -> 46300 | C40: =TEXT(B40,"mmm-yyyy") -> Oct-2026 | D40: 13 | E40: =C$1 -> 13536.716 | F40: =E40-G40 -> 9746.5076 | G40: =H39*C$12 -> 3790.2085 | H40: =H39-F40 -> 403730.79 | L40: (-) | M40: Paid up Capital: | R40: =-C7 -> -10000
B41: =DATE(YEAR(E$24),MONTH(E$24)+D41+1,DAY(E$24)) -> 46331 | C41: =TEXT(B41,"mmm-yyyy") -> Nov-2026 | D41: 14 | E41: =C$1 -> 13536.716 | F41: =E41-G41 -> 9835.8506 | G41: =H40*C$12 -> 3700.8655 | H41: =H40-F41 -> 393894.93 | L41: (-) | M41: Service Fee | R41: =-C5 -> -39963.33 | X41: LOAN ID: | AF41: DEDUCTION CODE: | AR41: LOAN PURPOSE:
B42: =DATE(YEAR(E$24),MONTH(E$24)+D42+1,DAY(E$24)) -> 46361 | C42: =TEXT(B42,"mmm-yyyy") -> Dec-2026 | D42: 15 | E42: =C$1 -> 13536.716 | F42: =E42-G42 -> 9926.0126 | G42: =H41*C$12 -> 3610.7036 | H42: =H41-F42 -> 383968.92 | L42: (-) | M42: Insurance Premium - Paramount | R42: =-C6 -> -21313.776 | X42: MEM ID: | AG42: Regular Member | AS42: Old Member
B43: =DATE(YEAR(E$24),MONTH(E$24)+D43+1,DAY(E$24)) -> 46392 | C43: =TEXT(B43,"mmm-yyyy") -> Jan-2027 | D43: 16 | E43: =C$1 -> 13536.716 | F43: =E43-G43 -> 10017.001 | G43: =H42*C$12 -> 3519.7151 | H43: =H42-F43 -> 373951.92 | L43: (-) | M43: Advance Interest | R43: =-C9 -> -8140.6783 | AG43: Associate Member | AS43: New Member
B44: =DATE(YEAR(E$24),MONTH(E$24)+D44+1,DAY(E$24)) -> 46423 | C44: =TEXT(B44,"mmm-yyyy") -> Feb-2027 | D44: 17 | E44: =C$1 -> 13536.716 | F44: =E44-G44 -> 10108.824 | G44: =H43*C$12 -> 3427.8926 | H44: =H43-F44 -> 363843.1 | L44: NET PROCEEDS (Php): | R44: =SUM(R36:T43) -> 352669.13 | X44: BORROWER'S INFORMATION
B45: =DATE(YEAR(E$24),MONTH(E$24)+D45+1,DAY(E$24)) -> 46451 | C45: =TEXT(B45,"mmm-yyyy") -> Mar-2027 | D45: 18 | E45: =C$1 -> 13536.716 | F45: =E45-G45 -> 10201.488 | G45: =H44*C$12 -> 3335.2284 | H45: =H44-F45 -> 353641.61 | X45: SINENSE | AD45: SEVERO | AN45: BATOBATO
B46: =DATE(YEAR(E$24),MONTH(E$24)+D46+1,DAY(E$24)) -> 46482 | C46: =TEXT(B46,"mmm-yyyy") -> Apr-2027 | D46: 19 | E46: =C$1 -> 13536.716 | F46: =E46-G46 -> 10295.001 | G46: =H45*C$12 -> 3241.7148 | H46: =H45-F46 -> 343346.61 | K46: PAYMENT | X46: (LAST NAME) | AD46: (FIRST NAME) | AN46: (MIDDLE NAME) | AZ46: (SUFFIX)
B47: =DATE(YEAR(E$24),MONTH(E$24)+D47+1,DAY(E$24)) -> 46512 | C47: =TEXT(B47,"mmm-yyyy") -> May-2027 | D47: 20 | E47: =C$1 -> 13536.716 | F47: =E47-G47 -> 10389.372 | G47: =H46*C$12 -> 3147.3439 | H47: =H46-F47 -> 332957.24 | X47: Rank/Position: | AD47: Serial No.: | AI47: Branch of Service: | AO47: Date of Appointment: | AW47: Date of Retirement:
B48: =DATE(YEAR(E$24),MONTH(E$24)+D48+1,DAY(E$24)) -> 46543 | C48: =TEXT(B48,"mmm-yyyy") -> Jun-2027 | D48: 21 | E48: =C$1 -> 13536.716 | F48: =E48-G48 -> 10484.608 | G48: =H47*C$12 -> 3052.108 | H48: =H47-F48 -> 322472.63 | L48: Term of loan in months: | R48: =E25 -> 48 | T48: month(s) | X48: COL | AD48: =D23 -> O-121408 | AI48: PA | AP48: , | AR48: , | AX48: , | AZ48: ,
B49: =DATE(YEAR(E$24),MONTH(E$24)+D49+1,DAY(E$24)) -> 46573 | C49: =TEXT(B49,"mmm-yyyy") -> Jul-2027 | D49: 22 | E49: =C$1 -> 13536.716 | F49: =E49-G49 -> 10580.717 | G49: =H48*C$12 -> 2955.9991 | H49: =H48-F49 -> 311891.91 | L49: Monthly Amortization | R49: =C1 -> 13536.716 | AO49: m | AP49: m | AQ49: d | AR49: d | AS49: y | AT49: y | AU49: y | AV49: y | AW49: m | AX49: m | AY49: d | AZ49: d | BA49: y | BB49: y | BC49: y | BD49: y
B50: =DATE(YEAR(E$24),MONTH(E$24)+D50+1,DAY(E$24)) -> 46604 | C50: =TEXT(B50,"mmm-yyyy") -> Aug-2027 | D50: 23 | E50: =C$1 -> 13536.716 | F50: =E50-G50 -> 10677.707 | G50: =H49*C$12 -> 2859.0092 | H50: =H49-F50 -> 301214.2 | L50: First Payment Due On: | R50: =E24 -> 45874
B51: =DATE(YEAR(E$24),MONTH(E$24)+D51+1,DAY(E$24)) -> 46635 | C51: =TEXT(B51,"mmm-yyyy") -> Sep-2027 | D51: 24 | E51: =C$1 -> 13536.716 | F51: =E51-G51 -> 10775.586 | G51: =H50*C$12 -> 2761.1302 | H51: =H50-F51 -> 290438.62 | L51: Maturity: | R51: =G24 -> 47366 | X51: Length of Service: | AE51: Date of Birth: | AJ51: Age: | AK51: 70 | AM51: Civil Status: | AR51: Single | AU51: Widower | AX51: Home Phone No.
B52: =DATE(YEAR(E$24),MONTH(E$24)+D52+1,DAY(E$24)) -> 46665 | C52: =TEXT(B52,"mmm-yyyy") -> Oct-2027 | D52: 25 | E52: =C$1 -> 13536.716 | F52: =E52-G52 -> 10874.362 | G52: =H51*C$12 -> 2662.354 | H52: =H51-F52 -> 279564.26 | L52: EIR (%): | R52: =C16 -> 0.12736174 | AE52: OCTOBER 10 1954 | AR52: Married | AU52: Separated
B53: =DATE(YEAR(E$24),MONTH(E$24)+D53+1,DAY(E$24)) -> 46696 | C53: =TEXT(B53,"mmm-yyyy") -> Nov-2027 | D53: 26 | E53: =C$1 -> 13536.716 | F53: =E53-G53 -> 10974.044 | G53: =H52*C$12 -> 2562.6723 | H53: =H52-F53 -> 268590.21 | L53: Interest Rate per Month (%): | R53: =C15 -> 0.01 | X53: Unit Assignment: | AE53: Unit/Office/Business Address: | AX53: Unit/Office Telephone No/s:
B54: =DATE(YEAR(E$24),MONTH(E$24)+D54+1,DAY(E$24)) -> 46726 | C54: =TEXT(B54,"mmm-yyyy") -> Dec-2027 | D54: 27 | E54: =C$1 -> 13536.716 | F54: =E54-G54 -> 11074.639 | G54: =H53*C$12 -> 2462.0769 | H54: =H53-F54 -> 257515.57 | AX54: 0956-936-5968
B55: =DATE(YEAR(E$24),MONTH(E$24)+D55+1,DAY(E$24)) -> 46757 | C55: =TEXT(B55,"mmm-yyyy") -> Jan-2028 | D55: 28 | E55: =C$1 -> 13536.716 | F55: =E55-G55 -> 11176.157 | G55: =H54*C$12 -> 2360.5594 | H55: =H54-F55 -> 246339.42 | X55: AFP/Company ID No: | AG55: Email Address: | AT55: Tax Identification No/s:
B56: =DATE(YEAR(E$24),MONTH(E$24)+D56+1,DAY(E$24)) -> 46788 | C56: =TEXT(B56,"mmm-yyyy") -> Feb-2028 | D56: 29 | E56: =C$1 -> 13536.716 | F56: =E56-G56 -> 11278.605 | G56: =H55*C$12 -> 2258.1113 | H56: =H55-F56 -> 235060.81 | K56: Certified & Corrected by: | R56: Verified by: | AG56: severo1954.55@gmail.com | AT56: 1 | AU56: 3 | AV56: 7 | AW56: - | AX56: 6 | AY56: 2 | AZ56: 4 | BA56: - | BB56: 8 | BC56: 2 | BD56: 9
B57: =DATE(YEAR(E$24),MONTH(E$24)+D57+1,DAY(E$24)) -> 46817 | C57: =TEXT(B57,"mmm-yyyy") -> Mar-2028 | D57: 30 | E57: =C$1 -> 13536.716 | F57: =E57-G57 -> 11381.992 | G57: =H56*C$12 -> 2154.7241 | H57: =H56-F57 -> 223678.82 | X57: Present Address: | AB57: =N34 -> P7 CABUGAO, ECHAGUE, ISABELA
B58: =DATE(YEAR(E$24),MONTH(E$24)+D58+1,DAY(E$24)) -> 46848 | C58: =TEXT(B58,"mmm-yyyy") -> Apr-2028 | D58: 31 | E58: =C$1 -> 13536.716 | F58: =E58-G58 -> 11486.327 | G58: =H57*C$12 -> 2050.3892 | H58: =H57-F58 -> 212192.49 | X58: NOTIFICATION CLAUSE
B59: =DATE(YEAR(E$24),MONTH(E$24)+D59+1,DAY(E$24)) -> 46878 | C59: =TEXT(B59,"mmm-yyyy") -> May-2028 | D59: 32 | E59: =C$1 -> 13536.716 | F59: =E59-G59 -> 11591.618 | G59: =H58*C$12 -> 1945.0978 | H59: =H58-F59 -> 200600.87
B60: =DATE(YEAR(E$24),MONTH(E$24)+D60+1,DAY(E$24)) -> 46909 | C60: =TEXT(B60,"mmm-yyyy") -> Jun-2028 | D60: 33 | E60: =C$1 -> 13536.716 | F60: =E60-G60 -> 11697.875 | G60: =H59*C$12 -> 1838.8413 | H60: =H59-F60 -> 188903 | K60: PAMELA CHERRY A. REYES | R60: ALEXANDER A. FERIA JR. | Y60: I hereby acknowledge and authorized the People's Multi-Purpose Cooperative (PMPC) for the following: 1) the regular submission and disclosure
B61: =DATE(YEAR(E$24),MONTH(E$24)+D61+1,DAY(E$24)) -> 46939 | C61: =TEXT(B61,"mmm-yyyy") -> Jul-2028 | D61: 34 | E61: =C$1 -> 13536.716 | F61: =E61-G61 -> 11805.105 | G61: =H60*C$12 -> 1731.6108 | H61: =H60-F61 -> 177097.89 | K61: Processor | R61: Verifier/PELVAMS Liason | X61: of my basic credit data (as defined under Republic Act Nr 9510 and its Implementing Rules and Regulations) to the Credit Information Corporation (CIC)
B62: =DATE(YEAR(E$24),MONTH(E$24)+D62+1,DAY(E$24)) -> 46970 | C62: =TEXT(B62,"mmm-yyyy") -> Aug-2028 | D62: 35 | E62: =C$1 -> 13536.716 | F62: =E62-G62 -> 11913.319 | G62: =H61*C$12 -> 1623.3974 | H62: =H61-F62 -> 165184.58 | X62: as well as any updates or corrections thereof; and 2) the sharing of my basic data and with other lenders authorized by the CIC, and credit reporting
B63: =DATE(YEAR(E$24),MONTH(E$24)+D63+1,DAY(E$24)) -> 47001 | C63: =TEXT(B63,"mmm-yyyy") -> Sep-2028 | D63: 36 | E63: =C$1 -> 13536.716 | F63: =E63-G63 -> 12022.524 | G63: =H62*C$12 -> 1514.1919 | H63: =H62-F63 -> 153162.05 | X63: agencies duly accredited by the CIC.
B64: =DATE(YEAR(E$24),MONTH(E$24)+D64+1,DAY(E$24)) -> 47031 | C64: =TEXT(B64,"mmm-yyyy") -> Oct-2028 | D64: 37 | E64: =C$1 -> 13536.716 | F64: =E64-G64 -> 12132.731 | G64: =H63*C$12 -> 1403.9855 | H64: =H63-F64 -> 141029.32 | AU64: =D22 -> SEVERO B. SINENSE
B65: =DATE(YEAR(E$24),MONTH(E$24)+D65+1,DAY(E$24)) -> 47062 | C65: =TEXT(B65,"mmm-yyyy") -> Nov-2028 | D65: 38 | E65: =C$1 -> 13536.716 | F65: =E65-G65 -> 12243.947 | G65: =H64*C$12 -> 1292.7688 | H65: =H64-F65 -> 128785.37 | AU65: Printed Name & Signature of Borrower
B66: =DATE(YEAR(E$24),MONTH(E$24)+D66+1,DAY(E$24)) -> 47092 | C66: =TEXT(B66,"mmm-yyyy") -> Dec-2028 | D66: 39 | E66: =C$1 -> 13536.716 | F66: =E66-G66 -> 12356.184 | G66: =H65*C$12 -> 1180.5326 | H66: =H65-F66 -> 116429.19 | K66: Received By: | R66: Approved By: | X66: CERTIFICATION
B67: =DATE(YEAR(E$24),MONTH(E$24)+D67+1,DAY(E$24)) -> 47123 | C67: =TEXT(B67,"mmm-yyyy") -> Jan-2029 | D67: 40 | E67: =C$1 -> 13536.716 | F67: =E67-G67 -> 12469.449 | G67: =H66*C$12 -> 1067.2676 | H67: =H66-F67 -> 103959.74
B68: =DATE(YEAR(E$24),MONTH(E$24)+D68+1,DAY(E$24)) -> 47154 | C68: =TEXT(B68,"mmm-yyyy") -> Feb-2029 | D68: 41 | E68: =C$1 -> 13536.716 | F68: =E68-G68 -> 12583.752 | G68: =H67*C$12 -> 952.9643 | H68: =H67-F68 -> 91375.989 | Y68: I hereby certify that the applicant is assigned to this Office; is not on leave without pay; has no pending case; and, that all information he/she
B69: =DATE(YEAR(E$24),MONTH(E$24)+D69+1,DAY(E$24)) -> 47182 | C69: =TEXT(B69,"mmm-yyyy") -> Mar-2029 | D69: 42 | E69: =C$1 -> 13536.716 | F69: =E69-G69 -> 12699.103 | G69: =H68*C$12 -> 837.61324 | H69: =H68-F69 -> 78676.887 | K69: =D22 -> SEVERO B. SINENSE | P69: COL.ALEXANDER L. FERIA (RET) CPA MNSA | X69: provided is true and correct.
B70: =DATE(YEAR(E$24),MONTH(E$24)+D70+1,DAY(E$24)) -> 47213 | C70: =TEXT(B70,"mmm-yyyy") -> Apr-2029 | D70: 43 | E70: =C$1 -> 13536.716 | F70: =E70-G70 -> 12815.511 | G70: =H69*C$12 -> 721.20479 | H70: =H69-F70 -> 65861.375 | K70: Signature Over Printed Name/Date | R70: President
B71: =DATE(YEAR(E$24),MONTH(E$24)+D71+1,DAY(E$24)) -> 47243 | C71: =TEXT(B71,"mmm-yyyy") -> May-2029 | D71: 44 | E71: =C$1 -> 13536.716 | F71: =E71-G71 -> 12932.987 | G71: =H70*C$12 -> 603.72927 | H71: =H70-F71 -> 52928.388
B72: =DATE(YEAR(E$24),MONTH(E$24)+D72+1,DAY(E$24)) -> 47274 | C72: =TEXT(B72,"mmm-yyyy") -> Jun-2029 | D72: 45 | E72: =C$1 -> 13536.716 | F72: =E72-G72 -> 13051.539 | G72: =H71*C$12 -> 485.17689 | H72: =H71-F72 -> 39876.849 | X72: CERTIFYING OFFICER | AG72: DESIGNATION | AP72: OFFICE | AX72: CONTACT NUMBER
B73: =DATE(YEAR(E$24),MONTH(E$24)+D73+1,DAY(E$24)) -> 47304 | C73: =TEXT(B73,"mmm-yyyy") -> Jul-2029 | D73: 46 | E73: =C$1 -> 13536.716 | F73: =E73-G73 -> 13171.178 | G73: =H72*C$12 -> 365.53778 | H73: =H72-F73 -> 26705.671 | X73: (Signature Over Printed Name)
B74: =DATE(YEAR(E$24),MONTH(E$24)+D74+1,DAY(E$24)) -> 47335 | C74: =TEXT(B74,"mmm-yyyy") -> Aug-2029 | D74: 47 | E74: =C$1 -> 13536.716 | F74: =E74-G74 -> 13291.914 | G74: =H73*C$12 -> 244.80198 | H74: =H73-F74 -> 13413.757 | X74: CREDIT HISTORY
B75: =DATE(YEAR(E$24),MONTH(E$24)+D75+1,DAY(E$24)) -> 47366 | C75: =TEXT(B75,"mmm-yyyy") -> Sep-2029 | D75: 48 | E75: =C$1 -> 13536.716 | F75: =E75-G75 -> 13413.757 | G75: =H74*C$12 -> 122.95944 | H75: =H74-F75 -> -1.0550139e-10 | X75: Loan ID | AA75: Date Granted | AE75: Loan Granted | AJ75: Term | AM75: Maturity Date | AR75: MA | AU75: Status/Remarks | AZ75: Principal Balance
E76: =SUM(E28:E75) -> 649762.37 | F76: =SUM(F28:F75) -> 523754.78 | G76: =SUM(G28:G75) -> 126007.59
X81: LOAN APPROVAL
X82: Loan Amount: | AC82: MA: | AG82: Term: | AK82: Required NTHP: | AR82: NTHP after MA | AW82: Total Loan Exposure:
X83: =C4 -> 523754.78 | AC83: =C1 -> 13536.716 | AG83: =R48 -> 48 | AK83: 650 | AW83: =C3 -> 649762.37
X84: PROCESSED & VERIFIED BY:
AJ86: ZYRENE MAE T. DAMASO
W87: SIGNATURE OVER PRINTED NAME
X90: RECOMMEND APPROVAL/DISAPPROVAL: | AO90: APPROVED/DISAPPROVED:
AB92: ALEXANDER A FERIA JR | AS92: ALEXANDER L FERIA
X93: SIGNATURE OVER PRINTED NAME | AO93: SIGNATURE OVER PRINTED NAME
X99: PROMISORY NOTE NO:
Y100: FOR VALUE RECEIVED, the undersigned promise to pay the People's Multi-Purpose Cooperative (PMPC) the sum of Php | AY100: =AW83 -> 649762.37
AA101: in | AB101: =AG83 -> 48 | AC101: equal monthly installments amounting to Php | AN101: =AC83 -> 13536.716 | AR101: each, to be paid on the 28th day of every month starting on
X102: =B28 -> 45935 | AB102: / Single Payment of due on unpaid installments from maturity will bear charges on unpaid principal
X103: at the rate of 2% per month as penatly thereof.
X104: I hereby waive presentment for payment and notice of dishonor. PMPC may accept partial payment reserving its right of recourse against me. PMPC is hereby authorized and empowered to set off or apply without notice what is due under this Note from whatever funds I have in the Cooperative.
X107: It is further agreed that in case of separation from the service of whatever cause, the unpaid balance with its accumulated surcharges and interest as stipulated above be deducted from my last paymnet, commutation of leave/furlough and/or from my pension.
X110: It is further agreed that when installments are not paid when due and payable, the whole of the principal sum remaining unpaid shall forthwith become due and payable at the election of the Cooperative. I promise and agree to pay for a reasonable attorney's fee if this note is not paid according to its legal tenor and effect when palced in a lawyer's hand for collection. In case litigation, venue shall be vested in the competent court as may be allowed by the Rules of Court at the sole option of PMPC.
X115: Further, I hereby agree and authorized PMPC to encumber, assign or sell to any person or entity any right which it may have under thi Note, and/or any assignment, mortgage lien, pledge or other encumbrances constituted in favor of PMPC pursuant to the provisions of this Note if any. The consent herein granted is recognized and acknowledged by me/us as a waiver, to all intent and purposes of whatever right I may have to notice of actual encumbrance/ assignment.
AM119: Military/Pensioners ID
AM120: Employee's ID/Office ID
AM121: Driver's License
Z122: =N32 -> SEVERO B. SINENSE | AM122: Others:
X123: Signature over Printed Name
X125: ID No:
X126: Expiration Date: | AT126: LEFT THUMBMARK | AZ126: RIGHT THUMBMARK
X129: ACKNOWLEDGEMENT
X131: REPUBLIC OF THE PHILIPPINES
X132: (20-E, 2nd Camarilla St., Cor. 15th Ave.,BRGY San Roque, Murphy Cubao, Quezon City) S.S
X134: BEFORE ME, a Notary Public for and in Cubao, Quezon City this _______ day of _______________, 20_____, personally appeared __________________
X135: __________, who presented to me the Identification Cards mentioned above, known to me to be the same person who executed the forgoing application for loan and promissory note and acknowledged that the same as his/her true act and deed and took oath that the statement herein are true and correct and that the application is made for the purpose under consideration.
...

Sheet 5 years
A1: \ | B1: Amortization | C1: ='DATA ENTRY'!G16 -> 10499.998
B2: Timeline | C2: 0 | D2: 1 | E2: 2 | F2: 3 | G2: 4 | H2: 5 | I2: 6 | J2: 7 | K2: 8 | L2: 9 | M2: 10 | N2: 11 | O2: 12 | P2: 13 | Q2: 14 | R2: 15 | S2: 16 | T2: 17 | U2: 18 | V2: 19 | W2: 20 | X2: 21 | Y2: 22 | Z2: 23 | AA2: 24 | AB2: 25 | AC2: 26 | AD2: 27 | AE2: 28 | AF2: 29 | AG2: 30 | AH2: 31 | AI2: 32 | AJ2: 33 | AK2: 34 | AL2: 35 | AM2: 36 | AN2: 37 | AO2: 38 | AP2: 39 | AQ2: 40 | AR2: 41 | AS2: 42 | AT2: 43 | AU2: 44 | AV2: 45 | AW2: 46 | AX2: 47 | AY2: 48 | AZ2: 49 | BA2: 50 | BB2: 51 | BC2: 52 | BD2: 53 | BE2: 54 | BF2: 55 | BG2: 56 | BH2: 57 | BI2: 58 | BJ2: 59 | BK2: 60
B3: GROSS AMOUNT | C3: ='DATA ENTRY'!G4 -> 629999.88
B4: LOAN AMOUNT | C4: ='DATA ENTRY'!G13 -> 472027.82 | D4: =-$C1 -> -10499.998 | E4: =-$C1 -> -10499.998 | F4: =-$C1 -> -10499.998 | G4: =-$C1 -> -10499.998 | H4: =-$C1 -> -10499.998 | I4: =-$C1 -> -10499.998 | J4: =-$C1 -> -10499.998 | K4: =-$C1 -> -10499.998 | ... BK4: =-$C1 -> -10499.998
B5: Service Fee | C5: ='DATA ENTRY'!G8 -> 47022.536
B6: Insurance | C6: ='DATA ENTRY'!G9 -> 23316.96
B7: CapCon | C7: ='DATA ENTRY'!G10 -> 5000
B8: membership fee | C8: ='DATA ENTRY'!G11 -> 300
B9: Advance Interest | C9: ='DATA ENTRY'!G12 -> 7772.32
B10: NET PROCEEDS/CASH FLOW | C10: =C4-C5-C6-C7-C8-C9 -> 388616
B12: Interest Rate of Return | C12: =IRR(C4:BK4) -> 0.01
B14: Loan Balance | C14: 261703.78
B15: Monthly Interest Rate | C15: ='DATA ENTRY'!G14/12 -> 0.01
B16: Effective Interest Rate | C16: ='DATA ENTRY'!G15 -> 0.12736174 | K16: APPROVED
C20: LOAN LEDGER CARD
C22: Name: | D22: ALBERTO B MAGISTRADO | G22: Loan Voucher No. | H22: LV- 005-BO
C23: Serial Nr: | D23: 665147 | E23: Address: | F23: BLK 7 LOT 11 PHASE 2 REGINA VILLE 2000 BRGY INCENCIO TRECE MARTIRES CITY CAVITE | G23: Amount: | H23: =C10-C14 -> 126912.22
C24: Posting date | D24: Date of Loan: | E24: 45903 | F24: Maturity Date | G24: =B63 -> 47029 | K24: PEOPLE'S MULTI-PURPOSE COOPERATIVE
D25: Term: | E25: 60 | F25: MOS | K25: 20-E 2nd Camarilla St. corner 15th Ave., Brgy. San Roque, Murphy Cubao, Quezon City | X25: 20-E 2nd Camarilla St corner 15th Avenue,
D26: Loan | E26: Installment | F26: Principal | G26: EIR | H26: Balance | X26: Brgy San Roque, Murphy Cubao, Quezon City
D27: Month 0 | H27: =C4 -> 472027.82 | K27: LOAN RELEASE VOUCHER | X27: Mobile No. (+63)953-033-1580 (GLOBE)
B28: =DATE(YEAR(E$24),MONTH(E$24)+D28+1,DAY(E$24)) -> 45964 | C28: =TEXT(B28,"mmm-yyyy") -> Nov-2025 | D28: 1 | E28: =C$1 -> 10499.998 | F28: =E28-G28 -> 5779.7199 | G28: =H27*C$12 -> 4720.2782 | H28: =H27-F28 -> 466248.1
B29: =DATE(YEAR(E$24),MONTH(E$24)+D29+1,DAY(E$24)) -> 45994 | C29: =TEXT(B29,"mmm-yyyy") -> Dec-2025 | D29: 2 | E29: =C$1 -> 10499.998 | F29: =E29-G29 -> 5837.5171 | G29: =H28*C$12 -> 4662.481 | H29: =H28-F29 -> 460410.58 | R29: Date: | S29: =E24 -> 45903 | X29: LOAN APPLICATION FORM
B30: =DATE(YEAR(E$24),MONTH(E$24)+D30+1,DAY(E$24)) -> 46025 | C30: =TEXT(B30,"mmm-yyyy") -> Jan-2026 | D30: 3 | E30: =C$1 -> 10499.998 | F30: =E30-G30 -> 5895.8923 | G30: =H29*C$12 -> 4604.1058 | H30: =H29-F30 -> 454514.69 | R30: LV No: | S30: =H22 -> LV- 005-BO | AU30: Date: | AW30: 0 | AX30: 9 | AY30: 0 | AZ30: 3 | BA30: 2 | BB30: 0 | BC30: 2 | BD30: 5
B31: =DATE(YEAR(E$24),MONTH(E$24)+D31+1,DAY(E$24)) -> 46056 | C31: =TEXT(B31,"mmm-yyyy") -> Feb-2026 | D31: 4 | E31: =C$1 -> 10499.998 | F31: =E31-G31 -> 5954.8512 | G31: =H30*C$12 -> 4545.1469 | H31: =H30-F31 -> 448559.84 | AW31: m | AX31: m | AY31: d | AZ31: d | BA31: y | BB31: y | BC31: y | BD31: y
B32: =DATE(YEAR(E$24),MONTH(E$24)+D32+1,DAY(E$24)) -> 46084 | C32: =TEXT(B32,"mmm-yyyy") -> Mar-2026 | D32: 5 | E32: =C$1 -> 10499.998 | F32: =E32-G32 -> 6014.3997 | G32: =H31*C$12 -> 4485.5984 | H32: =H31-F32 -> 442545.44 | K32: Name of Borrower: | N32: =D22 -> ALBERTO B MAGISTRADO | X32: APPLICATION TYPE | AE32: LOAN CLASSIFICATION | AM32: TERM | AT32: RELEASE OF LOAN PROCEEDS
B33: =DATE(YEAR(E$24),MONTH(E$24)+D33+1,DAY(E$24)) -> 46115 | C33: =TEXT(B33,"mmm-yyyy") -> Apr-2026 | D33: 6 | E33: =C$1 -> 10499.998 | F33: =E33-G33 -> 6074.5437 | G33: =H32*C$12 -> 4425.4544 | H33: =H32-F33 -> 436470.89 | K33: Serial No.: | N33: =D23 -> 665147 | Y33: New | AF33: Salary Loan | AN33: 12 Months | AU33: Check
B34: =DATE(YEAR(E$24),MONTH(E$24)+D34+1,DAY(E$24)) -> 46145 | C34: =TEXT(B34,"mmm-yyyy") -> May-2026 | D34: 7 | E34: =C$1 -> 10499.998 | F34: =E34-G34 -> 6135.2891 | G34: =H33*C$12 -> 4364.7089 | H34: =H33-F34 -> 430335.6 | K34: Address: | N34: =F23 -> BLK 7 LOT 11 PHASE 2 REGINA VILLE 2000 BRGY INCENCIO TRECE MARTIRES CITY CAVITE | Y34: Renewal | AF34: Pension Loan | AN34: 24 Months | AU34: Bank Electronic Transfer to Borrowers Account
B35: =DATE(YEAR(E$24),MONTH(E$24)+D35+1,DAY(E$24)) -> 46176 | C35: =TEXT(B35,"mmm-yyyy") -> Jun-2026 | D35: 8 | E35: =C$1 -> 10499.998 | F35: =E35-G35 -> 6196.642 | G35: =H34*C$12 -> 4303.356 | H35: =H34-F35 -> 424138.96 | Y35: Additional | AF35: Emergency | AN35: 36 Months | AU35: Others:
B36: =DATE(YEAR(E$24),MONTH(E$24)+D36+1,DAY(E$24)) -> 46206 | C36: =TEXT(B36,"mmm-yyyy") -> Jul-2026 | D36: 9 | E36: =C$1 -> 10499.998 | F36: =E36-G36 -> 6258.6084 | G36: =H35*C$12 -> 4241.3896 | H36: =H35-F36 -> 417880.35 | L36: Principal Amount | R36: =C4 -> 472027.82 | Y36: Reloan | AF36: Health Assistance Loan | AN36: 48 Months
B37: =DATE(YEAR(E$24),MONTH(E$24)+D37+1,DAY(E$24)) -> 46237 | C37: =TEXT(B37,"mmm-yyyy") -> Aug-2026 | D37: 10 | E37: =C$1 -> 10499.998 | F37: =E37-G37 -> 6321.1945 | G37: =H36*C$12 -> 4178.8035 | H37: =H36-F37 -> 411559.16 | Y37: Restructure | AF37: Educational Loan | AN37: 60 Months
B38: =DATE(YEAR(E$24),MONTH(E$24)+D38+1,DAY(E$24)) -> 46268 | C38: =TEXT(B38,"mmm-yyyy") -> Sep-2026 | D38: 11 | E38: =C$1 -> 10499.998 | F38: =E38-G38 -> 6384.4065 | G38: =H37*C$12 -> 4115.5916 | H38: =H37-F38 -> 405174.75 | L38: (-) | M38: Balance Old Loan(s) | R38: =-C14 -> -261703.78 | AF38: Others: | AN38: Others:
B39: =DATE(YEAR(E$24),MONTH(E$24)+D39+1,DAY(E$24)) -> 46298 | C39: =TEXT(B39,"mmm-yyyy") -> Oct-2026 | D39: 12 | E39: =C$1 -> 10499.998 | F39: =E39-G39 -> 6448.2505 | G39: =H38*C$12 -> 4051.7475 | H39: =H38-F39 -> 398726.5 | L39: (-) | M39: Membership Fee: | R39: =-C8 -> -300 | X39: AMOUNT APPLIED: | AB39: =R44 -> 126912.22 | AN39: MONTHLY AMORTIZATION: | AT39: =R49 -> 10499.998
B40: =DATE(YEAR(E$24),MONTH(E$24)+D40+1,DAY(E$24)) -> 46329 | C40: =TEXT(B40,"mmm-yyyy") -> Nov-2026 | D40: 13 | E40: =C$1 -> 10499.998 | F40: =E40-G40 -> 6512.733 | G40: =H39*C$12 -> 3987.265 | H40: =H39-F40 -> 392213.77 | L40: (-) | M40: Paid up Capital: | R40: =-C7 -> -5000
B41: =DATE(YEAR(E$24),MONTH(E$24)+D41+1,DAY(E$24)) -> 46359 | C41: =TEXT(B41,"mmm-yyyy") -> Dec-2026 | D41: 14 | E41: =C$1 -> 10499.998 | F41: =E41-G41 -> 6577.8604 | G41: =H40*C$12 -> 3922.1377 | H41: =H40-F41 -> 385635.91 | L41: (-) | M41: Service Fee | R41: =-C5 -> -47022.536 | X41: LOAN ID: | AF41: DEDUCTION CODE: | AR41: LOAN PURPOSE:
B42: =DATE(YEAR(E$24),MONTH(E$24)+D42+1,DAY(E$24)) -> 46390 | C42: =TEXT(B42,"mmm-yyyy") -> Jan-2027 | D42: 15 | E42: =C$1 -> 10499.998 | F42: =E42-G42 -> 6643.639 | G42: =H41*C$12 -> 3856.3591 | H42: =H41-F42 -> 378992.27 | L42: (-) | M42: Insurance Premium - Paramount | R42: =-C6 -> -23316.96 | X42: MEM ID: | AG42: Regular Member | AS42: Old Member
B43: =DATE(YEAR(E$24),MONTH(E$24)+D43+1,DAY(E$24)) -> 46421 | C43: =TEXT(B43,"mmm-yyyy") -> Feb-2027 | D43: 16 | E43: =C$1 -> 10499.998 | F43: =E43-G43 -> 6710.0754 | G43: =H42*C$12 -> 3789.9227 | H43: =H42-F43 -> 372282.19 | L43: (-) | M43: Advance Interest | R43: =-C9 -> -7772.32 | AG43: Associate Member | AS43: New Member
B44: =DATE(YEAR(E$24),MONTH(E$24)+D44+1,DAY(E$24)) -> 46449 | C44: =TEXT(B44,"mmm-yyyy") -> Mar-2027 | D44: 17 | E44: =C$1 -> 10499.998 | F44: =E44-G44 -> 6777.1761 | G44: =H43*C$12 -> 3722.8219 | H44: =H43-F44 -> 365505.02 | L44: NET PROCEEDS (Php): | R44: =SUM(R36:T43) -> 126912.22 | X44: BORROWER'S INFORMATION
B45: =DATE(YEAR(E$24),MONTH(E$24)+D45+1,DAY(E$24)) -> 46480 | C45: =TEXT(B45,"mmm-yyyy") -> Apr-2027 | D45: 18 | E45: =C$1 -> 10499.998 | F45: =E45-G45 -> 6844.9479 | G45: =H44*C$12 -> 3655.0502 | H45: =H44-F45 -> 358660.07 | X45: MAGISTRADO | AD45: ALBERTO | AN45: BENJAMIN
B46: =DATE(YEAR(E$24),MONTH(E$24)+D46+1,DAY(E$24)) -> 46510 | C46: =TEXT(B46,"mmm-yyyy") -> May-2027 | D46: 19 | E46: =C$1 -> 10499.998 | F46: =E46-G46 -> 6913.3974 | G46: =H45*C$12 -> 3586.6007 | H46: =H45-F46 -> 351746.67 | K46: PAYMENT | X46: (LAST NAME) | AD46: (FIRST NAME) | AN46: (MIDDLE NAME) | AZ46: (SUFFIX)
B47: =DATE(YEAR(E$24),MONTH(E$24)+D47+1,DAY(E$24)) -> 46541 | C47: =TEXT(B47,"mmm-yyyy") -> Jun-2027 | D47: 20 | E47: =C$1 -> 10499.998 | F47: =E47-G47 -> 6982.5313 | G47: =H46*C$12 -> 3517.4667 | H47: =H46-F47 -> 344764.14 | X47: Rank/Position: | AD47: Serial No.: | AI47: Branch of Service: | AO47: Date of Appointment: | AW47: Date of Retirement:
B48: =DATE(YEAR(E$24),MONTH(E$24)+D48+1,DAY(E$24)) -> 46571 | C48: =TEXT(B48,"mmm-yyyy") -> Jul-2027 | D48: 21 | E48: =C$1 -> 10499.998 | F48: =E48-G48 -> 7052.3567 | G48: =H47*C$12 -> 3447.6414 | H48: =H47-F48 -> 337711.78 | L48: Term of loan in months: | R48: =E25 -> 60 | T48: month(s) | X48: MSGT | AD48: =N33 -> 665147 | AI48: PN | AP48: , | AR48: , | AX48: , | AZ48: ,
B49: =DATE(YEAR(E$24),MONTH(E$24)+D49+1,DAY(E$24)) -> 46602 | C49: =TEXT(B49,"mmm-yyyy") -> Aug-2027 | D49: 22 | E49: =C$1 -> 10499.998 | F49: =E49-G49 -> 7122.8802 | G49: =H48*C$12 -> 3377.1178 | H49: =H48-F49 -> 330588.9 | L49: Monthly Amortization | R49: =C1 -> 10499.998 | AO49: m | AP49: m | AQ49: d | AR49: d | AS49: y | AT49: y | AU49: y | AV49: y | AW49: m | AX49: m | AY49: d | AZ49: d | BA49: y | BB49: y | BC49: y | BD49: y
B50: =DATE(YEAR(E$24),MONTH(E$24)+D50+1,DAY(E$24)) -> 46633 | C50: =TEXT(B50,"mmm-yyyy") -> Sep-2027 | D50: 23 | E50: =C$1 -> 10499.998 | F50: =E50-G50 -> 7194.109 | G50: =H49*C$12 -> 3305.889 | H50: =H49-F50 -> 323394.79 | L50: First Payment Due On:
B51: =DATE(YEAR(E$24),MONTH(E$24)+D51+1,DAY(E$24)) -> 46663 | C51: =TEXT(B51,"mmm-yyyy") -> Oct-2027 | D51: 24 | E51: =C$1 -> 10499.998 | F51: =E51-G51 -> 7266.0501 | G51: =H50*C$12 -> 3233.9479 | H51: =H50-F51 -> 316128.74 | L51: Maturity: | R51: =B87 -> 47759 | X51: Length of Service: | AE51: Date of Birth: | AJ51: Age: | AK51: 68 | AM51: Civil Status: | AR51: Single | AU51: Widower | AX51: Home Phone No.
B52: =DATE(YEAR(E$24),MONTH(E$24)+D52+1,DAY(E$24)) -> 46694 | C52: =TEXT(B52,"mmm-yyyy") -> Nov-2027 | D52: 25 | E52: =C$1 -> 10499.998 | F52: =E52-G52 -> 7338.7106 | G52: =H51*C$12 -> 3161.2874 | H52: =H51-F52 -> 308790.03 | L52: EIR (%): | R52: =C16 -> 0.12736174 | AE52: DECEMBER 25 1956 | AR52: Married | AU52: Separated
B53: =DATE(YEAR(E$24),MONTH(E$24)+D53+1,DAY(E$24)) -> 46724 | C53: =TEXT(B53,"mmm-yyyy") -> Dec-2027 | D53: 26 | E53: =C$1 -> 10499.998 | F53: =E53-G53 -> 7412.0977 | G53: =H52*C$12 -> 3087.9003 | H53: =H52-F53 -> 301377.94 | L53: Interest Rate per Month (%): | R53: =C15 -> 0.01 | X53: Unit Assignment: | AE53: Unit/Office/Business Address: | AX53: Unit/Office Telephone No/s:
B54: =DATE(YEAR(E$24),MONTH(E$24)+D54+1,DAY(E$24)) -> 46755 | C54: =TEXT(B54,"mmm-yyyy") -> Jan-2028 | D54: 27 | E54: =C$1 -> 10499.998 | F54: =E54-G54 -> 7486.2187 | G54: =H53*C$12 -> 3013.7794 | H54: =H53-F54 -> 293891.72
B55: =DATE(YEAR(E$24),MONTH(E$24)+D55+1,DAY(E$24)) -> 46786 | C55: =TEXT(B55,"mmm-yyyy") -> Feb-2028 | D55: 28 | E55: =C$1 -> 10499.998 | F55: =E55-G55 -> 7561.0809 | G55: =H54*C$12 -> 2938.9172 | H55: =H54-F55 -> 286330.64 | X55: AFP/Company ID No: | AG55: Email Address: | AT55: Tax Identification No/s:
B56: =DATE(YEAR(E$24),MONTH(E$24)+D56+1,DAY(E$24)) -> 46815 | C56: =TEXT(B56,"mmm-yyyy") -> Mar-2028 | D56: 29 | E56: =C$1 -> 10499.998 | F56: =E56-G56 -> 7636.6917 | G56: =H55*C$12 -> 2863.3064 | H56: =H55-F56 -> 278693.94 | K56: Certified & Corrected by: | R56: Verified by: | AT56: 1 | AU56: 2 | AV56: 4 | AW56: - | AX56: 2 | AY56: 4 | AZ56: 0 | BA56: - | BB56: 6 | BC56: 7 | BD56: 4
B57: =DATE(YEAR(E$24),MONTH(E$24)+D57+1,DAY(E$24)) -> 46846 | C57: =TEXT(B57,"mmm-yyyy") -> Apr-2028 | D57: 30 | E57: =C$1 -> 10499.998 | F57: =E57-G57 -> 7713.0586 | G57: =H56*C$12 -> 2786.9394 | H57: =H56-F57 -> 270980.89 | X57: Present Address: | AB57: =N34 -> BLK 7 LOT 11 PHASE 2 REGINA VILLE 2000 BRGY INCENCIO TRECE MARTIRES CITY CAVITE
B58: =DATE(YEAR(E$24),MONTH(E$24)+D58+1,DAY(E$24)) -> 46876 | C58: =TEXT(B58,"mmm-yyyy") -> May-2028 | D58: 31 | E58: =C$1 -> 10499.998 | F58: =E58-G58 -> 7790.1892 | G58: =H57*C$12 -> 2709.8089 | H58: =H57-F58 -> 263190.7 | X58: NOTIFICATION CLAUSE
B59: =DATE(YEAR(E$24),MONTH(E$24)+D59+1,DAY(E$24)) -> 46907 | C59: =TEXT(B59,"mmm-yyyy") -> Jun-2028 | D59: 32 | E59: =C$1 -> 10499.998 | F59: =E59-G59 -> 7868.0911 | G59: =H58*C$12 -> 2631.907 | H59: =H58-F59 -> 255322.61
B60: =DATE(YEAR(E$24),MONTH(E$24)+D60+1,DAY(E$24)) -> 46937 | C60: =TEXT(B60,"mmm-yyyy") -> Jul-2028 | D60: 33 | E60: =C$1 -> 10499.998 | F60: =E60-G60 -> 7946.772 | G60: =H59*C$12 -> 2553.2261 | H60: =H59-F60 -> 247375.83 | K60: ALEXANDER A. FERIA JR. | R60: ALEXANDER A. FERIA JR. | Y60: I hereby acknowledge and authorized the People's Multi-Purpose Cooperative (PMPC) for the following: 1) the regular submission and disclosure
B61: =DATE(YEAR(E$24),MONTH(E$24)+D61+1,DAY(E$24)) -> 46968 | C61: =TEXT(B61,"mmm-yyyy") -> Aug-2028 | D61: 34 | E61: =C$1 -> 10499.998 | F61: =E61-G61 -> 8026.2397 | G61: =H60*C$12 -> 2473.7583 | H61: =H60-F61 -> 239349.59 | K61: Processor | R61: Verifier/PELVAMS Liason | X61: of my basic credit data (as defined under Republic Act Nr 9510 and its Implementing Rules and Regulations) to the Credit Information Corporation (CIC)
B62: =DATE(YEAR(E$24),MONTH(E$24)+D62+1,DAY(E$24)) -> 46999 | C62: =TEXT(B62,"mmm-yyyy") -> Sep-2028 | D62: 35 | E62: =C$1 -> 10499.998 | F62: =E62-G62 -> 8106.5021 | G62: =H61*C$12 -> 2393.4959 | H62: =H61-F62 -> 231243.09 | X62: as well as any updates or corrections thereof; and 2) the sharing of my basic data and with other lenders authorized by the CIC, and credit reporting
B63: =DATE(YEAR(E$24),MONTH(E$24)+D63+1,DAY(E$24)) -> 47029 | C63: =TEXT(B63,"mmm-yyyy") -> Oct-2028 | D63: 36 | E63: =C$1 -> 10499.998 | F63: =E63-G63 -> 8187.5671 | G63: =H62*C$12 -> 2312.4309 | H63: =H62-F63 -> 223055.52 | X63: agencies duly accredited by the CIC.
B64: =DATE(YEAR(E$24),MONTH(E$24)+D64+1,DAY(E$24)) -> 47060 | C64: =TEXT(B64,"mmm-yyyy") -> Nov-2028 | D64: 37 | E64: =C$1 -> 10499.998 | F64: =E64-G64 -> 8269.4428 | G64: =H63*C$12 -> 2230.5552 | H64: =H63-F64 -> 214786.08 | AU64: =D22 -> ALBERTO B MAGISTRADO
B65: =DATE(YEAR(E$24),MONTH(E$24)+D65+1,DAY(E$24)) -> 47090 | C65: =TEXT(B65,"mmm-yyyy") -> Dec-2028 | D65: 38 | E65: =C$1 -> 10499.998 | F65: =E65-G65 -> 8352.1372 | G65: =H64*C$12 -> 2147.8608 | H65: =H64-F65 -> 206433.94 | AU65: Printed Name & Signature of Borrower
B66: =DATE(YEAR(E$24),MONTH(E$24)+D66+1,DAY(E$24)) -> 47121 | C66: =TEXT(B66,"mmm-yyyy") -> Jan-2029 | D66: 39 | E66: =C$1 -> 10499.998 | F66: =E66-G66 -> 8435.6586 | G66: =H65*C$12 -> 2064.3394 | H66: =H65-F66 -> 197998.29 | K66: Received By: | R66: Approved By: | X66: CERTIFICATION
B67: =DATE(YEAR(E$24),MONTH(E$24)+D67+1,DAY(E$24)) -> 47152 | C67: =TEXT(B67,"mmm-yyyy") -> Feb-2029 | D67: 40 | E67: =C$1 -> 10499.998 | F67: =E67-G67 -> 8520.0152 | G67: =H66*C$12 -> 1979.9829 | H67: =H66-F67 -> 189478.27
B68: =DATE(YEAR(E$24),MONTH(E$24)+D68+1,DAY(E$24)) -> 47180 | C68: =TEXT(B68,"mmm-yyyy") -> Mar-2029 | D68: 41 | E68: =C$1 -> 10499.998 | F68: =E68-G68 -> 8605.2153 | G68: =H67*C$12 -> 1894.7827 | H68: =H67-F68 -> 180873.06 | Y68: I hereby certify that the applicant is assigned to this Office; is not on leave without pay; has no pending case; and, that all information he/she
B69: =DATE(YEAR(E$24),MONTH(E$24)+D69+1,DAY(E$24)) -> 47211 | C69: =TEXT(B69,"mmm-yyyy") -> Apr-2029 | D69: 42 | E69: =C$1 -> 10499.998 | F69: =E69-G69 -> 8691.2675 | G69: =H68*C$12 -> 1808.7306 | H69: =H68-F69 -> 172181.79 | K69: =D22 -> ALBERTO B MAGISTRADO | P69: COL.ALEXANDER L. FERIA (RET) CPA MNSA | X69: provided is true and correct.
B70: =DATE(YEAR(E$24),MONTH(E$24)+D70+1,DAY(E$24)) -> 47241 | C70: =TEXT(B70,"mmm-yyyy") -> May-2029 | D70: 43 | E70: =C$1 -> 10499.998 | F70: =E70-G70 -> 8778.1802 | G70: =H69*C$12 -> 1721.8179 | H70: =H69-F70 -> 163403.61 | K70: Signature Over Printed Name/Date | R70: President
B71: =DATE(YEAR(E$24),MONTH(E$24)+D71+1,DAY(E$24)) -> 47272 | C71: =TEXT(B71,"mmm-yyyy") -> Jun-2029 | D71: 44 | E71: =C$1 -> 10499.998 | F71: =E71-G71 -> 8865.962 | G71: =H70*C$12 -> 1634.0361 | H71: =H70-F71 -> 154537.65
B72: =DATE(YEAR(E$24),MONTH(E$24)+D72+1,DAY(E$24)) -> 47302 | C72: =TEXT(B72,"mmm-yyyy") -> Jul-2029 | D72: 45 | E72: =C$1 -> 10499.998 | F72: =E72-G72 -> 8954.6216 | G72: =H71*C$12 -> 1545.3765 | H72: =H71-F72 -> 145583.02 | X72: CERTIFYING OFFICER | AG72: DESIGNATION | AP72: OFFICE | AX72: CONTACT NUMBER
B73: =DATE(YEAR(E$24),MONTH(E$24)+D73+1,DAY(E$24)) -> 47333 | C73: =TEXT(B73,"mmm-yyyy") -> Aug-2029 | D73: 46 | E73: =C$1 -> 10499.998 | F73: =E73-G73 -> 9044.1678 | G73: =H72*C$12 -> 1455.8302 | H73: =H72-F73 -> 136538.86 | X73: (Signature Over Printed Name)
B74: =DATE(YEAR(E$24),MONTH(E$24)+D74+1,DAY(E$24)) -> 47364 | C74: =TEXT(B74,"mmm-yyyy") -> Sep-2029 | D74: 47 | E74: =C$1 -> 10499.998 | F74: =E74-G74 -> 9134.6095 | G74: =H73*C$12 -> 1365.3886 | H74: =H73-F74 -> 127404.25 | X74: CREDIT HISTORY
B75: =DATE(YEAR(E$24),MONTH(E$24)+D75+1,DAY(E$24)) -> 47394 | C75: =TEXT(B75,"mmm-yyyy") -> Oct-2029 | D75: 48 | E75: =C$1 -> 10499.998 | F75: =E75-G75 -> 9225.9556 | G75: =H74*C$12 -> 1274.0425 | H75: =H74-F75 -> 118178.29 | X75: Loan ID | AA75: Date Granted | AE75: Loan Granted | AJ75: Term | AM75: Maturity Date | AR75: MA | AU75: Status/Remarks | AZ75: Principal Balance
B76: =DATE(YEAR(E$24),MONTH(E$24)+D76+1,DAY(E$24)) -> 47425 | C76: =TEXT(B76,"mmm-yyyy") -> Nov-2029 | D76: 49 | E76: =C$1 -> 10499.998 | F76: =E76-G76 -> 9318.2151 | G76: =H75*C$12 -> 1181.7829 | H76: =H75-F76 -> 108860.08
B77: =DATE(YEAR(E$24),MONTH(E$24)+D77+1,DAY(E$24)) -> 47455 | C77: =TEXT(B77,"mmm-yyyy") -> Dec-2029 | D77: 50 | E77: =C$1 -> 10499.998 | F77: =E77-G77 -> 9411.3973 | G77: =H76*C$12 -> 1088.6008 | H77: =H76-F77 -> 99448.679
B78: =DATE(YEAR(E$24),MONTH(E$24)+D78+1,DAY(E$24)) -> 47486 | C78: =TEXT(B78,"mmm-yyyy") -> Jan-2030 | D78: 51 | E78: =C$1 -> 10499.998 | F78: =E78-G78 -> 9505.5113 | G78: =H77*C$12 -> 994.48679 | H78: =H77-F78 -> 89943.168
B79: =DATE(YEAR(E$24),MONTH(E$24)+D79+1,DAY(E$24)) -> 47517 | C79: =TEXT(B79,"mmm-yyyy") -> Feb-2030 | D79: 52 | E79: =C$1 -> 10499.998 | F79: =E79-G79 -> 9600.5664 | G79: =H78*C$12 -> 899.43168 | H79: =H78-F79 -> 80342.602
B80: =DATE(YEAR(E$24),MONTH(E$24)+D80+1,DAY(E$24)) -> 47545 | C80: =TEXT(B80,"mmm-yyyy") -> Mar-2030 | D80: 53 | E80: =C$1 -> 10499.998 | F80: =E80-G80 -> 9696.572 | G80: =H79*C$12 -> 803.42602 | H80: =H79-F80 -> 70646.029
B81: =DATE(YEAR(E$24),MONTH(E$24)+D81+1,DAY(E$24)) -> 47576 | C81: =TEXT(B81,"mmm-yyyy") -> Apr-2030 | D81: 54 | E81: =C$1 -> 10499.998 | F81: =E81-G81 -> 9793.5378 | G81: =H80*C$12 -> 706.46029 | H81: =H80-F81 -> 60852.492 | X81: LOAN APPROVAL
B82: =DATE(YEAR(E$24),MONTH(E$24)+D82+1,DAY(E$24)) -> 47606 | C82: =TEXT(B82,"mmm-yyyy") -> May-2030 | D82: 55 | E82: =C$1 -> 10499.998 | F82: =E82-G82 -> 9891.4731 | G82: =H81*C$12 -> 608.52492 | H82: =H81-F82 -> 50961.019 | X82: Loan Amount: | AC82: MA: | AG82: Term: | AK82: Required NTHP: | AR82: NTHP after MA | AW82: Total Loan Exposure:
B83: =DATE(YEAR(E$24),MONTH(E$24)+D83+1,DAY(E$24)) -> 47637 | C83: =TEXT(B83,"mmm-yyyy") -> Jun-2030 | D83: 56 | E83: =C$1 -> 10499.998 | F83: =E83-G83 -> 9990.3879 | G83: =H82*C$12 -> 509.61019 | H83: =H82-F83 -> 40970.631 | X83: =C4 -> 472027.82 | AC83: =C1 -> 10499.998 | AG83: =E25 -> 60 | AK83: 650 | AW83: =C3 -> 629999.88
B84: =DATE(YEAR(E$24),MONTH(E$24)+D84+1,DAY(E$24)) -> 47667 | C84: =TEXT(B84,"mmm-yyyy") -> Jul-2030 | D84: 57 | E84: =C$1 -> 10499.998 | F84: =E84-G84 -> 10090.292 | G84: =H83*C$12 -> 409.70631 | H84: =H83-F84 -> 30880.339 | X84: PROCESSED & VERIFIED BY:
B85: =DATE(YEAR(E$24),MONTH(E$24)+D85+1,DAY(E$24)) -> 47698 | C85: =TEXT(B85,"mmm-yyyy") -> Aug-2030 | D85: 58 | E85: =C$1 -> 10499.998 | F85: =E85-G85 -> 10191.195 | G85: =H84*C$12 -> 308.80339 | H85: =H84-F85 -> 20689.144
B86: =DATE(YEAR(E$24),MONTH(E$24)+D86+1,DAY(E$24)) -> 47729 | C86: =TEXT(B86,"mmm-yyyy") -> Sep-2030 | D86: 59 | E86: =C$1 -> 10499.998 | F86: =E86-G86 -> 10293.107 | G86: =H85*C$12 -> 206.89144 | H86: =H85-F86 -> 10396.038 | AJ86: =K60 -> ALEXANDER A. FERIA JR.
B87: =DATE(YEAR(E$24),MONTH(E$24)+D87+1,DAY(E$24)) -> 47759 | C87: =TEXT(B87,"mmm-yyyy") -> Oct-2030 | D87: 60 | E87: =C$1 -> 10499.998 | F87: =E87-G87 -> 10396.038 | G87: =H86*C$12 -> 103.96038 | H87: =H86-F87 -> -4.4383341e-09 | W87: SIGNATURE OVER PRINTED NAME
E88: =SUM(E28:E87) -> 629999.88 | F88: =SUM(F28:F87) -> 472027.82 | G88: =SUM(G28:G87) -> 157972.07
X90: RECOMMEND APPROVAL/DISAPPROVAL: | AO90: APPROVED/DISAPPROVED:
E92: =E88-F88 -> 157972.07 | AB92: ALEXANDER A FERIA JR | AS92: ALEXANDER L FERIA
F93: =E92/60 -> 2632.8678 | X93: SIGNATURE OVER PRINTED NAME | AO93: SIGNATURE OVER PRINTED NAME
G94: =F93*4 -> 10531.471
X100: PROMISORY NOTE NO: | AL100: =S30 -> LV- 005-BO
Y101: FOR VALUE RECEIVED, the undersigned promise to pay the People's Multi-Purpose Cooperative (PMPC) the sum of Php | AY101: =AW83 -> 629999.88
AA102: in | AB102: =AG83 -> 60 | AC102: equal monthly installments amounting to Php | AN102: =AC83 -> 10499.998 | AR102: each, to be paid on the 28th day of every month starting on
X103: =B28 -> 45964 | AB103: / Single Payment of due on unpaid installments from maturity will bear charges on unpaid principal
X104: at the rate of 2% per month as penatly thereof.
X105: I hereby waive presentment for payment and notice of dishonor. PMPC may accept partial payment reserving its right of recourse against me. PMPC is hereby authorized and empowered to set off or apply without notice what is due under this Note from whatever funds I have in the Cooperative.
X108: It is further agreed that in case of separation from the service of whatever cause, the unpaid balance with its accumulated surcharges and interest as stipulated above be deducted from my last paymnet, commutation of leave/furlough and/or from my pension.
X111: It is further agreed that when installments are not paid when due and payable, the whole of the principal sum remaining unpaid shall forthwith become due and payable at the election of the Cooperative. I promise and agree to pay for a reasonable attorney's fee if this note is not paid according to its legal tenor and effect when palced in a lawyer's hand for collection. In case litigation, venue shall be vested in the competent court as may be allowed by the Rules of Court at the sole option of PMPC.
X116: Further, I hereby agree and authorized PMPC to encumber, assign or sell to any person or entity any right which it may have under thi Note, and/or any assignment, mortgage lien, pledge or other encumbrances constituted in favor of PMPC pursuant to the provisions of this Note if any. The consent herein granted is recognized and acknowledged by me/us as a waiver, to all intent and purposes of whatever right I may have to notice of actual encumbrance/ assignment.
AM120: Military/Pensioners ID
AM121: Employee's ID/Office ID
AM122: Driver's License
Z123: =N32 -> ALBERTO B MAGISTRADO | AM123: Others:
X124: Signature over Printed Name
...
